Workbook
Name AmortizaciónInterés: -IPMT('[1]Calculadora de préstamos'!TasaInterés/12,'[1]Calculadora de préstamos'!NúmeroDePago,'[1]Calculadora de préstamos'!NúmeroDePagos,'[1]Calculadora de préstamos'!CantidadPréstamo)
Name PagoMensual: -PMT('[2]Calculadora de préstamos'!TasaInterés/12,'[2]Calculadora de préstamos'!NúmeroDePagos,'[2]Calculadora de préstamos'!CantidadPréstamo)
Name PréstamoNoPagado: IF([1]!NúmeroDePago<=[1]!NúmeroDePagos,1,0)
Name PréstamoPagado: IF([1]!CantidadPréstamo*[1]!TasaInterés*'[1]Calculadora de préstamos'!AñosPréstamo*'[1]Calculadora de préstamos'!FechaInicioPréstamo>0,1,0)
Name Principal: -PPMT([1]!TasaInterés/12,[1]!NúmeroDePago,[1]!NúmeroDePagos,[1]!CantidadPréstamo)
Name SCS: IF('[2]Calculadora de préstamos'!CantidadPréstamo*'[2]Calculadora de préstamos'!TasaInterés*'[2]Calculadora de préstamos'!AñosPréstamo*'[2]Calculadora de préstamos'!FechaInicioPréstamo>0,1,0)
Name ÚltimaFila: MATCH(9.99E+307,'[1]Calculadora de préstamos'!$B:$B)
Name USD: Ej_Costos!$O$1

Sheet PASO A PASO
B2: PASO A PASO — ACTUALIZAR EL PLAN DE NEGOCIOS CON NUEVAS PROYECCIONES DE VENTAS
B3: Alianza del Acero · Modelo a 10 años (Año 1 = 2026 … Año 10 = 2035) · Libro base: INFORME2 ajustado a 10 años (09/06/2026) · Guía preparada el 13/10/2026 y actualizada el 16/10/2026 · Controles y datos para el PowerPoint en la hoja «CONTROLES Y PPT».
B5: CÓMO USAR ESTA GUÍA
B6: • | C6: Seguir las fases en orden: A Preparar → B Correcciones únicas → C Ventas → D Costos → E Caja y préstamos CP → F Resultados y controles → G PowerPoint. Al terminar cada fase presionar F9 y revisar en «CONTROLES Y PPT» los controles que indica cada paso (columna «Control / resultado esperado»). Los controles 13, 14 y 23 (caja, préstamos CP y dividendos) recién deben quedar en OK al terminar la fase E; en el paso F1, todos (salvo el 13 si depende de la decisión de dividendos: paso E5).
B7: • | C7: Columna «Dónde»: hacer clic para ir a la celda. Los vínculos a hojas ocultas funcionan después del paso A3.
B8: • | C8: Colores del modelo: relleno azul claro = dato real; relleno amarillo = proyección cargada a mano; fuente verde = plan original (no se toca). En estas dos hojas, fuente azul sobre amarillo = dato de entrada o referencia fija.
B9: • | C9: Las fórmulas de esta guía están escritas para Excel en español (separador «;»). Si su Excel usa «,» como separador, reemplazarlo.
B10: • | C10: Escribir solo en las celdas indicadas. No escribir en columnas de total o promedio (O y AD de Ej_Producción, Ej_Ingresos, Ej_Costos, Ej_Resultados y Ej_Deuda; O, AB, AO, BB, BO, CB, CO, DB, DO, EB y EF de Ej_Flujo), salvo las celdas que un paso indica expresamente: Ej_Producción!O31:O32 y O46:O47 (B4), Ej_Costos!O9:O19 y AD9:AD19 (B5), Ej_Costos!O1 (D2) y Ej_Flujo!O37 y O40 (E2). Tampoco en el plan original (columnas P y AE de esas cinco hojas, salvo el rótulo Ej_Costos!P1, que se actualiza en el paso D2; columna E de Supuestos). En Ej_Flujo no hay columnas de plan: P, AD y AE son meses (ene-2027, feb-2028 y mar-2028) y se editan cuando un paso lo indica. El auxiliar Ej_Costos!O88:P114 (paso D5) no es plan ni total.
B11: • | C11: Trabajar sobre este libro (INFORME2). El libro «ORIGINAL» es casi idéntico, pero tiene #¡REF! en Payback y depende de este archivo por un vínculo externo: no copiar celdas desde él.
B13: CRITERIOS DEL MODELO (mantenerlos; si alguno cambia, anotarlo en el registro del final)
B14: # | C14: Tema | D14: Criterio
B15: 1 | C15: Horizonte | D15: Año 1 = 2026 (real hasta el corte + proyección); Año 2 = 2027 (proyección mensual); Años 3-10 = 2028-2035 (proyección anual).
B16: 2 | C16: Volumen años 1 y 2 | D16: Tn producidas y vendidas por producto y mes en Ej_Producción (filas 22-32 producción; 37-47 ventas). El modelo a 10 años toma los totales (columnas O y AD).
B17: 3 | C17: Volumen años 3-10 | D17: Producción = año anterior × (1 + Supuestos!B11, hoy 5%). Venta = producción × (1 − Supuestos!B8, merma 1,5%). Igual para los 11 productos.
B18: 4 | C18: Precio | D18: Años 1 y 2: promedio ponderado por Tn de Ej_Ingresos (filas 8-18, USD/Tn sin IVA, régimen maquila). Año 3 = año 2 × (1 + B14, 5%); años 4-10 = año anterior × (1 + B15, 2%).
B19: 5 | C19: Costo de materia prima | D19: USD/Tn por producto y mes en Ej_Costos (filas 9-19) × Tn PRODUCIDAS. Años 3-10: costo/Tn promedio de 2027 × (1 + B18, 3%) por año.
B20: 6 | C20: Otros costos | D20: Insumos, packaging, mantenimiento y movimiento de carga: en 2026, tarifa del plan por Tn × Tn del mes (el mantenimiento 2026 está tipeado); en 2027, plan × (2 − MP plan / MP proyectada), repartido por las Tn de cada mes. Años 3-10: insumos (Supuestos!B61 × Tn producidas), packaging (B62 × MP) y seguro caución (20% × 1,8% × MP) siguen al volumen; mantenimiento, movimiento de carga y energía crecen 10% anual fijo (Costos filas 11, 15 y 16) y no cambian con la prospección. Mano de obra y gastos fijos no siguen al volumen: la MO crece 3% anual desde el año 3 (cargas 43,09%; en los años 1-2 el factor 1,42 está incluido).
B21: 7 | C21: Capital de trabajo | D21: Días de Supuestos!B77:B83: caja 2, sueldos 15, stock MP 45, ventas a crédito 90, producto terminado 0, crédito de proveedores de MP 0 (sin crédito del proveedor de chapa) y proveedores menores 15. En el flujo mensual, las ventas se cobran a los 3 meses.
B22: 8 | C22: Impuesto | D22: Tributo maquila: 1% de las ventas (Supuestos!B68).
B23: 9 | C23: Préstamos CP para chapas | D23: Desembolsos tipeados en Ej_Flujo fila 8; devolución en la fila 16; interés 8% sobre la devolución (fila 17). El interés baja la utilidad, pero no entra al VAN.
B24: 10 | C24: Valuación | D24: VAN a 10 años al WACC (9,87%), sin valor terminal, con recupero del capital de trabajo en el año 10; TIR del mismo flujo (VAN-TIR fila 15). Es el método con que se calculó el VAN del plan: no cambiarlo.
B25: 11 | C25: Payback | D25: Inversión propia: dividendos descontados a Ke (16,32%) contra el aporte propio (USD 606.000). Los dividendos siguen un calendario fijo que empieza en el año 6 (Resultados filas 18 y 26-31).
B26: 12 | C26: Plan original | D26: En el libro solo están el plan de los años 1 y 2 (columnas P y AE de Ej_Producción, Ej_Ingresos, Ej_Costos, Ej_Resultados y Ej_Deuda) y los supuestos originales (Supuestos, columna E). En «CONTROLES Y PPT», el VAN, la TIR, el payback y los rótulos acumulados del plan están en la sección 4, y las series plan de los gráficos (los 10 años, copiadas del PPT de junio) en la sección 3, filas 82, 85, 87 y 89.
B28: FASE A — PREPARAR LA ACTUALIZACIÓN
B29: Paso | C29: Qué hacer | D29: Dónde | E29: Cómo / criterio | F29: Control / resultado esperado
B30: A1 | C30: Guardar una copia con versión | D30: (libro) | E30: Archivo > Guardar como: «…_RV01_PROSPECCION_AAAAMMDD.xlsx». Trabajar siempre sobre la copia y conservar la versión anterior para comparar. Antes de la fase G, hacer lo mismo con el PowerPoint (Informe_Ejecutivo_Plan_vs_Actualizado_ALIANZA_DEL_ACERO_10_AÑOS.pptx): guardarlo con un nombre nuevo («…_RV01_AAAAMMDD.pptx») y editar solo la copia. | F30: El nombre del libro indica versión y fecha (y, antes de empezar la fase G, también el del PPT).
B31: A2 | C31: Abrir sin actualizar vínculos y con cálculo automático | D31: Servicio Deuda!D18 | E31: Al abrir el libro, ante el aviso de vínculos externos, elegir «No actualizar»: la deuda LP de 'Servicio Deuda'!D18:I20 viene del archivo CALCULADORA PRESTAMO, que no está en este equipo. En Datos > Editar vínculos se puede confirmar que el vínculo quedó sin actualizar. Fórmulas > Opciones para el cálculo > Automático. | F31: Después del paso A3 (la hoja Servicio Deuda está oculta): 'Servicio Deuda'!D18 sigue en 29.277,76, sin error.
B32: A3 | C32: Mostrar las hojas ocultas y expandir los grupos | D32: Ej_Producción!B6 | E32: Hojas ocultas: Ej_Producción, Ej_Ingresos, Ej_Costos, Ej_Resultados, Ej_Deuda, Dashboard Ejec., Productos, Maquinaria, Mano de Obra, Servicio Deuda, Depreciación, IVA y Estr. Costos. Clic derecho en una pestaña > Mostrar (una vez por hoja). En Ej_Producción y Ej_Ingresos expandir filas y columnas con los botones de nivel «2». En Ej_Costos mostrar las filas 22-34. En Ej_Ingresos: Vista > Inmovilizar > Movilizar paneles y volver a inmovilizar en C8. | F32: Se ven los meses ene…dic de 2026 y 2027.
B33: A4 | C33: Guardar la foto «antes» | D33: CONTROLES Y PPT, sección 2 | E33: La columna «PPT jun-2026» de la sección 2 ya guarda las cifras de la versión anterior. Antes de cargar, copiar la columna «Libro (vivo)» y pegarla como valores en una hoja «Foto_antes». Sirve para explicar las variaciones. | F33: Hoy: VAN 2.844.948; TIR 14,92%; EBITDA acumulado 25,4M.
B34: A5 | C34: Definir el corte y reunir la prospección | D34: — | E34: Definir el último mes real (hoy el libro tiene volúmenes reales hasta mayo-2026 y precios hasta abril-2026). Reunir por producto y mes: Tn producidas, Tn vendidas y precio USD/Tn sin IVA del resto de 2026 y de 2027; costo de chapa USD/Tn; dotación de personal. Para 2028-2035: tasas de crecimiento, o Tn y precio por producto y año. | F34: Información con fuente y fecha (Comercial, Compras, RR. HH.).
B36: FASE B — CORRECCIONES ÚNICAS (una sola vez, antes de cargar; sin ellas la nueva prospección no llega a la caja ni al payback)
B37: Paso | C37: Qué hacer | D37: Dónde | E37: Cómo / criterio | F37: Control / resultado esperado
B38: B1 | C38: Vincular los cobros 2028-2036 (hoy son valores pegados) | D38: Ej_Flujo!AC6 | E38: Mismo criterio del modelo (venta anual / 12, cobrada a 90 días). AC6 =Ej_Ingresos!AA34; AD6 =Ej_Ingresos!AB34; AE6 =Ej_Ingresos!AC34. AF6:AN6 y AP6:AR6 =$AF$40; AS6:BA6 y BC6:BE6 =$AS$40; BF6:BN6 y BP6:BR6 =$BF$40; BS6:CA6 y CC6:CE6 =$BS$40; CF6:CN6 y CP6:CR6 =$CE$40; CS6:DA6 y DC6:DE6 =$CS$40; DF6:DN6 y DP6:DR6 =$DF$40; DS6:EA6 y EC6:EE6 =$DS$40. No escribir en las columnas de total. Con los datos actuales los valores no cambian (se verificó celda por celda). | F38: Controles 10 y 11 en OK.
B39: B2 | C39: Vincular el impuesto maquila 2028-2035 (hoy repite el de 2027) | D39: Ej_Flujo!AC24 | E39: Se paga al mes siguiente. AC24 =Ej_Resultados!AC18; AD24:AN24 y AP24 =Resultados!$E$13/12; AQ24:BA24 y BC24 =Resultados!$F$13/12; BD24:BN24 y BP24 =Resultados!$G$13/12; BQ24:CA24 y CC24 =Resultados!$H$13/12; CD24:CN24 y CP24 =Resultados!$I$13/12; CQ24:DA24 y DC24 =Resultados!$J$13/12; DD24:DN24 y DP24 =Resultados!$K$13/12; DQ24:EA24 =Resultados!$L$13/12. | F39: Control 12 en OK.
B40: B3 | C40: Completar las cuotas LP de jul-oct 2031 (faltan) | D40: Ej_Flujo!AC23 | E40: AC23:AN23 =('Servicio Deuda'!$F$23+'Servicio Deuda'!$F$24+'Servicio Deuda'!$F$25)/12; AP23:BA23 igual con la columna G; BC23:BN23 con la H; BP23:BY23 =('Servicio Deuda'!$I$23+'Servicio Deuda'!$I$24+'Servicio Deuda'!$I$25)/10. Agrega unos USD 464.000 de egresos en jul-oct 2031 (4 × 116.058) y, neto de la baja de las cuotas de ene-2028 a jun-2031 (≈ USD 77.000), unos USD 387.000 (≈ valor actual del control 17). Después hay que revisar los préstamos CP (paso E3). | F40: Control 17 en OK.
B41: B4 | C41: Crear los totales 2026 de Steel Frame y Accesorios y vincular Producción!D26 | D41: Ej_Producción!O31 | E41: En Ej_Producción escribir O31 =SUMA(C31:N31) y copiarla a O32; escribir O46 =SUMA(C46:N46) y copiarla a O47 (hoy las cuatro están vacías, a diferencia de O30 y O45). Luego Producción!D26 =+Ej_Producción!O32 (hoy es un 0 tipeado; D24, D25 y D27 ya apuntan a O31, O46 y O47). Sin esto, si Steel Frame o Accesorios producen o venden en 2026, su volumen no llega al modelo anual: Tn, precio promedio (Ej_Ingresos!O17:O18) y costo/Tn (Ej_Costos!O18:O19) quedan en 0. | F41: Control 9 en OK.
B42: B5 | C42: Proteger el costo/Tn y reparar los productos 4, 10 y 11 | D42: Ej_Costos!O9 | E42: O9 =SI(Ej_Producción!O22=0;0;O23/Ej_Producción!O22) y copiar a O10:O19 (reemplaza los 0 tipeados de O18:O19). AD9 =SI(Ej_Producción!AD22=0;0;AD23/Ej_Producción!AD22) y copiar a AD10:AD19. Copiar E26 en C26:D26 (falta la fórmula de ene-feb del producto 4). | F42: Control 25 en OK (sin #¡DIV/0! si un producto queda en 0 Tn).
B43: B6 | C43: Corregir los exponentes del payback de la inversión total | D43: Payback!D11 | E43: Hoy todas las columnas descuentan con ^1. D11 ='VAN-TIR'!D28/(1+Supuestos!$B$73)^(COLUMNA()-COLUMNA($C$11)) y copiar hasta M11 (equivale a ^1, ^2 … ^10). | F43: Control 22 en OK (Payback!M12 ≈ 986.333 con los datos actuales).
B44: B7 | C44: Calcular el payback con fórmula (hoy es texto tipeado) | D44: Payback!C8 | E44: En Payback!B8 escribir el rótulo «Payback inversión propia (años)» y en Payback!C8: =SI.ERROR(CONTAR.SI(D7:M7;"<0")+(-INDICE(C7:M7;CONTAR.SI(C7:M7;"<0")))/INDICE(C6:M6;CONTAR.SI(C7:M7;"<0")+1);"No recupera en 10 años"). En Payback!B13 escribir «Payback inversión total (años)» y en Payback!C13: =SI.ERROR(CONTAR.SI(D12:M12;"<0")+(-INDICE(C12:M12;CONTAR.SI(C12:M12;"<0")))/INDICE(C11:M11;CONTAR.SI(C12:M12;"<0")+1);"No recupera en 10 años"). Luego Dashboard!C12 =Payback!C8 y Dashboard!C13 =Payback!C13 (hoy dicen «4 Años» y «7 Años» tipeados), con formato 0,0 "años". | F44: Control 21 en OK. Hoy: propia 6,4 años (recupera en el año 7); total ≈ 8,1 años después de B6.
B45: B8 | C45: Vincular los demás egresos operativos 2028-2035 (hoy son valores pegados) | D45: Ej_Flujo!AC13 | E45: Mismo mapeo que 2027, con el costo anual de la hoja Costos / 12. Para 2028: AC13:AN13 =(Costos!$F$10+Costos!$F$13+Costos!$F$27)/12 (insumos, packaging y honorarios); AC19:AN19 =(Costos!$F$7+Costos!$F$8+Costos!$F$14+Costos!$F$20+Costos!$F$21)/12 (nómina y alimentación); AC21:AN21 =(Costos!$F$16+Costos!$F$22+Costos!$F$23)/12 (energía, servicios y alquileres); AC22:AN22 =(Costos!$F$9+Costos!$F$11+Costos!$F$12+Costos!$F$15+Costos!$F$24+Costos!$F$25+Costos!$F$26)/12 (otros). Repetir con la columna G de Costos en AP:BA, H en BC:BN, I en BP:CA, J en CC:CN, K en CP:DA, L en DC:DN y M en DP:EA, sin escribir en las columnas de total. Hoy esas filas son valores pegados, iguales en los ocho años 2028-2035 (parecidos a 2027, pero no iguales en las filas 13 y 22), y no siguen al volumen: el cambio agrega ≈ USD 1,62M de egresos en 2028-2035. Atención: la fila 25 («Inversiones / CAPEX») repite desde feb-2027 los servicios de terceros de Steel Frame que ya están en la fila 22 (USD 3.750/mes; 371.250 en 2027-2035). Confirmarlo con quien armó el modelo; si es una duplicación, dejar en 0 las columnas de mes de la fila 25 desde feb-2027 y anotarlo en el registro. | F45: Control 26 en OK. Con B2, B3 y B8 la caja empeora: es esperable y se resuelve en E3 y E5.
B47: FASE C — CARGAR LA PROSPECCIÓN DE VENTAS
B48: Paso | C48: Qué hacer | D48: Dónde | E48: Cómo / criterio | F48: Control / resultado esperado
B49: C1 | C49: Actualizar los meses reales hasta el corte | D49: Ej_Producción!H22 | E49: Rangos (ejemplo con corte a setiembre; si el corte es otro, terminar en la columna de ese mes): Ej_Producción!H22:K32 (producción) y H37:K47 (ventas); Ej_Ingresos!G8:K18 (precio). Desde el primer mes no real (hoy: volumen desde junio, columna H; precio desde mayo, columna G) hasta el mes del corte (setiembre = columna K). Producción en Tn producidas y ventas en Tn facturadas, por producto y mes. Precio = facturación del mes en USD sin IVA ÷ Tn vendidas del mismo producto (si se facturó en Gs, convertir con el TC del mes). Mes sin venta: Tn = 0. Pasar los meses reales a formato azul (Copiar formato desde C22 y C8) y actualizar los títulos B2: en Ej_Producción y Ej_Ingresos, «…EJECUTADO A ABRIL…» → mes del corte; en Ej_Costos, «…EJECUTADO & PROYECTADO» → «…EJECUTADO A <MES> & PROYECTADO». | F49: Controles 1 a 5 en OK; totales iguales a la facturación contable.
B50: C2 | C50: Cargar la prospección del resto de 2026 | D50: Ej_Producción!L22 | E50: Rangos: Ej_Producción!L22:N32 y L37:N47; Ej_Ingresos!L8:N18. Meses posteriores al corte (con corte a setiembre: oct-dic, columnas L:N), en las celdas amarillas. Criterio del modelo: Tn vendidas tipeadas según la prospección comercial (hoy sin merma en los años 1 y 2; la merma de 1,5% se aplica desde el año 3). Si se decide aplicar la merma también en 2026, anotarlo en el registro, igual que en C3 (b). La venta acumulada no puede superar a la producción acumulada más el stock inicial. Si hay Tn vendidas, el precio no puede quedar vacío. | F50: Controles 5 y 7 en OK.
B51: C3 | C51: Cargar 2027 mes a mes | D51: Ej_Producción!R22 | E51: Rangos: Ej_Producción!R22:AC32 y R37:AC47; Ej_Ingresos!R8:AC18. Si la prospección trae un total anual por producto, repartirlo en 12 meses según la rampa comercial (o /12). El total (columna AD) y el precio promedio ponderado (Ej_Ingresos!AD8:AD18) son la base de los años 3-10. Decidir y anotar en el registro: (a) si el precio 2027 lleva +5% (el plan sí; la proyección actual no); (b) si la venta lleva la merma de 1,5% (hoy venta = producción). No tocar AD, AE ni AF. | F51: Controles 2 a 5 en OK.
B52: C4 | C52: Años 2028-2035, si la prospección viene como tasas | D52: Supuestos!B11 | E52: Escribir la tasa como fracción (5% = 0,05): B11 crecimiento anual de la producción; B8 merma producción-venta; B14 aumento de precio del año 3; B15 aumento de precio de los años 4-10. Son iguales para los 11 productos. No modificar la columna E (ORIGINALES). | F52: Producción!F6/E6 − 1 ≈ B11 en cada producto (por el redondeo a Tn enteras difiere hasta ±0,2 puntos; hoy da entre 4,96% y 5,15% con B11 = 5%).
B53: C5 | C53: Años 2028-2035, si la prospección trae Tn por producto y año | D53: Producción!F6 | E53: Crear una hoja «Prosp_Tn» con la misma grilla que Producción (rótulos en B:C, años en F:M). Cargar solo las Tn de PRODUCCIÓN que traiga la prospección y dejar vacío lo demás. En Producción!F6: =SI(ESNUMERO(Prosp_Tn!F6);Prosp_Tn!F6;REDONDEAR(E6*(1+Supuestos!$B$11);0)); copiar a G6:M6 y pegar solo fórmulas en las filas pares 8 a 26. Las filas impares (venta) no se tocan: siguen aplicando la merma. Si el dato viene en Tn vendidas, cargar =REDONDEAR(venta/(1-Supuestos!$B$8);0). | F53: Las celdas con dato coinciden con Prosp_Tn; las vacías siguen la tasa B11.
B54: C6 | C54: Precios por producto y año (opcional) | D54: Ingresos!F6 | E54: Crear una hoja «Prosp_Precio» con la misma grilla que Ingresos. Ingresos!F6: =SI(ESNUMERO(Prosp_Precio!F6);Prosp_Precio!F6;E6*(1+Supuestos!$B$14)); Ingresos!G6: =SI(ESNUMERO(Prosp_Precio!G6);Prosp_Precio!G6;F6*(1+Supuestos!$B$15)), copiada a H6:M6. Repetir en las filas pares 8 a 26. No tocar las filas impares (ingreso = precio × venta) ni las filas 28-29. | F54: Las celdas con dato coinciden con Prosp_Precio; los años vacíos siguen B14/B15 a partir del último precio cargado. Ingresos!F28:M28 cambia desde el primer año con dato nuevo en adelante.
B55: C7 | C55: Productos 10 y 11 en 2026, o productos que arrancan después de 2027 | D55: Ej_Producción!C31 | E55: Rangos: Ej_Producción!C31:N32 y C46:N47; Ej_Ingresos!C17:N18; Ej_Costos!C18:N19. Steel Frame y Accesorios Metálicos arrancan hoy en ene-2027. Si venden en 2026, primero aplicar B4 (crea los totales Ej_Producción!O31, O32, O46 y O47, hoy vacíos) y B5; después cargar Tn, precio y costo de chapa en esas filas. Un producto con 2027 = 0 queda en 0 en los años 3-10: cargarlo con los pasos C5 y C6 y escribir su costo/Tn en su fila par de Materia Prima (columnas F:M). | F55: Controles 5, 6 y 9 en OK.
B56: C8 | C56: Producto nuevo (12.°) | D56: Producción!D28 | E56: Primero evaluar asimilarlo a la fila del producto más parecido en precio y costo (más simple y sin riesgo). Si se agrega: insertar filas dentro de cada bloque (Ej_Producción filas 17, 32 y 47; Ej_Ingresos 18 y 33; Ej_Costos 19 y 33; un par de filas antes de la 26 en Producción, Ingresos y Materia Prima), copiar las fórmulas de la fila vecina y sumar la fila nueva A MANO en Producción!D28:M28 y D29:M29, Ingresos!D28:M28 y Materia Prima!D28:M28: son sumas celda por celda, no SUMA de rango. | F56: Controles 1 a 4 y 8 en OK.
B58: FASE D — COSTOS QUE ACOMPAÑAN A LAS VENTAS
B59: Paso | C59: Qué hacer | D59: Dónde | E59: Cómo / criterio | F59: Control / resultado esperado
B60: D1 | C60: Confirmar que la producción está cargada | D60: Ej_Producción!C22 | E60: El costo de chapa se calcula sobre Tn PRODUCIDAS, no vendidas: si solo se cargan ventas, el costo no cambia y el margen se infla. | F60: Control 7 en OK (venta ≤ producción).
B61: D2 | C61: Tipo de cambio | D61: Ej_Costos!O1 | E61: Ej_Costos!O1 (hoy 6.028,12, «TC cierre de mayo-2026») convierte los gastos reales cargados en Gs (fórmulas =MontoGs/USD). Cambiarlo solo con un nuevo cierre, y actualizar el rótulo P1: revalúa también los meses ya cerrados. Supuestos!B6 (6.145) es informativo: no recalcula nada. Los meses proyectados están en USD calculados a 6.145. No tocar Supuestos!E6 (7.800). | F61: Un único TC de proyección, anotado en el registro.
B62: D3 | C62: Costo de chapa (USD/Tn) por producto y mes | D62: Ej_Costos!G9 | E62: Rangos: G9:N19 (2026) y R9:AC19 (2027). USD/Tn sin IVA, una fila por producto (mismo orden que Ej_Producción 22-32). Criterio vigente para 2027 (productos 2 a 9): enero = dic-2026 y feb-dic = dic-2026 × 1,07. Producto 1: todo 2027 = dic-2026 × 1,07. Productos 10 y 11: valor fijo todo el año (986,54 y 957,72), sin dato de 2026. Documentar toda cotización nueva. Todo mes con Tn producidas debe tener costo > 0. No escribir en los promedios (O, AD), ya corregidos en B5, ni en el plan (P, AE). El promedio 2027 (AD9:AD19) es la base de los años 3-10. | F62: Controles 6 y 8 en OK.
B63: D4 | C63: Gastos reales de los meses cerrados | D63: Ej_Costos!G34 | E63: Rango (ejemplo con corte a setiembre): G34:K54 (may-sep, meses cerrados). Mismo criterio que ene-abr: los montos en Gs se cargan como =MontoGs/USD (p. ej. =29898626/USD), encima de la fórmula de proyección del mes. Los meses sin gasto, en 0. Las filas 35 y 48 quedan en 0 porque las cargas sociales ya están en las filas 34 y 47. | F63: Ej_Costos!O65 cambia solo con lo cargado.
B64: D5 | C64: Mano de obra según la dotación que requiere el nuevo volumen | D64: Ej_Costos!R34 | E64: Rangos: G34:N34 y R34:AC34 (fábrica); G47:N47 y R47:AC47 (administración). USD/mes con cargas = salario Gs × 1,42 / TC × N.° de personas (auxiliar Ej_Costos!O88:P114). Recalcular todo R34:AC34: en R34:T34 cambiar la constante «+6702»; U34:AC34 son valores tipeados que repiten T34 (18.379,63 = 11.677,63 + 6.702): reemplazarlos también. Si cambia la administración, recalcular R47:AC47 (todo tipeado: R47:S47 = 7.304,97 y T47:AC47 = 8.228,97). Actualizar las notas de ingreso de personal (filas 68-71). Desde 2028 la MO solo crece 3% (Supuestos!B21): si la dotación crece después, ajustarlo en Mano de Obra y documentarlo. | F64: =(Costos!F7+Costos!F8+Costos!F20+Costos!F21)/(Costos!E7+Costos!E8+Costos!E20+Costos!E21)-1 ≈ 3,8% (= 1,03 × 1,4309 / 1,42 − 1, cualquiera sea la dotación de 2027).
B65: D6 | C65: Insumos, packaging, mantenimiento y movimiento de carga (automáticos) | D65: Ej_Costos!AJ37 | E65: No se cargan. En 2026: tarifa del plan por Tn × Tn del mes (el mantenimiento 2026 está tipeado). En 2027: plan × (2 − MP plan / MP proyectada), repartido por las Tn de cada mes. Verificar que Ej_Costos!AM37/AE37 sea > 0 y razonable frente a AD22/AE22; si la MP 2027 se aleja mucho del plan, revisar el criterio y documentarlo. En los años 3-10 solo insumos, packaging y seguro caución siguen al volumen; mantenimiento, movimiento de carga y energía crecen 10% anual fijo (Costos filas 11, 15 y 16): si el nuevo volumen exige más, ajustarlo y documentarlo. | F65: Ningún costo negativo en Ej_Costos filas 37-42.
B66: D7 | C66: Servicios de terceros de Steel Frame | D66: Ej_Costos!R36 | E66: Si cambia el volumen de Steel Frame, tipear los meses 2027 en R36:AC36 (sin tocar AE36, que es plan) y poner Mano de Obra!D13 =Ej_Costos!AD36, que es la base de los años 3-10. | F66: Mano de Obra!D13 = Ej_Costos!AD36.
B67: D8 | C67: Parámetros de costos de los años 3-10 | D67: Supuestos!B18 | E67: Solo la columna B: B18 costo MP/Tn (+3%); B21 salarios (+3%); B22 cargas (43,09%); B61 insumos (5 USD/Tn); B62 packaging (0,95% de la MP); B64 alimentación; B56 seguros; B58 honorarios. No tienen ningún efecto: B6, B53, B54, B55, B57, B63, B65, B75, B86 y B87. | F67: Costos!F17/E17 − 1 razonable (hoy 8,1%).
B69: FASE E — CAPITAL DE TRABAJO, CAJA Y PRÉSTAMOS CP
B70: Paso | C70: Qué hacer | D70: Dónde | E70: Cómo / criterio | F70: Control / resultado esperado
B71: E1 | C71: Días de capital de trabajo | D71: Supuestos!B77 | E71: Mantener B77 caja 2, B78 sueldos 15, B79 stock MP 45, B80 ventas a crédito 90, B81 producto terminado 0, B82 crédito de proveedores de MP 0 y B83 proveedores menores 15 (días), salvo un cambio de política. Si cambia B80 (cobro), también hay que mover el desfase de los cobros de Ej_Flujo fila 6 (hoy cada mes cobra la venta de 3 meses antes; p. ej. F6 =+Ej_Ingresos!C34 cobra en abril la venta de enero) y corregir los rótulos de Capital Trabajo!B7:B15. Ese desfase solo afecta la caja mensual: el VAN toma el capital de trabajo de la hoja Capital Trabajo. | F71: Control 18 en OK.
B72: E2 | C72: Base de compra de chapas 2027 | D72: Ej_Flujo!O40 | E72: O40 = MP 2027 redondeada: =REDONDEAR(Costos!E6;-5) (hoy 14.100.000). O37 (órdenes hasta ene-2027) solo cambia si esas órdenes no se emitieron. | F72: Ej_Flujo!O40 − Costos!E6 entre −100.000 y +100.000.
B73: E3 | C73: Redimensionar los préstamos CP para chapas | D73: Ej_Flujo!P8 | E73: Se escribe en las filas 8, 16 y 17 (solo columnas de mes); la fila 29 (saldo acumulado) es fórmula y solo se lee. Con la fase B completa (B1-B8) y la prospección cargada, recorrer el saldo mensual (fila 29) desde ago-2026. Para cada préstamo: (a) monto en la fila 8 del mes de desembolso (múltiplos de 100.000); (b) en la fila 16 del mes de devolución =+<celda de la fila 8> (ej. V16 =+P8); (c) en la fila 17 de esa columna =((8%/365)*DÍAS)*<celda fila 16>, con DÍAS = 30 × meses (ene→jul = 180); (d) si se mueve o elimina un desembolso, mover o borrar también su devolución y su interés; (e) un préstamo CP en 2026 se carga igual; si se devuelve dentro de 2026, sumar su interés en Ej_Costos (paso E4). L16 (2.779.626) y L17 (125.862) son la devolución a CIE S.A., no préstamos CP: no tocarlas. Meta: saldo ≥ 0 todos los meses, con un colchón de 100.000 a 400.000, y todo devuelto a más tardar en dic-2035 (columna EA). Antes de la fase B el único déficit es ago-2032 (CJ29 = −245.726). Después de la fase B, con los datos actuales, hay faltantes de calce desde abr-2030 (máximo −736.000 en ago-2032 sin contar dividendos) y el saldo de dic-2035 queda en ≈ −2,22M después de los dividendos: ver E5. | F73: Controles 13 y 14 en OK (el 13, salvo que dependa de la decisión de dividendos: paso E5).
B74: E4 | C74: Intereses CP de 2027 en Resultados | D74: Ej_Costos!R62 | E74: Hoy solo X62, AA62 y AC62 suman Ej_Flujo!V17, Y17 y AA17. Si una devolución de 2027 cambió de mes: R62 =+Ej_Deuda!R7+Ej_Deuda!R13+Ej_Flujo!P17 y copiar hasta AC62 (columna de Ej_Costos = columna de Ej_Flujo + 2). Si un préstamo CP se devuelve dentro de 2026, sumar su interés en la misma columna de Ej_Costos (en 2026 coinciden; p. ej. M62 =+Ej_Deuda!M7+Ej_Deuda!M13+Ej_Flujo!M17), sin incluir L17. Para 2028-2035 no hay que hacer nada: Costos!F34:M34 ya toman los totales de la fila 17. | F74: Controles 15 y 16 en OK.
B75: E5 | C75: Iterar dividendos y caja | D75: Resultados!H18 | E75: Las nuevas utilidades cambian los dividendos (Resultados fila 18, calculados en las filas 25-31 sobre la retención de utilidades de la fila 17). El calendario es fijo: en 2031 se paga el 50% de la utilidad de 2027; en 2032, el otro 50% de 2027 y la de 2028; en 2033, la de 2029; en 2034, la de 2030 y 500.000 de la de 2031 (H29, tipeado); en 2035, el resto de 2031 y 800.000 de la de 2032 (I30, tipeado). Se pagan en diciembre en Ej_Flujo fila 20 (CA20, CN20, DA20, DN20 y EA20; esa fila no tiene totales anuales). Si cambia la caja, volver a E3 hasta que el saldo mínimo se estabilice (2 o 3 vueltas). Si con todos los CP devueltos el saldo de dic-2035 sigue negativo (hoy ≈ −2,22M después de la fase B, con ≈ USD 10M de dividendos en 2031-2035), el calendario de dividendos excede la caja disponible: la Gerencia presenta a la Dirección las alternativas (diferir o reducir dividendos, mantener deuda CP al cierre o refinanciar a largo plazo). No cambiar la política sin instrucción de la Dirección. | F75: Control 23 en OK.
B77: FASE F — RESULTADOS Y CONTROLES
B78: Paso | C78: Qué hacer | D78: Dónde | E78: Cómo / criterio | F78: Control / resultado esperado
B79: F1 | C79: Recalcular y revisar los controles | D79: CONTROLES Y PPT, sección 1 | E79: Presionar F9 (o Ctrl+Alt+F9). Todos los controles deben quedar en OK; la última columna indica qué paso revisar. Con el libro tal como llegó hay 8 controles en REVISAR: el 9, 11, 12, 17, 21, 22 y 26 se corrigen en la fase B; el 13 (déficit de caja) se corrige en E3 y E5, y empeora después de la fase B. Excepción: si el control 13 solo puede pasar a OK cambiando la política de dividendos o dejando préstamos CP sin devolver al cierre (control 14), no forzarlo: dejarlo en REVISAR, anotar en el registro el saldo de dic-2035 y las alternativas presentadas (paso E5) y seguir con la fase G, aclarando en el PPT que la caja 2031-2035 depende de esa decisión. | F79: 26 de 26 controles en OK, o 25 de 26 con el control 13 pendiente de la decisión de dividendos y anotado en el registro.
B80: F2 | C80: Leer resultados y valuación (sin editar) | D80: VAN-TIR!C22 | E80: Confirmar que ingresos, EBITDA, gastos financieros y utilidad reflejan la prospección. El WACC debe seguir en 9,87% si no cambió el financiamiento. Para explicar el cambio del VAN, separar el efecto EBITDA (VAN-TIR fila 5) del efecto capital de trabajo (fila 9 y recupero en M6): cada USD 1M de ventas anuales adicionales inmoviliza ≈ USD 252.000 de capital de trabajo si viene de precio (caja 2 días + crédito 90 días) y ≈ USD 350.000 si viene de volumen (se suma el stock de MP de 45 días, con MP ≈ 81% de las ventas). | F80: VAN y TIR se mueven en el sentido esperado frente a la foto del paso A4.
B81: F3 | C81: Registrar la actualización | D81: Registro de actualizaciones | E81: Fecha, versión, corte de reales, fuente de la prospección y criterios modificados (precio 2027, merma, TC, dotación, préstamos CP). | F81: —
B83: FASE G — ACTUALIZAR EL POWERPOINT «PLAN ORIGINAL VS PROYECCIÓN ACTUALIZADA A 10 AÑOS»
B84: Paso | C84: Qué hacer | D84: Dónde | E84: Cómo / criterio | F84: Control / resultado esperado
B85: G1 | C85: Series de los gráficos | D85: CONTROLES Y PPT, sección 3 | E85: Copiar las celdas E:N de la fila «Actualizado» de la sección 3. En el PPT: clic derecho en el gráfico > Editar datos; seleccionar la primera celda de la serie > Pegado especial > Valores + Transponer (en el gráfico los años van en filas). Destinos: diap. 4 producción (fila 81) → C2; diap. 5 ingresos (fila 84) → C2; diap. 6 costos de producción (fila 86) → C2; diap. 7 EBITDA (fila 88) → C2; diap. 8 préstamos CP (fila 95) → B2; diap. 10 ventas (fila 83) → B2 y punto de equilibrio (fila 93) → C2. La serie «Plan original» (columna B de las diap. 4 a 7; filas 82, 85, 87 y 89 de la sección 3) no se toca. | F85: Los datos de cada gráfico coinciden con la sección 3 (años en A2:A11).
B86: G2 | C86: Tablas e indicadores | D86: CONTROLES Y PPT, sección 2 | E86: Copiar cada valor de la columna «Libro (vivo)» con el redondeo de la diapositiva (USD con separador de miles; % con 1 decimal; diferencias de TIR en puntos porcentuales). Las variaciones contra el plan se calculan contra los rótulos plan del PPT (sección 4 de «CONTROLES Y PPT»: 150K Tn, USD 180M, USD 21,1M y USD 17,8M), con el mismo criterio que la versión de junio; así la tabla de la diap. 3 queda coherente. | F86: Columna «Diferencia» explicada.
B87: G3 | C87: Textos y conclusiones | D87: Diapositivas 2 a 14 | E87: Buscar (Ctrl+F) cada cifra que cambió y reemplazarla en todas las diapositivas donde se repite, siempre con el valor vivo de las secciones 2 y 3 de «CONTROLES Y PPT» (con el libro ya actualizado). La versión de junio, además, tenía cifras que no coincidían con el libro de ese momento; como referencia (PPT de junio → libro de junio): ingresos acumulados 217M → 215,6M; EBITDA acumulado 26,4M → 25,4M; utilidad neta acumulada 19,6M → 18,0M; variaciones contra el plan +7% → +7,5% (producción, indicador 13; diap. 3, 4 y 13), +21% → +19,8% (ingresos, indicador 15; diap. 3, 5, 9 y 13), +25% → +20,4% (EBITDA, indicador 17; diap. 3, 7, 9 y 13) y +10% → +1,3% (utilidad neta, indicador 19; diap. 3); el «+25%» de la diap. 5 es otro dato (ingresos del año 10 contra el plan, hoy +25,3%): no reemplazarlo por el del EBITDA; TIR −0,29 → −0,27 pp; margen de seguridad 52-69% → 50-69% (diap. 10); préstamos CP «5-12M» → «4-12M» (diap. 11 y 13) y «5-11.9M» → «4-11.9M» (diap. 8); «11 vs 8 productos activos en Año 1» → «9 vs 8» (diap. 4); materia prima acumulada 183M → 181,1M (diap. 6); desvío del costo de MP 6-16% → 2,7-15,8%, o «5,9-15,8% sin Accesorios» si se documenta (diap. 2, 6, 11 y 13). Revisar también dos frases que no coinciden con las series: diap. 7, «los márgenes EBITDA actualizados son superiores en años 2-5» (solo el año 2 supera al plan: 14,1% frente a 12,8%; el año 3 queda igual y los años 4 a 10, por debajo); diap. 10, «a partir del Año 6 (fin de deuda LP), el PE baja significativamente» (sube de 6.204 Tn en el año 5 a 6.433 en el año 6, baja a 5.492 en el año 7 y vuelve a subir hasta 7.854 en el año 10). En la diap. 13, «USD 4-7M adicionales» = indicadores 31 y 32. El 95,3% de MP/costos del plan (diap. 6) es un valor plan: no cambiarlo sin definir la fuente oficial del plan (sección 4 de «CONTROLES Y PPT»). Rotular el año 1 como «real a <mes> + proyección». | F87: Cada cifra del PPT = celda de la sección 2 o 3 de «CONTROLES Y PPT».
B88: G4 | C88: Payback | D88: Diapositiva 9 | E88: Usar el valor calculado de la sección 2 de «CONTROLES Y PPT» (indicador 38: hoy 6,4 años; se recupera durante el año 7), no el texto del Dashboard. Actualizar también la diferencia contra el plan («(+3)»; plan = 3 años, sección 4 de «CONTROLES Y PPT») y la frase de la conclusión «extienden el Payback de inversión propia en 3 años más». En la nota «El Payback es considerado desde el año 6…», indicar el criterio del modelo: dividendos descontados a Ke (16,32%) contra el aporte propio (USD 606.000), con dividendos desde 2031 (año 6). | F88: —
B89: G5 | C89: Sensibilidad del VAN (diapositiva 12) | D89: Copia del libro | E89: El libro no tiene cálculo de sensibilidad. Para cada variable, en una COPIA del libro ya actualizado, aplicar el cambio a todos los meses posteriores al corte (con corte a setiembre: L:N de 2026 y R:AC de 2027; los años 3-10 se ajustan solos porque parten de 2027; si se usaron Prosp_Tn o Prosp_Precio, aplicar el mismo factor en esas hojas): precio, Ej_Ingresos!L8:N18 y R8:AC18 × 1,05; costo de MP, Ej_Costos!L9:N19 y R9:AC19 × 1,05; volumen, Ej_Producción!L22:N32, L37:N47, R22:AC32 y R37:AC47 × 1,10; cobranza, Supuestos!B80 = 60 (el VAN toma el capital de trabajo de la hoja Capital Trabajo y no depende de Ej_Flujo: no hace falta cambiar el desfase de la fila 6). Anotar VAN-TIR!C24 y restar el VAN base. Atención: con los datos actuales y este método, el VAN cambia ≈ ±USD 5,8M por ±5% de precio (≈ ±5,9M si el cambio se aplica a todo el año 1) y ≈ ∓USD 5,2M por ±5% de MP, muy por encima de lo que muestra la diapositiva de junio (±1,2M y ±1,0M); con un precio 5% menor, el VAN sería negativo (≈ −USD 3,0M). Tasa CP +2% y tipo de cambio ±10%: con este libro el VAN no cambia (el interés CP no entra al VAN y las proyecciones están en USD); informar ≈ 0 en VAN y, si se quiere mostrar, el efecto en la utilidad neta acumulada y en la caja (la tasa CP exige cambiar el 8% de cada fórmula de Ej_Flujo fila 17). | F89: Diferencias documentadas por escenario.
B90: G6 | C90: Fecha y fuente | D90: Portada y cierre | E90: Cambiar «Junio 2026» por la fecha de la nueva versión y citar el archivo y la versión del libro usados. | F90: —
B92: REGISTRO DE ACTUALIZACIONES
B93: N.° | C93: Fecha y versión | D93: Corte de reales y fuente de la prospección | E93: Criterios modificados y observaciones | F93: Responsable
B94: 0 | C94: 09/06/2026 · INFORME2 ajustado a 10 años | D94: Volumen real a mayo-2026; precio real a abril-2026 | E94: Versión base usada en el PPT «Plan vs Actualizado 10 años» de junio 2026. Guía y controles agregados el 13/10/2026 y actualizados el 16/10/2026, sin modificar el modelo. | F94: —
B95: 1
B96: 2
B97: 3
B98: 4
B99: 5
B100: 6

Sheet CONTROLES Y PPT
B2: CONTROLES DEL MODELO Y DATOS PARA EL POWERPOINT
B3: Las celdas de las columnas «Valor», «Libro» y de los años son fórmulas vivas: se recalculan al cargar la nueva prospección. Los valores en fuente azul son referencias fijas (plan original y PPT de junio 2026). Ver la hoja «PASO A PASO».
B5: 1. CONTROLES (todos en OK antes de pasar al PowerPoint, salvo el 13 si depende de la decisión de dividendos: ver paso E5)
B6: # | C6: Control | D6: Qué compara | E6: Valor | F6: Esperado | G6: Estado | H6: Si da REVISAR: qué hacer (paso de la hoja PASO A PASO)
B7: 1 | C7: Producción año 1 = detalle mensual (Tn) | D7: Producción!D28 − SUMA(Ej_Producción!C22:N32) | E7: =ROUND('Producción'!D28-SUM('Ej_Producción'!C22:N32),2) -> 0 | F7: 0 | G7: =IF(ABS(E7)<0.5,"OK","REVISAR") -> OK | H7: B4 (totales Ej_Producción!O31:O32 y Producción!D26) y C1-C2: revisar que Producción!D6:D26 (filas pares) tomen Ej_Producción!O22:O32.
B8: 2 | C8: Producción año 2 = detalle mensual (Tn) | D8: Producción!E28 − SUMA(Ej_Producción!R22:AC32) | E8: =ROUND('Producción'!E28-SUM('Ej_Producción'!R22:AC32),2) -> 0 | F8: 0 | G8: =IF(ABS(E8)<0.5,"OK","REVISAR") -> OK | H8: C3: revisar Ej_Producción!R22:AC32 y que Producción!E6:E26 tomen la columna AD.
B9: 3 | C9: Ventas años 1 y 2 = detalle mensual (Tn) | D9: |Producción!D29 − SUMA(Ej_Producción!C37:N47)| + |E29 − SUMA(R37:AC47)| | E9: =ROUND(ABS('Producción'!D29-SUM('Ej_Producción'!C37:N47))+ABS('Producción'!E29-SUM('Ej_Producción'!R37:AC47)),2) -> 0 | F9: 0 | G9: =IF(ABS(E9)<0.5,"OK","REVISAR") -> OK | H9: B4 (totales Ej_Producción!O46:O47) y C1-C3: revisar Ej_Producción filas 37-47 (ventas).
B10: 4 | C10: Ingresos años 1 y 2 = detalle mensual (USD) | D10: |Ingresos!D28 − Ej_Ingresos!O34| + |E28 − AD34| | E10: =ROUND(ABS('Ingresos'!D28-'Ej_Ingresos'!O34)+ABS('Ingresos'!E28-'Ej_Ingresos'!AD34),2) -> 0 | F10: 0 | G10: =IF(ABS(E10)<1,"OK","REVISAR") -> OK | H10: C1-C3: revisar precios Ej_Ingresos!C8:AC18 y que Ingresos!D/E tomen las columnas O/AD. Si Steel Frame o Accesorios venden en 2026, verificar los totales Ej_Producción!O46:O47 (paso B4).
B11: 5 | C11: Meses con venta y sin precio (cantidad) | D11: Tn vendidas > 0 con precio = 0 (2026 y 2027) | E11: =SUMPRODUCT(('Ej_Producción'!C37:N47>0)*('Ej_Ingresos'!C8:N18=0))+SUMPRODUCT(('Ej_Producción'!R37:AC47>0)*('Ej_Ingresos'!R8:AC18=0)) -> 0 | F11: 0 | G11: =IF(E11=0,"OK","REVISAR") -> OK | H11: C1-C3: cargar el precio USD/Tn de cada mes con venta.
B12: 6 | C12: Meses con producción y sin costo de chapa (cantidad) | D12: Tn producidas > 0 con USD/Tn = 0 (2026 y 2027) | E12: =SUMPRODUCT(('Ej_Producción'!C22:N32>0)*('Ej_Costos'!C9:N19=0))+SUMPRODUCT(('Ej_Producción'!R22:AC32>0)*('Ej_Costos'!R9:AC19=0)) -> 0 | F12: 0 | G12: =IF(E12=0,"OK","REVISAR") -> OK | H12: D3: cargar el costo USD/Tn de chapa en Ej_Costos para cada mes con producción.
B13: 7 | C13: Venta ≤ producción, años 1 y 2 (Tn) | D13: Mínimo de (producción − venta) año 1 y año 2 | E13: =ROUND(MIN('Producción'!D28-'Producción'!D29,'Producción'!E28-'Producción'!E29),2) -> 0 | F13: ≥ 0 | G13: =IF(E13>=0,"OK","REVISAR") -> OK | H13: C2-C3: la venta no puede superar la producción (salvo stock inicial documentado).
B14: 8 | C14: Materia prima igual en Ej_Costos, Costos y Materia Prima (USD) | D14: Años 1 y 2: Materia Prima!D28/E28 vs Costos!D6/E6 vs Ej_Costos!O22/AD22 | E14: =ROUND(ABS('Materia Prima'!D28-'Costos'!D6)+ABS('Costos'!D6-'Ej_Costos'!O22)+ABS('Materia Prima'!E28-'Costos'!E6)+ABS('Costos'!E6-'Ej_Costos'!AD22),2) -> 0 | F14: 0 | G14: =IF(ABS(E14)<1,"OK","REVISAR") -> OK | H14: B4 (totales Ej_Producción!O31:O32 y Producción!D26) y B5 (Ej_Costos!O18:O19 con fórmula).
B15: 9 | C15: Steel Frame y Accesorios del año 1 vinculados | D15: ¿Producción!D26 y Ej_Producción!O31, O32, O46 y O47 son fórmulas? | E15: =AND(_xlfn.ISFORMULA('Producción'!D26),_xlfn.ISFORMULA('Ej_Producción'!O31),_xlfn.ISFORMULA('Ej_Producción'!O32),_xlfn.ISFORMULA('Ej_Producción'!O46),_xlfn.ISFORMULA('Ej_Producción'!O47)) -> FALSE | F15: VERDADERO | G15: =IF(E15=TRUE,"OK","REVISAR") -> REVISAR | H15: B4: crear los totales Ej_Producción!O31, O32, O46 y O47 (hoy vacíos) y escribir =+Ej_Producción!O32 en Producción!D26.
B16: 10 | C16: Cobros 2026-2036 = ventas de los 10 años (USD) | D16: Suma de cobros de Ej_Flujo (totales) − SUMA(Ingresos!D28:M28) | E16: =ROUND(('Ej_Flujo'!O6+'Ej_Flujo'!AB6+'Ej_Flujo'!AO6+'Ej_Flujo'!BB6+'Ej_Flujo'!BO6+'Ej_Flujo'!CB6+'Ej_Flujo'!CO6+'Ej_Flujo'!DB6+'Ej_Flujo'!DO6+'Ej_Flujo'!EB6+'Ej_Flujo'!EF6)-SUM('Ingresos'!D28:M28),2) -> 0 | F16: 0 | G16: =IF(ABS(E16)<1,"OK","REVISAR") -> OK | H16: B1: vincular los cobros 2028-2036 (Ej_Flujo!AC6:EE6).
B17: 11 | C17: Cobros 2028-2036 vinculados a las ventas | D17: ¿Ej_Flujo!AF6 es fórmula? | E17: =_xlfn.ISFORMULA('Ej_Flujo'!AF6) -> FALSE | F17: VERDADERO | G17: =IF(E17=TRUE,"OK","REVISAR") -> REVISAR | H17: B1: hoy son valores pegados; no cambian con la nueva prospección.
B18: 12 | C18: Impuesto maquila pagado 2028-2035 = Resultados (USD) | D18: Ej_Flujo fila 24 (totales 2028-2035) − (impuesto dic-2027 + SUMA(Resultados!E13:L13) − 1/12 de L13) | E18: =ROUND(('Ej_Flujo'!AO24+'Ej_Flujo'!BB24+'Ej_Flujo'!BO24+'Ej_Flujo'!CB24+'Ej_Flujo'!CO24+'Ej_Flujo'!DB24+'Ej_Flujo'!DO24+'Ej_Flujo'!EB24)-('Ej_Resultados'!AC18+SUM('Resultados'!E13:L13)-'Resultados'!L13/12),2) -> -612871.03 | F18: 0 | G18: =IF(ABS(E18)<1,"OK","REVISAR") -> REVISAR | H18: B2: vincular Ej_Flujo!AC24:EA24 al 1% de las ventas de cada año (se paga al mes siguiente).
B19: 13 | C19: Saldo de caja mensual mínimo, ago-2026 a dic-2035 (USD) | D19: MIN(Ej_Flujo!J29:EA29) | E19: =ROUND(MIN('Ej_Flujo'!J29:EA29),2) -> -245725.67 | F19: ≥ 0 | G19: =IF(E19>=0,"OK","REVISAR") -> REVISAR | H19: E3: redimensionar los préstamos CP (Ej_Flujo fila 8) hasta que el saldo no sea negativo. Es normal que siga en REVISAR hasta terminar la fase E: la fase B lo empeora.
B20: 14 | C20: Préstamos CP: desembolsado − devuelto (USD) | D20: Ej_Flujo fila 8 − fila 16, 2026-2035 (sin L16, que es la devolución a CIE S.A.) | E20: =ROUND(('Ej_Flujo'!O8+'Ej_Flujo'!AB8+'Ej_Flujo'!AO8+'Ej_Flujo'!BB8+'Ej_Flujo'!BO8+'Ej_Flujo'!CB8+'Ej_Flujo'!CO8+'Ej_Flujo'!DB8+'Ej_Flujo'!DO8+'Ej_Flujo'!EB8)-(SUM('Ej_Flujo'!C16:K16)+SUM('Ej_Flujo'!M16:N16)+'Ej_Flujo'!AB16+'Ej_Flujo'!AO16+'Ej_Flujo'!BB16+'Ej_Flujo'!BO16+'Ej_Flujo'!CB16+'Ej_Flujo'!CO16+'Ej_Flujo'!DB16+'Ej_Flujo'!DO16+'Ej_Flujo'!EB16),2) -> 0 | F20: 0 | G20: =IF(ABS(E20)<1,"OK","REVISAR") -> OK | H20: E3: cada desembolso de la fila 8 necesita su devolución en la fila 16, a más tardar en dic-2035 (EA16).
B21: 15 | C21: Intereses 2027 completos en Ej_Costos (USD) | D21: Ej_Costos!AD63 − (Ej_Deuda!AD7 + AD13 + Ej_Flujo!AB17) | E21: =ROUND('Ej_Costos'!AD63-('Ej_Deuda'!AD7+'Ej_Deuda'!AD13+'Ej_Flujo'!AB17),2) -> 0 | F21: 0 | G21: =IF(ABS(E21)<1,"OK","REVISAR") -> OK | H21: E4: vincular Ej_Costos!R62:AC62 a Ej_Flujo fila 17 del mismo mes.
B22: 16 | C22: Intereses 2028 (LP + CP) en Resultados (USD) | D22: Resultados!E11 − ('Servicio Deuda'!F24 + Ej_Flujo!AO17) | E22: =ROUND('Resultados'!E11-('Servicio Deuda'!F24+'Ej_Flujo'!AO17),2) -> 0 | F22: 0 | G22: =IF(ABS(E22)<1,"OK","REVISAR") -> OK | H22: E3-E4: revisar Costos!F34 y los intereses CP de Ej_Flujo fila 17.
B23: 17 | C23: Cuotas LP del flujo = Servicio Deuda (USD) | D23: Ej_Flujo fila 23 (2026-2031) − SUMA('Servicio Deuda'!D23:I25) | E23: =ROUND(('Ej_Flujo'!O23+'Ej_Flujo'!AB23+'Ej_Flujo'!AO23+'Ej_Flujo'!BB23+'Ej_Flujo'!BO23+'Ej_Flujo'!CB23)-SUM('Servicio Deuda'!D23:I25),2) -> -387346.81 | F23: ≈ 0 (± 1.000) | G23: =IF(ABS(E23)<1000,"OK","REVISAR") -> REVISAR | H23: B3: faltan las cuotas de jul-oct 2031 (Ej_Flujo!BV23:BY23).
B24: 18 | C24: Capital de trabajo sigue a las ventas (USD) | D24: Capital Trabajo!D9 − Ingresos!E28 × Supuestos!B80 / 365 | E24: =ROUND('Capital Trabajo'!D9-'Ingresos'!E28*'Supuestos'!B80/365,2) -> 0 | F24: 0 | G24: =IF(ABS(E24)<1,"OK","REVISAR") -> OK | H24: E1: no escribir valores en Capital Trabajo; revisar Supuestos!B77:B83.
B25: 19 | C25: Recupero de CT del VAN = CT neto año 10 (USD) | D25: VAN-TIR!M6 − Capital Trabajo!L18 | E25: =ROUND('VAN-TIR'!M6-'Capital Trabajo'!L18,2) -> 0 | F25: 0 | G25: =IF(ABS(E25)<1,"OK","REVISAR") -> OK | H25: F2: no modificar VAN-TIR; revisar la hoja Capital Trabajo.
B26: 20 | C26: VAN reproducible (USD) | D26: VNA(WACC; flujos años 1-10) + flujo año 0 − VAN-TIR!C24 | E26: =ROUND(NPV('VAN-TIR'!C22,'VAN-TIR'!D15:M15)+'VAN-TIR'!C15-'VAN-TIR'!C24,2) -> 0 | F26: 0 | G26: =IF(ABS(E26)<1,"OK","REVISAR") -> OK | H26: F2: la fórmula de VAN-TIR!C24 fue alterada; restituir =VNA(C22;D15:M15)+C15.
B27: 21 | C27: Payback del Dashboard calculado con fórmula | D27: ¿Dashboard!C12 es fórmula y da un número? | E27: =AND(_xlfn.ISFORMULA('Dashboard'!C12),ISNUMBER('Dashboard'!C12)) -> FALSE | F27: VERDADERO | G27: =IF(E27=TRUE,"OK","REVISAR") -> REVISAR | H27: B7: hoy dice «4 Años» tipeado; vincular a Payback!C8.
B28: 22 | C28: Payback total descontado correctamente (USD) | D28: Payback!M12 − (VNA(Ke; VAN-TIR!D28:M28) + C28) | E28: =ROUND('Payback'!M12-(NPV('Supuestos'!B73,'VAN-TIR'!D28:M28)+'VAN-TIR'!C28),2) -> 7774618.4 | F28: 0 | G28: =IF(ABS(E28)<1,"OK","REVISAR") -> REVISAR | H28: B6: corregir los exponentes de Payback!D11:M11 (^1 … ^10).
B29: 23 | C29: Dividendos no negativos (USD) | D29: Mínimo de Resultados!C18:L18, H30 e I31 | E29: =ROUND(MIN(MIN('Resultados'!C18:L18),'Resultados'!H30,'Resultados'!I31),2) -> 0 | F29: ≥ 0 | G29: =IF(E29>=0,"OK","REVISAR") -> OK | H29: E5: con utilidades menores a 500.000 (año 6) u 800.000 (año 7) el calendario fijo da negativo; la Gerencia lo presenta a la Dirección.
B30: 24 | C30: Plan original intacto | D30: Ej_Producción!P18, AE18; Ej_Ingresos!P34, AE34; Ej_Resultados!P13; Supuestos!E11 | E30: =AND('Ej_Producción'!P18=11087,'Ej_Producción'!AE18=12587,'Ej_Ingresos'!P34=10820400,'Ej_Ingresos'!AE34=13591134,ROUND('Ej_Resultados'!P13,0)=841163,'Supuestos'!E11=0.05) -> TRUE | F30: VERDADERO | G30: =IF(E30=TRUE,"OK","REVISAR") -> OK | H30: No escribir en columnas P/AE de las hojas Ej_ ni en la columna E de Supuestos; restaurar desde la copia.
B31: 25 | C31: Errores de fórmula en hojas de resultados (cantidad) | D31: Celdas con error (REF, DIV/0, VALOR, N/A) en Resultados, VAN-TIR, Payback, Dashboard, Capital Trabajo, Materia Prima y Costos | E31: =SUMPRODUCT(--ISERROR('Resultados'!C5:L22))+SUMPRODUCT(--ISERROR('VAN-TIR'!C5:M28))+SUMPRODUCT(--ISERROR('Payback'!C6:M12))+SUMPRODUCT(--ISERROR('Dashboard'!C6:L26))+SUMPRODUCT(--ISERROR('Capital Trabajo'!C6:L20))+SUMPRODUCT(--ISERROR('Materia Prima'!D6:M28))+SUMPRODUCT(--ISERROR('Costos'!D6:M38)) -> 0 | F31: 0 | G31: =IF(E31=0,"OK","REVISAR") -> OK | H31: B5 (división por cero en Ej_Costos) o referencias borradas; usar Ctrl+B «#» en valores.
B32: 26 | C32: Egresos operativos 2028-2035 del flujo = Costos (USD) | D32: Ej_Flujo filas 13, 19, 21 y 22 (totales 2028-2035) − Costos!F:M filas 7-16 y 20-27 | E32: =ROUND(('Ej_Flujo'!AO13+'Ej_Flujo'!AO19+'Ej_Flujo'!AO21+'Ej_Flujo'!AO22+'Ej_Flujo'!BB13+'Ej_Flujo'!BB19+'Ej_Flujo'!BB21+'Ej_Flujo'!BB22+'Ej_Flujo'!BO13+'Ej_Flujo'!BO19+'Ej_Flujo'!BO21+'Ej_Flujo'!BO22+'Ej_Flujo'!CB13+'Ej_Flujo'!CB19+'Ej_Flujo'!CB21+'Ej_Flujo'!CB22+'Ej_Flujo'!CO13+'Ej_Flujo'!CO19+'Ej_Flujo'!CO21+'Ej_Flujo'!CO22+'Ej_Flujo'!DB13+'Ej_Flujo'!DB19+'Ej_Flujo'!DB21+'Ej_Flujo'!DB22+'Ej_Flujo'!DO13+'Ej_Flujo'!DO19+'Ej_Flujo'!DO21+'Ej_Flujo'!DO22+'Ej_Flujo'!EB13+'Ej_Flujo'!EB19+'Ej_Flujo'!EB21+'Ej_Flujo'!EB22)-(SUM('Costos'!F7:M16)+SUM('Costos'!F20:M27)),2) -> -1617237.6 | F32: 0 | G32: =IF(ABS(E32)<1,"OK","REVISAR") -> REVISAR | H32: B8: vincular Ej_Flujo filas 13, 19, 21 y 22 de 2028-2035 a la hoja Costos (hoy son valores pegados).
C34: Resumen de controles | D34: =COUNTIF(G7:G32,"OK")&" de "&ROWS(G7:G32)&" en OK" -> 18 de 26 en OK | E34: Con el libro tal como llegó (09/06/2026) hay 8 controles en REVISAR: el 9, 11, 12, 17, 21, 22 y 26 se corrigen en la fase B (verificado: después de B1-B8 quedan 25 de 26 en OK); el 13 (caja) se corrige en E3 y E5, y empeora con la fase B.
B36: 2. INDICADORES PARA EL POWERPOINT (tablas y textos)
B37: # | C37: Dato | D37: Celda o cálculo de origen | E37: Libro (vivo) | F37: PPT jun-2026 | G37: Diferencia | H37: Diapositivas y observaciones
B38: 1 | C38: Inversión total (USD) | D38: Inversión!C7 | E38: ='Inversión'!C7 -> 5074594 | F38: 5074594 | G38: =IF(ISNUMBER(E38),E38-F38,"") -> 0 | H38: Diap. 3. Igual en plan y actualizado.
B39: 2 | C39: VAN con financiamiento (USD) | D39: VAN-TIR!C24 | E39: ='VAN-TIR'!C24 -> 2844947.8 | F39: 2844948 | G39: =IF(ISNUMBER(E39),E39-F39,"") -> -0.24030234 | H39: Diap. 2, 3, 9 y 13.
B40: 3 | C40: TIR con financiamiento | D40: VAN-TIR!C23 | E40: ='VAN-TIR'!C23 -> 0.14915446 | F40: 0.149 | G40: =IF(ISNUMBER(E40),E40-F40,"") -> 0.00015445575 | H40: Diap. 2, 3, 9 y 13. Mostrar con 1 decimal (14,9%).
B41: 4 | C41: WACC | D41: VAN-TIR!C22 | E41: ='VAN-TIR'!C22 -> 0.098741428 | F41: 0.0987 | G41: =IF(ISNUMBER(E41),E41-F41,"") -> 4.1428378e-05 | H41: Diap. 3, 9 y 13. No cambia si no cambia el financiamiento.
B42: 5 | C42: Spread TIR − WACC (puntos porcentuales) | D42: VAN-TIR!C23 − C22 | E42: ='VAN-TIR'!C23-'VAN-TIR'!C22 -> 0.050413027 | F42: 0.05 | G42: =IF(ISNUMBER(E42),E42-F42,"") -> 0.00041302737 | H42: Diap. 9 y 13 («5,0 pp»). Plan: 5,3 pp.
B43: 6 | C43: VAN actualizado − VAN plan (USD) | D43: VAN-TIR!C24 − VAN plan (sección 4) | E43: ='VAN-TIR'!C24-E103 -> 1419.7597 | F43: 1400 | G43: =IF(ISNUMBER(E43),E43-F43,"") -> 19.759698 | H43: Diap. 9 («Mejora VAN +USD 1,4K»).
B44: 7 | C44: VAN actualizado vs plan (%) | D44: VAN-TIR!C24 / VAN plan − 1 | E44: ='VAN-TIR'!C24/E103-1 -> 0.00049929514 | F44: 0.0005 | G44: =IF(ISNUMBER(E44),E44-F44,"") -> -7.0486464e-07 | H44: Diap. 2, 3, 9 y 13 («+0,05%»).
B45: 8 | C45: TIR actualizada − TIR plan (pp) | D45: VAN-TIR!C23 − TIR plan (sección 4) | E45: ='VAN-TIR'!C23-E104 -> -0.0027455443 | F45: -0.0029 | G45: =IF(ISNUMBER(E45),E45-F45,"") -> 0.00015445575 | H45: Diap. 3, 9 y 13. Hoy −0,27 pp (el PPT dice −0,29).
B46: 9 | C46: Producción año 1 (Tn) | D46: Producción!D28 | E46: ='Producción'!D28 -> 4315.166 | F46: 4315 | G46: =IF(ISNUMBER(E46),E46-F46,"") -> 0.166 | H46: Diap. 2 y 4. Es real hasta el corte + proyección: rotularlo así.
B47: 10 | C47: Producción año 1 / plan | D47: Ej_Producción!P33 | E47: ='Ej_Producción'!P33 -> 0.38920952 | F47: 0.39 | G47: =IF(ISNUMBER(E47),E47-F47,"") -> -0.00079047533 | H47: Diap. 2 y 4 («39% del Plan»; la diap. 4 dice además «61% inferior al Plan» = 1 − este valor).
B48: 11 | C48: Utilidad neta año 1 (USD) | D48: Resultados!C14 | E48: ='Resultados'!C14 -> -334777.75 | F48: -335000 | G48: =IF(ISNUMBER(E48),E48-F48,"") -> 222.24714 | H48: Diap. 7 y 13 («pérdida de USD 335K»).
B49: 12 | C49: Producción acumulada 10 años (Tn) | D49: SUMA(Producción!D28:M28) | E49: =SUM('Producción'!D28:M28) -> 161292.17 | F49: 161000 | G49: =IF(ISNUMBER(E49),E49-F49,"") -> 292.166 | H49: Diap. 3 y 4.
B50: 13 | C50: Producción acumulada vs plan | D50: Acumulado / rótulo plan del PPT (150K Tn) − 1 | E50: =O81/E107-1 -> 0.075281107 | F50: 0.07 | G50: =IF(ISNUMBER(E50),E50-F50,"") -> 0.0052811067 | H50: Diap. 3, 4 y 13. Hoy +7,5% (el PPT dice +7%). Contra la suma de la serie plan del gráfico (149.875 Tn) daría +7,6%: ver sección 4.
B51: 14 | C51: Ingresos acumulados 10 años (USD) | D51: SUMA(Ingresos!D28:M28) | E51: =SUM('Ingresos'!D28:M28) -> 2.1564095e+08 | F51: 217000000 | G51: =IF(ISNUMBER(E51),E51-F51,"") -> -1359046.6 | H51: Diap. 3 y 5. El PPT de junio dice 217M; el libro da 215,6M.
B52: 15 | C52: Ingresos acumulados vs plan | D52: Acumulado / rótulo plan del PPT (USD 180M) − 1 | E52: =O84/E108-1 -> 0.1980053 | F52: 0.21 | G52: =IF(ISNUMBER(E52),E52-F52,"") -> -0.011994703 | H52: Diap. 3, 5, 9 y 13. Hoy +19,8% (el PPT dice +21%). Contra la serie plan del gráfico (179,2M) daría +20,3%.
B53: 16 | C53: EBITDA acumulado 10 años (USD) | D53: SUMA(Resultados!C9:L9) | E53: =SUM('Resultados'!C9:L9) -> 25409764 | F53: 26400000 | G53: =IF(ISNUMBER(E53),E53-F53,"") -> -990236.38 | H53: Diap. 3, 7 y 13. El PPT de junio dice 26,4M; el libro da 25,4M.
B54: 17 | C54: EBITDA acumulado vs plan | D54: Acumulado / rótulo plan del PPT (USD 21,1M) − 1 | E54: =O88/E109-1 -> 0.2042542 | F54: 0.25 | G54: =IF(ISNUMBER(E54),E54-F54,"") -> -0.0457458 | H54: Diap. 3, 7, 9 y 13. Hoy +20,4% (el PPT dice +25%). Contra la serie plan del gráfico (21,6M) daría +17,5%: ver sección 4.
B55: 18 | C55: Utilidad neta acumulada 10 años (USD) | D55: SUMA(Resultados!C14:L14) | E55: =SUM('Resultados'!C14:L14) -> 18029154 | F55: 19600000 | G55: =IF(ISNUMBER(E55),E55-F55,"") -> -1570845.9 | H55: Diap. 3. El PPT de junio dice 19,6M; el libro da 18,0M.
B56: 19 | C56: Utilidad neta acumulada vs plan (base 17,8M) | D56: Acumulado / 17,8M − 1 | E56: =O90/E110-1 -> 0.012873828 | F56: 0.1 | G56: =IF(ISNUMBER(E56),E56-F56,"") -> -0.087126172 | H56: Diap. 3. Hoy +1,3% (el PPT dice +10%). No hay serie anual del plan.
B57: 20 | C57: Materia prima acumulada 10 años (USD) | D57: SUMA(Costos!D6:M6) | E57: =SUM('Costos'!D6:M6) -> 1.8109407e+08 | F57: 183000000 | G57: =IF(ISNUMBER(E57),E57-F57,"") -> -1905934.2 | H57: Diap. 6. El PPT dice 183M; el libro da 181,1M.
B58: 21 | C58: Materia prima año 2 (USD) | D58: Costos!E6 | E58: ='Costos'!E6 -> 14101734 | F58: 14100000 | G58: =IF(ISNUMBER(E58),E58-F58,"") -> 1733.5882 | H58: Diap. 6 («14,1M»). Plan año 2 = Ej_Costos!AE22 (11,1M).
B59: 22 | C59: Materia prima / costo de producción año 2 | D59: Costos!E6 / Costos!E17 | E59: ='Costos'!E6/'Costos'!E17 -> 0.96138319 | F59: 0.961 | G59: =IF(ISNUMBER(E59),E59-F59,"") -> 0.00038318863 | H59: Diap. 6 (tabla «96.1%» y texto «>96% de los costos variables»), 11 y 13 («>96% de costos variables»). Plan en el libro: Ej_Costos!AE22/AE44 = 96,45% (el PPT dice 95,3%).
B60: 23 | C60: Desvío costo MP/Tn año 2 vs plan — mínimo | D60: MÍN(Ej_Costos!AF9:AF11; AF13:AF19) | E60: =MIN('Ej_Costos'!AF9:AF11,'Ej_Costos'!AF13:AF19) -> 0.026610462 | F60: 0.06 | G60: =IF(ISNUMBER(E60),E60-F60,"") -> -0.033389538 | H60: Diap. 2, 6, 11 y 13 («6-16%»). Hoy 2,7% (Accesorios); sin Accesorios 5,9%.
B61: 24 | C61: Desvío costo MP/Tn año 2 vs plan — máximo | D61: MÁX(Ej_Costos!AF9:AF11; AF13:AF19) | E61: =MAX('Ej_Costos'!AF9:AF11,'Ej_Costos'!AF13:AF19) -> 0.15778068 | F61: 0.16 | G61: =IF(ISNUMBER(E61),E61-F61,"") -> -0.002219321 | H61: Idem. El producto 4 (AF12) no tiene plan.
B62: 25 | C62: Precio promedio año 2 (USD/Tn) | D62: Ingresos!E29 | E62: ='Ingresos'!E29 -> 1219.2023 | F62: 1219 | G62: =IF(ISNUMBER(E62),E62-F62,"") -> 0.20231823 | H62: Diap. 5.
B63: 26 | C63: Precio promedio plan año 2 (USD/Tn) | D63: Ej_Ingresos!AE34 / Ej_Producción!AE48 | E63: ='Ej_Ingresos'!AE34/'Ej_Producción'!AE48 -> 1096.3244 | F63: 1096 | G63: =IF(ISNUMBER(E63),E63-F63,"") -> 0.32443333 | H63: Diap. 5. Es plan: no debería cambiar.
B64: 27 | C64: Precio Accesorios Metálicos año 2 (USD/Tn) | D64: Ingresos!E26 | E64: ='Ingresos'!E26 -> 5202 | F64: 5202 | G64: =IF(ISNUMBER(E64),E64-F64,"") -> 0 | H64: Diap. 5.
B65: 28 | C65: Capital de trabajo neto año 1 (USD) | D65: Capital Trabajo!C18 | E65: ='Capital Trabajo'!C18 -> 1541094.4 | F65: 1540000 | G65: =IF(ISNUMBER(E65),E65-F65,"") -> 1094.4313 | H65: Diap. 8.
B66: 29 | C66: Capital de trabajo neto año 2 (USD) | D66: Capital Trabajo!D18 | E66: ='Capital Trabajo'!D18 -> 6115600.3 | F66: 6120000 | G66: =IF(ISNUMBER(E66),E66-F66,"") -> -4399.6968 | H66: Diap. 8.
B67: 30 | C67: Capital de trabajo neto año 10 (USD) | D67: Capital Trabajo!L18 | E67: ='Capital Trabajo'!L18 -> 10928041 | F67: 10930000 | G67: =IF(ISNUMBER(E67),E67-F67,"") -> -1959.4196 | H67: Diap. 8.
B68: 31 | C68: Ventas a crédito año 2 (USD) | D68: Capital Trabajo!D9 | E68: ='Capital Trabajo'!D9 -> 4279400.1 | F68: 4280000 | G68: =IF(ISNUMBER(E68),E68-F68,"") -> -599.86301 | H68: Diap. 8 y 13 («USD 4-7M adicionales»).
B69: 32 | C69: Cuentas por cobrar año 10 (USD) | D69: Capital Trabajo!L9 | E69: ='Capital Trabajo'!L9 -> 7509783.1 | F69: 7500000 | G69: =IF(ISNUMBER(E69),E69-F69,"") -> 9783.1483 | H69: Diap. 8 y 13.
B70: 33 | C70: Préstamos CP por año, años 2-10 — mínimo (USD) | D70: MÍN de la serie «Préstamos CP» (sección 3) | E70: =MIN(F95:N95) -> 4000000 | F70: 5000000 | G70: =IF(ISNUMBER(E70),E70-F70,"") -> -1000000 | H70: Diap. 8 («USD 5-11.9M/año»), 11 y 13 («USD 5-12M/año»); el máximo también va en la diap. 2 («hasta USD 11.9M/año»). Hoy el año 7 es 4,0M.
B71: 34 | C71: Préstamos CP por año, años 2-10 — máximo (USD) | D71: MÁX de la serie «Préstamos CP» (sección 3) | E71: =MAX(F95:N95) -> 11900000 | F71: 11900000 | G71: =IF(ISNUMBER(E71),E71-F71,"") -> 0 | H71: Idem.
B72: 35 | C72: Margen de seguridad años 2-10 — mínimo | D72: MÍN de la serie «Margen de seguridad» (sección 3) | E72: =MIN(F94:N94) -> 0.5039955 | F72: 0.52 | G72: =IF(ISNUMBER(E72),E72-F72,"") -> -0.016004503 | H72: Diap. 10 («52-69%»). Hoy el año 3 da 50,4%.
B73: 36 | C73: Margen de seguridad años 2-10 — máximo | D73: MÁX de la serie «Margen de seguridad» (sección 3) | E73: =MAX(F94:N94) -> 0.69313209 | F73: 0.69 | G73: =IF(ISNUMBER(E73),E73-F73,"") -> 0.0031320917 | H73: Idem.
B74: 37 | C74: Concentración Slitter DW 0,43/0,48 (año 2, % de Tn) | D74: Producción!E8 / Producción!E28 | E74: ='Producción'!E8/'Producción'!E28 -> 0.33508957 | F74: 0.33 | G74: =IF(ISNUMBER(E74),E74-F74,"") -> 0.005089568 | H74: Diap. 11.
B75: 38 | C75: Payback inversión propia (años, calculado) | D75: Payback filas 6-7 (dividendos descontados a Ke) | E75: =IFERROR(COUNTIF('Payback'!D7:M7,"<0")+(-INDEX('Payback'!C7:M7,COUNTIF('Payback'!C7:M7,"<0")))/INDEX('Payback'!C6:M6,COUNTIF('Payback'!C7:M7,"<0")+1),"No recupera en 10 años") -> 6.3809271 | F75: 6 | G75: =IF(ISNUMBER(E75),E75-F75,"") -> 0.38092713 | H75: Diap. 9 («Actual: 6 Años»). Se recupera durante el año 7 (6,4 años).
B76: 39 | C76: Payback inversión total (años, calculado) | D76: Payback filas 11-12 (flujo sin financiamiento a Ke) | E76: =IFERROR(COUNTIF('Payback'!D12:M12,"<0")+(-INDEX('Payback'!C12:M12,COUNTIF('Payback'!C12:M12,"<0")))/INDEX('Payback'!C11:M11,COUNTIF('Payback'!C12:M12,"<0")+1),"No recupera en 10 años") -> 5.0244278 | H76: No está en el PPT. Hoy 5,0 por el error de exponentes; corregido (paso B6) ≈ 8,1.
B77: 40 | C77: Payback tipeado en el Dashboard | D77: Dashboard!C12 (texto) | E77: ='Dashboard'!C12 -> 4 Años | H77: Hoy «4 Años» en INFORME2 («6 Años» en ORIGINAL). Reemplazar por fórmula (paso B7).
B79: 3. SERIES ANUALES PARA LOS GRÁFICOS (copiar E:N de la fila «Actualizado»; en el PPT: Editar datos > primera celda de la serie > Pegado especial > Valores + Transponer; ver paso G1)
B80: # | C80: Serie | D80: Origen | E80: Año 1 2026 | F80: Año 2 2027 | G80: Año 3 2028 | H80: Año 4 2029 | I80: Año 5 2030 | J80: Año 6 2031 | K80: Año 7 2032 | L80: Año 8 2033 | M80: Año 9 2034 | N80: Año 10 2035 | O80: Total 10 años
B81: 1 | C81: Producción (Tn) — Actualizado | D81: Producción!D28:M28 | E81: ='Producción'!D28 -> 4315.166 | F81: ='Producción'!E28 -> 14235 | G81: ='Producción'!F28 -> 14950 | H81: ='Producción'!G28 -> 15698 | I81: ='Producción'!H28 -> 16482 | J81: ='Producción'!I28 -> 17306 | K81: ='Producción'!J28 -> 18170 | L81: ='Producción'!K28 -> 19076 | ... N81: ='Producción'!M28 -> 21030 | O81: =SUM(E81:N81) -> 161292.17
B82: 2 | C82: Producción (Tn) — Plan original | D82: PPT jun-2026 (fijo) | E82: 11087 | F82: 12587 | G82: 13216 | H82: 13876 | I82: 14570 | J82: 15299 | K82: 16065 | L82: 16868 | M82: 17711 | N82: 18596 | O82: =SUM(E82:N82) -> 149875
B83: 3 | C83: Ventas (Tn) — Actualizado | D83: Producción!D29:M29 | E83: ='Producción'!D29 -> 4195.166 | F83: ='Producción'!E29 -> 14235 | G83: ='Producción'!F29 -> 14726 | H83: ='Producción'!G29 -> 15464 | I83: ='Producción'!H29 -> 16235 | J83: ='Producción'!I29 -> 17046 | K83: ='Producción'!J29 -> 17897 | L83: ='Producción'!K29 -> 18789 | ... N83: ='Producción'!M29 -> 20713 | O83: =SUM(E83:N83) -> 159028.17
B84: 4 | C84: Ingresos (USD) — Actualizado | D84: Ingresos!D28:M28 | E84: ='Ingresos'!D28 -> 4208607.2 | F84: ='Ingresos'!E28 -> 17355345 | G84: ='Ingresos'!F28 -> 18854496 | H84: ='Ingresos'!G28 -> 20195139 | I84: ='Ingresos'!H28 -> 21621692 | J84: ='Ingresos'!I28 -> 23156433 | K84: ='Ingresos'!J28 -> 24800444 | L84: ='Ingresos'!K28 -> 26553500 | ... N84: ='Ingresos'!M28 -> 30456343 | O84: =SUM(E84:N84) -> 2.1564095e+08
B85: 5 | C85: Ingresos (USD) — Plan original | D85: PPT jun-2026 (fijo) | E85: 10820400 | F85: 13591134 | G85: 14986567 | H85: 16104783 | I85: 17250523 | J85: 18474024 | K85: 19789483 | L85: 21195174 | M85: 22699886 | N85: 24308765 | O85: =SUM(E85:N85) -> 179220739
B86: 6 | C86: Costos de producción (USD) — Actualizado | D86: Resultados!C6:L6 | E86: ='Resultados'!C6 -> 4032136.4 | F86: ='Resultados'!D6 -> 14668172 | G86: ='Resultados'!E6 -> 15861608 | H86: ='Resultados'!F6 -> 17138115 | I86: ='Resultados'!G6 -> 18516473 | J86: ='Resultados'!H6 -> 20007681 | K86: ='Resultados'!I6 -> 21618460 | L86: ='Resultados'!J6 -> 23358575 | ... N86: ='Resultados'!L6 -> 27278715 | O86: =SUM(E86:N86) -> 1.8772323e+08
B87: 7 | C87: Costos de producción (USD) — Plan original | D87: PPT jun-2026 (fijo) | E87: 9852158 | F87: 11621795 | G87: 12557052 | H87: 13563820 | I87: 14652622 | J87: 15829707 | K87: 17102792 | L87: 18477528 | M87: 19963439 | N87: 21569494 | O87: =SUM(E87:N87) -> 155190407
B88: 8 | C88: EBITDA (USD) — Actualizado | D88: Resultados!C9:L9 | E88: ='Resultados'!C9 -> -23859.586 | F88: ='Resultados'!D9 -> 2449376.1 | G88: ='Resultados'!E9 -> 2750225.2 | H88: ='Resultados'!F9 -> 2810091.9 | I88: ='Resultados'!G9 -> 2853865.5 | J88: ='Resultados'!H9 -> 2892816.5 | K88: ='Resultados'!I9 -> 2921302.6 | L88: ='Resultados'!J9 -> 2929326.8 | ... N88: ='Resultados'!L9 -> 2901653.1 | O88: =SUM(E88:N88) -> 25409764
B89: 9 | C89: EBITDA (USD) — Plan original | D89: PPT jun-2026 (fijo) | E89: 732980 | F89: 1734077 | G89: 2192768 | H89: 2302686 | I89: 2358049 | J89: 2402842 | K89: 2443544 | L89: 2472777 | M89: 2489805 | N89: 2490803 | O89: =SUM(E89:N89) -> 21620331
B90: 10 | C90: Utilidad neta (USD) — Actualizado | D90: Resultados!C14:L14 | E90: ='Resultados'!C14 -> -334777.75 | F90: ='Resultados'!D14 -> 1480799.4 | G90: ='Resultados'!E14 -> 1582364.2 | H90: ='Resultados'!F14 -> 1957769.2 | I90: ='Resultados'!G14 -> 2059600.4 | J90: ='Resultados'!H14 -> 2108638.1 | K90: ='Resultados'!I14 -> 2403682.9 | L90: ='Resultados'!J14 -> 2348149.2 | ... N90: ='Resultados'!L14 -> 2140077.2 | O90: =SUM(E90:N90) -> 18029154
B91: 11 | C91: Margen EBITDA — Actualizado | D91: EBITDA / Ingresos | E91: =IF('Ingresos'!D28=0,0,'Resultados'!C9/'Ingresos'!D28) -> -0.0056692355 | F91: =IF('Ingresos'!E28=0,0,'Resultados'!D9/'Ingresos'!E28) -> 0.14113094 | G91: =IF('Ingresos'!F28=0,0,'Resultados'!E9/'Ingresos'!F28) -> 0.14586575 | H91: =IF('Ingresos'!G28=0,0,'Resultados'!F9/'Ingresos'!G28) -> 0.13914694 | I91: =IF('Ingresos'!H28=0,0,'Resultados'!G9/'Ingresos'!H28) -> 0.13199085 | J91: =IF('Ingresos'!I28=0,0,'Resultados'!H9/'Ingresos'!I28) -> 0.12492496 | K91: =IF('Ingresos'!J28=0,0,'Resultados'!I9/'Ingresos'!J28) -> 0.11779235 | L91: =IF('Ingresos'!K28=0,0,'Resultados'!J9/'Ingresos'!K28) -> 0.11031791 | ... N91: =IF('Ingresos'!M28=0,0,'Resultados'!L9/'Ingresos'!M28) -> 0.095272539 | O91: =IF(O84=0,0,O88/O84) -> 0.11783366
B92: 12 | C92: Margen neto — Actualizado | D92: Utilidad neta / Ingresos | E92: =IF('Ingresos'!D28=0,0,'Resultados'!C14/'Ingresos'!D28) -> -0.079545972 | F92: =IF('Ingresos'!E28=0,0,'Resultados'!D14/'Ingresos'!E28) -> 0.085322386 | G92: =IF('Ingresos'!F28=0,0,'Resultados'!E14/'Ingresos'!F28) -> 0.083925031 | H92: =IF('Ingresos'!G28=0,0,'Resultados'!F14/'Ingresos'!G28) -> 0.096942594 | I92: =IF('Ingresos'!H28=0,0,'Resultados'!G14/'Ingresos'!H28) -> 0.095256207 | J92: =IF('Ingresos'!I28=0,0,'Resultados'!H14/'Ingresos'!I28) -> 0.091060575 | K92: =IF('Ingresos'!J28=0,0,'Resultados'!I14/'Ingresos'!J28) -> 0.096920963 | L92: =IF('Ingresos'!K28=0,0,'Resultados'!J14/'Ingresos'!K28) -> 0.088430871 | ... N92: =IF('Ingresos'!M28=0,0,'Resultados'!L14/'Ingresos'!M28) -> 0.070267046 | O92: =IF(O84=0,0,O90/O84) -> 0.083607283
B93: 13 | C93: Punto de equilibrio (Tn) — Actualizado | D93: Pto Equilibrio!C14:L14 | E93: ='Pto Equilibrio'!C14 -> 8239.5151 | F93: ='Pto Equilibrio'!D14 -> 6815.9496 | G93: ='Pto Equilibrio'!E14 -> 7304.1623 | H93: ='Pto Equilibrio'!F14 -> 6201.1965 | I93: ='Pto Equilibrio'!G14 -> 6204.0489 | J93: ='Pto Equilibrio'!H14 -> 6432.6567 | K93: ='Pto Equilibrio'!I14 -> 5492.015 | L93: ='Pto Equilibrio'!J14 -> 6115.2216 | ... N93: ='Pto Equilibrio'!L14 -> 7854.421
B94: 14 | C94: Margen de seguridad — Actualizado | D94: 1 − punto de equilibrio / ventas (Tn) | E94: =IF(E83=0,0,1-E93/E83) -> -0.96404984 | F94: =IF(F83=0,0,1-F93/F83) -> 0.52118373 | G94: =IF(G83=0,0,1-G93/G83) -> 0.5039955 | H94: =IF(H83=0,0,1-H93/H83) -> 0.59899143 | I94: =IF(I83=0,0,1-I93/I83) -> 0.61785963 | J94: =IF(J83=0,0,1-J93/J83) -> 0.62262955 | K94: =IF(K83=0,0,1-K93/K83) -> 0.69313209 | L94: =IF(L83=0,0,1-L93/L83) -> 0.67453182 | ... N94: =IF(N83=0,0,1-N93/N83) -> 0.62079752
B95: 15 | C95: Préstamos CP para chapas (USD/año) | D95: Ej_Flujo!O8, AB8, AO8 … EB8 | E95: ='Ej_Flujo'!O8 -> 0 | F95: ='Ej_Flujo'!AB8 -> 10900000 | G95: ='Ej_Flujo'!AO8 -> 11900000 | H95: ='Ej_Flujo'!BB8 -> 5000000 | I95: ='Ej_Flujo'!BO8 -> 6200000 | J95: ='Ej_Flujo'!CB8 -> 6000000 | K95: ='Ej_Flujo'!CO8 -> 4000000 | L95: ='Ej_Flujo'!DB8 -> 5300000 | M95: ='Ej_Flujo'!DO8 -> 5300000 | N95: ='Ej_Flujo'!EB8 -> 7000000 | O95: =SUM(E95:N95) -> 61600000
B96: 16 | C96: Capital de trabajo neto (USD) | D96: Capital Trabajo!C18:L18 | E96: ='Capital Trabajo'!C18 -> 1541094.4 | F96: ='Capital Trabajo'!D18 -> 6115600.3 | G96: ='Capital Trabajo'!E18 -> 6634952.6 | H96: ='Capital Trabajo'!F18 -> 7125811.4 | I96: ='Capital Trabajo'!G18 -> 7650561.4 | J96: ='Capital Trabajo'!H18 -> 8216141.1 | K96: ='Capital Trabajo'!I18 -> 8823630.5 | L96: ='Capital Trabajo'!J18 -> 9474146.1 | ... N96: ='Capital Trabajo'!L18 -> 10928041
B97: 17 | C97: Cuentas por cobrar (USD) | D97: Capital Trabajo!C9:L9 | E97: ='Capital Trabajo'!C9 -> 1037738.8 | F97: ='Capital Trabajo'!D9 -> 4279400.1 | G97: ='Capital Trabajo'!E9 -> 4649053.8 | H97: ='Capital Trabajo'!F9 -> 4979623.3 | I97: ='Capital Trabajo'!G9 -> 5331376.2 | J97: ='Capital Trabajo'!H9 -> 5709805.4 | K97: ='Capital Trabajo'!I9 -> 6115178 | L97: ='Capital Trabajo'!J9 -> 6547438.5 | ... N97: ='Capital Trabajo'!L9 -> 7509783.1
B98: 18 | C98: Gastos financieros LP + CP (USD) | D98: Resultados!C11:L11 | E98: ='Resultados'!C11 -> 229420.39 | F98: ='Resultados'!D11 -> 699654.62 | G98: ='Resultados'!E11 -> 883947.51 | H98: ='Resultados'!F11 -> 555002.71 | I98: ='Resultados'!G11 -> 482679.62 | J98: ='Resultados'!H11 -> 457245.44 | K98: ='Resultados'!I11 -> 174246.58 | L98: ='Resultados'!J11 -> 220273.97 | ... N98: ='Resultados'!L11 -> 361643.84 | O98: =SUM(E98:N98) -> 4326470.8
B99: 19 | C99: Materia prima (USD) | D99: Costos!D6:M6 | E99: ='Costos'!D6 -> 3876548.2 | F99: ='Costos'!E6 -> 14101734 | G99: ='Costos'!F6 -> 15254336 | H99: ='Costos'!G6 -> 16498217 | I99: ='Costos'!H6 -> 17841772 | J99: ='Costos'!I6 -> 19295791 | K99: ='Costos'!J6 -> 20866848 | L99: ='Costos'!K6 -> 22564513 | ... N99: ='Costos'!M6 -> 26390547 | O99: =SUM(E99:N99) -> 1.8109407e+08
B101: 4. PLAN ORIGINAL — VALORES DE REFERENCIA (fijos; no están en el Excel: vienen del PPT de junio 2026)
B102: # | C102: Dato | D102: Fuente | E102: Valor | F102: Observación
B103: 1 | C103: VAN con financiamiento — plan | D103: PPT «Plan vs Actualizado 10 años», jun-2026 | E103: 2843528 | F103: PPT jun-2026. No está en ningún Excel (plan de negocio original, PDF ene-2026).
B104: 2 | C104: TIR con financiamiento — plan | D104: PPT «Plan vs Actualizado 10 años», jun-2026 | E104: 0.1519 | F104: Idem.
B105: 3 | C105: WACC — plan | D105: PPT «Plan vs Actualizado 10 años», jun-2026 | E105: 0.0987 | F105: Igual al actual (VAN-TIR!C22).
B106: 4 | C106: Payback inversión propia — plan (años) | D106: PPT «Plan vs Actualizado 10 años», jun-2026 | E106: 3 | F106: PPT jun-2026. Sin cálculo de respaldo en el libro.
...

Sheet Ej_Producción
B2: SEGUIMIENTO PRODUCCIÓN AÑO 1 Y 2 — EJECUTADO A ABRIL & PROYECTADO vs PLAN
B3: Producción y Ventas en Toneladas (Tn)
C5: 2026 | R5: 2027
B6: PRODUCCIÓN PROYECTADA MENSUAL
B7: Producto | C7: Ene | D7: Feb | E7: Mar | F7: Abr | G7: May | H7: Jun | I7: Jul | J7: Ago | K7: Sep | L7: Oct | M7: Nov | N7: Dic | O7: TOTAL PROY. | P7: PROY. AÑO 1 | Q7: % vs Anual | R7: Ene | S7: Feb | T7: Mar | U7: Abr | V7: May | W7: Jun | X7: Jul | Y7: Ago | Z7: Sep | AA7: Oct | AB7: Nov | AC7: Dic | AD7: TOTAL PROY. | AE7: PROY. AÑO 2 | AF7: % vs Anual
B8: 1. Slitter Portas Autom. | C8: =+$P$8/12 -> 233.5 | D8: =+$P$8/12 -> 233.5 | E8: =+$P$8/12 -> 233.5 | F8: =+$P$8/12 -> 233.5 | G8: =+$P$8/12 -> 233.5 | H8: =+$P$8/12 -> 233.5 | I8: =+$P$8/12 -> 233.5 | J8: =+$P$8/12 -> 233.5 | ... N8: =+$P$8/12 -> 233.5 | O8: =SUM(C8:N8) -> 2802 | P8: 2802 | Q8: =IF(P8=0,0,O8/P8) -> 1 | R8: =+$AE$8/12 -> 245.16667 | S8: =+$AE$8/12 -> 245.16667 | T8: =+$AE$8/12 -> 245.16667 | U8: =+$AE$8/12 -> 245.16667 | V8: =+$AE$8/12 -> 245.16667 | W8: =+$AE$8/12 -> 245.16667 | X8: =+$AE$8/12 -> 245.16667 | Y8: =+$AE$8/12 -> 245.16667 | ... AC8: =+$AE$8/12 -> 245.16667 | AD8: =SUM(R8:AC8) -> 2942 | AE8: 2942 | AF8: =IF(AE8=0,0,AD8/AE8) -> 1
B9: 2. Slitter Drywall 0,43/0,48 | C9: =+$P$9/12 -> 264 | D9: =+$P$9/12 -> 264 | E9: =+$P$9/12 -> 264 | F9: =+$P$9/12 -> 264 | G9: =+$P$9/12 -> 264 | H9: =+$P$9/12 -> 264 | I9: =+$P$9/12 -> 264 | J9: =+$P$9/12 -> 264 | ... N9: =+$P$9/12 -> 264 | O9: =SUM(C9:N9) -> 3168 | P9: 3168 | Q9: =IF(P9=0,0,O9/P9) -> 1 | R9: =+$AE$9/12 -> 277.16667 | S9: =+$AE$9/12 -> 277.16667 | T9: =+$AE$9/12 -> 277.16667 | U9: =+$AE$9/12 -> 277.16667 | V9: =+$AE$9/12 -> 277.16667 | W9: =+$AE$9/12 -> 277.16667 | X9: =+$AE$9/12 -> 277.16667 | Y9: =+$AE$9/12 -> 277.16667 | ... AC9: =+$AE$9/12 -> 277.16667 | AD9: =SUM(R9:AC9) -> 3326 | AE9: 3326 | AF9: =IF(AE9=0,0,AD9/AE9) -> 1
B10: 3. Slitter Drywall 0,50 | C10: =+$P$10/12 -> 30.416667 | D10: =+$P$10/12 -> 30.416667 | E10: =+$P$10/12 -> 30.416667 | F10: =+$P$10/12 -> 30.416667 | G10: =+$P$10/12 -> 30.416667 | H10: =+$P$10/12 -> 30.416667 | I10: =+$P$10/12 -> 30.416667 | J10: =+$P$10/12 -> 30.416667 | ... N10: =+$P$10/12 -> 30.416667 | O10: =SUM(C10:N10) -> 365 | P10: 365 | Q10: =IF(P10=0,0,O10/P10) -> 1 | R10: =+$AE$10/12 -> 31.916667 | S10: =+$AE$10/12 -> 31.916667 | T10: =+$AE$10/12 -> 31.916667 | U10: =+$AE$10/12 -> 31.916667 | V10: =+$AE$10/12 -> 31.916667 | W10: =+$AE$10/12 -> 31.916667 | X10: =+$AE$10/12 -> 31.916667 | Y10: =+$AE$10/12 -> 31.916667 | ... AC10: =+$AE$10/12 -> 31.916667 | AD10: =SUM(R10:AC10) -> 383 | AE10: 383 | AF10: =IF(AE10=0,0,AD10/AE10) -> 1
B11: 5. Telhas Met. Naturales | C11: =+$P$11/12 -> 142.16667 | D11: =+$P$11/12 -> 142.16667 | E11: =+$P$11/12 -> 142.16667 | F11: =+$P$11/12 -> 142.16667 | G11: =+$P$11/12 -> 142.16667 | H11: =+$P$11/12 -> 142.16667 | I11: =+$P$11/12 -> 142.16667 | J11: =+$P$11/12 -> 142.16667 | ... N11: =+$P$11/12 -> 142.16667 | O11: =SUM(C11:N11) -> 1706 | P11: 1706 | Q11: =IF(P11=0,0,O11/P11) -> 1 | R11: =+$AE$11/12 -> 149.25 | S11: =+$AE$11/12 -> 149.25 | T11: =+$AE$11/12 -> 149.25 | U11: =+$AE$11/12 -> 149.25 | V11: =+$AE$11/12 -> 149.25 | W11: =+$AE$11/12 -> 149.25 | X11: =+$AE$11/12 -> 149.25 | Y11: =+$AE$11/12 -> 149.25 | ... AC11: =+$AE$11/12 -> 149.25 | AD11: =SUM(R11:AC11) -> 1791 | AE11: 1791 | AF11: =IF(AE11=0,0,AD11/AE11) -> 1
B12: 6. Telhas Met. Pre Pintadas | C12: =+$P$12/12 -> 15.25 | D12: =+$P$12/12 -> 15.25 | E12: =+$P$12/12 -> 15.25 | F12: =+$P$12/12 -> 15.25 | G12: =+$P$12/12 -> 15.25 | H12: =+$P$12/12 -> 15.25 | I12: =+$P$12/12 -> 15.25 | J12: =+$P$12/12 -> 15.25 | ... N12: =+$P$12/12 -> 15.25 | O12: =SUM(C12:N12) -> 183 | P12: 183 | Q12: =IF(P12=0,0,O12/P12) -> 1 | R12: =+$AE$12/12 -> 16 | S12: =+$AE$12/12 -> 16 | T12: =+$AE$12/12 -> 16 | U12: =+$AE$12/12 -> 16 | V12: =+$AE$12/12 -> 16 | W12: =+$AE$12/12 -> 16 | X12: =+$AE$12/12 -> 16 | Y12: =+$AE$12/12 -> 16 | ... AC12: =+$AE$12/12 -> 16 | AD12: =SUM(R12:AC12) -> 192 | AE12: 192 | AF12: =IF(AE12=0,0,AD12/AE12) -> 1
B13: 7. Perfil DW 0,43 Prepint. | C13: =+$P$13/12 -> 35.5 | D13: =+$P$13/12 -> 35.5 | E13: =+$P$13/12 -> 35.5 | F13: =+$P$13/12 -> 35.5 | G13: =+$P$13/12 -> 35.5 | H13: =+$P$13/12 -> 35.5 | I13: =+$P$13/12 -> 35.5 | J13: =+$P$13/12 -> 35.5 | ... N13: =+$P$13/12 -> 35.5 | O13: =SUM(C13:N13) -> 426 | P13: 426 | Q13: =IF(P13=0,0,O13/P13) -> 1 | R13: =+$AE$13/12 -> 37.25 | S13: =+$AE$13/12 -> 37.25 | T13: =+$AE$13/12 -> 37.25 | U13: =+$AE$13/12 -> 37.25 | V13: =+$AE$13/12 -> 37.25 | W13: =+$AE$13/12 -> 37.25 | X13: =+$AE$13/12 -> 37.25 | Y13: =+$AE$13/12 -> 37.25 | ... AC13: =+$AE$13/12 -> 37.25 | AD13: =SUM(R13:AC13) -> 447 | AE13: 447 | AF13: =IF(AE13=0,0,AD13/AE13) -> 1
B14: 8. Perfil Drywall 0,50 | C14: =+$P$14/12 -> 60.916667 | D14: =+$P$14/12 -> 60.916667 | E14: =+$P$14/12 -> 60.916667 | F14: =+$P$14/12 -> 60.916667 | G14: =+$P$14/12 -> 60.916667 | H14: =+$P$14/12 -> 60.916667 | I14: =+$P$14/12 -> 60.916667 | J14: =+$P$14/12 -> 60.916667 | ... N14: =+$P$14/12 -> 60.916667 | O14: =SUM(C14:N14) -> 731 | P14: 731 | Q14: =IF(P14=0,0,O14/P14) -> 1 | R14: =+$AE$14/12 -> 64 | S14: =+$AE$14/12 -> 64 | T14: =+$AE$14/12 -> 64 | U14: =+$AE$14/12 -> 64 | V14: =+$AE$14/12 -> 64 | W14: =+$AE$14/12 -> 64 | X14: =+$AE$14/12 -> 64 | Y14: =+$AE$14/12 -> 64 | ... AC14: =+$AE$14/12 -> 64 | AD14: =SUM(R14:AC14) -> 768 | AE14: 768 | AF14: =IF(AE14=0,0,AD14/AE14) -> 1
B15: 9. Perfil Drywall 0,48 | C15: =+$P$15/12 -> 142.16667 | D15: =+$P$15/12 -> 142.16667 | E15: =+$P$15/12 -> 142.16667 | F15: =+$P$15/12 -> 142.16667 | G15: =+$P$15/12 -> 142.16667 | H15: =+$P$15/12 -> 142.16667 | I15: =+$P$15/12 -> 142.16667 | J15: =+$P$15/12 -> 142.16667 | ... N15: =+$P$15/12 -> 142.16667 | O15: =SUM(C15:N15) -> 1706 | P15: 1706 | Q15: =IF(P15=0,0,O15/P15) -> 1 | R15: =+$AE$15/12 -> 149.25 | S15: =+$AE$15/12 -> 149.25 | T15: =+$AE$15/12 -> 149.25 | U15: =+$AE$15/12 -> 149.25 | V15: =+$AE$15/12 -> 149.25 | W15: =+$AE$15/12 -> 149.25 | X15: =+$AE$15/12 -> 149.25 | Y15: =+$AE$15/12 -> 149.25 | ... AC15: =+$AE$15/12 -> 149.25 | AD15: =SUM(R15:AC15) -> 1791 | AE15: 1791 | AF15: =IF(AE15=0,0,AD15/AE15) -> 1
B16: 10. Steel Frame | P16: 0 | R16: =+$AE$16/12 -> 73.833333 | S16: =+$AE$16/12 -> 73.833333 | T16: =+$AE$16/12 -> 73.833333 | U16: =+$AE$16/12 -> 73.833333 | V16: =+$AE$16/12 -> 73.833333 | W16: =+$AE$16/12 -> 73.833333 | X16: =+$AE$16/12 -> 73.833333 | Y16: =+$AE$16/12 -> 73.833333 | ... AC16: =+$AE$16/12 -> 73.833333 | AD16: =SUM(R16:AC16) -> 886 | AE16: 886 | AF16: =IF(AE16=0,0,AD16/AE16) -> 1
B17: 11. Accesorios Metálicos | P17: 0 | R17: =+$AE$17/12 -> 5.0833333 | S17: =+$AE$17/12 -> 5.0833333 | T17: =+$AE$17/12 -> 5.0833333 | U17: =+$AE$17/12 -> 5.0833333 | V17: =+$AE$17/12 -> 5.0833333 | W17: =+$AE$17/12 -> 5.0833333 | X17: =+$AE$17/12 -> 5.0833333 | Y17: =+$AE$17/12 -> 5.0833333 | ... AC17: =+$AE$17/12 -> 5.0833333 | AD17: =SUM(R17:AC17) -> 61 | AE17: 61 | AF17: =IF(AE17=0,0,AD17/AE17) -> 1
B18: TOTAL PRODUCCIÓN PROY. | C18: =SUM(C8:C15) -> 923.91667 | D18: =SUM(D8:D15) -> 923.91667 | E18: =SUM(E8:E15) -> 923.91667 | F18: =SUM(F8:F15) -> 923.91667 | G18: =SUM(G8:G15) -> 923.91667 | H18: =SUM(H8:H15) -> 923.91667 | I18: =SUM(I8:I15) -> 923.91667 | J18: =SUM(J8:J15) -> 923.91667 | ... N18: =SUM(N8:N15) -> 923.91667 | O18: =SUM(O8:O17) -> 11087 | P18: =SUM(P8:P17) -> 11087 | R18: =SUM(R8:R17) -> 1048.9167 | S18: =SUM(S8:S17) -> 1048.9167 | T18: =SUM(T8:T17) -> 1048.9167 | U18: =SUM(U8:U17) -> 1048.9167 | V18: =SUM(V8:V17) -> 1048.9167 | W18: =SUM(W8:W17) -> 1048.9167 | X18: =SUM(X8:X17) -> 1048.9167 | Y18: =SUM(Y8:Y17) -> 1048.9167 | ... AE18: =SUM(AE8:AE17) -> 12587
B20: PRODUCCIÓN EJECUTADA Y PROYEC. MENSUAL
B21: Producto | C21: Ene | D21: Feb | E21: Mar | F21: Abr | G21: May | H21: Jun | I21: Jul | J21: Ago | K21: Sep | L21: Oct | M21: Nov | N21: Dic | O21: TOTAL EJEC. | P21: % Avance vs Proy. | Q21: Desvío (Tn) | R21: Ene | S21: Feb | T21: Mar | U21: Abr | V21: May | W21: Jun | X21: Jul | Y21: Ago | Z21: Sep | AA21: Oct | AB21: Nov | AC21: Dic | AD21: TOTAL EJEC. | AE21: % Avance vs Proy. | AF21: Desvío (Tn)
B22: 1. Slitter Portas Autom. | C22: 29.7 | D22: 0 | E22: 22.335 | F22: 59.945 | G22: 14 | H22: 46 | I22: 90 | J22: 90 | K22: 90 | L22: 90 | M22: 90 | N22: 90 | O22: =SUM(C22:N22) -> 711.98 | P22: =IF(O8=0,0,O22/O8) -> 0.25409707 | Q22: =O22-O8 -> -2090.02 | R22: 30 | S22: 60 | T22: 90 | U22: 90 | V22: 90 | W22: 90 | X22: 90 | Y22: 90 | Z22: 90 | AA22: 90 | AB22: 90 | AC22: 90 | AD22: =SUM(R22:AC22) -> 990 | AE22: =IF(AD8=0,0,AD22/AD8) -> 0.33650578 | AF22: =AD22-AD8 -> -1952
B23: 2. Slitter Drywall 0,43/0,48 | C23: 0 | D23: 0 | E23: 121.97 | F23: 134.773 | G23: 350.47 | H23: 348.832 | I23: 110 | J23: 50 | K23: 0 | L23: 150 | M23: 300 | N23: 240 | O23: =SUM(C23:N23) -> 1806.045 | P23: =IF(O9=0,0,O23/O9) -> 0.57008996 | Q23: =O23-O9 -> -1361.955 | R23: 300 | S23: 300 | T23: 390 | U23: 420 | V23: 420 | W23: 420 | X23: 420 | Y23: 420 | Z23: 420 | AA23: 420 | AB23: 420 | AC23: 420 | AD23: =SUM(R23:AC23) -> 4770 | AE23: =IF(AD9=0,0,AD23/AD9) -> 1.4341551 | AF23: =AD23-AD9 -> 1444
B24: 3. Slitter Drywall 0,50 | C24: 0 | D24: 0 | E24: 5.16 | F24: 14.688 | G24: 59.125 | H24: 10.168 | I24: 70 | J24: 50 | K24: 50 | L24: 30 | M24: 60 | N24: 60 | O24: =SUM(C24:N24) -> 409.141 | P24: =IF(O10=0,0,O24/O10) -> 1.1209342 | Q24: =O24-O10 -> 44.141 | R24: 90 | S24: 90 | T24: 120 | U24: 150 | V24: 150 | W24: 150 | X24: 150 | Y24: 150 | Z24: 150 | AA24: 150 | AB24: 150 | AC24: 150 | AD24: =SUM(R24:AC24) -> 1650 | AE24: =IF(AD10=0,0,AD24/AD10) -> 4.308094 | AF24: =AD24-AD10 -> 1267
B25: 4. Slitter Steel Frame 0,80/0,95 | C25: 0 | D25: 0 | E25: 0 | F25: 0 | G25: 0 | H25: 0 | I25: 0 | J25: 0 | K25: 30 | L25: 180 | M25: 150 | N25: 120 | O25: =SUM(C25:N25) -> 480 | P25: =IF(O19=0,0,O25/O19) -> 0 | Q25: =O25-O19 -> 480 | R25: 90 | S25: 90 | T25: 120 | U25: 150 | V25: 150 | W25: 150 | X25: 150 | Y25: 150 | Z25: 150 | AA25: 150 | AB25: 150 | AC25: 150 | AD25: =SUM(R25:AC25) -> 1650 | AE25: =IF(AD19=0,0,AD25/AD19) -> 0 | AF25: =AD25-AD19 -> 1650
B26: 5. Telhas Met. Naturales | C26: 0 | D26: 0 | E26: 0 | F26: 0 | G26: 0 | H26: 0 | I26: 0 | J26: 60 | K26: 60 | L26: 60 | M26: 30 | N26: 30 | O26: =SUM(C26:N26) -> 240 | P26: =IF(O11=0,0,O26/O11) -> 0.14067995 | Q26: =O26-O11 -> -1466 | R26: 30 | S26: 30 | T26: 60 | U26: 60 | V26: 60 | W26: 60 | X26: 60 | Y26: 60 | Z26: 60 | AA26: 60 | AB26: 60 | AC26: 60 | AD26: =SUM(R26:AC26) -> 660 | AE26: =IF(AD11=0,0,AD26/AD11) -> 0.36850921 | AF26: =AD26-AD11 -> -1131
B27: 6. Telhas Met. Pre Pintadas | C27: 0 | D27: 0 | E27: 0 | F27: 0 | G27: 8 | H27: 0 | I27: 0 | J27: 30 | K27: 30 | L27: 30 | M27: 30 | N27: 30 | O27: =SUM(C27:N27) -> 158 | P27: =IF(O12=0,0,O27/O12) -> 0.86338798 | Q27: =O27-O12 -> -25 | R27: 0 | S27: 30 | T27: 30 | U27: 30 | V27: 30 | W27: 30 | X27: 30 | Y27: 30 | Z27: 30 | AA27: 30 | AB27: 30 | AC27: 30 | AD27: =SUM(R27:AC27) -> 330 | AE27: =IF(AD12=0,0,AD27/AD12) -> 1.71875 | AF27: =AD27-AD12 -> 138
B28: 7. Perfil DW 0,43 Prepint. | C28: 0 | D28: 0 | E28: 0 | F28: 0 | G28: 0 | H28: 0 | I28: 0 | J28: 0 | K28: 30 | L28: 30 | M28: 30 | N28: 30 | O28: =SUM(C28:N28) -> 120 | P28: =IF(O13=0,0,O28/O13) -> 0.28169014 | Q28: =O28-O13 -> -306 | R28: 30 | S28: 30 | T28: 45 | U28: 60 | V28: 60 | W28: 60 | X28: 60 | Y28: 60 | Z28: 60 | AA28: 60 | AB28: 60 | AC28: 60 | AD28: =SUM(R28:AC28) -> 645 | AE28: =IF(AD13=0,0,AD28/AD13) -> 1.442953 | AF28: =AD28-AD13 -> 198
B29: 8. Perfil Drywall 0,50 | C29: 0 | D29: 0 | E29: 0 | F29: 0 | G29: 6 | H29: 0 | I29: 0 | J29: 0 | K29: 0 | L29: 54 | M29: 30 | N29: 30 | O29: =SUM(C29:N29) -> 120 | P29: =IF(O14=0,0,O29/O14) -> 0.16415869 | Q29: =O29-O14 -> -611 | R29: 30 | S29: 30 | T29: 60 | U29: 60 | V29: 60 | W29: 60 | X29: 60 | Y29: 60 | Z29: 60 | AA29: 60 | AB29: 60 | AC29: 60 | AD29: =SUM(R29:AC29) -> 660 | AE29: =IF(AD14=0,0,AD29/AD14) -> 0.859375 | AF29: =AD29-AD14 -> -108
B30: 9. Perfil Drywall 0,48 | C30: 0 | D30: 0 | E30: 0 | F30: 0 | G30: 74 | H30: 0 | I30: 0 | J30: 0 | K30: 0 | L30: 16 | M30: 120 | N30: 60 | O30: =SUM(C30:N30) -> 270 | P30: =IF(O15=0,0,O30/O15) -> 0.15826495 | Q30: =O30-O15 -> -1436 | R30: 90 | S30: 90 | T30: 120 | U30: 120 | V30: 150 | W30: 150 | X30: 150 | Y30: 150 | Z30: 150 | AA30: 150 | AB30: 150 | AC30: 150 | AD30: =SUM(R30:AC30) -> 1620 | AE30: =IF(AD15=0,0,AD30/AD15) -> 0.90452261 | AF30: =AD30-AD15 -> -171
B31: 10. Steel Frame | R31: 30 | S31: 60 | T31: 60 | U31: 60 | V31: 90 | W31: 90 | X31: 90 | Y31: 90 | Z31: 90 | AA31: 90 | AB31: 90 | AC31: 90 | AD31: =SUM(R31:AC31) -> 930 | AE31: =IF(AD16=0,0,AD31/AD16) -> 1.0496614 | AF31: =AD31-AD16 -> 44
B32: 11. Accesorios Metálicos | R32: 15 | S32: 15 | T32: 30 | U32: 30 | V32: 30 | W32: 30 | X32: 30 | Y32: 30 | Z32: 30 | AA32: 30 | AB32: 30 | AC32: 30 | AD32: =SUM(R32:AC32) -> 330 | AE32: =IF(AD17=0,0,AD32/AD17) -> 5.4098361 | AF32: =AD32-AD17 -> 269
B33: TOTAL PRODUCCIÓN EJEC. | C33: =SUM(C22:C32) -> 29.7 | D33: =SUM(D22:D32) -> 0 | E33: =SUM(E22:E32) -> 149.465 | F33: =SUM(F22:F32) -> 209.406 | G33: =SUM(G22:G32) -> 511.595 | H33: =SUM(H22:H32) -> 405 | I33: =SUM(I22:I32) -> 270 | J33: =SUM(J22:J32) -> 280 | ... O33: =SUM(O22:O32) -> 4315.166 | P33: =+O33/O18 -> 0.38920952 | Q33: =SUM(Q22:Q32) -> -6771.834 | R33: =SUM(R22:R32) -> 735 | S33: =SUM(S22:S32) -> 825 | T33: =SUM(T22:T32) -> 1125 | U33: =SUM(U22:U32) -> 1230 | V33: =SUM(V22:V32) -> 1290 | W33: =SUM(W22:W32) -> 1290 | X33: =SUM(X22:X32) -> 1290 | ... AD33: =SUM(AD22:AD32) -> 14235 | AE33: =+AD33/AD18 -> 1.1309287 | AF33: =SUM(AF22:AF32) -> 1648
C34: =+C33/$O$33 -> 0.0068827016 | D34: =+D33/$O$33 -> 0 | E34: =+E33/$O$33 -> 0.034637138 | F34: =+F33/$O$33 -> 0.048527913 | G34: =+G33/$O$33 -> 0.11855743 | H34: =+H33/$O$33 -> 0.093855022 | I34: =+I33/$O$33 -> 0.062570015 | J34: =+J33/$O$33 -> 0.064887423 | ... N34: =+N33/$O$33 -> 0.15990115 | Q34: =+Q33/O18 -> -0.61079048 | R34: =+R33/$AD$33 -> 0.051633298 | S34: =+S33/$AD$33 -> 0.057955743 | T34: =+T33/$AD$33 -> 0.079030558 | U34: =+U33/$AD$33 -> 0.086406744 | V34: =+V33/$AD$33 -> 0.090621707 | W34: =+W33/$AD$33 -> 0.090621707 | X34: =+X33/$AD$33 -> 0.090621707 | Y34: =+Y33/$AD$33 -> 0.090621707 | ... AC34: =+AC33/$AD$33 -> 0.090621707 | AF34: =+AF33/AD18 -> 0.13092874
B35: VENTAS EJECUTADAS Y PROYEC. MENSUAL (Tn)
B36: Producto | C36: Ene | D36: Feb | E36: Mar | F36: Abr | G36: May | H36: Jun | I36: Jul | J36: Ago | K36: Sep | L36: Oct | M36: Nov | N36: Dic | O36: TOTAL VTA EJEC | P36: PROY. VTA AÑO1 | Q36: Desvío (Tn) | R36: Ene | S36: Feb | T36: Mar | U36: Abr | V36: May | W36: Jun | X36: Jul | Y36: Ago | Z36: Sep | AA36: Oct | AB36: Nov | AC36: Dic | AD36: TOTAL VTA EJEC | AE36: PROY. VTA AÑO2 | AF36: Desvío (Tn)
B37: 1. Slitter Portas Autom. | C37: 29.7 | D37: 0 | E37: 22.335 | F37: 59.945 | G37: 0 | H37: 60 | I37: 90 | J37: 90 | K37: 90 | L37: 90 | M37: 90 | N37: 90 | O37: =SUM(C37:N37) -> 711.98 | P37: 2760 | Q37: =O37-P37 -> -2048.02 | R37: 30 | S37: 60 | T37: 90 | U37: 90 | V37: 90 | W37: 90 | X37: 90 | Y37: 90 | Z37: 90 | AA37: 90 | AB37: 90 | AC37: 90 | AD37: =SUM(R37:AC37) -> 990 | AE37: 2898 | AF37: =AD37-AE37 -> -1908
B38: 2. Slitter Drywall 0,43/0,48 | C38: 0 | D38: 0 | E38: 121.97 | F38: 134.773 | G38: 224.47 | H38: 474.832 | I38: 110 | J38: 50 | K38: 0 | L38: 120 | M38: 300 | N38: 210 | O38: =SUM(C38:N38) -> 1746.045 | P38: 3120 | Q38: =O38-P38 -> -1373.955 | R38: 300 | S38: 300 | T38: 390 | U38: 420 | V38: 420 | W38: 420 | X38: 420 | Y38: 420 | Z38: 420 | AA38: 420 | AB38: 420 | AC38: 420 | AD38: =SUM(R38:AC38) -> 4770 | AE38: 3276 | AF38: =AD38-AE38 -> 1494
B39: 3. Slitter Drywall 0,50 | C39: 0 | D39: 0 | E39: 5.16 | F39: 14.688 | G39: 34.125 | H39: 35.168 | I39: 70 | J39: 50 | K39: 50 | L39: 30 | M39: 60 | N39: 30 | O39: =SUM(C39:N39) -> 379.141 | P39: 360 | Q39: =O39-P39 -> 19.141 | R39: 90 | S39: 90 | T39: 120 | U39: 150 | V39: 150 | W39: 150 | X39: 150 | Y39: 150 | Z39: 150 | AA39: 150 | AB39: 150 | AC39: 150 | AD39: =SUM(R39:AC39) -> 1650 | AE39: 377 | AF39: =AD39-AE39 -> 1273
B40: 4. Slitter Steel Frame 0,80/0,95 | C40: 0 | D40: 0 | E40: 0 | F40: 0 | G40: 0 | H40: 0 | I40: 0 | J40: 0 | K40: 30 | L40: 150 | M40: 120 | N40: 150 | O40: =SUM(C40:N40) -> 450 | P40: 0 | Q40: =O40-P40 -> 450 | R40: 90 | S40: 90 | T40: 120 | U40: 150 | V40: 150 | W40: 150 | X40: 150 | Y40: 150 | Z40: 150 | AA40: 150 | AB40: 150 | AC40: 150 | AD40: =SUM(R40:AC40) -> 1650 | AE40: 0 | AF40: =AD40-AE40 -> 1650
B41: 5. Telhas Met. Naturales | C41: 0 | D41: 0 | E41: 0 | F41: 0 | G41: 0 | H41: 0 | I41: 0 | J41: 60 | K41: 60 | L41: 60 | M41: 30 | N41: 30 | O41: =SUM(C41:N41) -> 240 | P41: 1680 | Q41: =O41-P41 -> -1440 | R41: 30 | S41: 30 | T41: 60 | U41: 60 | V41: 60 | W41: 60 | X41: 60 | Y41: 60 | Z41: 60 | AA41: 60 | AB41: 60 | AC41: 60 | AD41: =SUM(R41:AC41) -> 660 | AE41: 1764 | AF41: =AD41-AE41 -> -1104
B42: 6. Telhas Met. Pre Pintadas | C42: 0 | D42: 0 | E42: 0 | F42: 0 | G42: 8 | H42: 0 | I42: 0 | J42: 30 | K42: 30 | L42: 30 | M42: 30 | N42: 30 | O42: =SUM(C42:N42) -> 158 | P42: 180 | Q42: =O42-P42 -> -22 | R42: 0 | S42: 30 | T42: 30 | U42: 30 | V42: 30 | W42: 30 | X42: 30 | Y42: 30 | Z42: 30 | AA42: 30 | AB42: 30 | AC42: 30 | AD42: =SUM(R42:AC42) -> 330 | AE42: 189 | AF42: =AD42-AE42 -> 141
B43: 7. Perfil DW 0,43 Prepint. | C43: 0 | D43: 0 | E43: 0 | F43: 0 | G43: 0 | H43: 0 | I43: 0 | J43: 0 | K43: 30 | L43: 30 | M43: 30 | N43: 30 | O43: =SUM(C43:N43) -> 120 | P43: 420 | Q43: =O43-P43 -> -300 | R43: 30 | S43: 30 | T43: 45 | U43: 60 | V43: 60 | W43: 60 | X43: 60 | Y43: 60 | Z43: 60 | AA43: 60 | AB43: 60 | AC43: 60 | AD43: =SUM(R43:AC43) -> 645 | AE43: 440 | AF43: =AD43-AE43 -> 205
B44: 8. Perfil Drywall 0,50 | C44: 0 | D44: 0 | E44: 0 | F44: 0 | G44: 0 | H44: 0 | I44: 0 | J44: 0 | K44: 0 | L44: 45 | M44: 45 | N44: 30 | O44: =SUM(C44:N44) -> 120 | P44: 720 | Q44: =O44-P44 -> -600 | R44: 30 | S44: 30 | T44: 60 | U44: 60 | V44: 60 | W44: 60 | X44: 60 | Y44: 60 | Z44: 60 | AA44: 60 | AB44: 60 | AC44: 60 | AD44: =SUM(R44:AC44) -> 660 | AE44: 756 | AF44: =AD44-AE44 -> -96
B45: 9. Perfil Drywall 0,48 | C45: 0 | D45: 0 | E45: 0 | F45: 0 | G45: 0 | H45: 0 | I45: 0 | J45: 0 | K45: 0 | L45: 90 | M45: 120 | N45: 60 | O45: =SUM(C45:N45) -> 270 | P45: 1680 | Q45: =O45-P45 -> -1410 | R45: 90 | S45: 90 | T45: 120 | U45: 120 | V45: 150 | W45: 150 | X45: 150 | Y45: 150 | Z45: 150 | AA45: 150 | AB45: 150 | AC45: 150 | AD45: =SUM(R45:AC45) -> 1620 | AE45: 1764 | AF45: =AD45-AE45 -> -144
B46: 10. Steel Frame | R46: 30 | S46: 60 | T46: 60 | U46: 60 | V46: 90 | W46: 90 | X46: 90 | Y46: 90 | Z46: 90 | AA46: 90 | AB46: 90 | AC46: 90 | AD46: =SUM(R46:AC46) -> 930 | AE46: 873 | AF46: =AD46-AE46 -> 57
B47: 11. Accesorios Metálicos | R47: 15 | S47: 15 | T47: 30 | U47: 30 | V47: 30 | W47: 30 | X47: 30 | Y47: 30 | Z47: 30 | AA47: 30 | AB47: 30 | AC47: 30 | AD47: =SUM(R47:AC47) -> 330 | AE47: 60 | AF47: =AD47-AE47 -> 270
B48: TOTAL VENTAS EJEC. | C48: =SUM(C37:C47) -> 29.7 | D48: =SUM(D37:D47) -> 0 | E48: =SUM(E37:E47) -> 149.465 | F48: =SUM(F37:F47) -> 209.406 | G48: =SUM(G37:G47) -> 266.595 | H48: =SUM(H37:H47) -> 570 | I48: =SUM(I37:I47) -> 270 | J48: =SUM(J37:J47) -> 280 | ... AF48: =SUM(AF37:AF47) -> 1838
P49: =+O48/P48 -> 0.38417271 | Q49: =+Q48/P48 -> -0.61582729 | AE49: =+AD48/AE48 -> 1.1482617 | AF49: =+AF48/AE48 -> 0.14826168

Sheet Ej_Ingresos
B2: SEGUIMIENTO INGRESOS AÑO 1 Y 2 — EJECUTADO A ABRIL & PROYECTADO vs PLAN
B3: Valores en USD
C5: 2026 | R5: 2027
B6: PRECIOS REALES DE VENTA (USD/Tn) — EJECUTADO Y PROYECTADO
B7: Producto | C7: Ene | D7: Feb | E7: Mar | F7: Abr | G7: May | H7: Jun | I7: Jul | J7: Ago | K7: Sep | L7: Oct | M7: Nov | N7: Dic | O7: PRECIO PROM EJEC | P7: PRECIO PROY. | Q7: DESVÍO % | R7: Ene | S7: Feb | T7: Mar | U7: Abr | V7: May | W7: Jun | X7: Jul | Y7: Ago | Z7: Sep | AA7: Oct | AB7: Nov | AC7: Dic | AD7: PRECIO PROM P. EJEC | AE7: PRECIO PROY. | AF7: DESVÍO %
B8: 1. Slitter Portas Autom. | C8: 680 | D8: 0 | E8: 660 | F8: 760 | G8: 680 | H8: 858 | I8: 858 | J8: 858 | K8: 858 | L8: 858 | M8: 858 | N8: 858 | O8: =IF(Ej_Producción!O37=0,0,O23/Ej_Producción!O37) -> 836.11239 | P8: 800 | Q8: =IF(P8=0,0,(O8-P8)/P8) -> 0.045140488 | R8: 858 | S8: 858 | T8: 858 | U8: 858 | V8: 858 | W8: 858 | X8: 858 | Y8: 858 | Z8: 858 | AA8: 858 | AB8: 858 | AC8: 858 | AD8: =IF(Ej_Producción!AD37=0,0,AD23/Ej_Producción!AD37) -> 858 | AE8: 840 | AF8: =IF(AE8=0,0,(AD8-AE8)/AE8) -> 0.021428571
B9: 2. Slitter Drywall 0,43/0,48 | C9: 0 | D9: 0 | E9: 741.04 | F9: 720.05 | G9: 776.65 | H9: 964 | I9: 964 | J9: 964 | K9: 964 | L9: 964 | M9: 964 | N9: 964 | O9: =IF(Ej_Producción!O38=0,0,O24/Ej_Producción!O38) -> 905.50966 | P9: 900 | Q9: =IF(P9=0,0,(O9-P9)/P9) -> 0.0061218487 | R9: 964 | S9: 964 | T9: 964 | U9: 964 | V9: 964 | W9: 964 | X9: 964 | Y9: 964 | Z9: 964 | AA9: 964 | AB9: 964 | AC9: 964 | AD9: =IF(Ej_Producción!AD38=0,0,AD24/Ej_Producción!AD38) -> 964 | AE9: 945 | AF9: =IF(AE9=0,0,(AD9-AE9)/AE9) -> 0.02010582
B10: 3. Slitter Drywall 0,50 | C10: 0 | D10: 0 | E10: 770 | F10: 840 | G10: 870 | H10: 1080 | I10: 1080 | J10: 1080 | K10: 1080 | L10: 1080 | M10: 1080 | N10: 1080 | O10: =IF(Ej_Producción!O39=0,0,O25/Ej_Producción!O39) -> 1047.5821 | P10: 1010 | Q10: =IF(P10=0,0,(O10-P10)/P10) -> 0.037209961 | R10: 1080 | S10: 1080 | T10: 1080 | U10: 1080 | V10: 1080 | W10: 1080 | X10: 1080 | Y10: 1080 | Z10: 1080 | AA10: 1080 | AB10: 1080 | AC10: 1080 | AD10: =IF(Ej_Producción!AD39=0,0,AD25/Ej_Producción!AD39) -> 1080 | AE10: 1060.5 | AF10: =IF(AE10=0,0,(AD10-AE10)/AE10) -> 0.018387553
B11: 4. Slitter Steel Frame 0,80/0,95 | C11: 0 | D11: 0 | E11: 0 | F11: 0 | G11: 0 | H11: 1080 | I11: 1080 | J11: 1080 | K11: 1080 | L11: 1080 | M11: 1080 | N11: 1080 | O11: =IF(Ej_Producción!O40=0,0,O26/Ej_Producción!O40) -> 1080 | P11: 0 | Q11: =IF(P11=0,0,(O11-P11)/P11) -> 0 | R11: 1080 | S11: 1080 | T11: 1080 | U11: 1080 | V11: 1080 | W11: 1080 | X11: 1080 | Y11: 1080 | Z11: 1080 | AA11: 1080 | AB11: 1080 | AC11: 1080 | AD11: =IF(Ej_Producción!AD40=0,0,AD26/Ej_Producción!AD40) -> 1080 | AE11: 0 | AF11: =IF(AE11=0,0,(AD11-AE11)/AE11) -> 0
B12: 5. Telhas Met. Naturales | C12: 0 | D12: 0 | E12: 0 | F12: 0 | G12: 0 | H12: 1218 | I12: 1218 | J12: 1218 | K12: 1218 | L12: 1218 | M12: 1218 | N12: 1218 | O12: =IF(Ej_Producción!O41=0,0,O27/Ej_Producción!O41) -> 1218 | P12: 1150 | Q12: =IF(P12=0,0,(O12-P12)/P12) -> 0.059130435 | R12: 1218 | S12: 1218 | T12: 1218 | U12: 1218 | V12: 1218 | W12: 1218 | X12: 1218 | Y12: 1218 | Z12: 1218 | AA12: 1218 | AB12: 1218 | AC12: 1218 | AD12: =IF(Ej_Producción!AD41=0,0,AD27/Ej_Producción!AD41) -> 1218 | AE12: 1207.5 | AF12: =IF(AE12=0,0,(AD12-AE12)/AE12) -> 0.0086956522
B13: 6. Telhas Met. Pre Pintadas | C13: 0 | D13: 0 | E13: 0 | F13: 0 | G13: 1040 | H13: 1399 | I13: 1399 | J13: 1399 | K13: 1399 | L13: 1399 | M13: 1399 | N13: 1399 | O13: =IF(Ej_Producción!O42=0,0,O28/Ej_Producción!O42) -> 1380.8228 | P13: 1310 | Q13: =IF(P13=0,0,(O13-P13)/P13) -> 0.054063195 | R13: 1399 | S13: 1399 | T13: 1399 | U13: 1399 | V13: 1399 | W13: 1399 | X13: 1399 | Y13: 1399 | Z13: 1399 | AA13: 1399 | AB13: 1399 | AC13: 1399 | AD13: =IF(Ej_Producción!AD42=0,0,AD28/Ej_Producción!AD42) -> 1399 | AE13: 1375.5 | AF13: =IF(AE13=0,0,(AD13-AE13)/AE13) -> 0.017084696
B14: 7. Perfil DW 0,43 Prepint. | C14: 0 | D14: 0 | E14: 0 | F14: 0 | G14: 0 | H14: 1399 | I14: 1399 | J14: 1399 | K14: 1399 | L14: 1399 | M14: 1399 | N14: 1399 | O14: =IF(Ej_Producción!O43=0,0,O29/Ej_Producción!O43) -> 1399 | P14: 1330 | Q14: =IF(P14=0,0,(O14-P14)/P14) -> 0.051879699 | R14: 1399 | S14: 1399 | T14: 1399 | U14: 1399 | V14: 1399 | W14: 1399 | X14: 1399 | Y14: 1399 | Z14: 1399 | AA14: 1399 | AB14: 1399 | AC14: 1399 | AD14: =IF(Ej_Producción!AD43=0,0,AD29/Ej_Producción!AD43) -> 1399 | AE14: 1396.5 | AF14: =IF(AE14=0,0,(AD14-AE14)/AE14) -> 0.0017901898
B15: 8. Perfil Drywall 0,50 | C15: 0 | D15: 0 | E15: 0 | F15: 0 | G15: 0 | H15: 1272 | I15: 1272 | J15: 1272 | K15: 1272 | L15: 1272 | M15: 1272 | N15: 1272 | O15: =IF(Ej_Producción!O44=0,0,O30/Ej_Producción!O44) -> 1272 | P15: 1180 | Q15: =IF(P15=0,0,(O15-P15)/P15) -> 0.077966102 | R15: 1272 | S15: 1272 | T15: 1272 | U15: 1272 | V15: 1272 | W15: 1272 | X15: 1272 | Y15: 1272 | Z15: 1272 | AA15: 1272 | AB15: 1272 | AC15: 1272 | AD15: =IF(Ej_Producción!AD44=0,0,AD30/Ej_Producción!AD44) -> 1272 | AE15: 1239 | AF15: =IF(AE15=0,0,(AD15-AE15)/AE15) -> 0.026634383
B16: 9. Perfil Drywall 0,48 | C16: 0 | D16: 0 | E16: 0 | F16: 0 | G16: 0 | H16: 1178 | I16: 1178 | J16: 1178 | K16: 1178 | L16: 1178 | M16: 1178 | N16: 1178 | O16: =IF(Ej_Producción!O45=0,0,O31/Ej_Producción!O45) -> 1178 | P16: 1110 | Q16: =IF(P16=0,0,(O16-P16)/P16) -> 0.061261261 | R16: 1178 | S16: 1178 | T16: 1178 | U16: 1178 | V16: 1178 | W16: 1178 | X16: 1178 | Y16: 1178 | Z16: 1178 | AA16: 1178 | AB16: 1178 | AC16: 1178 | AD16: =IF(Ej_Producción!AD45=0,0,AD31/Ej_Producción!AD45) -> 1178 | AE16: 1165.5 | AF16: =IF(AE16=0,0,(AD16-AE16)/AE16) -> 0.010725011
B17: 10. Steel Frame | O17: =IF(Ej_Producción!O46=0,0,O32/Ej_Producción!O46) -> 0 | P17: 0 | Q17: =IF(P17=0,0,(O17-P17)/P17) -> 0 | R17: 1840 | S17: 1840 | T17: 1840 | U17: 1840 | V17: 1840 | W17: 1840 | X17: 1840 | Y17: 1840 | Z17: 1840 | AA17: 1840 | AB17: 1840 | AC17: 1840 | AD17: =IF(Ej_Producción!AD46=0,0,AD32/Ej_Producción!AD46) -> 1840 | AE17: 1700 | AF17: =IF(AE17=0,0,(AD17-AE17)/AE17) -> 0.082352941
B18: 11. Accesorios Metálicos | O18: =IF(Ej_Producción!O47=0,0,O33/Ej_Producción!O47) -> 0 | P18: 0 | Q18: =IF(P18=0,0,(O18-P18)/P18) -> 0 | R18: 5202 | S18: 5202 | T18: 5202 | U18: 5202 | V18: 5202 | W18: 5202 | X18: 5202 | Y18: 5202 | Z18: 5202 | AA18: 5202 | AB18: 5202 | AC18: 5202 | AD18: =IF(Ej_Producción!AD47=0,0,AD33/Ej_Producción!AD47) -> 5202 | AE18: 3000 | AF18: =IF(AE18=0,0,(AD18-AE18)/AE18) -> 0.734
B21: INGRESOS EJECUTADO Y PROYECTADO MENSUALES (USD)
B22: Producto | C22: Ene | D22: Feb | E22: Mar | F22: Abr | G22: May | H22: Jun | I22: Jul | J22: Ago | K22: Sep | L22: Oct | M22: Nov | N22: Dic | O22: TOTAL EJEC. PROY. | P22: PROY. AÑO 1 | Q22: DESVÍO USD | R22: Ene | S22: Feb | T22: Mar | U22: Abr | V22: May | W22: Jun | X22: Jul | Y22: Ago | Z22: Sep | AA22: Oct | AB22: Nov | AC22: Dic | AD22: TOTAL PROY. | AE22: PROY. AÑO 2 | AF22: DESVÍO USD
B23: 1. Slitter Portas Autom. | C23: =C8*Ej_Producción!C37 -> 20196 | D23: =D8*Ej_Producción!D37 -> 0 | E23: =E8*Ej_Producción!E37 -> 14741.1 | F23: =F8*Ej_Producción!F37 -> 45558.2 | G23: =G8*Ej_Producción!G37 -> 0 | H23: =H8*Ej_Producción!H37 -> 51480 | I23: =I8*Ej_Producción!I37 -> 77220 | J23: =J8*Ej_Producción!J37 -> 77220 | ... N23: =N8*Ej_Producción!N37 -> 77220 | O23: =SUM(C23:N23) -> 595295.3 | P23: 2208000 | Q23: =O23-P23 -> -1612704.7 | R23: =R8*Ej_Producción!R37 -> 25740 | S23: =S8*Ej_Producción!S37 -> 51480 | T23: =T8*Ej_Producción!T37 -> 77220 | U23: =U8*Ej_Producción!U37 -> 77220 | V23: =V8*Ej_Producción!V37 -> 77220 | W23: =W8*Ej_Producción!W37 -> 77220 | X23: =X8*Ej_Producción!X37 -> 77220 | Y23: =Y8*Ej_Producción!Y37 -> 77220 | ... AC23: =AC8*Ej_Producción!AC37 -> 77220 | AD23: =SUM(R23:AC23) -> 849420 | AE23: 2434320 | AF23: =AD23-AE23 -> -1584900
B24: 2. Slitter Drywall 0,43/0,48 | C24: =C9*Ej_Producción!C38 -> 0 | D24: =D9*Ej_Producción!D38 -> 0 | E24: =E9*Ej_Producción!E38 -> 90384.649 | F24: =F9*Ej_Producción!F38 -> 97043.299 | G24: =G9*Ej_Producción!G38 -> 174334.63 | H24: =H9*Ej_Producción!H38 -> 457738.05 | I24: =I9*Ej_Producción!I38 -> 106040 | J24: =J9*Ej_Producción!J38 -> 48200 | ... N24: =N9*Ej_Producción!N38 -> 202440 | O24: =SUM(C24:N24) -> 1581060.6 | P24: 2808000 | Q24: =O24-P24 -> -1226939.4 | R24: =R9*Ej_Producción!R38 -> 289200 | S24: =S9*Ej_Producción!S38 -> 289200 | T24: =T9*Ej_Producción!T38 -> 375960 | U24: =U9*Ej_Producción!U38 -> 404880 | V24: =V9*Ej_Producción!V38 -> 404880 | W24: =W9*Ej_Producción!W38 -> 404880 | X24: =X9*Ej_Producción!X38 -> 404880 | Y24: =Y9*Ej_Producción!Y38 -> 404880 | ... AC24: =AC9*Ej_Producción!AC38 -> 404880 | AD24: =SUM(R24:AC24) -> 4598280 | AE24: 3095820 | AF24: =AD24-AE24 -> 1502460
B25: 3. Slitter Drywall 0,50 | C25: =C10*Ej_Producción!C39 -> 0 | D25: =D10*Ej_Producción!D39 -> 0 | E25: =E10*Ej_Producción!E39 -> 3973.2 | F25: =F10*Ej_Producción!F39 -> 12337.92 | G25: =G10*Ej_Producción!G39 -> 29688.75 | H25: =H10*Ej_Producción!H39 -> 37981.44 | I25: =I10*Ej_Producción!I39 -> 75600 | J25: =J10*Ej_Producción!J39 -> 54000 | ... N25: =N10*Ej_Producción!N39 -> 32400 | O25: =SUM(C25:N25) -> 397181.31 | P25: 363600 | Q25: =O25-P25 -> 33581.31 | R25: =R10*Ej_Producción!R39 -> 97200 | S25: =S10*Ej_Producción!S39 -> 97200 | T25: =T10*Ej_Producción!T39 -> 129600 | U25: =U10*Ej_Producción!U39 -> 162000 | V25: =V10*Ej_Producción!V39 -> 162000 | W25: =W10*Ej_Producción!W39 -> 162000 | X25: =X10*Ej_Producción!X39 -> 162000 | Y25: =Y10*Ej_Producción!Y39 -> 162000 | ... AC25: =AC10*Ej_Producción!AC39 -> 162000 | AD25: =SUM(R25:AC25) -> 1782000 | AE25: 399808.5 | AF25: =AD25-AE25 -> 1382191.5
B26: 4. Slitter Steel Frame 0,80/0,95 | C26: =C11*Ej_Producción!C40 -> 0 | D26: =D11*Ej_Producción!D40 -> 0 | E26: =E11*Ej_Producción!E40 -> 0 | F26: =F11*Ej_Producción!F40 -> 0 | G26: =G11*Ej_Producción!G40 -> 0 | H26: =H11*Ej_Producción!H40 -> 0 | I26: =I11*Ej_Producción!I40 -> 0 | J26: =J11*Ej_Producción!J40 -> 0 | ... N26: =N11*Ej_Producción!N40 -> 162000 | O26: =SUM(C26:N26) -> 486000 | P26: 0 | Q26: =O26-P26 -> 486000 | R26: =R11*Ej_Producción!R40 -> 97200 | S26: =S11*Ej_Producción!S40 -> 97200 | T26: =T11*Ej_Producción!T40 -> 129600 | U26: =U11*Ej_Producción!U40 -> 162000 | V26: =V11*Ej_Producción!V40 -> 162000 | W26: =W11*Ej_Producción!W40 -> 162000 | X26: =X11*Ej_Producción!X40 -> 162000 | Y26: =Y11*Ej_Producción!Y40 -> 162000 | ... AC26: =AC11*Ej_Producción!AC40 -> 162000 | AD26: =SUM(R26:AC26) -> 1782000 | AE26: 0 | AF26: =AD26-AE26 -> 1782000
B27: 5. Telhas Met. Naturales | C27: =C12*Ej_Producción!C41 -> 0 | D27: =D12*Ej_Producción!D41 -> 0 | E27: =E12*Ej_Producción!E41 -> 0 | F27: =F12*Ej_Producción!F41 -> 0 | G27: =G12*Ej_Producción!G41 -> 0 | H27: =H12*Ej_Producción!H41 -> 0 | I27: =I12*Ej_Producción!I41 -> 0 | J27: =J12*Ej_Producción!J41 -> 73080 | ... N27: =N12*Ej_Producción!N41 -> 36540 | O27: =SUM(C27:N27) -> 292320 | P27: 1932000 | Q27: =O27-P27 -> -1639680 | R27: =R12*Ej_Producción!R41 -> 36540 | S27: =S12*Ej_Producción!S41 -> 36540 | T27: =T12*Ej_Producción!T41 -> 73080 | U27: =U12*Ej_Producción!U41 -> 73080 | V27: =V12*Ej_Producción!V41 -> 73080 | W27: =W12*Ej_Producción!W41 -> 73080 | X27: =X12*Ej_Producción!X41 -> 73080 | Y27: =Y12*Ej_Producción!Y41 -> 73080 | ... AC27: =AC12*Ej_Producción!AC41 -> 73080 | AD27: =SUM(R27:AC27) -> 803880 | AE27: 2130030 | AF27: =AD27-AE27 -> -1326150
B28: 6. Telhas Met. Pre Pintadas | C28: =C13*Ej_Producción!C42 -> 0 | D28: =D13*Ej_Producción!D42 -> 0 | E28: =E13*Ej_Producción!E42 -> 0 | F28: =F13*Ej_Producción!F42 -> 0 | G28: =G13*Ej_Producción!G42 -> 8320 | H28: =H13*Ej_Producción!H42 -> 0 | I28: =I13*Ej_Producción!I42 -> 0 | J28: =J13*Ej_Producción!J42 -> 41970 | ... N28: =N13*Ej_Producción!N42 -> 41970 | O28: =SUM(C28:N28) -> 218170 | P28: 235800 | Q28: =O28-P28 -> -17630 | R28: =R13*Ej_Producción!R42 -> 0 | S28: =S13*Ej_Producción!S42 -> 41970 | T28: =T13*Ej_Producción!T42 -> 41970 | U28: =U13*Ej_Producción!U42 -> 41970 | V28: =V13*Ej_Producción!V42 -> 41970 | W28: =W13*Ej_Producción!W42 -> 41970 | X28: =X13*Ej_Producción!X42 -> 41970 | Y28: =Y13*Ej_Producción!Y42 -> 41970 | ... AC28: =AC13*Ej_Producción!AC42 -> 41970 | AD28: =SUM(R28:AC28) -> 461670 | AE28: 259969.5 | AF28: =AD28-AE28 -> 201700.5
B29: 7. Perfil DW 0,43 Prepint. | C29: =C14*Ej_Producción!C43 -> 0 | D29: =D14*Ej_Producción!D43 -> 0 | E29: =E14*Ej_Producción!E43 -> 0 | F29: =F14*Ej_Producción!F43 -> 0 | G29: =G14*Ej_Producción!G43 -> 0 | H29: =H14*Ej_Producción!H43 -> 0 | I29: =I14*Ej_Producción!I43 -> 0 | J29: =J14*Ej_Producción!J43 -> 0 | ... N29: =N14*Ej_Producción!N43 -> 41970 | O29: =SUM(C29:N29) -> 167880 | P29: 558600 | Q29: =O29-P29 -> -390720 | R29: =R14*Ej_Producción!R43 -> 41970 | S29: =S14*Ej_Producción!S43 -> 41970 | T29: =T14*Ej_Producción!T43 -> 62955 | U29: =U14*Ej_Producción!U43 -> 83940 | V29: =V14*Ej_Producción!V43 -> 83940 | W29: =W14*Ej_Producción!W43 -> 83940 | X29: =X14*Ej_Producción!X43 -> 83940 | Y29: =Y14*Ej_Producción!Y43 -> 83940 | ... AC29: =AC14*Ej_Producción!AC43 -> 83940 | AD29: =SUM(R29:AC29) -> 902355 | AE29: 614460 | AF29: =AD29-AE29 -> 287895
B30: 8. Perfil Drywall 0,50 | C30: =C15*Ej_Producción!C44 -> 0 | D30: =D15*Ej_Producción!D44 -> 0 | E30: =E15*Ej_Producción!E44 -> 0 | F30: =F15*Ej_Producción!F44 -> 0 | G30: =G15*Ej_Producción!G44 -> 0 | H30: =H15*Ej_Producción!H44 -> 0 | I30: =I15*Ej_Producción!I44 -> 0 | J30: =J15*Ej_Producción!J44 -> 0 | ... N30: =N15*Ej_Producción!N44 -> 38160 | O30: =SUM(C30:N30) -> 152640 | P30: 849600 | Q30: =O30-P30 -> -696960 | R30: =R15*Ej_Producción!R44 -> 38160 | S30: =S15*Ej_Producción!S44 -> 38160 | T30: =T15*Ej_Producción!T44 -> 76320 | U30: =U15*Ej_Producción!U44 -> 76320 | V30: =V15*Ej_Producción!V44 -> 76320 | W30: =W15*Ej_Producción!W44 -> 76320 | X30: =X15*Ej_Producción!X44 -> 76320 | Y30: =Y15*Ej_Producción!Y44 -> 76320 | ... AC30: =AC15*Ej_Producción!AC44 -> 76320 | AD30: =SUM(R30:AC30) -> 839520 | AE30: 936684 | AF30: =AD30-AE30 -> -97164
B31: 9. Perfil Drywall 0,48 | C31: =C16*Ej_Producción!C45 -> 0 | D31: =D16*Ej_Producción!D45 -> 0 | E31: =E16*Ej_Producción!E45 -> 0 | F31: =F16*Ej_Producción!F45 -> 0 | G31: =G16*Ej_Producción!G45 -> 0 | H31: =H16*Ej_Producción!H45 -> 0 | I31: =I16*Ej_Producción!I45 -> 0 | J31: =J16*Ej_Producción!J45 -> 0 | ... N31: =N16*Ej_Producción!N45 -> 70680 | O31: =SUM(C31:N31) -> 318060 | P31: 1864800 | Q31: =O31-P31 -> -1546740 | R31: =R16*Ej_Producción!R45 -> 106020 | S31: =S16*Ej_Producción!S45 -> 106020 | T31: =T16*Ej_Producción!T45 -> 141360 | U31: =U16*Ej_Producción!U45 -> 141360 | V31: =V16*Ej_Producción!V45 -> 176700 | W31: =W16*Ej_Producción!W45 -> 176700 | X31: =X16*Ej_Producción!X45 -> 176700 | Y31: =Y16*Ej_Producción!Y45 -> 176700 | ... AC31: =AC16*Ej_Producción!AC45 -> 176700 | AD31: =SUM(R31:AC31) -> 1908360 | AE31: 2055942 | AF31: =AD31-AE31 -> -147582
B32: 10. Steel Frame | C32: =C17*Ej_Producción!C46 -> 0 | D32: =D17*Ej_Producción!D46 -> 0 | E32: =E17*Ej_Producción!E46 -> 0 | F32: =F17*Ej_Producción!F46 -> 0 | G32: =G17*Ej_Producción!G46 -> 0 | H32: =H17*Ej_Producción!H46 -> 0 | I32: =I17*Ej_Producción!I46 -> 0 | J32: =J17*Ej_Producción!J46 -> 0 | ... N32: =N17*Ej_Producción!N46 -> 0 | O32: =SUM(C32:N32) -> 0 | P32: 0 | Q32: =O32-P32 -> 0 | R32: =R17*Ej_Producción!R46 -> 55200 | S32: =S17*Ej_Producción!S46 -> 110400 | T32: =T17*Ej_Producción!T46 -> 110400 | U32: =U17*Ej_Producción!U46 -> 110400 | V32: =V17*Ej_Producción!V46 -> 165600 | W32: =W17*Ej_Producción!W46 -> 165600 | X32: =X17*Ej_Producción!X46 -> 165600 | Y32: =Y17*Ej_Producción!Y46 -> 165600 | ... AC32: =AC17*Ej_Producción!AC46 -> 165600 | AD32: =SUM(R32:AC32) -> 1711200 | AE32: 1484100 | AF32: =AD32-AE32 -> 227100
B33: 11. Accesorios Metálicos | C33: =C18*Ej_Producción!C47 -> 0 | D33: =D18*Ej_Producción!D47 -> 0 | E33: =E18*Ej_Producción!E47 -> 0 | F33: =F18*Ej_Producción!F47 -> 0 | G33: =G18*Ej_Producción!G47 -> 0 | H33: =H18*Ej_Producción!H47 -> 0 | I33: =I18*Ej_Producción!I47 -> 0 | J33: =J18*Ej_Producción!J47 -> 0 | ... N33: =N18*Ej_Producción!N47 -> 0 | O33: =SUM(C33:N33) -> 0 | P33: 0 | Q33: =O33-P33 -> 0 | R33: =R18*Ej_Producción!R47 -> 78030 | S33: =S18*Ej_Producción!S47 -> 78030 | T33: =T18*Ej_Producción!T47 -> 156060 | U33: =U18*Ej_Producción!U47 -> 156060 | V33: =V18*Ej_Producción!V47 -> 156060 | W33: =W18*Ej_Producción!W47 -> 156060 | X33: =X18*Ej_Producción!X47 -> 156060 | Y33: =Y18*Ej_Producción!Y47 -> 156060 | ... AC33: =AC18*Ej_Producción!AC47 -> 156060 | AD33: =SUM(R33:AC33) -> 1716660 | AE33: 180000 | AF33: =AD33-AE33 -> 1536660
B34: TOTAL INGRESOS EJECUTADOS | C34: =SUM(C23:C33) -> 20196 | D34: =SUM(D23:D33) -> 0 | E34: =SUM(E23:E33) -> 109098.95 | F34: =SUM(F23:F33) -> 154939.42 | G34: =SUM(G23:G33) -> 212343.38 | H34: =SUM(H23:H33) -> 547199.49 | I34: =SUM(I23:I33) -> 258860 | J34: =SUM(J23:J33) -> 294470 | ... AF34: =SUM(AF23:AF33) -> 3764211
P35: =+O34/P34 -> 0.38895117 | Q35: =+Q34/P34 -> -0.61104883 | AE35: =+AD34/AE34 -> 1.2769608 | AF35: =+AF34/AE34 -> 0.27696077
B36: INGRESO PROYECTADO MENSUAL EN PLAN DE NEGOCIO | C36: =+$O$36/12 -> 901700 | D36: =+$O$36/12 -> 901700 | E36: =+$O$36/12 -> 901700 | F36: =+$O$36/12 -> 901700 | G36: =+$O$36/12 -> 901700 | H36: =+$O$36/12 -> 901700 | I36: =+$O$36/12 -> 901700 | J36: =+$O$36/12 -> 901700 | ... N36: =+$O$36/12 -> 901700 | O36: =+P34 -> 10820400 | R36: =+$AD$36/12 -> 1132594.5 | S36: =+$AD$36/12 -> 1132594.5 | T36: =+$AD$36/12 -> 1132594.5 | U36: =+$AD$36/12 -> 1132594.5 | V36: =+$AD$36/12 -> 1132594.5 | W36: =+$AD$36/12 -> 1132594.5 | X36: =+$AD$36/12 -> 1132594.5 | Y36: =+$AD$36/12 -> 1132594.5 | ... AC36: =+$AD$36/12 -> 1132594.5 | AD36: =+AE34 -> 13591134

Sheet Ej_Costos
O1: 6028.12 | P1: TC cierre de mayo-2026
B2: SEGUIMIENTO COSTOS AÑO 1 Y 2 — EJECUTADO & PROYECTADO | P2: =+Ej_Producción!P33 -> 0.38920952 | Q2: *Produc.
B3: Valores en USD
C4: 2026 | R4: 2027
B6: Concepto | C6: Ene | D6: Feb | E6: Mar | F6: Abr | G6: May | H6: Jun | I6: Jul | J6: Ago | K6: Sep | L6: Oct | M6: Nov | N6: Dic | O6: TOTAL EJEC. | P6: PROY. AÑO 1 | Q6: DESVÍO USD | R6: Ene | S6: Feb | T6: Mar | U6: Abr | V6: May | W6: Jun | X6: Jul | Y6: Ago | Z6: Sep | AA6: Oct | AB6: Nov | AC6: Dic | AD6: TOTAL EJEC. | AE6: PROY. AÑO 2 | AF6: DESVÍO USD
O7: PROM
B8: COSTO DE CHAPAS/TON
B9: 1. Slitter Portas Autom. | C9: 822.0642 | D9: 822.0642 | E9: 822.0642 | F9: 822.0642 | G9: 822.0642 | H9: 822.0642 | I9: 822.0642 | J9: 822.0642 | K9: 822.0642 | L9: 822.0642 | M9: 822.0642 | N9: 822.0642 | O9: =O23/Ej_Producción!O22 -> 822.0642 | P9: 775.73 | Q9: =IF(P9=0,0,(O9-P9)/P9) -> 0.059729808 | R9: 879.6087 | S9: 879.6087 | T9: 879.6087 | U9: 879.6087 | V9: 879.6087 | W9: 879.6087 | X9: 879.6087 | Y9: 879.6087 | Z9: 879.6087 | AA9: 879.6087 | AB9: 879.6087 | AC9: 879.6087 | AD9: =AD23/Ej_Producción!AD22 -> 879.6087 | AE9: 799.0019 | AF9: =IF(AE9=0,0,(AD9-AE9)/AE9) -> 0.10088436
B10: 2. Slitter Drywall 0,43/0,48 | C10: 860.78 | D10: 860.78 | E10: 860.78 | F10: 860.78 | G10: 860.78 | H10: 860.78 | I10: 860.78 | J10: 860.78 | K10: 860.78 | L10: 860.78 | M10: 886 | N10: 886 | O10: =O24/Ej_Producción!O23 -> 868.32068 | P10: 845.68 | Q10: =IF(P10=0,0,(O10-P10)/P10) -> 0.026772155 | R10: 886 | S10: 948.02 | T10: 948.02 | U10: 948.02 | V10: 948.02 | W10: 948.02 | X10: 948.02 | Y10: 948.02 | Z10: 948.02 | AA10: 948.02 | AB10: 948.02 | AC10: 948.02 | AD10: =AD24/Ej_Producción!AD23 -> 944.11937 | AE10: 871.0504 | AF10: =IF(AE10=0,0,(AD10-AE10)/AE10) -> 0.083886043
B11: 3. Slitter Drywall 0,50 | C11: 983.37979 | D11: 983.37979 | E11: 983.37979 | F11: 983.37979 | G11: 983.37979 | H11: 983.37979 | I11: 983.37979 | J11: 983.37979 | K11: 983.37979 | L11: 983.37979 | M11: 1064 | N11: 1064 | O11: =O25/Ej_Producción!O24 -> 1007.0255 | P11: 951.85 | Q11: =IF(P11=0,0,(O11-P11)/P11) -> 0.057966577 | R11: 1064 | S11: 1138.48 | T11: 1138.48 | U11: 1138.48 | V11: 1138.48 | W11: 1138.48 | X11: 1138.48 | Y11: 1138.48 | Z11: 1138.48 | AA11: 1138.48 | AB11: 1138.48 | AC11: 1138.48 | AD11: =AD25/Ej_Producción!AD24 -> 1134.4175 | AE11: 980.4055 | AF11: =IF(AE11=0,0,(AD11-AE11)/AE11) -> 0.15709006
B12: 4. Slitter Steel Frame 0,80/0,95 | C12: 0 | D12: 0 | E12: 0 | F12: 0 | G12: 0 | H12: 922 | I12: 922 | J12: 922 | K12: 922 | L12: 922 | M12: 922 | N12: 922 | O12: =O26/Ej_Producción!O25 -> 922 | P12: 0 | Q12: =IF(P12=0,0,(O12-P12)/P12) -> 0 | R12: 922 | S12: 986.54 | T12: 986.54 | U12: 986.54 | V12: 986.54 | W12: 986.54 | X12: 986.54 | Y12: 986.54 | Z12: 986.54 | AA12: 986.54 | AB12: 986.54 | AC12: 986.54 | AD12: =AD26/Ej_Producción!AD25 -> 983.01964 | AE12: 0 | AF12: =IF(AE12=0,0,(AD12-AE12)/AE12) -> 0
B13: 5. Telhas Met. Naturales | C13: 945.95457 | D13: 945.95457 | E13: 945.95457 | F13: 945.95457 | G13: 945.95457 | H13: 945.95457 | I13: 945.95457 | J13: 945.95457 | K13: 945.95457 | L13: 945.95457 | M13: 945.95457 | N13: 945.95457 | O13: =O27/Ej_Producción!O26 -> 945.95457 | P13: 888.15 | Q13: =IF(P13=0,0,(O13-P13)/P13) -> 0.065084243 | R13: 945.95457 | S13: 1012.1714 | T13: 1012.1714 | U13: 1012.1714 | V13: 1012.1714 | W13: 1012.1714 | X13: 1012.1714 | Y13: 1012.1714 | Z13: 1012.1714 | AA13: 1012.1714 | AB13: 1012.1714 | AC13: 1012.1714 | AD13: =AD27/Ej_Producción!AD26 -> 1009.1615 | AE13: 914.7945 | AF13: =IF(AE13=0,0,(AD13-AE13)/AE13) -> 0.10315654
B14: 6. Telhas Met. Pre Pintadas | C14: 1013.0619 | D14: 1013.0619 | E14: 1013.0619 | F14: 1013.0619 | G14: 1013.0619 | H14: 1013.0619 | I14: 1013.0619 | J14: 1013.0619 | K14: 1013.0619 | L14: 1013.0619 | M14: 1013.0619 | N14: 1013.0619 | O14: =O28/Ej_Producción!O27 -> 1013.0619 | P14: 980.58 | Q14: =IF(P14=0,0,(O14-P14)/P14) -> 0.033125142 | R14: 1013.0619 | S14: 1083.9762 | T14: 1083.9762 | U14: 1083.9762 | V14: 1083.9762 | W14: 1083.9762 | X14: 1083.9762 | Y14: 1083.9762 | Z14: 1083.9762 | AA14: 1083.9762 | AB14: 1083.9762 | AC14: 1083.9762 | AD14: =AD28/Ej_Producción!AD27 -> 1083.9762 | AE14: 1009.9974 | AF14: =IF(AE14=0,0,(AD14-AE14)/AE14) -> 0.073246507
B15: 7. Perfil DW 0,43 Prepint. | C15: 1013.0619 | D15: 1013.0619 | E15: 1013.0619 | F15: 1013.0619 | G15: 1013.0619 | H15: 1013.0619 | I15: 1013.0619 | J15: 1013.0619 | K15: 1013.0619 | L15: 1013.0619 | M15: 1013.0619 | N15: 1013.0619 | O15: =O29/Ej_Producción!O28 -> 1013.0619 | P15: 980.58 | Q15: =IF(P15=0,0,(O15-P15)/P15) -> 0.033125142 | R15: 1013.0619 | S15: 1083.9762 | T15: 1083.9762 | U15: 1083.9762 | V15: 1083.9762 | W15: 1083.9762 | X15: 1083.9762 | Y15: 1083.9762 | Z15: 1083.9762 | AA15: 1083.9762 | AB15: 1083.9762 | AC15: 1083.9762 | AD15: =AD29/Ej_Producción!AD28 -> 1080.6778 | AE15: 1009.9974 | AF15: =IF(AE15=0,0,(AD15-AE15)/AE15) -> 0.069980815
B16: 8. Perfil Drywall 0,50 | C16: 983.37979 | D16: 983.37979 | E16: 983.37979 | F16: 983.37979 | G16: 983.37979 | H16: 983.37979 | I16: 983.37979 | J16: 983.37979 | K16: 983.37979 | L16: 983.37979 | M16: 1064 | N16: 1064 | O16: =O30/Ej_Producción!O29 -> 1023.6899 | P16: 951.85 | Q16: =IF(P16=0,0,(O16-P16)/P16) -> 0.075473964 | R16: 1064 | S16: 1138.48 | T16: 1138.48 | U16: 1138.48 | V16: 1138.48 | W16: 1138.48 | X16: 1138.48 | Y16: 1138.48 | Z16: 1138.48 | AA16: 1138.48 | AB16: 1138.48 | AC16: 1138.48 | AD16: =AD30/Ej_Producción!AD29 -> 1135.0945 | AE16: 980.4055 | AF16: =IF(AE16=0,0,(AD16-AE16)/AE16) -> 0.15778068
B17: 9. Perfil Drywall 0,48 | C17: 860.77994 | D17: 860.77994 | E17: 860.77994 | F17: 860.77994 | G17: 860.77994 | H17: 860.77994 | I17: 860.77994 | J17: 860.77994 | K17: 860.77994 | L17: 860.77994 | M17: 886 | N17: 886 | O17: =O31/Ej_Producción!O30 -> 877.59331 | P17: 833.19 | Q17: =IF(P17=0,0,(O17-P17)/P17) -> 0.053293144 | R17: 886 | S17: 948.02 | T17: 948.02 | U17: 948.02 | V17: 948.02 | W17: 948.02 | X17: 948.02 | Y17: 948.02 | Z17: 948.02 | AA17: 948.02 | AB17: 948.02 | AC17: 948.02 | AD17: =AD31/Ej_Producción!AD30 -> 944.57444 | AE17: 858.1857 | AF17: =IF(AE17=0,0,(AD17-AE17)/AE17) -> 0.1006644
B18: 10. Steel Frame | C18: 0 | D18: 0 | E18: 0 | F18: 0 | G18: 0 | H18: 0 | I18: 0 | J18: 0 | K18: 0 | L18: 0 | M18: 0 | N18: 0 | O18: 0 | P18: 0 | Q18: =IF(P18=0,0,(O18-P18)/P18) -> 0 | R18: 986.54 | S18: 986.54 | T18: 986.54 | U18: 986.54 | V18: 986.54 | W18: 986.54 | X18: 986.54 | Y18: 986.54 | Z18: 986.54 | AA18: 986.54 | AB18: 986.54 | AC18: 986.54 | AD18: =AD32/Ej_Producción!AD31 -> 986.54 | AE18: 932 | AF18: =IF(AE18=0,0,(AD18-AE18)/AE18) -> 0.058519313
B19: 11. Accesorios Metálicos | C19: 0 | D19: 0 | E19: 0 | F19: 0 | G19: 0 | H19: 0 | I19: 0 | J19: 0 | K19: 0 | L19: 0 | M19: 0 | N19: 0 | O19: 0 | P19: 0 | Q19: =IF(P19=0,0,(O19-P19)/P19) -> 0 | R19: 957.7249 | S19: 957.7249 | T19: 957.7249 | U19: 957.7249 | V19: 957.7249 | W19: 957.7249 | X19: 957.7249 | Y19: 957.7249 | Z19: 957.7249 | AA19: 957.7249 | AB19: 957.7249 | AC19: 957.7249 | AD19: =AD33/Ej_Producción!AD32 -> 957.7249 | AE19: 932.9 | AF19: =IF(AE19=0,0,(AD19-AE19)/AE19) -> 0.026610462
B21: 1. COSTOS DE PRODUCCIÓN
B22: a. Materia prima e insumos | C22: =SUM(C23:C33) -> 24415.307 | D22: =SUM(D23:D33) -> 0 | E22: =SUM(E23:E33) -> 128424.38 | F22: =SUM(F23:F33) -> 179732.42 | G22: =SUM(G23:G33) -> 449031.28 | H22: =SUM(H23:H33) -> 348081.57 | I22: =SUM(I23:I33) -> 237508.16 | J22: =SUM(J23:J33) -> 253342.9 | ... N22: =SUM(N23:N33) -> 635348.13 | O22: =SUM(C22:N22) -> 3876548.2 | P22: 9429716.6 | Q22: =O22-P22 -> -5553168.4 | R22: =SUM(R23:R33) -> 685320.83 | S22: =SUM(S23:S33) -> 816872.51 | T22: =SUM(T23:T33) -> 1115918.8 | U22: =SUM(U23:U33) -> 1224369.7 | V22: =SUM(V23:V33) -> 1282406.5 | W22: =SUM(W23:W33) -> 1282406.5 | X22: =SUM(X23:X33) -> 1282406.5 | Y22: =SUM(Y23:Y33) -> 1282406.5 | ... AC22: =SUM(AC23:AC33) -> 1282406.5 | AD22: =SUM(R22:AC22) -> 14101734 | AE22: 11079679 | AF22: =AD22-AE22 -> 3022054.9
B23: 1. Slitter Portas Autom. | C23: =+C9*Ej_Producción!C22 -> 24415.307 | D23: =+D9*Ej_Producción!D22 -> 0 | E23: =+E9*Ej_Producción!E22 -> 18360.804 | F23: =+F9*Ej_Producción!F22 -> 49278.639 | G23: =+G9*Ej_Producción!G22 -> 11508.899 | H23: =+H9*Ej_Producción!H22 -> 37814.953 | I23: =+I9*Ej_Producción!I22 -> 73985.778 | J23: =+J9*Ej_Producción!J22 -> 73985.778 | ... N23: =+N9*Ej_Producción!N22 -> 73985.778 | O23: =SUM(C23:N23) -> 585293.27 | R23: =+R9*Ej_Producción!R22 -> 26388.261 | S23: =+S9*Ej_Producción!S22 -> 52776.522 | T23: =+T9*Ej_Producción!T22 -> 79164.783 | U23: =+U9*Ej_Producción!U22 -> 79164.783 | V23: =+V9*Ej_Producción!V22 -> 79164.783 | W23: =+W9*Ej_Producción!W22 -> 79164.783 | X23: =+X9*Ej_Producción!X22 -> 79164.783 | Y23: =+Y9*Ej_Producción!Y22 -> 79164.783 | ... AC23: =+AC9*Ej_Producción!AC22 -> 79164.783 | AD23: =SUM(R23:AC23) -> 870812.61
B24: 2. Slitter Drywall 0,43/0,48 | C24: =+C10*Ej_Producción!C23 -> 0 | D24: =+D10*Ej_Producción!D23 -> 0 | E24: =+E10*Ej_Producción!E23 -> 104989.34 | F24: =+F10*Ej_Producción!F23 -> 116009.9 | G24: =+G10*Ej_Producción!G23 -> 301677.57 | H24: =+H10*Ej_Producción!H23 -> 300267.61 | I24: =+I10*Ej_Producción!I23 -> 94685.8 | J24: =+J10*Ej_Producción!J23 -> 43039 | ... N24: =+N10*Ej_Producción!N23 -> 212640 | O24: =SUM(C24:N24) -> 1568226.2 | R24: =+R10*Ej_Producción!R23 -> 265800 | S24: =+S10*Ej_Producción!S23 -> 284406 | T24: =+T10*Ej_Producción!T23 -> 369727.8 | U24: =+U10*Ej_Producción!U23 -> 398168.4 | V24: =+V10*Ej_Producción!V23 -> 398168.4 | W24: =+W10*Ej_Producción!W23 -> 398168.4 | X24: =+X10*Ej_Producción!X23 -> 398168.4 | Y24: =+Y10*Ej_Producción!Y23 -> 398168.4 | ... AC24: =+AC10*Ej_Producción!AC23 -> 398168.4 | AD24: =SUM(R24:AC24) -> 4503449.4
B25: 3. Slitter Drywall 0,50 | C25: =+C11*Ej_Producción!C24 -> 0 | D25: =+D11*Ej_Producción!D24 -> 0 | E25: =+E11*Ej_Producción!E24 -> 5074.2397 | F25: =+F11*Ej_Producción!F24 -> 14443.882 | G25: =+G11*Ej_Producción!G24 -> 58142.33 | H25: =+H11*Ej_Producción!H24 -> 9999.0057 | I25: =+I11*Ej_Producción!I24 -> 68836.585 | J25: =+J11*Ej_Producción!J24 -> 49168.989 | ... N25: =+N11*Ej_Producción!N24 -> 63840 | O25: =SUM(C25:N25) -> 412015.41 | R25: =+R11*Ej_Producción!R24 -> 95760 | S25: =+S11*Ej_Producción!S24 -> 102463.2 | T25: =+T11*Ej_Producción!T24 -> 136617.6 | U25: =+U11*Ej_Producción!U24 -> 170772 | V25: =+V11*Ej_Producción!V24 -> 170772 | W25: =+W11*Ej_Producción!W24 -> 170772 | X25: =+X11*Ej_Producción!X24 -> 170772 | Y25: =+Y11*Ej_Producción!Y24 -> 170772 | ... AC25: =+AC11*Ej_Producción!AC24 -> 170772 | AD25: =SUM(R25:AC25) -> 1871788.8
B26: 4. Slitter Steel Frame 0,80/0,95 | E26: =+E12*Ej_Producción!E25 -> 0 | F26: =+F12*Ej_Producción!F25 -> 0 | G26: =+G12*Ej_Producción!G25 -> 0 | H26: =+H12*Ej_Producción!H25 -> 0 | I26: =+I12*Ej_Producción!I25 -> 0 | J26: =+J12*Ej_Producción!J25 -> 0 | K26: =+K12*Ej_Producción!K25 -> 27660 | L26: =+L12*Ej_Producción!L25 -> 165960 | ... N26: =+N12*Ej_Producción!N25 -> 110640 | O26: =SUM(C26:N26) -> 442560 | R26: =+R12*Ej_Producción!R25 -> 82980 | S26: =+S12*Ej_Producción!S25 -> 88788.6 | T26: =+T12*Ej_Producción!T25 -> 118384.8 | U26: =+U12*Ej_Producción!U25 -> 147981 | V26: =+V12*Ej_Producción!V25 -> 147981 | W26: =+W12*Ej_Producción!W25 -> 147981 | X26: =+X12*Ej_Producción!X25 -> 147981 | Y26: =+Y12*Ej_Producción!Y25 -> 147981 | ... AC26: =+AC12*Ej_Producción!AC25 -> 147981 | AD26: =SUM(R26:AC26) -> 1621982.4
B27: 5. Telhas Met. Naturales | C27: =+C13*Ej_Producción!C26 -> 0 | D27: =+D13*Ej_Producción!D26 -> 0 | E27: =+E13*Ej_Producción!E26 -> 0 | F27: =+F13*Ej_Producción!F26 -> 0 | G27: =+G13*Ej_Producción!G26 -> 0 | H27: =+H13*Ej_Producción!H26 -> 0 | I27: =+I13*Ej_Producción!I26 -> 0 | J27: =+J13*Ej_Producción!J26 -> 56757.274 | ... N27: =+N13*Ej_Producción!N26 -> 28378.637 | O27: =SUM(C27:N27) -> 227029.1 | R27: =+R13*Ej_Producción!R26 -> 28378.637 | S27: =+S13*Ej_Producción!S26 -> 30365.142 | T27: =+T13*Ej_Producción!T26 -> 60730.283 | U27: =+U13*Ej_Producción!U26 -> 60730.283 | V27: =+V13*Ej_Producción!V26 -> 60730.283 | W27: =+W13*Ej_Producción!W26 -> 60730.283 | X27: =+X13*Ej_Producción!X26 -> 60730.283 | Y27: =+Y13*Ej_Producción!Y26 -> 60730.283 | ... AC27: =+AC13*Ej_Producción!AC26 -> 60730.283 | AD27: =SUM(R27:AC27) -> 666046.61
B28: 6. Telhas Met. Pre Pintadas | C28: =+C14*Ej_Producción!C27 -> 0 | D28: =+D14*Ej_Producción!D27 -> 0 | E28: =+E14*Ej_Producción!E27 -> 0 | F28: =+F14*Ej_Producción!F27 -> 0 | G28: =+G14*Ej_Producción!G27 -> 8104.4948 | H28: =+H14*Ej_Producción!H27 -> 0 | I28: =+I14*Ej_Producción!I27 -> 0 | J28: =+J14*Ej_Producción!J27 -> 30391.856 | ... N28: =+N14*Ej_Producción!N27 -> 30391.856 | O28: =SUM(C28:N28) -> 160063.77 | R28: =+R14*Ej_Producción!R27 -> 0 | S28: =+S14*Ej_Producción!S27 -> 32519.285 | T28: =+T14*Ej_Producción!T27 -> 32519.285 | U28: =+U14*Ej_Producción!U27 -> 32519.285 | V28: =+V14*Ej_Producción!V27 -> 32519.285 | W28: =+W14*Ej_Producción!W27 -> 32519.285 | X28: =+X14*Ej_Producción!X27 -> 32519.285 | Y28: =+Y14*Ej_Producción!Y27 -> 32519.285 | ... AC28: =+AC14*Ej_Producción!AC27 -> 32519.285 | AD28: =SUM(R28:AC28) -> 357712.14
B29: 7. Perfil DW 0,43 Prepint. | C29: =+C15*Ej_Producción!C28 -> 0 | D29: =+D15*Ej_Producción!D28 -> 0 | E29: =+E15*Ej_Producción!E28 -> 0 | F29: =+F15*Ej_Producción!F28 -> 0 | G29: =+G15*Ej_Producción!G28 -> 0 | H29: =+H15*Ej_Producción!H28 -> 0 | I29: =+I15*Ej_Producción!I28 -> 0 | J29: =+J15*Ej_Producción!J28 -> 0 | ... N29: =+N15*Ej_Producción!N28 -> 30391.856 | O29: =SUM(C29:N29) -> 121567.42 | R29: =+R15*Ej_Producción!R28 -> 30391.856 | S29: =+S15*Ej_Producción!S28 -> 32519.285 | T29: =+T15*Ej_Producción!T28 -> 48778.928 | U29: =+U15*Ej_Producción!U28 -> 65038.571 | V29: =+V15*Ej_Producción!V28 -> 65038.571 | W29: =+W15*Ej_Producción!W28 -> 65038.571 | X29: =+X15*Ej_Producción!X28 -> 65038.571 | Y29: =+Y15*Ej_Producción!Y28 -> 65038.571 | ... AC29: =+AC15*Ej_Producción!AC28 -> 65038.571 | AD29: =SUM(R29:AC29) -> 697037.21
B30: 8. Perfil Drywall 0,50 | C30: =+C16*Ej_Producción!C29 -> 0 | D30: =+D16*Ej_Producción!D29 -> 0 | E30: =+E16*Ej_Producción!E29 -> 0 | F30: =+F16*Ej_Producción!F29 -> 0 | G30: =+G16*Ej_Producción!G29 -> 5900.2787 | H30: =+H16*Ej_Producción!H29 -> 0 | I30: =+I16*Ej_Producción!I29 -> 0 | J30: =+J16*Ej_Producción!J29 -> 0 | ... N30: =+N16*Ej_Producción!N29 -> 31920 | O30: =SUM(C30:N30) -> 122842.79 | R30: =+R16*Ej_Producción!R29 -> 31920 | S30: =+S16*Ej_Producción!S29 -> 34154.4 | T30: =+T16*Ej_Producción!T29 -> 68308.8 | U30: =+U16*Ej_Producción!U29 -> 68308.8 | V30: =+V16*Ej_Producción!V29 -> 68308.8 | W30: =+W16*Ej_Producción!W29 -> 68308.8 | X30: =+X16*Ej_Producción!X29 -> 68308.8 | Y30: =+Y16*Ej_Producción!Y29 -> 68308.8 | ... AC30: =+AC16*Ej_Producción!AC29 -> 68308.8 | AD30: =SUM(R30:AC30) -> 749162.4
B31: 9. Perfil Drywall 0,48 | C31: =+C17*Ej_Producción!C30 -> 0 | D31: =+D17*Ej_Producción!D30 -> 0 | E31: =+E17*Ej_Producción!E30 -> 0 | F31: =+F17*Ej_Producción!F30 -> 0 | G31: =+G17*Ej_Producción!G30 -> 63697.716 | H31: =+H17*Ej_Producción!H30 -> 0 | I31: =+I17*Ej_Producción!I30 -> 0 | J31: =+J17*Ej_Producción!J30 -> 0 | ... N31: =+N17*Ej_Producción!N30 -> 53160 | O31: =SUM(C31:N31) -> 236950.19 | R31: =+R17*Ej_Producción!R30 -> 79740 | S31: =+S17*Ej_Producción!S30 -> 85321.8 | T31: =+T17*Ej_Producción!T30 -> 113762.4 | U31: =+U17*Ej_Producción!U30 -> 113762.4 | V31: =+V17*Ej_Producción!V30 -> 142203 | W31: =+W17*Ej_Producción!W30 -> 142203 | X31: =+X17*Ej_Producción!X30 -> 142203 | Y31: =+Y17*Ej_Producción!Y30 -> 142203 | ... AC31: =+AC17*Ej_Producción!AC30 -> 142203 | AD31: =SUM(R31:AC31) -> 1530210.6
B32: 10. Steel Frame | C32: =+C18*Ej_Producción!C31 -> 0 | D32: =+D18*Ej_Producción!D31 -> 0 | E32: =+E18*Ej_Producción!E31 -> 0 | F32: =+F18*Ej_Producción!F31 -> 0 | G32: =+G18*Ej_Producción!G31 -> 0 | H32: =+H18*Ej_Producción!H31 -> 0 | I32: =+I18*Ej_Producción!I31 -> 0 | J32: =+J18*Ej_Producción!J31 -> 0 | ... N32: =+N18*Ej_Producción!N31 -> 0 | O32: =SUM(C32:N32) -> 0 | R32: =+R18*Ej_Producción!R31 -> 29596.2 | S32: =+S18*Ej_Producción!S31 -> 59192.4 | T32: =+T18*Ej_Producción!T31 -> 59192.4 | U32: =+U18*Ej_Producción!U31 -> 59192.4 | V32: =+V18*Ej_Producción!V31 -> 88788.6 | W32: =+W18*Ej_Producción!W31 -> 88788.6 | X32: =+X18*Ej_Producción!X31 -> 88788.6 | Y32: =+Y18*Ej_Producción!Y31 -> 88788.6 | ... AC32: =+AC18*Ej_Producción!AC31 -> 88788.6 | AD32: =SUM(R32:AC32) -> 917482.2
B33: 11. Accesorios Metálicos | C33: =+C19*Ej_Producción!C32 -> 0 | D33: =+D19*Ej_Producción!D32 -> 0 | E33: =+E19*Ej_Producción!E32 -> 0 | F33: =+F19*Ej_Producción!F32 -> 0 | G33: =+G19*Ej_Producción!G32 -> 0 | H33: =+H19*Ej_Producción!H32 -> 0 | I33: =+I19*Ej_Producción!I32 -> 0 | J33: =+J19*Ej_Producción!J32 -> 0 | ... N33: =+N19*Ej_Producción!N32 -> 0 | O33: =SUM(C33:N33) -> 0 | R33: =+R19*Ej_Producción!R32 -> 14365.874 | S33: =+S19*Ej_Producción!S32 -> 14365.874 | T33: =+T19*Ej_Producción!T32 -> 28731.747 | U33: =+U19*Ej_Producción!U32 -> 28731.747 | V33: =+V19*Ej_Producción!V32 -> 28731.747 | W33: =+W19*Ej_Producción!W32 -> 28731.747 | X33: =+X19*Ej_Producción!X32 -> 28731.747 | Y33: =+Y19*Ej_Producción!Y32 -> 28731.747 | ... AC33: =+AC19*Ej_Producción!AC32 -> 28731.747 | AD33: =SUM(R33:AC33) -> 316049.22
B34: b. Mano de obra fábrica | C34: =31612648/USD -> 5244.1969 | D34: =30044273/USD -> 4984.0204 | E34: =34736505/USD -> 5762.411 | F34: =29898626/USD -> 4959.8591 | G34: 4865.6793 | H34: 4865.6793 | I34: 4865.6793 | J34: 4865.6793 | K34: 4865.6793 | L34: 9731.3585 | M34: 9731.3585 | N34: 9731.3585 | O34: =SUM(C34:N34) -> 74472.959 | P34: 87896 | Q34: =O34-P34 -> -13423.041 | R34: =9731.35854706418+6702 -> 16433.359 | S34: =9731.35854706418+6702 -> 16433.359 | T34: =11677.630256477+6702 -> 18379.63 | U34: 18379.63 | V34: 18379.63 | W34: 18379.63 | X34: 18379.63 | Y34: 18379.63 | Z34: 18379.63 | AA34: 18379.63 | AB34: 18379.63 | AC34: 18379.63 | AD34: =SUM(R34:AC34) -> 216663.02 | AE34: 97079 | AF34: =AD34-AE34 -> 119584.02
B35: c. Prestaciones sociales fábrica | C35: 0 | D35: 0 | E35: 0 | F35: 0 | G35: 0 | H35: 0 | I35: 0 | J35: 0 | K35: 0 | L35: 0 | M35: 0 | N35: 0 | O35: =SUM(C35:N35) -> 0 | P35: 37874.386 | Q35: =O35-P35 -> -37874.386 | R35: 0 | S35: 0 | T35: 0 | U35: 0 | V35: 0 | W35: 0 | X35: 0 | Y35: 0 | Z35: 0 | AA35: 0 | AB35: 0 | AC35: 0 | AD35: =SUM(R35:AC35) -> 0 | AE35: 41831.341 | AF35: =AD35-AE35 -> -41831.341
B36: f. Servicios terceros Steel Frame | C36: 0 | D36: 0 | E36: 0 | F36: 0 | G36: 0 | H36: 0 | I36: 0 | J36: 0 | K36: 0 | L36: 0 | M36: 0 | N36: 0 | O36: =SUM(C36:N36) -> 0 | P36: 0 | Q36: =O36-P36 -> 0 | R36: =+$AE$36/12 -> 3750 | S36: =+$AE$36/12 -> 3750 | T36: =+$AE$36/12 -> 3750 | U36: =+$AE$36/12 -> 3750 | V36: =+$AE$36/12 -> 3750 | W36: =+$AE$36/12 -> 3750 | X36: =+$AE$36/12 -> 3750 | Y36: =+$AE$36/12 -> 3750 | ... AC36: =+$AE$36/12 -> 3750 | AD36: =SUM(R36:AC36) -> 45000 | AE36: 45000 | AF36: =AD36-AE36 -> 0
B37: g. Insumos menores | C37: =13244328/USD -> 2197.091 | D37: =14004545/USD -> 2323.2028 | E37: =11876548/USD -> 1970.191 | F37: =3087979/USD -> 512.26236 | G37: =($P$37*$P$2)*Ej_Producción!G34 -> 2302.1775 | H37: =($P$37*$P$2)*Ej_Producción!H34 -> 1822.5 | I37: =($P$37*$P$2)*Ej_Producción!I34 -> 1215 | J37: =($P$37*$P$2)*Ej_Producción!J34 -> 1260 | K37: =($P$37*$P$2)*Ej_Producción!K34 -> 1305 | L37: =($P$37*$P$2)*Ej_Producción!L34 -> 2880 | M37: =($P$37*$P$2)*Ej_Producción!M34 -> 3780 | N37: =($P$37*$P$2)*Ej_Producción!N34 -> 3105 | O37: =SUM(C37:N37) -> 24672.425 | P37: 49891.5 | Q37: =O37-P37 -> -25219.075 | R37: =+$AM$37*Ej_Producción!R34 -> 3551.3376 | S37: =+$AM$37*Ej_Producción!S34 -> 3986.1953 | T37: =+$AM$37*Ej_Producción!T34 -> 5435.7208 | U37: =+$AM$37*Ej_Producción!U34 -> 5943.0548 | V37: =+$AM$37*Ej_Producción!V34 -> 6232.9599 | W37: =+$AM$37*Ej_Producción!W34 -> 6232.9599 | X37: =+$AM$37*Ej_Producción!X34 -> 6232.9599 | Y37: =+$AM$37*Ej_Producción!Y34 -> 6232.9599 | ... AC37: =+$AM$37*Ej_Producción!AC34 -> 6232.9599 | AD37: =SUM(R37:AC37) -> 68779.988 | AE37: 56641.5 | AF37: =AD37-AE37 -> 12138.488 | AJ37: =+AE22/AD22 -> 0.78569622 | AK37: =100%-AJ37 -> 0.21430378 | AL37: =+AE37*AK37 -> 12138.488 | AM37: =+AE37+AL37 -> 68779.988
B38: j. Mantenimiento y rep. equipos | C38: 0 | D38: 0 | E38: =5909091/USD -> 980.25437 | F38: 0 | G38: 0 | H38: 2000 | I38: 0 | J38: 0 | K38: 800 | L38: 0 | M38: 0 | N38: 0 | O38: =SUM(C38:N38) -> 3780.2544 | P38: 0 | Q38: =O38-P38 -> 3780.2544 | R38: =+$AM$38*Ej_Producción!R34 -> 547.79688 | S38: =+$AM$38*Ej_Producción!S34 -> 614.87404 | T38: =+$AM$38*Ej_Producción!T34 -> 838.46461 | U38: =+$AM$38*Ej_Producción!U34 -> 916.7213 | V38: =+$AM$38*Ej_Producción!V34 -> 961.43942 | W38: =+$AM$38*Ej_Producción!W34 -> 961.43942 | X38: =+$AM$38*Ej_Producción!X34 -> 961.43942 | Y38: =+$AM$38*Ej_Producción!Y34 -> 961.43942 | ... AC38: =+$AM$38*Ej_Producción!AC34 -> 961.43942 | AD38: =SUM(R38:AC38) -> 10609.372 | AE38: 8737 | AF38: =AD38-AE38 -> 1872.3722 | AL38: =+AE38*AK37 -> 1872.3722 | AM38: =+AE38+AL38 -> 10609.372
B39: l. Seguro caución Maquila | C39: 0 | D39: 0 | E39: 0 | F39: 0 | G39: 0 | H39: 0 | I39: 0 | J39: 0 | K39: 0 | L39: 0 | M39: 0 | N39: 0 | O39: =SUM(C39:N39) -> 0 | P39: 10279 | Q39: =O39-P39 -> -10279 | R39: =(R22*20%)*1.8% -> 2467.155 | S39: =(S22*20%)*1.8% -> 2940.741 | T39: =(T22*20%)*1.8% -> 4017.3078 | U39: =(U22*20%)*1.8% -> 4407.7308 | V39: =(V22*20%)*1.8% -> 4616.6633 | W39: =(W22*20%)*1.8% -> 4616.6633 | X39: =(X22*20%)*1.8% -> 4616.6633 | Y39: =(Y22*20%)*1.8% -> 4616.6633 | ... AC39: =(AC22*20%)*1.8% -> 4616.6633 | AD39: =SUM(R39:AC39) -> 50766.241 | AE39: 12914 | AF39: =AD39-AE39 -> 37852.241
B40: n. Packaging | C40: =8377273/USD -> 1389.6991 | D40: =11033090/USD -> 1830.2705 | E40: =18840909/USD -> 3125.5033 | F40: =31963636/USD -> 5302.422 | G40: =($P$40*$P$2)*Ej_Producción!G34 -> 4133.6575 | H40: =($P$40*$P$2)*Ej_Producción!H34 -> 3272.3762 | I40: =($P$40*$P$2)*Ej_Producción!I34 -> 2181.5841 | J40: =($P$40*$P$2)*Ej_Producción!J34 -> 2262.3835 | K40: =($P$40*$P$2)*Ej_Producción!K34 -> 2343.1829 | L40: =($P$40*$P$2)*Ej_Producción!L34 -> 5171.1623 | M40: =($P$40*$P$2)*Ej_Producción!M34 -> 6787.1506 | N40: =($P$40*$P$2)*Ej_Producción!N34 -> 5575.1594 | O40: =SUM(C40:N40) -> 43374.551 | P40: 89582.307 | Q40: =O40-P40 -> -46207.756 | R40: =+$AM$40*Ej_Producción!R34 -> 6599.4537 | S40: =+$AM$40*Ej_Producción!S34 -> 7407.5501 | T40: =+$AM$40*Ej_Producción!T34 -> 10101.205 | U40: =+$AM$40*Ej_Producción!U34 -> 11043.984 | V40: =+$AM$40*Ej_Producción!V34 -> 11582.715 | W40: =+$AM$40*Ej_Producción!W34 -> 11582.715 | X40: =+$AM$40*Ej_Producción!X34 -> 11582.715 | Y40: =+$AM$40*Ej_Producción!Y34 -> 11582.715 | ... AC40: =+$AM$40*Ej_Producción!AC34 -> 11582.715 | AD40: =SUM(R40:AC40) -> 127813.91 | AE40: 105256.95 | AF40: =AD40-AE40 -> 22556.962 | AL40: =+AE40*AK37 -> 22556.962 | AM40: =+AE40+AL40 -> 127813.91
B41: o. Alimentación de personal | C41: 0 | D41: 0 | E41: 0 | F41: 0 | G41: 0 | H41: 0 | I41: 0 | J41: 0 | K41: 0 | L41: 0 | M41: 0 | N41: 0 | O41: =SUM(C41:N41) -> 0 | P41: 16917 | Q41: =O41-P41 -> -16917 | R41: =+$AE$41/12 -> 1409.75 | S41: =+$AE$41/12 -> 1409.75 | T41: =+$AE$41/12 -> 1409.75 | U41: =+$AE$41/12 -> 1409.75 | V41: =+$AE$41/12 -> 1409.75 | W41: =+$AE$41/12 -> 1409.75 | X41: =+$AE$41/12 -> 1409.75 | Y41: =+$AE$41/12 -> 1409.75 | ... AC41: =+$AE$41/12 -> 1409.75 | AD41: =SUM(R41:AC41) -> 16917 | AE41: 16917 | AF41: =AD41-AE41 -> 0
B42: p. Movimiento de carga | C42: 0 | D42: 0 | E42: =1090909/USD -> 180.97002 | F42: 0 | G42: =($P$42*$P$2)*Ej_Producción!G34 -> 1006.7628 | H42: =($P$42*$P$2)*Ej_Producción!H34 -> 796.99558 | I42: =($P$42*$P$2)*Ej_Producción!I34 -> 531.33039 | J42: =($P$42*$P$2)*Ej_Producción!J34 -> 551.00929 | K42: =($P$42*$P$2)*Ej_Producción!K34 -> 570.68819 | L42: =($P$42*$P$2)*Ej_Producción!L34 -> 1259.4498 | M42: =($P$42*$P$2)*Ej_Producción!M34 -> 1653.0279 | N42: =($P$42*$P$2)*Ej_Producción!N34 -> 1357.8443 | O42: =SUM(C42:N42) -> 7908.0783 | P42: 21818 | Q42: =O42-P42 -> -13909.922 | R42: =+$AM$42*Ej_Producción!R34 -> 1436.3602 | S42: =+$AM$42*Ej_Producción!S34 -> 1612.241 | T42: =+$AM$42*Ej_Producción!T34 -> 2198.5104 | U42: =+$AM$42*Ej_Producción!U34 -> 2403.7047 | V42: =+$AM$42*Ej_Producción!V34 -> 2520.9586 | W42: =+$AM$42*Ej_Producción!W34 -> 2520.9586 | X42: =+$AM$42*Ej_Producción!X34 -> 2520.9586 | Y42: =+$AM$42*Ej_Producción!Y34 -> 2520.9586 | ... AC42: =+$AM$42*Ej_Producción!AC34 -> 2520.9586 | AD42: =SUM(R42:AC42) -> 27818.485 | AE42: 22909 | AF42: =AD42-AE42 -> 4909.4854 | AL42: =+AE42*AK37 -> 4909.4854 | AM42: =+AE42+AL42 -> 27818.485
B43: q. Energia electrica Fabrica | C43: 115 | D43: 115 | E43: 115 | F43: 115 | G43: 115 | H43: 115 | I43: 115 | J43: 115 | K43: 115 | L43: 115 | M43: 115 | N43: 115 | O43: =SUM(C43:N43) -> 1380 | P43: 0 | Q43: =O43-P43 -> 1380 | R43: 172.5 | S43: 172.5 | T43: 172.5 | U43: 172.5 | V43: 172.5 | W43: 172.5 | X43: 172.5 | Y43: 172.5 | Z43: 172.5 | AA43: 172.5 | AB43: 172.5 | AC43: 172.5 | AD43: =SUM(R43:AC43) -> 2070 | AE43: 0 | AF43: =AD43-AE43 -> 2070
B44: SUBTOTAL PRODUCCIÓN | C44: =SUM(C34:C43)+C22 -> 33361.294 | D44: =SUM(D34:D43)+D22 -> 9252.4936 | E44: =SUM(E34:E43)+E22 -> 140558.71 | F44: =SUM(F34:F43)+F22 -> 190621.97 | G44: =SUM(G34:G43)+G22 -> 461454.56 | H44: =SUM(H34:H43)+H22 -> 360954.12 | I44: =SUM(I34:I43)+I22 -> 246416.76 | J44: =SUM(J34:J43)+J22 -> 262396.97 | ... N44: =SUM(N34:N43)+N22 -> 655232.49 | O44: =SUM(C44:N44) -> 4032136.4 | P44: 9743974.8 | Q44: =O44-P44 -> -5711838.3 | R44: =SUM(R34:R43)+R22 -> 721688.54 | S44: =SUM(S34:S43)+S22 -> 855199.72 | T44: =SUM(T34:T43)+T22 -> 1162221.9 | U44: =SUM(U34:U43)+U22 -> 1272796.7 | V44: =SUM(V34:V43)+V22 -> 1332033.1 | W44: =SUM(W34:W43)+W22 -> 1332033.1 | X44: =SUM(X34:X43)+X22 -> 1332033.1 | Y44: =SUM(Y34:Y43)+Y22 -> 1332033.1 | ... AC44: =SUM(AC34:AC43)+AC22 -> 1332033.1 | AD44: =SUM(R44:AC44) -> 14668172 | AE44: 11486965 | AF44: =AD44-AE44 -> 3181207.1
P45: =+O44/P44 -> 0.41380818 | Q45: =+Q44/P44 -> -0.58619182 | AD45: =+Ej_Producción!AD33*Ej_Costos!N45 -> 0 | AE45: =+AD44/AE44 -> 1.2769406 | AF45: =+AF44/AE44 -> 0.27694062
B46: 2. GASTOS DE ADMINISTRACIÓN | R46: =+R22/Ej_Producción!R33 -> 932.40929 | S46: =+S22/Ej_Producción!S33 -> 990.14849 | T46: =+T22/Ej_Producción!T33 -> 991.92785 | U46: =+U22/Ej_Producción!U33 -> 995.4225 | V46: =+V22/Ej_Producción!V33 -> 994.11354 | W46: =+W22/Ej_Producción!W33 -> 994.11354 | X46: =+X22/Ej_Producción!X33 -> 994.11354 | Y46: =+Y22/Ej_Producción!Y33 -> 994.11354 | ... AD46: =+AD22/Ej_Producción!AD33 -> 990.63812 | AE46: =+AE22/Ej_Producción!AD18 -> 880.24777
B47: a. Mano de obra administrativa | C47: =15929255/USD -> 2642.4914 | D47: =13649666/USD -> 2264.3322 | E47: =13649666/USD -> 2264.3322 | F47: =13649666/USD -> 2264.3322 | G47: 2221 | H47: 7304.9734 | I47: 7304.9734 | J47: 7304.9734 | K47: 7304.9734 | L47: 7304.9734 | M47: 7304.9734 | N47: 7304.9734 | O47: =SUM(C47:N47) -> 62791.302 | P47: 34597 | Q47: =O47-P47 -> 28194.302 | R47: 7304.9734 | S47: 7304.9734 | T47: 8228.9734 | U47: 8228.9734 | V47: 8228.9734 | W47: 8228.9734 | X47: 8228.9734 | Y47: 8228.9734 | Z47: 8228.9734 | AA47: 8228.9734 | AB47: 8228.9734 | AC47: 8228.9734 | AD47: =SUM(R47:AC47) -> 96899.681 | AE47: 34597 | AF47: =AD47-AE47 -> 62302.681
B48: b. Prestaciones sociales admin. | C48: 0 | D48: 0 | E48: 0 | F48: 0 | G48: 0 | H48: 0 | I48: 0 | J48: 0 | K48: 0 | L48: 0 | M48: 0 | N48: 0 | O48: =SUM(C48:N48) -> 0 | P48: 14907.847 | Q48: =O48-P48 -> -14907.847 | R48: 0 | S48: 0 | T48: 0 | U48: 0 | V48: 0 | W48: 0 | X48: 0 | Y48: 0 | Z48: 0 | AA48: 0 | AB48: 0 | AC48: 0 | AD48: =SUM(R48:AC48) -> 0 | AE48: 14907.847 | AF48: =AD48-AE48 -> -14907.847
B49: c. Agua, comunicaciones, elect. | C49: =44166/USD -> 7.3266624 | D49: =45865/USD -> 7.6085081 | E49: =45783/USD -> 7.5949052 | F49: =45374/USD -> 7.5270565 | G49: =+$P$49/12 -> 87.416667 | H49: =+$P$49/12 -> 87.416667 | I49: =+$P$49/12 -> 87.416667 | J49: =+$P$49/12 -> 87.416667 | K49: =+$P$49/12 -> 87.416667 | L49: =+$P$49/12 -> 87.416667 | M49: =+$P$49/12 -> 87.416667 | N49: =+$P$49/12 -> 87.416667 | O49: =SUM(C49:N49) -> 729.39047 | P49: 1049 | Q49: =O49-P49 -> -319.60953 | R49: =+$AE$49/12 -> 87.416667 | S49: =+$AE$49/12 -> 87.416667 | T49: =+$AE$49/12 -> 87.416667 | U49: =+$AE$49/12 -> 87.416667 | V49: =+$AE$49/12 -> 87.416667 | W49: =+$AE$49/12 -> 87.416667 | X49: =+$AE$49/12 -> 87.416667 | Y49: =+$AE$49/12 -> 87.416667 | ... AC49: =+$AE$49/12 -> 87.416667 | AD49: =SUM(R49:AC49) -> 1049 | AE49: 1049 | AF49: =AD49-AE49 -> 0
A50: P | B50: d. Alquileres | C50: 7170.8 | D50: 7170.8 | E50: 7170.8 | F50: 7170.8 | G50: 7170.8 | H50: 7170.8 | I50: 7170.8 | J50: 7170.8 | K50: 7170.8 | L50: 7170.8 | M50: 7170.8 | N50: 7170.8 | O50: =SUM(C50:N50) -> 86049.6 | P50: 130909 | Q50: =O50-P50 -> -44859.4 | R50: 7170.8 | S50: 7170.8 | T50: 7170.8 | U50: 7170.8 | V50: 7170.8 | W50: 7170.8 | X50: 7170.8 | Y50: 7170.8 | Z50: 7170.8 | AA50: 7170.8 | AB50: 7170.8 | AC50: 7170.8 | AD50: =SUM(R50:AC50) -> 86049.6 | AE50: 130909 | AF50: =AD50-AE50 -> -44859.4
B51: e. Mantenimiento y reparaciones | C51: 0 | D51: =363636/USD -> 60.323285 | E51: 0 | F51: 0 | G51: =+$P$51/12 -> 349.66667 | H51: =+$P$51/12 -> 349.66667 | I51: =+$P$51/12 -> 349.66667 | J51: =+$P$51/12 -> 349.66667 | K51: =+$P$51/12 -> 349.66667 | L51: =+$P$51/12 -> 349.66667 | M51: =+$P$51/12 -> 349.66667 | N51: =+$P$51/12 -> 349.66667 | O51: =SUM(C51:N51) -> 2857.6566 | P51: 4196 | Q51: =O51-P51 -> -1338.3434 | R51: =+$AE$51/12 -> 349.66667 | S51: =+$AE$51/12 -> 349.66667 | T51: =+$AE$51/12 -> 349.66667 | U51: =+$AE$51/12 -> 349.66667 | V51: =+$AE$51/12 -> 349.66667 | W51: =+$AE$51/12 -> 349.66667 | X51: =+$AE$51/12 -> 349.66667 | Y51: =+$AE$51/12 -> 349.66667 | ... AC51: =+$AE$51/12 -> 349.66667 | AD51: =SUM(R51:AC51) -> 4196 | AE51: 4196 | AF51: =AD51-AE51 -> 0
B52: f. Seguros sobre activos fijos | C52: =500000/USD -> 82.9446 | D52: 0 | E52: 0 | F52: 0 | G52: =+$P$52/12 -> 582.75 | H52: =+$P$52/12 -> 582.75 | I52: =+$P$52/12 -> 582.75 | J52: =+$P$52/12 -> 582.75 | K52: =+$P$52/12 -> 582.75 | L52: =+$P$52/12 -> 582.75 | M52: =+$P$52/12 -> 582.75 | N52: =+$P$52/12 -> 582.75 | O52: =SUM(C52:N52) -> 4744.9446 | P52: 6993 | Q52: =O52-P52 -> -2248.0554 | R52: =+$AE$52/12 -> 582.75 | S52: =+$AE$52/12 -> 582.75 | T52: =+$AE$52/12 -> 582.75 | U52: =+$AE$52/12 -> 582.75 | V52: =+$AE$52/12 -> 582.75 | W52: =+$AE$52/12 -> 582.75 | X52: =+$AE$52/12 -> 582.75 | Y52: =+$AE$52/12 -> 582.75 | ... AC52: =+$AE$52/12 -> 582.75 | AD52: =SUM(R52:AC52) -> 6993 | AE52: 6993 | AF52: =AD52-AE52 -> 0
B53: g. Gastos generales | C53: =9400026/USD -> 1559.3628 | D53: =6865219/USD -> 1138.8657 | E53: =2028775/USD -> 336.55186 | F53: =1941361/USD -> 322.05082 | G53: =+$P$53/12 -> 1550.0833 | H53: =+$P$53/12 -> 1550.0833 | I53: =+$P$53/12 -> 1550.0833 | J53: =+$P$53/12 -> 1550.0833 | K53: =+$P$53/12 -> 1550.0833 | L53: =+$P$53/12 -> 1550.0833 | M53: =+$P$53/12 -> 1550.0833 | N53: =+$P$53/12 -> 1550.0833 | O53: =SUM(C53:N53) -> 15757.498 | P53: 18601 | Q53: =O53-P53 -> -2843.5022 | R53: =+$AE$53/12 -> 1550.0833 | S53: =+$AE$53/12 -> 1550.0833 | T53: =+$AE$53/12 -> 1550.0833 | U53: =+$AE$53/12 -> 1550.0833 | V53: =+$AE$53/12 -> 1550.0833 | W53: =+$AE$53/12 -> 1550.0833 | X53: =+$AE$53/12 -> 1550.0833 | Y53: =+$AE$53/12 -> 1550.0833 | ... AC53: =+$AE$53/12 -> 1550.0833 | AD53: =SUM(R53:AC53) -> 18601 | AE53: 18601 | AF53: =AD53-AE53 -> 0
B54: i. Honorarios y otros fijos | C54: 0 | D54: =11027159/USD -> 1829.2866 | E54: =46565747/USD -> 7724.7545 | F54: =11091385/USD -> 1839.941 | G54: =+$P$54/12 -> 2000.75 | H54: =+$P$54/12 -> 2000.75 | I54: =+$P$54/12 -> 2000.75 | J54: =+$P$54/12 -> 2000.75 | K54: =+$P$54/12 -> 2000.75 | L54: =+$P$54/12 -> 2000.75 | M54: =+$P$54/12 -> 2000.75 | N54: =+$P$54/12 -> 2000.75 | O54: =SUM(C54:N54) -> 27399.982 | P54: 24009 | Q54: =O54-P54 -> 3390.982 | R54: =+$AE$54/12 -> 2000.75 | S54: =+$AE$54/12 -> 2000.75 | T54: =+$AE$54/12 -> 2000.75 | U54: =+$AE$54/12 -> 2000.75 | V54: =+$AE$54/12 -> 2000.75 | W54: =+$AE$54/12 -> 2000.75 | X54: =+$AE$54/12 -> 2000.75 | Y54: =+$AE$54/12 -> 2000.75 | ... AC54: =+$AE$54/12 -> 2000.75 | AD54: =SUM(R54:AC54) -> 24009 | AE54: 24009 | AF54: =AD54-AE54 -> 0
B55: SUBTOTAL ADMINISTRACIÓN | C55: =SUM(C47:C54) -> 11462.925 | D55: =SUM(D47:D54) -> 12471.216 | E55: =SUM(E47:E54) -> 17504.033 | F55: =SUM(F47:F54) -> 11604.651 | G55: =SUM(G47:G54) -> 13962.467 | H55: =SUM(H47:H54) -> 19046.44 | I55: =SUM(I47:I54) -> 19046.44 | J55: =SUM(J47:J54) -> 19046.44 | ... N55: =SUM(N47:N54) -> 19046.44 | O55: =SUM(C55:N55) -> 200330.37 | P55: 235261.85 | Q55: =O55-P55 -> -34931.474 | R55: =SUM(R47:R54) -> 19046.44 | S55: =SUM(S47:S54) -> 19046.44 | T55: =SUM(T47:T54) -> 19970.44 | U55: =SUM(U47:U54) -> 19970.44 | V55: =SUM(V47:V54) -> 19970.44 | W55: =SUM(W47:W54) -> 19970.44 | X55: =SUM(X47:X54) -> 19970.44 | Y55: =SUM(Y47:Y54) -> 19970.44 | ... AC55: =SUM(AC47:AC54) -> 19970.44 | AD55: =SUM(R55:AC55) -> 237797.28 | AE55: 235261.85 | AF55: =AD55-AE55 -> 2535.434
P56: =+O55/P55 -> 0.85152087 | Q56: =+Q55/P55 -> -0.14847913 | AE56: =+AD55/AE55 -> 1.0107771 | AF56: =+AF55/AE55 -> 0.010777073
B57: 3. GASTOS NO DESEMBOLSADOS
B58: a. Depreciación de activos fijos | C58: 1312.0698 | D58: 1312.0698 | E58: 1312.0698 | F58: 1312.0698 | G58: 2064.2557 | H58: 2064.2557 | I58: 2064.2557 | J58: 2064.2557 | K58: 2064.2557 | L58: 7947.3833 | M58: 7947.3833 | N58: 7947.3833 | O58: =SUM(C58:N58) -> 39411.708 | P58: =+Depreciación!F7 -> 95368.6 | Q58: =O58-P58 -> -55956.892 | R58: =+AE58/12 -> 7947.3833 | S58: 7947.3833 | T58: 7947.3833 | U58: 7947.3833 | V58: 7947.3833 | W58: 7947.3833 | X58: 7947.3833 | Y58: 7947.3833 | Z58: 7947.3833 | AA58: 7947.3833 | AB58: 7947.3833 | AC58: 7947.3833 | AD58: =SUM(R58:AC58) -> 95368.6 | AE58: =+Depreciación!G7 -> 95368.6 | AF58: =AD58-AE58 -> 0
B59: SUBTOTAL NO DESEMBOLSADOS | C59: =C58 -> 1312.0698 | D59: =D58 -> 1312.0698 | E59: =E58 -> 1312.0698 | F59: =F58 -> 1312.0698 | G59: =G58 -> 2064.2557 | H59: =H58 -> 2064.2557 | I59: =I58 -> 2064.2557 | J59: =J58 -> 2064.2557 | ... N59: =N58 -> 7947.3833 | O59: =SUM(C59:N59) -> 39411.708 | P59: =+P58 -> 95368.6 | Q59: =O59-P59 -> -55956.892 | R59: =R58 -> 7947.3833 | S59: =S58 -> 7947.3833 | T59: =T58 -> 7947.3833 | U59: =U58 -> 7947.3833 | V59: =V58 -> 7947.3833 | W59: =W58 -> 7947.3833 | X59: =X58 -> 7947.3833 | Y59: =Y58 -> 7947.3833 | ... AC59: =AC58 -> 7947.3833 | AD59: =SUM(R59:AC59) -> 95368.6 | AE59: =+AE58 -> 95368.6 | AF59: =AD59-AE59 -> 0
P60: =+O59/P59 -> 0.41325664 | Q60: =+Q59/P59 -> -0.58674336 | AE60: =+AD59/AE59 -> 1 | AF60: =+AF59/AE59 -> 0
B61: 4. GASTOS FINANCIEROS
B62: Intereses totales | C62: =+Ej_Deuda!C7+Ej_Deuda!C13 -> 16667.808 | D62: =+Ej_Deuda!D7+Ej_Deuda!D13 -> 15054.795 | E62: =+Ej_Deuda!E7+Ej_Deuda!E13 -> 16667.808 | F62: =+Ej_Deuda!F7+Ej_Deuda!F13 -> 16136.986 | G62: =+Ej_Deuda!G7+Ej_Deuda!G13 -> 13801.37 | H62: =+Ej_Deuda!H7+Ej_Deuda!H13 -> 13356.164 | I62: =+Ej_Deuda!I7+Ej_Deuda!I13 -> 13801.37 | J62: =+Ej_Deuda!J7+Ej_Deuda!J13 -> 13801.37 | ... N62: =+Ej_Deuda!N7+Ej_Deuda!N13 -> 41210.727 | O62: =SUM(C62:N62) -> 229420.39 | P62: 372101 | Q62: =O62-P62 -> -142680.61 | R62: =+Ej_Deuda!R7+Ej_Deuda!R13 -> 40652.846 | S62: =+Ej_Deuda!S7+Ej_Deuda!S13 -> 40090.781 | T62: =+Ej_Deuda!T7+Ej_Deuda!T13 -> 39524.5 | U62: =+Ej_Deuda!U7+Ej_Deuda!U13 -> 38953.973 | V62: =+Ej_Deuda!V7+Ej_Deuda!V13 -> 38379.166 | W62: =+Ej_Deuda!W7+Ej_Deuda!W13 -> 37800.049 | X62: =+Ej_Deuda!X7+Ej_Deuda!X13+Ej_Flujo!V17 -> 155572.76 | Y62: =+Ej_Deuda!Y7+Ej_Deuda!Y13 -> 36628.751 | Z62: =+Ej_Deuda!Z7+Ej_Deuda!Z13 -> 36036.501 | AA62: =+Ej_Deuda!AA7+Ej_Deuda!AA13+Ej_Flujo!Y17 -> 153792.98 | AB62: =+Ej_Deuda!AB7+Ej_Deuda!AB13 -> 34838.652 | AC62: =+Ej_Deuda!AC7+Ej_Deuda!AC13+Ej_Flujo!AA17 -> 47383.665 | AD62: =SUM(R62:AC62) -> 699654.62 | AE62: 394184 | AF62: =AD62-AE62 -> 305470.62
B63: SUBTOTAL FINANCIEROS | C63: =C62 -> 16667.808 | D63: =D62 -> 15054.795 | E63: =E62 -> 16667.808 | F63: =F62 -> 16136.986 | G63: =G62 -> 13801.37 | H63: =H62 -> 13356.164 | I63: =I62 -> 13801.37 | J63: =J62 -> 13801.37 | ... N63: =N62 -> 41210.727 | O63: =SUM(C63:N63) -> 229420.39 | P63: =+P62 -> 372101 | Q63: =O63-P63 -> -142680.61 | R63: =R62 -> 40652.846 | S63: =S62 -> 40090.781 | T63: =T62 -> 39524.5 | U63: =U62 -> 38953.973 | V63: =V62 -> 38379.166 | W63: =W62 -> 37800.049 | X63: =X62 -> 155572.76 | Y63: =Y62 -> 36628.751 | ... AC63: =AC62 -> 47383.665 | AD63: =SUM(R63:AC63) -> 699654.62 | AE63: =+AE62 -> 394184 | AF63: =AD63-AE63 -> 305470.62
P64: =+O63/P63 -> 0.61655407 | Q64: =+Q63/P63 -> -0.38344593 | AE64: =+AD63/AE63 -> 1.7749442 | AF64: =+AF63/AE63 -> 0.77494424
B65: TOTAL COSTOS EJECUTADOS | C65: =C44+C55+C59+C63 -> 62804.097 | D65: =D44+D55+D59+D63 -> 38090.574 | E65: =E44+E55+E59+E63 -> 176042.62 | F65: =F44+F55+F59+F63 -> 219675.67 | G65: =G44+G55+G59+G63 -> 491282.65 | H65: =H44+H55+H59+H63 -> 395420.98 | I65: =I44+I55+I59+I63 -> 281328.82 | J65: =J44+J55+J59+J63 -> 297309.04 | ... N65: =N44+N55+N59+N63 -> 723437.04 | O65: =SUM(C65:N65) -> 4501298.9 | P65: 10351338 | Q65: =O65-P65 -> -5850038.7 | R65: =R44+R55+R59+R63 -> 789335.21 | S65: =S44+S55+S59+S63 -> 922284.32 | T65: =T44+T55+T59+T63 -> 1229664.2 | U65: =U44+U55+U59+U63 -> 1339668.5 | V65: =V44+V55+V59+V63 -> 1398330.1 | W65: =W44+W55+W59+W63 -> 1397751 | X65: =X44+X55+X59+X63 -> 1515523.7 | Y65: =Y44+Y55+Y59+Y63 -> 1396579.7 | ... AC65: =AC44+AC55+AC59+AC63 -> 1407334.6 | AD65: =SUM(R65:AC65) -> 15700992 | AE65: 12211779 | AF65: =AD65-AE65 -> 3489213.1
P66: =+O65/P65 -> 0.43485191 | Q66: =+Q65/P65 -> -0.56514809 | AE66: =+AD65/AE65 -> 1.2857252 | AF66: =+AF65/AE65 -> 0.28572521
C68: OBSERVACIONES: | H68: Junio | L68: Octubre | R68: Enero | T68: Marzo
H69: *Ingresa en Man. Obra Adm. | L69: *Ingresa en Man. Obra Fabrica | P69: =+P22/Ej_Ingresos!P34 -> 0.87147578 | R69: *Ingresa en Man. Obra Fabrica | T69: *Ingresa en Man. Obra Fabrica & Adm.
H70: Administrador | L70: 5 Operadores | P70: =+O22/Ej_Ingresos!O34 -> 0.92110001 | R70: 9 Operadores p/ Accesorios Met. | T70: 3 Operadores por aumento de Producc.
H71: PCP | P71: =+P70-P69 -> 0.04962423 | T71: 1 Aux. Admin.
O88: salario | P88: 4000000
B89: salario | C89: Tc | D89: Usd | O89: pres. soc. | P89: =+P88*42% -> 1680000
B90: 10000000 | C90: 7800 | D90: =+B90/C90 -> 1282.0513 | E90: Plan | O90: total | P90: =+P88+P89 -> 5680000
C91: =+USD -> 6028.12 | D91: =+B90/C91 -> 1658.892 | E91: Ejecutado | J91: 5145 | K91: TOTAL | O91: usd | P91: =+P90/USD -> 942.25065
D92: =+D90-D91 -> -376.84071 | E92: Diferencia de cambio | J92: =+J91*41% -> 2109.45 | K92: BEN. SOC. | O92: usdx2 | P92: =+P91*2 -> 1884.5013
C93: =+C90-C91 -> 1771.88 | J93: =+J91*59% -> 3035.55 | K93: SALAR.
J94: =+J92+J93 -> 5145 | K94: TOTAL
O97: 1970
O98: 3.64
O99: =+O97*O98 -> 7170.8
O102: salario | P102: 3000000
O103: pres. soc. | P103: =+P102*42% -> 1260000
O104: total | P104: =+P102+P103 -> 4260000
O105: usd | P105: =+P104/USD -> 706.68799
P106: =+P105*5 -> 3533.4399
O108: salario | P108: 3500000
O109: pres. soc. | P109: =+P108*42% -> 1470000
O110: total | P110: =+P108+P109 -> 4970000
O111: usd | P111: =+P110/USD -> 824.46932
P112: =+P111*4 -> 3297.8773
P114: =+P106+P112 -> 6831.3172

Sheet Ej_Resultados
B2: ESTADO DE RESULTADOS EJECUTADO AÑO 1 y 2 vs PROYECTADO
B3: Valores en USD — Calculado automáticamente desde hojas de ejecución
C4: 2026 | R4: 2027
B5: Concepto | C5: Ene | D5: Feb | E5: Mar | F5: Abr | G5: May | H5: Jun | I5: Jul | J5: Ago | K5: Sep | L5: Oct | M5: Nov | N5: Dic | O5: TOTAL EJEC. | P5: PROY. AÑO 1 | Q5: DESVÍO % | R5: Ene | S5: Feb | T5: Mar | U5: Abr | V5: May | W5: Jun | X5: Jul | Y5: Ago | Z5: Sep | AA5: Oct | AB5: Nov | AC5: Dic | AD5: TOTAL EJEC. | AE5: PROY. AÑO 2 | AF5: DESVÍO %
B6: Ingresos netos ejecutados | C6: =Ej_Ingresos!C34 -> 20196 | D6: =Ej_Ingresos!D34 -> 0 | E6: =Ej_Ingresos!E34 -> 109098.95 | F6: =Ej_Ingresos!F34 -> 154939.42 | G6: =Ej_Ingresos!G34 -> 212343.38 | H6: =Ej_Ingresos!H34 -> 547199.49 | I6: =Ej_Ingresos!I34 -> 258860 | J6: =Ej_Ingresos!J34 -> 294470 | ... N6: =Ej_Ingresos!N34 -> 703380 | O6: =SUM(C6:N6) -> 4208607.2 | P6: 10820400 | Q6: =IF(P6=0,0,(O6-P6)/P6) -> -0.61104883 | R6: =Ej_Ingresos!R34 -> 865260 | S6: =Ej_Ingresos!S34 -> 988170 | T6: =Ej_Ingresos!T34 -> 1374525 | U6: =Ej_Ingresos!U34 -> 1489230 | V6: =Ej_Ingresos!V34 -> 1579770 | W6: =Ej_Ingresos!W34 -> 1579770 | X6: =Ej_Ingresos!X34 -> 1579770 | Y6: =Ej_Ingresos!Y34 -> 1579770 | ... AC6: =Ej_Ingresos!AC34 -> 1579770 | AD6: =SUM(R6:AC6) -> 17355345 | AE6: 13591134 | AF6: =IF(AE6=0,0,(AD6-AE6)/AE6) -> 0.27696077
B7: Costos de producción ejecutados | C7: =Ej_Costos!C44 -> 33361.294 | D7: =Ej_Costos!D44 -> 9252.4936 | E7: =Ej_Costos!E44 -> 140558.71 | F7: =Ej_Costos!F44 -> 190621.97 | G7: =Ej_Costos!G44 -> 461454.56 | H7: =Ej_Costos!H44 -> 360954.12 | I7: =Ej_Costos!I44 -> 246416.76 | J7: =Ej_Costos!J44 -> 262396.97 | ... N7: =Ej_Costos!N44 -> 655232.49 | O7: =SUM(C7:N7) -> 4032136.4 | P7: 9743974.8 | Q7: =IF(P7=0,0,(O7-P7)/P7) -> -0.58619182 | R7: =Ej_Costos!R44 -> 721688.54 | S7: =Ej_Costos!S44 -> 855199.72 | T7: =Ej_Costos!T44 -> 1162221.9 | U7: =Ej_Costos!U44 -> 1272796.7 | V7: =Ej_Costos!V44 -> 1332033.1 | W7: =Ej_Costos!W44 -> 1332033.1 | X7: =Ej_Costos!X44 -> 1332033.1 | Y7: =Ej_Costos!Y44 -> 1332033.1 | ... AC7: =Ej_Costos!AC44 -> 1332033.1 | AD7: =SUM(R7:AC7) -> 14668172 | AE7: 11486965 | AF7: =IF(AE7=0,0,(AD7-AE7)/AE7) -> 0.27694062
B9: MARGEN BRUTO | O9: =+O6-O7 -> 176470.79 | P9: =+P6-P7 -> 1076425.2 | Q9: =IF(P9=0,0,(O9-P9)/P9) -> -0.83605848 | AD9: =+AD6-AD7 -> 2687173.4 | AE9: =+AE6-AE7 -> 2104169.5 | AF9: =IF(AE9=0,0,(AD9-AE9)/AE9) -> 0.2770708
B11: Gastos de administración ejecutados | C11: =Ej_Costos!C55 -> 11462.925 | D11: =Ej_Costos!D55 -> 12471.216 | E11: =Ej_Costos!E55 -> 17504.033 | F11: =Ej_Costos!F55 -> 11604.651 | G11: =Ej_Costos!G55 -> 13962.467 | H11: =Ej_Costos!H55 -> 19046.44 | I11: =Ej_Costos!I55 -> 19046.44 | J11: =Ej_Costos!J55 -> 19046.44 | ... N11: =Ej_Costos!N55 -> 19046.44 | O11: =SUM(C11:N11) -> 200330.37 | P11: 235261.85 | Q11: =IF(P11=0,0,(O11-P11)/P11) -> -0.14847913 | R11: =Ej_Costos!R55 -> 19046.44 | S11: =Ej_Costos!S55 -> 19046.44 | T11: =Ej_Costos!T55 -> 19970.44 | U11: =Ej_Costos!U55 -> 19970.44 | V11: =Ej_Costos!V55 -> 19970.44 | W11: =Ej_Costos!W55 -> 19970.44 | X11: =Ej_Costos!X55 -> 19970.44 | Y11: =Ej_Costos!Y55 -> 19970.44 | ... AC11: =Ej_Costos!AC55 -> 19970.44 | AD11: =SUM(R11:AC11) -> 237797.28 | AE11: 235261.85 | AF11: =IF(AE11=0,0,(AD11-AE11)/AE11) -> 0.010777073
B13: EBITDA EJECUTADO | C13: =C6-C7-C11 -> -24628.219 | D13: =D6-D7-D11 -> -21723.71 | E13: =E6-E7-E11 -> -48963.795 | F13: =F6-F7-F11 -> -47287.2 | G13: =G6-G7-G11 -> -263073.65 | H13: =H6-H7-H11 -> 167198.93 | I13: =I6-I7-I11 -> -6603.1972 | J13: =J6-J7-J11 -> 13026.59 | ... N13: =N6-N7-N11 -> 29101.071 | O13: =SUM(C13:N13) -> -23859.586 | P13: 841163.4 | Q13: =IF(P13=0,0,(O13-P13)/P13) -> -1.028365 | R13: =R6-R7-R11 -> 124525.02 | S13: =S6-S7-S11 -> 113923.84 | T13: =T6-T7-T11 -> 192332.64 | U13: =U6-U7-U11 -> 196462.81 | V13: =V6-V7-V11 -> 227766.47 | W13: =W6-W7-W11 -> 227766.47 | X13: =X6-X7-X11 -> 227766.47 | Y13: =Y6-Y7-Y11 -> 227766.47 | ... AC13: =AC6-AC7-AC11 -> 227766.47 | AD13: =SUM(R13:AC13) -> 2449376.1 | AE13: 1868907.6 | AF13: =IF(AE13=0,0,(AD13-AE13)/AE13) -> 0.31059238
B14: Gastos no desembolsados (depreciación) | C14: =+Ej_Costos!C58 -> 1312.0698 | D14: =+Ej_Costos!D58 -> 1312.0698 | E14: =+Ej_Costos!E58 -> 1312.0698 | F14: =+Ej_Costos!F58 -> 1312.0698 | G14: =+Ej_Costos!G58 -> 2064.2557 | H14: =+Ej_Costos!H58 -> 2064.2557 | I14: =+Ej_Costos!I58 -> 2064.2557 | J14: =+Ej_Costos!J58 -> 2064.2557 | ... N14: =+Ej_Costos!N58 -> 7947.3833 | O14: =SUM(C14:N14) -> 39411.708 | P14: =+Ej_Costos!P58 -> 95368.6 | Q14: =IF(P14=0,0,(O14-P14)/P14) -> -0.58674336 | R14: =+Ej_Costos!R58 -> 7947.3833 | S14: =+Ej_Costos!S58 -> 7947.3833 | T14: =+Ej_Costos!T58 -> 7947.3833 | U14: =+Ej_Costos!U58 -> 7947.3833 | V14: =+Ej_Costos!V58 -> 7947.3833 | W14: =+Ej_Costos!W58 -> 7947.3833 | X14: =+Ej_Costos!X58 -> 7947.3833 | Y14: =+Ej_Costos!Y58 -> 7947.3833 | ... AC14: =+Ej_Costos!AC58 -> 7947.3833 | AD14: =SUM(R14:AC14) -> 95368.6 | AE14: =+Ej_Costos!AE58 -> 95368.6 | AF14: =IF(AE14=0,0,(AD14-AE14)/AE14) -> -1.5258602e-16
B15: Gastos financieros ejecutados | C15: =Ej_Costos!C63 -> 16667.808 | D15: =Ej_Costos!D63 -> 15054.795 | E15: =Ej_Costos!E63 -> 16667.808 | F15: =Ej_Costos!F63 -> 16136.986 | G15: =Ej_Costos!G63 -> 13801.37 | H15: =Ej_Costos!H63 -> 13356.164 | I15: =Ej_Costos!I63 -> 13801.37 | J15: =Ej_Costos!J63 -> 13801.37 | ... N15: =Ej_Costos!N63 -> 41210.727 | O15: =SUM(C15:N15) -> 229420.39 | P15: 372101 | Q15: =IF(P15=0,0,(O15-P15)/P15) -> -0.38344593 | R15: =Ej_Costos!R63 -> 40652.846 | S15: =Ej_Costos!S63 -> 40090.781 | T15: =Ej_Costos!T63 -> 39524.5 | U15: =Ej_Costos!U63 -> 38953.973 | V15: =Ej_Costos!V63 -> 38379.166 | W15: =Ej_Costos!W63 -> 37800.049 | X15: =Ej_Costos!X63 -> 155572.76 | Y15: =Ej_Costos!Y63 -> 36628.751 | ... AC15: =Ej_Costos!AC63 -> 47383.665 | AD15: =SUM(R15:AC15) -> 699654.62 | AE15: 394184 | AF15: =IF(AE15=0,0,(AD15-AE15)/AE15) -> 0.77494424
B17: Utilidad antes de impuesto | C17: =C13-C14-C15 -> -42608.097 | D17: =D13-D14-D15 -> -38090.574 | E17: =E13-E14-E15 -> -66943.673 | F17: =F13-F14-F15 -> -64736.256 | G17: =G13-G14-G15 -> -278939.28 | H17: =H13-H14-H15 -> 151778.51 | I17: =I13-I14-I15 -> -22468.823 | J17: =J13-J14-J15 -> -2839.0351 | ... N17: =N13-N14-N15 -> -20057.039 | O17: =SUM(C17:N17) -> -292691.68 | P17: 469062.4 | R17: =R13-R14-R15 -> 75924.791 | S17: =S13-S14-S15 -> 65885.678 | T17: =T13-T14-T15 -> 144860.76 | U17: =U13-U14-U15 -> 149561.46 | V17: =V13-V14-V15 -> 181439.92 | W17: =W13-W14-W15 -> 182019.04 | X17: =X13-X14-X15 -> 64246.336 | Y17: =Y13-Y14-Y15 -> 183190.34 | ... AC17: =AC13-AC14-AC15 -> 172435.43 | AD17: =SUM(R17:AC17) -> 1654352.9 | AE17: 1379355 | AF17: =IF(AE17=0,0,(AD17-AE17)/AE17) -> 0.19936699
B18: Impuesto Maquila (1% ingresos) | C18: =C6*Supuestos!B68 -> 201.96 | D18: =D6*Supuestos!B68 -> 0 | E18: =E6*Supuestos!B68 -> 1090.9895 | F18: =F6*Supuestos!B68 -> 1549.3942 | G18: =G6*Supuestos!B68 -> 2123.4338 | H18: =H6*Supuestos!B68 -> 5471.9949 | I18: =I6*Supuestos!B68 -> 2588.6 | J18: =J6*Supuestos!B68 -> 2944.7 | K18: =K6*Supuestos!B68 -> 3206.4 | L18: =L6*Supuestos!B68 -> 7075.8 | M18: =M6*Supuestos!B68 -> 8799 | N18: =N6*Supuestos!B68 -> 7033.8 | O18: =SUM(C18:N18) -> 42086.072 | P18: 108204 | Q18: =IF(P18=0,0,(O18-P18)/P18) -> -0.61104883 | R18: =R6*Supuestos!$B$68 -> 8652.6 | S18: =S6*Supuestos!$B$68 -> 9881.7 | T18: =T6*Supuestos!$B$68 -> 13745.25 | U18: =U6*Supuestos!$B$68 -> 14892.3 | V18: =V6*Supuestos!$B$68 -> 15797.7 | W18: =W6*Supuestos!$B$68 -> 15797.7 | X18: =X6*Supuestos!$B$68 -> 15797.7 | Y18: =Y6*Supuestos!$B$68 -> 15797.7 | ... AC18: =AC6*Supuestos!$B$68 -> 15797.7 | AD18: =SUM(R18:AC18) -> 173553.45 | AE18: 135911.34 | AF18: =IF(AE18=0,0,(AD18-AE18)/AE18) -> 0.27696077
B20: UTILIDAD NETA EJECUTADA | C20: =C17-C18 -> -42810.057 | D20: =D17-D18 -> -38090.574 | E20: =E17-E18 -> -68034.662 | F20: =F17-F18 -> -66285.65 | G20: =G17-G18 -> -281062.71 | H20: =H17-H18 -> 146306.51 | I20: =I17-I18 -> -25057.423 | J20: =J17-J18 -> -5783.7351 | ... N20: =N17-N18 -> -27090.839 | O20: =SUM(C20:N20) -> -334777.75 | P20: 360858.4 | Q20: =IF(P20=0,0,(O20-P20)/P20) -> -1.9277261 | R20: =R17-R18 -> 67272.191 | S20: =S17-S18 -> 56003.978 | T20: =T17-T18 -> 131115.51 | U20: =U17-U18 -> 134669.16 | V20: =V17-V18 -> 165642.22 | W20: =W17-W18 -> 166221.34 | X20: =X17-X18 -> 48448.636 | Y20: =Y17-Y18 -> 167392.64 | ... AC20: =AC17-AC18 -> 156637.73 | AD20: =SUM(R20:AC20) -> 1480799.4 | AE20: 1243443.7 | AF20: =IF(AE20=0,0,(AD20-AE20)/AE20) -> 0.1908858
B22: Margen Bruto | O22: =IF(O6=0,0,O9/O6) -> 0.041930924 | P22: =IF(P6=0,0,P9/P6) -> 0.099481096 | AD22: =IF(AD6=0,0,AD9/AD6) -> 0.15483261 | AE22: =IF(AE6=0,0,AE9/AE6) -> 0.15481927
B23: Margen EBITDA | C23: =IF(C6=0,0,C13/C6) -> -1.2194602 | D23: =IF(D6=0,0,D13/D6) -> 0 | E23: =IF(E6=0,0,E13/E6) -> -0.44880171 | F23: =IF(F6=0,0,F13/F6) -> -0.30519799 | G23: =IF(G6=0,0,G13/G6) -> -1.2389068 | H23: =IF(H6=0,0,H13/H6) -> 0.30555388 | I23: =IF(I6=0,0,I13/I6) -> -0.025508758 | J23: =IF(J6=0,0,J13/J6) -> 0.044237411 | ... P23: =IF(P6=0,0,P13/P6) -> 0.07773866 | R23: =IF(R6=0,0,R13/R6) -> 0.1439163 | S23: =IF(S6=0,0,S13/S6) -> 0.1152877 | T23: =IF(T6=0,0,T13/T6) -> 0.13992663 | U23: =IF(U6=0,0,U13/U6) -> 0.13192241 | V23: =IF(V6=0,0,V13/V6) -> 0.14417698 | W23: =IF(W6=0,0,W13/W6) -> 0.14417698 | X23: =IF(X6=0,0,X13/X6) -> 0.14417698 | Y23: =IF(Y6=0,0,Y13/Y6) -> 0.14417698 | ... AE23: =IF(AE6=0,0,AE13/AE6) -> 0.13750932
B24: Margen Neto | C24: =IF(C6=0,0,C20/C6) -> -2.1197295 | D24: =IF(D6=0,0,D20/D6) -> 0 | E24: =IF(E6=0,0,E20/E6) -> -0.62360511 | F24: =IF(F6=0,0,F20/F6) -> -0.42781657 | G24: =IF(G6=0,0,G20/G6) -> -1.3236236 | H24: =IF(H6=0,0,H20/H6) -> 0.26737327 | I24: =IF(I6=0,0,I20/I6) -> -0.09679913 | J24: =IF(J6=0,0,J20/J6) -> -0.019641169 | ... P24: =IF(P6=0,0,P20/P6) -> 0.033349821 | R24: =IF(R6=0,0,R20/R6) -> 0.07774795 | S24: =IF(S6=0,0,S20/S6) -> 0.056674436 | T24: =IF(T6=0,0,T20/T6) -> 0.095389688 | U24: =IF(U6=0,0,U20/U6) -> 0.090428717 | V24: =IF(V6=0,0,V20/V6) -> 0.10485211 | W24: =IF(W6=0,0,W20/W6) -> 0.1052187 | X24: =IF(X6=0,0,X20/X6) -> 0.030668158 | Y24: =IF(Y6=0,0,Y20/Y6) -> 0.10596013 | ... AE24: =IF(AE6=0,0,AE20/AE6) -> 0.091489327

Sheet Ej_Deuda
B2: SEGUIMIENTO SERVICIO DE DEUDA LARGO PLAZO
C3: 2026 | R3: 2027
B4: PRÉSTAMO 1 - INICIAL | C4: Ene | D4: Feb | E4: Mar | F4: Abr | G4: May | H4: Jun | I4: Jul | J4: Ago | K4: Sep | L4: Oct | M4: Nov | N4: Dic | O4: TOTAL EJEC. | P4: PROY. AÑO 1 | Q4: DESVÍO | R4: Ene | S4: Feb | T4: Mar | U4: Abr | V4: May | W4: Jun | X4: Jul | Y4: Ago | Z4: Sep | AA4: Oct | AB4: Nov | AC4: Dic | AD4: TOTAL EJEC. | AE4: PROY. AÑO 2 | AF4: DESVÍO
B5: Cuota mensual pagada | C5: =C6+C7+C8 -> 18334.589 | D5: =D6+D7+D8 -> 16560.274 | E5: =E6+E7+E8 -> 18334.589 | F5: =F6+F7+F8 -> 17750.685 | G5: =G6+G7+G8 -> 15181.507 | H5: =H6+H7+H8 -> 14691.781 | I5: =I6+I7+I8 -> 15181.507 | J5: =J6+J7+J8 -> 15181.507 | ... N5: =N6+N7+N8 -> 96067.672 | O5: =SUM(C5:N5) -> 353269.51 | R5: =R6+R7+R8 -> 96022.905 | S5: =S6+S7+S8 -> 95977.801 | T5: =T6+T7+T8 -> 95932.359 | U5: =U6+U7+U8 -> 95886.576 | V5: =V6+V7+V8 -> 95840.45 | W5: =W6+W7+W8 -> 95793.978 | X5: =X6+X7+X8 -> 95747.156 | Y5: =Y6+Y7+Y8 -> 95699.984 | ... AC5: =AC6+AC7+AC8 -> 95507.732 | AD5: =SUM(R5:AC5) -> 1149219
B6: Capital amortizado | C6: 0 | D6: 0 | E6: 0 | F6: 0 | G6: 0 | H6: 0 | I6: 0 | J6: 0 | K6: 0 | L6: 0 | M6: 59246.207 | N6: 59690.553 | O6: =SUM(C6:N6) -> 118936.76 | P6: ='Servicio Deuda'!D9 -> 118936.76 | Q6: =O6-P6 -> -0.00022168402 | R6: 60138.232 | S6: 60589.269 | T6: 61043.689 | U6: 61501.516 | V6: 61962.778 | W6: 62427.498 | X6: 62895.7 | Y6: 63367.42 | Z6: 63842.68 | AA6: 64321.5 | AB6: 64803.91 | AC6: 65289.94 | AD6: =SUM(R6:AC6) -> 752184.13 | AE6: ='Servicio Deuda'!E9 -> 752184.13 | AF6: =AD6-AE6 -> 0.0022280441
B7: Intereses pagados | C7: 16667.808 | D7: 15054.795 | E7: 16667.808 | F7: 16136.986 | G7: 13801.37 | H7: 13356.164 | I7: 13801.37 | J7: 13801.37 | K7: 13356.164 | L7: 13801.37 | M7: 33514.455 | N7: 33070.108 | O7: =SUM(C7:N7) -> 213029.77 | P7: ='Servicio Deuda'!D11 -> 66584.56 | Q7: =O7-P7 -> 146445.21 | R7: 32622.429 | S7: 32171.393 | T7: 31716.973 | U7: 31259.145 | V7: 30797.884 | W7: 30333.163 | X7: 29864.96 | Y7: 29393.24 | Z7: 28917.98 | AA7: 28436.16 | AB7: 27956.75 | AC7: 27470.72 | AD7: =SUM(R7:AC7) -> 360940.8 | AE7: ='Servicio Deuda'!E11 -> 360943.81 | AF7: =AD7-AE7 -> -3.0125419
B8: IVA sobre intereses | C8: =+C7*10% -> 1666.7808 | D8: =+D7*10% -> 1505.4795 | E8: =+E7*10% -> 1666.7808 | F8: =+F7*10% -> 1613.6986 | G8: =+G7*10% -> 1380.137 | H8: =+H7*10% -> 1335.6164 | I8: =+I7*10% -> 1380.137 | J8: =+J7*10% -> 1380.137 | ... N8: =+N7*10% -> 3307.0108 | O8: =SUM(C8:N8) -> 21302.977 | P8: ='Servicio Deuda'!D12 -> 6658.456 | Q8: =O8-P8 -> 14644.521 | R8: =+R7*10% -> 3262.2429 | S8: =+S7*10% -> 3217.1393 | T8: =+T7*10% -> 3171.6973 | U8: =+U7*10% -> 3125.9145 | V8: =+V7*10% -> 3079.7884 | W8: =+W7*10% -> 3033.3163 | X8: =+X7*10% -> 2986.496 | Y8: =+Y7*10% -> 2939.324 | ... AC8: =+AC7*10% -> 2747.072 | AD8: =SUM(R8:AC8) -> 36094.08 | AE8: ='Servicio Deuda'!E12 -> 36094.381 | AF8: =AD8-AE8 -> -0.30125419
B10: PRÉSTAMO 2 - OPERATIVO | C10: Ene | D10: Feb | E10: Mar | F10: Abr | G10: May | H10: Jun | I10: Jul | J10: Ago | K10: Sep | L10: Oct | M10: Nov | N10: Dic | O10: TOTAL EJEC. | P10: PROY. AÑO 1 | Q10: DESVÍO | R10: Ene | S10: Feb | T10: Mar | U10: Abr | V10: May | W10: Jun | X10: Jul | Y10: Ago | Z10: Sep | AA10: Oct | AB10: Nov | AC10: Dic | AD10: TOTAL EJEC. | AE10: PROY. AÑO 2 | AF10: DESVÍO
B11: Cuota mensual pagada | C11: 0 | D11: 0 | E11: 0 | F11: 0 | G11: 0 | H11: 0 | I11: 0 | J11: 0 | K11: 0 | L11: 0 | M11: =M12+M13+M14 -> 23659.191 | N11: =N12+N13+N14 -> 23648.253 | O11: =SUM(C11:N11) -> 47307.443 | R11: =R12+R13+R14 -> 23637.232 | S11: =S12+S13+S14 -> 23626.13 | T11: =T12+T13+T14 -> 23614.943 | U11: =U12+U13+U14 -> 23603.673 | V11: =V12+V13+V14 -> 23592.319 | W11: =W12+W13+W14 -> 23580.879 | X11: =X12+X13+X14 -> 23569.354 | Y11: =Y12+Y13+Y14 -> 23557.742 | ... AC11: =AC12+AC13+AC14 -> 23510.417 | AD11: =SUM(R11:AC11) -> 282895.37
B12: Capital amortizado | C12: 0 | D12: 0 | E12: 0 | F12: 0 | G12: 0 | H12: 0 | I12: 0 | J12: 0 | K12: 0 | L12: 0 | M12: 14584.191 | N12: 14693.572 | O12: =SUM(C12:N12) -> 29277.763 | P12: 0 | Q12: =O12-P12 -> 29277.763 | R12: 14803.774 | S12: 14914.802 | T12: 15026.663 | U12: 15139.363 | V12: 15252.908 | W12: 15367.305 | X12: 15482.56 | Y12: 15598.679 | Z12: 15715.669 | AA12: 15833.537 | AB12: 15952.288 | AC12: 16071.931 | AD12: =SUM(R12:AC12) -> 185159.48 | AE12: ='Servicio Deuda'!D18 -> 29277.763 | AF12: =AD12-AE12 -> 155881.72
B13: Intereses pagados | C13: 0 | D13: 0 | E13: 0 | F13: 0 | G13: 0 | H13: 0 | I13: 0 | J13: 0 | K13: 0 | L13: 0 | M13: 8250 | N13: 8140.6186 | O13: =SUM(C13:N13) -> 16390.619 | P13: 0 | Q13: =O13-P13 -> 16390.619 | R13: 8030.4168 | S13: 7919.3885 | T13: 7807.5275 | U13: 7694.8275 | V13: 7581.2823 | W13: 7466.8854 | X13: 7351.6307 | Y13: 7235.5115 | Z13: 7118.5214 | AA13: 7000.6538 | AB13: 6881.9023 | AC13: 6762.2601 | AD13: =SUM(R13:AC13) -> 88850.808 | AE13: ='Servicio Deuda'!D20 -> 16390.619 | AF13: =AD13-AE13 -> 72460.189
B14: IVA sobre intereses | C14: 0 | D14: 0 | E14: 0 | F14: 0 | G14: 0 | H14: 0 | I14: 0 | J14: 0 | K14: 0 | L14: 0 | M14: =+M13*10% -> 825 | N14: =+N13*10% -> 814.06186 | O14: =SUM(C14:N14) -> 1639.0619 | P14: 0 | Q14: =O14-P14 -> 1639.0619 | R14: =+R13*10% -> 803.04168 | S14: =+S13*10% -> 791.93885 | T14: =+T13*10% -> 780.75275 | U14: =+U13*10% -> 769.48275 | V14: =+V13*10% -> 758.12823 | W14: =+W13*10% -> 746.68854 | X14: =+X13*10% -> 735.16307 | Y14: =+Y13*10% -> 723.55115 | ... AC14: =+AC13*10% -> 676.22601 | AD14: =SUM(R14:AC14) -> 8885.0808 | AE14: ='Servicio Deuda'!D21 -> 1639.0619 | AF14: =AD14-AE14 -> 7246.0189
B16: Saldo de deuda P CIE | C16: 2500000 | D16: =+C16 -> 2500000 | E16: =+D16 -> 2500000 | F16: =+E16 -> 2500000 | G16: =+F16 -> 2500000 | H16: =+G16 -> 2500000 | I16: =+H16 -> 2500000 | J16: =+I16 -> 2500000 | K16: =+J16 -> 2500000 | L16: =+K16 -> 2500000
B17: Saldo de deuda P1 | L17: 4468594 | M17: =L17-M6 -> 4409347.8 | N17: =M17-N6 -> 4349657.2 | R17: =N17-R6 -> 4289519 | S17: =R17-S6 -> 4228929.7 | T17: =S17-T6 -> 4167886.1 | U17: =T17-U6 -> 4106384.5 | V17: =U17-V6 -> 4044421.8 | W17: =V17-W6 -> 3981994.3 | X17: =W17-X6 -> 3919098.6 | Y17: =X17-Y6 -> 3855731.1 | Z17: =Y17-Z6 -> 3791888.5 | ... AC17: =AB17-AC6 -> 3597473.1
B18: Saldo de deuda P2 | L18: 1100000 | M18: =L18-M12 -> 1085415.8 | N18: =M18-N12 -> 1070722.2 | R18: =N18-R12 -> 1055918.5 | S18: =R18-S12 -> 1041003.7 | T18: =S18-T12 -> 1025977 | U18: =T18-U12 -> 1010837.6 | V18: =U18-V12 -> 995584.73 | W18: =V18-W12 -> 980217.42 | X18: =W18-X12 -> 964734.86 | Y18: =X18-Y12 -> 949136.18 | Z18: =Y18-Z12 -> 933420.51 | ... AC18: =AB18-AC12 -> 885562.76
AC19: =+AC17+AC18 -> 4483035.9
C20: De enero a octubre intereses + IVA por financiamiento de CIE S.A. (sin contar con intereses ya abonados anteriormente)
C22: P1 tomado por Aliaza del Acero y cancelación de crédito a CIE S.A. (capital + Intereses + IVA)
C23: Cuotas a abonar según plan P1:
C24: 4468594 | D24: Monto préstamo 1 (USD)
C25: 0.09 | D25: Tasa anual préstamo 1 (%)
C26: 60 | D26: Plazo préstamo 1 (meses)
C27: 0.1 | D27: IVA sobre intereses (%)
C29: P2 tomado por Aliaza del Acero
C30: Cuotas a abonar según plan P2:
C31: 1100000 | D31: Monto préstamo 1 (USD)
C32: 0.09 | D32: Tasa anual préstamo 1 (%)
C33: 60 | D33: Plazo préstamo 1 (meses)
C34: 0.1 | D34: IVA sobre intereses (%)

Sheet Dashboard Ejec.
B2: DASHBOARD DE EJECUCIÓN AÑO 1 | J2: DASHBOARD DE EJECUCIÓN AÑO 2
B3: Comparativo Proyectado vs Ejecutado — Actualización automática | J3: Comparativo Proyectado vs Ejecutado — Actualización automática
B5: INDICADORES PRINCIPALES | C5: EJECUTADO | D5: PROYECTADO | E5: DESVÍO % | J5: INDICADORES PRINCIPALES | K5: EJECUTADO | L5: PROYECTADO | M5: DESVÍO %
B6: Ingresos Netos (USD) | C6: =Ej_Resultados!O6 -> 4208607.2 | D6: =+Ej_Resultados!P6 -> 10820400 | E6: =IF(D6=0,0,(C6-D6)/ABS(D6)) -> -0.61104883 | J6: Ingresos Netos (USD) | K6: =+Ej_Resultados!AD6 -> 17355345 | L6: =+Ej_Resultados!AE6 -> 13591134 | M6: =IF(L6=0,0,(K6-L6)/ABS(L6)) -> 0.27696077
B7: Costos Totales (USD) | C7: =Ej_Costos!O65 -> 4501298.9 | D7: =+Ej_Resultados!P7 -> 9743974.8 | E7: =IF(D7=0,0,(C7-D7)/ABS(D7)) -> -0.53804284 | J7: Costos Totales (USD) | K7: =+Ej_Costos!AD65 -> 15700992 | L7: =+Ej_Costos!AE65 -> 12211779 | M7: =IF(L7=0,0,(K7-L7)/ABS(L7)) -> 0.28572521
B8: EBITDA (USD) | C8: =Ej_Resultados!O13 -> -23859.586 | D8: =+Ej_Resultados!P13 -> 841163.4 | E8: =IF(D8=0,0,(C8-D8)/ABS(D8)) -> -1.028365 | J8: EBITDA (USD) | K8: =+Ej_Resultados!AD13 -> 2449376.1 | L8: =+Ej_Resultados!AE13 -> 1868907.6 | M8: =IF(L8=0,0,(K8-L8)/ABS(L8)) -> 0.31059238
B9: Utilidad Neta (USD) | C9: =Ej_Resultados!O20 -> -334777.75 | D9: =+Ej_Resultados!P20 -> 360858.4 | E9: =IF(D9=0,0,(C9-D9)/ABS(D9)) -> -1.9277261 | J9: Utilidad Neta (USD) | K9: =+Ej_Resultados!AD20 -> 1480799.4 | L9: =+Ej_Resultados!AE20 -> 1243443.7 | M9: =IF(L9=0,0,(K9-L9)/ABS(L9)) -> 0.1908858
B10: Margen EBITDA (%) | C10: =Ej_Resultados!O23 -> -0.0056692355 | D10: =+Ej_Resultados!P23 -> 0.07773866 | E10: =IF(D10=0,0,(C10-D10)/ABS(D10)) -> -1.0729268 | J10: Margen EBITDA (%) | K10: =+Ej_Resultados!AD23 -> 0.14113094 | L10: =+Ej_Resultados!AE23 -> 0.13750932 | M10: =IF(L10=0,0,(K10-L10)/ABS(L10)) -> 0.02633723
B11: Margen Neto (%) | C11: =Ej_Resultados!O24 -> -0.079545972 | D11: =+Ej_Resultados!P24 -> 0.033349821 | E11: =IF(D11=0,0,(C11-D11)/ABS(D11)) -> -3.3851994 | J11: Margen Neto (%) | K11: =+Ej_Resultados!AD24 -> 0.085322386 | L11: =+Ej_Resultados!AE24 -> 0.091489327 | M11: =IF(L11=0,0,(K11-L11)/ABS(L11)) -> -0.06740612
B12: Producción Total (Tn) | C12: =Ej_Producción!O33 -> 4315.166 | D12: =+Ej_Producción!O18 -> 11087 | E12: =IF(D12=0,0,(C12-D12)/ABS(D12)) -> -0.61079048 | J12: Producción Total (Tn) | K12: =+Ej_Producción!AD33 -> 14235 | L12: =+Ej_Producción!AE18 -> 12587 | M12: =IF(L12=0,0,(K12-L12)/ABS(L12)) -> 0.13092874
B13: Ventas Total (Tn) | C13: =Ej_Producción!O48 -> 4195.166 | D13: =+Ej_Producción!P48 -> 10920 | E13: =IF(D13=0,0,(C13-D13)/ABS(D13)) -> -0.61582729 | J13: Ventas Total (Tn) | K13: =+Ej_Producción!AD48 -> 14235 | L13: =+Ej_Producción!AE48 -> 12397 | M13: =IF(L13=0,0,(K13-L13)/ABS(L13)) -> 0.14826168
B15: EVOLUCIÓN MENSUAL ACUMULADA | J15: EVOLUCIÓN MENSUAL ACUMULADA
B16: Mes | C16: Ingresos Ejec. Acum. | D16: Ingresos Proy. Acum. | E16: EBITDA Ejec. Acum. | F16: EBITDA Proy. Acum. | J16: Mes | K16: Ingresos Ejec. Acum. | L16: Ingresos Proy. Acum. | M16: EBITDA Ejec. Acum. | N16: EBITDA Proy. Acum.
B17: Ene | C17: =SUM(Ej_Ingresos!C34:C34) -> 20196 | D17: 901700 | E17: =SUM(Ej_Resultados!$C$13:$C$13) -> -24628.219 | F17: 70096.95 | J17: Ene | K17: =SUM(Ej_Ingresos!$R$34:R34) -> 865260 | L17: =(+Ej_Ingresos!$AE$34/12)*1 -> 1132594.5 | M17: =SUM(Ej_Resultados!$R$13:R13) -> 124525.02 | N17: =Ej_Resultados!$AE$13/12*1 -> 155742.3
B18: Feb | C18: =SUM(Ej_Ingresos!C34:D34) -> 20196 | D18: 1803400 | E18: =SUM(Ej_Resultados!$C$13:$D$13) -> -46351.929 | F18: 140193.9 | J18: Feb | K18: =SUM(Ej_Ingresos!$R$34:S34) -> 1853430 | L18: =(+Ej_Ingresos!$AE$34/12)*2 -> 2265189 | M18: =SUM(Ej_Resultados!$R$13:S13) -> 238448.86 | N18: =Ej_Resultados!$AE$13/12*2 -> 311484.61
B19: Mar | C19: =SUM(Ej_Ingresos!C34:E34) -> 129294.95 | D19: 2705100 | E19: =SUM(Ej_Resultados!$C$13:$E$13) -> -95315.724 | F19: 210290.85 | J19: Mar | K19: =SUM(Ej_Ingresos!$R$34:T34) -> 3227955 | L19: =(+Ej_Ingresos!$AE$34/12)*3 -> 3397783.5 | M19: =SUM(Ej_Resultados!$R$13:T13) -> 430781.51 | N19: =Ej_Resultados!$AE$13/12*3 -> 467226.91
B20: Abr | C20: =SUM(Ej_Ingresos!C34:F34) -> 284234.37 | D20: 3606800 | E20: =SUM(Ej_Resultados!$C$13:$F$13) -> -142602.92 | F20: 280387.8 | J20: Abr | K20: =SUM(Ej_Ingresos!$R$34:U34) -> 4717185 | L20: =(+Ej_Ingresos!$AE$34/12)*4 -> 4530378 | M20: =SUM(Ej_Resultados!$R$13:U13) -> 627244.32 | N20: =Ej_Resultados!$AE$13/12*4 -> 622969.21
B21: May | C21: =SUM(Ej_Ingresos!C34:G34) -> 496577.74 | D21: 4508500 | E21: =SUM(Ej_Resultados!$C$13:$G$13) -> -405676.58 | F21: 350484.75 | J21: May | K21: =SUM(Ej_Ingresos!$R$34:V34) -> 6296955 | L21: =(+Ej_Ingresos!$AE$34/12)*5 -> 5662972.5 | M21: =SUM(Ej_Resultados!$R$13:V13) -> 855010.8 | N21: =Ej_Resultados!$AE$13/12*5 -> 778711.52
B22: Jun | C22: =SUM(Ej_Ingresos!C34:H34) -> 1043777.2 | D22: 5410200 | E22: =SUM(Ej_Resultados!$C$13:$H$13) -> -238477.65 | F22: 420581.7 | J22: Jun | K22: =SUM(Ej_Ingresos!$R$34:W34) -> 7876725 | L22: =(+Ej_Ingresos!$AE$34/12)*6 -> 6795567 | M22: =SUM(Ej_Resultados!$R$13:W13) -> 1082777.3 | N22: =Ej_Resultados!$AE$13/12*6 -> 934453.82
B23: Jul | C23: =SUM(Ej_Ingresos!C34:I34) -> 1302637.2 | D23: 6311900 | E23: =SUM(Ej_Resultados!$C$13:$I$13) -> -245080.84 | F23: 490678.65 | J23: Jul | K23: =SUM(Ej_Ingresos!$R$34:X34) -> 9456495 | L23: =(+Ej_Ingresos!$AE$34/12)*7 -> 7928161.5 | M23: =SUM(Ej_Resultados!$R$13:X13) -> 1310543.7 | N23: =Ej_Resultados!$AE$13/12*7 -> 1090196.1
B24: Ago | C24: =SUM(Ej_Ingresos!C34:J34) -> 1597107.2 | D24: 7213600 | E24: =SUM(Ej_Resultados!$C$13:$J$13) -> -232054.25 | F24: 560775.6 | J24: Ago | K24: =SUM(Ej_Ingresos!$R$34:Y34) -> 11036265 | L24: =(+Ej_Ingresos!$AE$34/12)*8 -> 9060756 | M24: =SUM(Ej_Resultados!$R$13:Y13) -> 1538310.2 | N24: =Ej_Resultados!$AE$13/12*8 -> 1245938.4
B25: Sep | C25: =SUM(Ej_Ingresos!C34:K34) -> 1917747.2 | D25: 8115300 | E25: =SUM(Ej_Resultados!$C$13:$K$13) -> -208816 | F25: 630872.55 | J25: Sep | K25: =SUM(Ej_Ingresos!$R$34:Z34) -> 12616035 | L25: =(+Ej_Ingresos!$AE$34/12)*9 -> 10193350 | M25: =SUM(Ej_Resultados!$R$13:Z13) -> 1766076.7 | N25: =Ej_Resultados!$AE$13/12*9 -> 1401680.7
B26: Oct | C26: =SUM(Ej_Ingresos!C34:L34) -> 2625327.2 | D26: 9017000 | E26: =SUM(Ej_Resultados!$C$13:$L$13) -> -122419.55 | F26: 700969.5 | J26: Oct | K26: =SUM(Ej_Ingresos!$R$34:AA34) -> 14195805 | L26: =(+Ej_Ingresos!$AE$34/12)*10 -> 11325945 | M26: =SUM(Ej_Resultados!$R$13:AA13) -> 1993843.2 | N26: =Ej_Resultados!$AE$13/12*10 -> 1557423
B27: Nov | C27: =SUM(Ej_Ingresos!C34:M34) -> 3505227.2 | D27: 9918700 | E27: =SUM(Ej_Resultados!$C$13:$M$13) -> -52960.657 | F27: 771066.45 | J27: Nov | K27: =SUM(Ej_Ingresos!$R$34:AB34) -> 15775575 | L27: =(+Ej_Ingresos!$AE$34/12)*11 -> 12458540 | M27: =SUM(Ej_Resultados!$R$13:AB13) -> 2221609.6 | N27: =Ej_Resultados!$AE$13/12*11 -> 1713165.3
B28: Dic | C28: =SUM(Ej_Ingresos!C34:N34) -> 4208607.2 | D28: 10820400 | E28: =SUM(Ej_Resultados!$C$13:$N$13) -> -23859.586 | F28: 841163.4 | J28: Dic | K28: =SUM(Ej_Ingresos!$R$34:AC34) -> 17355345 | L28: =(+Ej_Ingresos!$AE$34/12)*12 -> 13591134 | M28: =SUM(Ej_Resultados!$R$13:AC13) -> 2449376.1 | N28: =Ej_Resultados!$AE$13/12*12 -> 1868907.6

Sheet Supuestos
A1: PROYECTO CIE - ACOPARÁ
A2: Procesamiento de Chapas para Fines Diversos
A3: SUPUESTOS E INPUTS DEL MODELO
A5: PARÁMETROS GENERALES | E5: ORIGINALES
A6: Tipo de cambio (Gs/USD) | B6: 6145 | D6: Gs por USD | E6: 7800
A7: Horizonte del proyecto (años) | B7: 10 | E7: 10
A8: Merma producción-venta (%) | B8: 0.015 | D8: 1.5% entre producción y venta | E8: 0.015
A10: CRECIMIENTO DE PRODUCCIÓN
A11: Incremento anual producción (%) | B11: 0.05 | D11: 5% acumulativo | E11: 0.05
A13: CRECIMIENTO DE PRECIOS DE VENTA
A14: Incremento precio Año 2-3 (%) | B14: 0.05 | D14: 5% acumulativo | E14: 0.05
A15: Incremento precio Año 4+ (%) | B15: 0.02 | D15: 2% acumulativo | E15: 0.02
A17: CRECIMIENTO COSTOS MATERIA PRIMA
A18: Incremento costo MP anual (%) | B18: 0.03 | D18: 3% acumulativo desde Año 2 | E18: 0.03
A20: MANO DE OBRA
A21: Incremento salarial anual (%) | B21: 0.03 | D21: 3% acumulativo | E21: 0.03
A22: Cargas sociales (%) | B22: 0.4309 | D22: 43.09% | E22: 0.4309
A24: FINANCIAMIENTO - PRÉSTAMO 1 (INICIAL)
A25: Monto préstamo 1 (USD) | B25: 4468594 | E25: 4468594
A26: Tasa anual préstamo 1 (%) | B26: 0.09 | D26: 9% anual | E26: 0.09
A27: Plazo préstamo 1 (meses) | B27: 60 | D27: 5 años | E27: 60
A28: IVA sobre intereses (%) | B28: 0.1 | D28: 10% | E28: 0.1
A30: FINANCIAMIENTO - PRÉSTAMO 2 (OPERATIVO)
A31: Monto préstamo 2 (USD) | B31: 1100000 | E31: 1100000
A32: Tasa anual préstamo 2 (%) | B32: 0.09 | D32: 9% anual | E32: 0.09
A33: Plazo préstamo 2 (meses) | B33: 60 | D33: 5 años | E33: 60
A35: APORTES
A36: Aporte CIE - Capital operativo (USD) | B36: 300000 | E36: 300000
A37: Aporte ACOPARÁ - Máquinas (USD) | B37: 306000 | D37: Valor FOB | E37: 306000
A38: Total aporte propio (USD) | B38: =B36+B37 -> 606000 | D38: FORMULA_PLACEHOLDER | E38: =E36+E37 -> 606000
A40: DEPRECIACIONES
A41: Vida útil maquinarias (años) | B41: 10 | E41: 10
A42: Vida útil obras civiles (años) | B42: 20 | E42: 20
A44: INVERSIONES FIJAS
A45: Obras civiles (USD) | B45: 150000 | E45: 150000
A46: IVA obras civiles (USD) | B46: 15000 | D46: 10% | E46: 15000
A47: Maquinaria y equipos importados (USD) | B47: 848239 | D47: Valor CIF total | E47: 848239
A48: Gastos de despacho (USD) | B48: 25447 | D48: 3% aprox | E48: 25447
A49: Imprevistos (USD) | B49: 10000 | E49: 10000
A50: IVA imprevistos (USD) | B50: 1000 | E50: 1000
B51: =SUM(B45:B50) -> 1049686 | C51: =(+B25+B38)-B51 -> 4024908 | E51: =SUM(E45:E50) -> 1049686
A52: COSTOS ADMINISTRATIVOS FIJOS (ANUALES) | F52: iva | G52: sin iva
A53: Alquiler tinglado 3000 m2 (USD/mes) | B53: 12000 | D53: USD 4/m2 IVA inc. | E53: 12000 | F53: =+E53*10% -> 1200 | G53: =+E53-F53 -> 10800
A54: Agua, comunicaciones, electricidad (USD/año) | B54: 1049 | E54: 1049
A55: Mantenimiento obras civiles (USD/año) | B55: 4196 | E55: 4196
A56: Seguros sobre activos fijos (USD/año) | B56: 6993 | E56: 6993
A57: Gastos generales (USD/año) | B57: 18601 | E57: 18601
A58: Honorarios y otros fijos (USD/año) | B58: 24009 | E58: 24009
A60: COSTOS DE PRODUCCIÓN VARIABLES
A61: Insumos menores (USD/Tn) | B61: 5 | D61: Aprox | E61: 4.5
A62: Packaging (% sobre costo MP) | B62: 0.0095 | D62: 1% | E62: 0.0095
A63: Seguro caución Maquila (% sobre ventas) | B63: 0.01 | D63: 1% | E63: 0.01
A64: Alimentación de personal (USD/año) | B64: 16917 | D64: Fijo | E64: 16917
A65: Movimiento de carga base (USD/año) | B65: 21818 | D65: Año 1 | E65: 21818
A67: IMPUESTOS
A68: Impuesto Maquila Exportación (%) | B68: 0.01 | D68: 1% del valor exportado | E68: 0.01
A69: IVA tasa general (%) | B69: 0.1 | D69: 10% | E69: 0.1
A70: IVA débito por ventas (%) | B70: 0 | D70: 0% - Régimen Maquila | E70: 0
A72: COSTO DE OPORTUNIDAD
A73: Costo capital propio (%) | B73: 0.1632 | D73: 16.32% | E73: 0.1632
A74: Costo deuda (%) | B74: 0.09 | D74: 9% | E74: 0.09
A75: Tasa crecimiento perpetuo - Valor Terminal (%) | B75: 0.01 | E75: 0.03
A76: CAPITAL DE TRABAJO - DÍAS
A77: Caja y bancos (días) | B77: 2 | E77: 2
A78: Sueldos y anticipos (días) | B78: 15 | E78: 15
A79: Stock materia prima (días) | B79: 45 | E79: 90
A80: Ventas a crédito (días) | B80: 90 | E80: 0
A81: Producto terminado (días) | B81: 0 | E81: 60
A82: Crédito proveedores MP (días) | B82: 0 | E82: 0
A83: Crédito proveedores menores (días) | B83: 15 | C83: ** | E83: 34
A85: FINANCIAMIENTO - CRÉDITO CP ROTATIVO (CUENTAS POR COBRAR)
A86: Tasa anual crédito CP rotativo (%) | B86: 0.09
A87: IVA sobre intereses CP rotativo (%) | B87: 0.1

Sheet Productos
A1: ok
B2: PRODUCTOS - PRECIOS Y COSTOS BASE
D3: ok | E3: ok | F3: ok | G3: ok
B4: # | C4: Producto | D4: Precio Venta USD/Tn Año1 | E4: Costo MP USD/Tn Año1 | F4: Producción Tn Año1 | G4: Venta Tn Año1
C5: 1. Slitter Portas Autom. | D5: =+Ej_Ingresos!O8 -> 836.11239 | E5: =+Ej_Costos!O9 -> 822.0642 | F5: =+Ej_Producción!O22 -> 711.98 | G5: =+Ej_Producción!O37 -> 711.98
C6: 2. Slitter Drywall 0,43/0,48 | D6: =+Ej_Ingresos!O9 -> 905.50966 | E6: =+Ej_Costos!O10 -> 868.32068 | F6: =+Ej_Producción!O23 -> 1806.045 | G6: =+Ej_Producción!O38 -> 1746.045
C7: 3. Slitter Drywall 0,50 | D7: =+Ej_Ingresos!O10 -> 1047.5821 | E7: =+Ej_Costos!O11 -> 1007.0255 | F7: =+Ej_Producción!O24 -> 409.141 | G7: =+Ej_Producción!O39 -> 379.141
C8: 4. Slitter Steel Frame 0,80/0,95 | D8: =+Ej_Ingresos!O11 -> 1080 | E8: =+Ej_Costos!O12 -> 922 | F8: =+Ej_Producción!O25 -> 480 | G8: =+Ej_Producción!O40 -> 450
C9: 5. Telhas Met. Naturales | D9: =+Ej_Ingresos!O12 -> 1218 | E9: =+Ej_Costos!O13 -> 945.95457 | F9: =+Ej_Producción!O26 -> 240 | G9: =+Ej_Producción!O41 -> 240
C10: 6. Telhas Met. Pre Pintadas | D10: =+Ej_Ingresos!O13 -> 1380.8228 | E10: =+Ej_Costos!O14 -> 1013.0619 | F10: =+Ej_Producción!O27 -> 158 | G10: =+Ej_Producción!O42 -> 158
C11: 7. Perfil DW 0,43 Prepint. | D11: =+Ej_Ingresos!O14 -> 1399 | E11: =+Ej_Costos!O15 -> 1013.0619 | F11: =+Ej_Producción!O28 -> 120 | G11: =+Ej_Producción!O43 -> 120
C12: 8. Perfil Drywall 0,50 | D12: =+Ej_Ingresos!O15 -> 1272 | E12: =+Ej_Costos!O16 -> 1023.6899 | F12: =+Ej_Producción!O29 -> 120 | G12: =+Ej_Producción!O44 -> 120
C13: 9. Perfil Drywall 0,48 | D13: =+Ej_Ingresos!O16 -> 1178 | E13: =+Ej_Costos!O17 -> 877.59331 | F13: =+Ej_Producción!O30 -> 270 | G13: =+Ej_Producción!O45 -> 270
C14: 10. Steel Frame | D14: =+Ej_Ingresos!O17 -> 0 | E14: =+Ej_Costos!O18 -> 0 | F14: =+Ej_Producción!O31 -> 0 | G14: =+Ej_Producción!O46 -> 0
C15: 11. Accesorios Metálicos | D15: =+Ej_Ingresos!O18 -> 0 | E15: =+Ej_Costos!O19 -> 0 | F15: =+Ej_Producción!O32 -> 0 | G15: =+Ej_Producción!O47 -> 0
F16: =SUM(F5:F15) -> 4315.166 | G16: =SUM(G5:G15) -> 4195.166

Sheet Inversión
B2: INVERSIÓN Y FINANCIAMIENTO (Cuadro 1)
B3: Valores en dólares
B5: Concepto | C5: TOTAL | D5: APORTE PROPIO | E5: BANCO LOCAL | F5: %
B7: TOTAL DE LA INVERSIÓN | C7: =C9+C18 -> 5074594 | D7: =D9 -> 606000 | E7: =C7-D7 -> 4468594 | F7: =C7/C7 -> 1
B9: TOTAL INVERSIÓN FIJA | C9: =SUM(C10:C15) -> 1049686 | D9: =Supuestos!B38 -> 606000 | E9: =C9-D9 -> 443686
B10: OBRAS CIVILES | C10: =Supuestos!B45 -> 150000 | D10: 0 | E10: =C10-D10 -> 150000
B11: - IVA Obras Civiles | C11: =Supuestos!B46 -> 15000 | D11: 0 | E11: =C11-D11 -> 15000
B12: MAQUINARIA Y EQUIPOS IMPORTADOS | C12: =Supuestos!B47 -> 848239 | D12: =Supuestos!B37 -> 306000 | E12: =C12-D12 -> 542239
B13: - Gastos de despacho | C13: =Supuestos!B48 -> 25447 | D13: 0 | E13: =C13-D13 -> 25447
B14: IMPREVISTOS | C14: =Supuestos!B49 -> 10000 | D14: 0 | E14: =C14-D14 -> 10000
B15: - IVA Imprevistos | C15: =Supuestos!B50 -> 1000 | D15: 0 | E15: =C15-D15 -> 1000
B18: CAPITAL OPERATIVO INICIAL | C18: 4024908 | D18: 0 | E18: =C18-D18 -> 4024908
B20: Tipo de Cambio de Referencia: | C20: =Supuestos!B6 -> 6145 | D20: Gs = 1 USD

Sheet Maquinaria
B2: MÁQUINAS Y EQUIPOS A IMPORTAR (Cuadro 2)
B3: Valores en dólares
B5: Item | C5: Descripción | D5: Cond. | E5: EUR FOB | F5: USD Seg/Flete | G5: USD CIF
B6: 1 | C6: Máquina perfiladora de telhas | D6: CIF | G6: 105554
B7: 2 | C7: Máquina Slitter | D7: CIF | G7: 272935
B8: 3 | C8: Máq. producción 1er año Perfiles DryWall + Empaquetadora | D8: CIF | G8: 162000
B9: 4 | C9: Máq. producción 2do año Steel Frame Light | D9: FOB | E9: 195000 | F9: 29250 | G9: 224250
B10: 5 | C10: Montacargas | D10: CIF | G10: 18500
B11: 6 | C11: Máquina de corte y prensa | D11: CIF | G11: 50000
B12: 7 | C12: Compresor | D12: CIF | G12: 15000
C13: SUBTOTAL CIF | G13: =SUM(G6:G12) -> 848239
C14: Gastos de despacho | G14: 25447
C15: TOTAL INGRESADO AL PAÍS | G15: =G13+G14 -> 873686

Sheet Mano de Obra
A1: ok
B2: MANO DE OBRA (Cuadro 3/4)
C3: ok | D3: ok
B4: Concepto | C4: AÑO 1 | D4: AÑO 2 | E4: AÑO 3 | F4: AÑO 4 | G4: AÑO 5 | H4: AÑO 6 | I4: AÑO 7 | J4: AÑO 8 | K4: AÑO 9 | L4: AÑO 10
B5: Mano de obra fábrica | C5: =+Ej_Costos!O34/1.42 -> 52445.746 | D5: =+Ej_Costos!AD34/1.42 -> 152579.59 | E5: =D5*(1+Supuestos!B21) -> 157156.98 | F5: =E5*(1+Supuestos!B21) -> 161871.69 | G5: =F5*(1+Supuestos!B21) -> 166727.84 | H5: =G5*(1+Supuestos!B21) -> 171729.67 | I5: =H5*(1+Supuestos!B21) -> 176881.56 | J5: =I5*(1+Supuestos!B21) -> 182188.01 | K5: =J5*(1+Supuestos!B21) -> 187653.65 | L5: =K5*(1+Supuestos!B21) -> 193283.26
B6: Prestaciones sociales | C6: =+Ej_Costos!O34-(Ej_Costos!O34/1.42) -> 22027.213 | D6: =Ej_Costos!AD34-(Ej_Costos!AD34/1.42) -> 64083.428 | E6: =E5*Supuestos!B22 -> 67718.942 | F6: =F5*Supuestos!B22 -> 69750.511 | G6: =G5*Supuestos!B22 -> 71843.026 | H6: =H5*Supuestos!B22 -> 73998.317 | I6: =I5*Supuestos!B22 -> 76218.266 | J6: =J5*Supuestos!B22 -> 78504.814 | K6: =K5*Supuestos!B22 -> 80859.959 | L6: =L5*Supuestos!B22 -> 83285.757
B8: Mano de obra administrativa | C8: =+Ej_Costos!O47/1.42 -> 44219.227 | D8: =+Ej_Costos!AD47/1.42 -> 68239.212 | E8: =D8*(1+Supuestos!B21) -> 70286.389 | F8: =E8*(1+Supuestos!B21) -> 72394.98 | G8: =F8*(1+Supuestos!B21) -> 74566.83 | H8: =G8*(1+Supuestos!B21) -> 76803.834 | I8: =H8*(1+Supuestos!B21) -> 79107.95 | J8: =I8*(1+Supuestos!B21) -> 81481.188 | K8: =J8*(1+Supuestos!B21) -> 83925.624 | L8: =K8*(1+Supuestos!B21) -> 86443.392
B9: Prestaciones sociales admin. | C9: =Ej_Costos!O47-(Ej_Costos!O47/1.42) -> 18572.075 | D9: =Ej_Costos!AD47-(Ej_Costos!AD47/1.42) -> 28660.469 | E9: =E8*Supuestos!B22 -> 30286.405 | F9: =F8*Supuestos!B22 -> 31194.997 | G9: =G8*Supuestos!B22 -> 32130.847 | H9: =H8*Supuestos!B22 -> 33094.772 | I9: =I8*Supuestos!B22 -> 34087.615 | J9: =J8*Supuestos!B22 -> 35110.244 | K9: =K8*Supuestos!B22 -> 36163.551 | L9: =L8*Supuestos!B22 -> 37248.458
B11: TOTAL MANO DE OBRA + CARGAS | C11: =C5+C6+C8+C9 -> 137264.26 | D11: =D5+D6+D8+D9 -> 313562.7 | E11: =E5+E6+E8+E9 -> 325448.71 | F11: =F5+F6+F8+F9 -> 335212.18 | G11: =G5+G6+G8+G9 -> 345268.54 | H11: =H5+H6+H8+H9 -> 355626.6 | I11: =I5+I6+I8+I9 -> 366295.4 | J11: =J5+J6+J8+J9 -> 377284.26 | ... L11: =L5+L6+L8+L9 -> 400260.87
B13: Servicios de terceros - Steel Frame | C13: 0 | D13: 45000 | E13: =D13*(1+Supuestos!B21) -> 46350 | F13: =E13*(1+Supuestos!B21) -> 47740.5 | G13: =F13*(1+Supuestos!B21) -> 49172.715 | H13: =G13*(1+Supuestos!B21) -> 50647.896 | I13: =H13*(1+Supuestos!B21) -> 52167.333 | J13: =I13*(1+Supuestos!B21) -> 53732.353 | K13: =J13*(1+Supuestos!B21) -> 55344.324 | L13: =K13*(1+Supuestos!B21) -> 57004.654
C50: =100%-Supuestos!B22 -> 0.5691

Sheet Producción
A1: ok
B2: PROGRAMA DE PRODUCCIÓN PROYECTADA (Cuadro 7)
B3: Información de Producción y Ventas en Toneladas (Tn)
D4: ok | E4: ok
B5: # | C5: Producto | D5: AÑO 1 | E5: AÑO 2 | F5: AÑO 3 | G5: AÑO 4 | H5: AÑO 5 | I5: AÑO 6 | J5: AÑO 7 | K5: AÑO 8 | L5: AÑO 9 | M5: AÑO 10
B6: 1 | C6: Slitter Portas Automatizadas - Producción | D6: =+Ej_Producción!O22 -> 711.98 | E6: =+Ej_Producción!AD22 -> 990 | F6: =ROUND(E6*(1+Supuestos!$B$11),0) -> 1040 | G6: =ROUND(F6*(1+Supuestos!$B$11),0) -> 1092 | H6: =ROUND(G6*(1+Supuestos!$B$11),0) -> 1147 | I6: =ROUND(H6*(1+Supuestos!$B$11),0) -> 1204 | J6: =ROUND(I6*(1+Supuestos!$B$11),0) -> 1264 | K6: =ROUND(J6*(1+Supuestos!$B$11),0) -> 1327 | L6: =ROUND(K6*(1+Supuestos!$B$11),0) -> 1393 | M6: =ROUND(L6*(1+Supuestos!$B$11),0) -> 1463 | N6: =SUM(D6:M6) -> 11631.98 | O6: =+N6-N7 -> 149
C7: Slitter Portas Automatizadas - Venta | D7: =+Ej_Producción!O37 -> 711.98 | E7: =+Ej_Producción!AD37 -> 990 | F7: =ROUND(F6*(1-Supuestos!$B$8),0) -> 1024 | G7: =ROUND(G6*(1-Supuestos!$B$8),0) -> 1076 | H7: =ROUND(H6*(1-Supuestos!$B$8),0) -> 1130 | I7: =ROUND(I6*(1-Supuestos!$B$8),0) -> 1186 | J7: =ROUND(J6*(1-Supuestos!$B$8),0) -> 1245 | K7: =ROUND(K6*(1-Supuestos!$B$8),0) -> 1307 | L7: =ROUND(L6*(1-Supuestos!$B$8),0) -> 1372 | M7: =ROUND(M6*(1-Supuestos!$B$8),0) -> 1441 | N7: =SUM(D7:M7) -> 11482.98
B8: 2 | C8: Slitter Drywall 0,43 y 0,48 - Producción | D8: =+Ej_Producción!O23 -> 1806.045 | E8: =+Ej_Producción!AD23 -> 4770 | F8: =ROUND(E8*(1+Supuestos!$B$11),0) -> 5009 | G8: =ROUND(F8*(1+Supuestos!$B$11),0) -> 5259 | H8: =ROUND(G8*(1+Supuestos!$B$11),0) -> 5522 | I8: =ROUND(H8*(1+Supuestos!$B$11),0) -> 5798 | J8: =ROUND(I8*(1+Supuestos!$B$11),0) -> 6088 | K8: =ROUND(J8*(1+Supuestos!$B$11),0) -> 6392 | L8: =ROUND(K8*(1+Supuestos!$B$11),0) -> 6712 | M8: =ROUND(L8*(1+Supuestos!$B$11),0) -> 7048 | N8: =SUM(D8:M8) -> 54404.045 | O8: =+N8-N9 -> 778
C9: Slitter Drywall 0,43 y 0,48 - Venta | D9: =+Ej_Producción!O38 -> 1746.045 | E9: =+Ej_Producción!AD38 -> 4770 | F9: =ROUND(F8*(1-Supuestos!$B$8),0) -> 4934 | G9: =ROUND(G8*(1-Supuestos!$B$8),0) -> 5180 | H9: =ROUND(H8*(1-Supuestos!$B$8),0) -> 5439 | I9: =ROUND(I8*(1-Supuestos!$B$8),0) -> 5711 | J9: =ROUND(J8*(1-Supuestos!$B$8),0) -> 5997 | K9: =ROUND(K8*(1-Supuestos!$B$8),0) -> 6296 | L9: =ROUND(L8*(1-Supuestos!$B$8),0) -> 6611 | M9: =ROUND(M8*(1-Supuestos!$B$8),0) -> 6942 | N9: =SUM(D9:M9) -> 53626.045
B10: 3 | C10: Slitter Drywall 0,50 - Producción | D10: =+Ej_Producción!O24 -> 409.141 | E10: =+Ej_Producción!AD24 -> 1650 | F10: =ROUND(E10*(1+Supuestos!$B$11),0) -> 1733 | G10: =ROUND(F10*(1+Supuestos!$B$11),0) -> 1820 | H10: =ROUND(G10*(1+Supuestos!$B$11),0) -> 1911 | I10: =ROUND(H10*(1+Supuestos!$B$11),0) -> 2007 | J10: =ROUND(I10*(1+Supuestos!$B$11),0) -> 2107 | K10: =ROUND(J10*(1+Supuestos!$B$11),0) -> 2212 | L10: =ROUND(K10*(1+Supuestos!$B$11),0) -> 2323 | M10: =ROUND(L10*(1+Supuestos!$B$11),0) -> 2439 | N10: =SUM(D10:M10) -> 18611.141 | O10: =+N10-N11 -> 279
C11: Slitter Drywall 0,50 - Venta | D11: =+Ej_Producción!O39 -> 379.141 | E11: =+Ej_Producción!AD39 -> 1650 | F11: =ROUND(F10*(1-Supuestos!$B$8),0) -> 1707 | G11: =ROUND(G10*(1-Supuestos!$B$8),0) -> 1793 | H11: =ROUND(H10*(1-Supuestos!$B$8),0) -> 1882 | I11: =ROUND(I10*(1-Supuestos!$B$8),0) -> 1977 | J11: =ROUND(J10*(1-Supuestos!$B$8),0) -> 2075 | K11: =ROUND(K10*(1-Supuestos!$B$8),0) -> 2179 | L11: =ROUND(L10*(1-Supuestos!$B$8),0) -> 2288 | M11: =ROUND(M10*(1-Supuestos!$B$8),0) -> 2402 | N11: =SUM(D11:M11) -> 18332.141
B12: 4 | C12: Slitter Steel Frame 0,80/0,95 Producción | D12: =+Ej_Producción!O25 -> 480 | E12: =+Ej_Producción!AD25 -> 1650 | F12: =ROUND(E12*(1+Supuestos!$B$11),0) -> 1733 | G12: =ROUND(F12*(1+Supuestos!$B$11),0) -> 1820 | H12: =ROUND(G12*(1+Supuestos!$B$11),0) -> 1911 | I12: =ROUND(H12*(1+Supuestos!$B$11),0) -> 2007 | J12: =ROUND(I12*(1+Supuestos!$B$11),0) -> 2107 | K12: =ROUND(J12*(1+Supuestos!$B$11),0) -> 2212 | L12: =ROUND(K12*(1+Supuestos!$B$11),0) -> 2323 | M12: =ROUND(L12*(1+Supuestos!$B$11),0) -> 2439 | N12: =SUM(D12:M12) -> 18682 | O12: =+N12-N13 -> 279
C13: Slitter Steel Frame 0,80/0,95 Venta | D13: =+Ej_Producción!O40 -> 450 | E13: =+Ej_Producción!AD40 -> 1650 | F13: =ROUND(F12*(1-Supuestos!$B$8),0) -> 1707 | G13: =ROUND(G12*(1-Supuestos!$B$8),0) -> 1793 | H13: =ROUND(H12*(1-Supuestos!$B$8),0) -> 1882 | I13: =ROUND(I12*(1-Supuestos!$B$8),0) -> 1977 | J13: =ROUND(J12*(1-Supuestos!$B$8),0) -> 2075 | K13: =ROUND(K12*(1-Supuestos!$B$8),0) -> 2179 | L13: =ROUND(L12*(1-Supuestos!$B$8),0) -> 2288 | M13: =ROUND(M12*(1-Supuestos!$B$8),0) -> 2402 | N13: =SUM(D13:M13) -> 18403
B14: 5 | C14: Telhas Metálicas Naturales - Producción | D14: =+Ej_Producción!O26 -> 240 | E14: =+Ej_Producción!AD26 -> 660 | F14: =ROUND(E14*(1+Supuestos!$B$11),0) -> 693 | G14: =ROUND(F14*(1+Supuestos!$B$11),0) -> 728 | H14: =ROUND(G14*(1+Supuestos!$B$11),0) -> 764 | I14: =ROUND(H14*(1+Supuestos!$B$11),0) -> 802 | J14: =ROUND(I14*(1+Supuestos!$B$11),0) -> 842 | K14: =ROUND(J14*(1+Supuestos!$B$11),0) -> 884 | L14: =ROUND(K14*(1+Supuestos!$B$11),0) -> 928 | M14: =ROUND(L14*(1+Supuestos!$B$11),0) -> 974 | N14: =SUM(D14:M14) -> 7515 | O14: =+N14-N15 -> 99
C15: Telhas Metálicas Naturales - Venta | D15: =+Ej_Producción!O41 -> 240 | E15: =+Ej_Producción!AD41 -> 660 | F15: =ROUND(F14*(1-Supuestos!$B$8),0) -> 683 | G15: =ROUND(G14*(1-Supuestos!$B$8),0) -> 717 | H15: =ROUND(H14*(1-Supuestos!$B$8),0) -> 753 | I15: =ROUND(I14*(1-Supuestos!$B$8),0) -> 790 | J15: =ROUND(J14*(1-Supuestos!$B$8),0) -> 829 | K15: =ROUND(K14*(1-Supuestos!$B$8),0) -> 871 | L15: =ROUND(L14*(1-Supuestos!$B$8),0) -> 914 | M15: =ROUND(M14*(1-Supuestos!$B$8),0) -> 959 | N15: =SUM(D15:M15) -> 7416
B16: 6 | C16: Telhas Metálicas Pre Pintadas - Producción | D16: =+Ej_Producción!O27 -> 158 | E16: =+Ej_Producción!AD27 -> 330 | F16: =ROUND(E16*(1+Supuestos!$B$11),0) -> 347 | G16: =ROUND(F16*(1+Supuestos!$B$11),0) -> 364 | H16: =ROUND(G16*(1+Supuestos!$B$11),0) -> 382 | I16: =ROUND(H16*(1+Supuestos!$B$11),0) -> 401 | J16: =ROUND(I16*(1+Supuestos!$B$11),0) -> 421 | K16: =ROUND(J16*(1+Supuestos!$B$11),0) -> 442 | L16: =ROUND(K16*(1+Supuestos!$B$11),0) -> 464 | M16: =ROUND(L16*(1+Supuestos!$B$11),0) -> 487 | N16: =SUM(D16:M16) -> 3796 | O16: =+N16-N17 -> 49
C17: Telhas Metálicas Pre Pintadas - Venta | D17: =+Ej_Producción!O42 -> 158 | E17: =+Ej_Producción!AD42 -> 330 | F17: =ROUND(F16*(1-Supuestos!$B$8),0) -> 342 | G17: =ROUND(G16*(1-Supuestos!$B$8),0) -> 359 | H17: =ROUND(H16*(1-Supuestos!$B$8),0) -> 376 | I17: =ROUND(I16*(1-Supuestos!$B$8),0) -> 395 | J17: =ROUND(J16*(1-Supuestos!$B$8),0) -> 415 | K17: =ROUND(K16*(1-Supuestos!$B$8),0) -> 435 | L17: =ROUND(L16*(1-Supuestos!$B$8),0) -> 457 | M17: =ROUND(M16*(1-Supuestos!$B$8),0) -> 480 | N17: =SUM(D17:M17) -> 3747
B18: 7 | C18: Perfil Drywall 0,43 Prepintado - Producción | D18: =+Ej_Producción!O28 -> 120 | E18: =+Ej_Producción!AD28 -> 645 | F18: =ROUND(E18*(1+Supuestos!$B$11),0) -> 677 | G18: =ROUND(F18*(1+Supuestos!$B$11),0) -> 711 | H18: =ROUND(G18*(1+Supuestos!$B$11),0) -> 747 | I18: =ROUND(H18*(1+Supuestos!$B$11),0) -> 784 | J18: =ROUND(I18*(1+Supuestos!$B$11),0) -> 823 | K18: =ROUND(J18*(1+Supuestos!$B$11),0) -> 864 | L18: =ROUND(K18*(1+Supuestos!$B$11),0) -> 907 | M18: =ROUND(L18*(1+Supuestos!$B$11),0) -> 952 | N18: =SUM(D18:M18) -> 7230 | O18: =+N18-N19 -> 97
C19: Perfil Drywall 0,43 Prepintado - Venta | D19: =+Ej_Producción!O43 -> 120 | E19: =+Ej_Producción!AD43 -> 645 | F19: =ROUND(F18*(1-Supuestos!$B$8),0) -> 667 | G19: =ROUND(G18*(1-Supuestos!$B$8),0) -> 700 | H19: =ROUND(H18*(1-Supuestos!$B$8),0) -> 736 | I19: =ROUND(I18*(1-Supuestos!$B$8),0) -> 772 | J19: =ROUND(J18*(1-Supuestos!$B$8),0) -> 811 | K19: =ROUND(K18*(1-Supuestos!$B$8),0) -> 851 | L19: =ROUND(L18*(1-Supuestos!$B$8),0) -> 893 | M19: =ROUND(M18*(1-Supuestos!$B$8),0) -> 938 | N19: =SUM(D19:M19) -> 7133
B20: 8 | C20: Perfil Drywall 0,50 - Producción | D20: =+Ej_Producción!O29 -> 120 | E20: =+Ej_Producción!AD29 -> 660 | F20: =ROUND(E20*(1+Supuestos!$B$11),0) -> 693 | G20: =ROUND(F20*(1+Supuestos!$B$11),0) -> 728 | H20: =ROUND(G20*(1+Supuestos!$B$11),0) -> 764 | I20: =ROUND(H20*(1+Supuestos!$B$11),0) -> 802 | J20: =ROUND(I20*(1+Supuestos!$B$11),0) -> 842 | K20: =ROUND(J20*(1+Supuestos!$B$11),0) -> 884 | L20: =ROUND(K20*(1+Supuestos!$B$11),0) -> 928 | M20: =ROUND(L20*(1+Supuestos!$B$11),0) -> 974 | N20: =SUM(D20:M20) -> 7395 | O20: =+N20-N21 -> 99
C21: Perfil Drywall 0,50 - Venta | D21: =+Ej_Producción!O44 -> 120 | E21: =+Ej_Producción!AD44 -> 660 | F21: =ROUND(F20*(1-Supuestos!$B$8),0) -> 683 | G21: =ROUND(G20*(1-Supuestos!$B$8),0) -> 717 | H21: =ROUND(H20*(1-Supuestos!$B$8),0) -> 753 | I21: =ROUND(I20*(1-Supuestos!$B$8),0) -> 790 | J21: =ROUND(J20*(1-Supuestos!$B$8),0) -> 829 | K21: =ROUND(K20*(1-Supuestos!$B$8),0) -> 871 | L21: =ROUND(L20*(1-Supuestos!$B$8),0) -> 914 | M21: =ROUND(M20*(1-Supuestos!$B$8),0) -> 959 | N21: =SUM(D21:M21) -> 7296
B22: 9 | C22: Perfil Drywall 0,48 - Producción | D22: =+Ej_Producción!O30 -> 270 | E22: =+Ej_Producción!AD30 -> 1620 | F22: =ROUND(E22*(1+Supuestos!$B$11),0) -> 1701 | G22: =ROUND(F22*(1+Supuestos!$B$11),0) -> 1786 | H22: =ROUND(G22*(1+Supuestos!$B$11),0) -> 1875 | I22: =ROUND(H22*(1+Supuestos!$B$11),0) -> 1969 | J22: =ROUND(I22*(1+Supuestos!$B$11),0) -> 2067 | K22: =ROUND(J22*(1+Supuestos!$B$11),0) -> 2170 | L22: =ROUND(K22*(1+Supuestos!$B$11),0) -> 2279 | M22: =ROUND(L22*(1+Supuestos!$B$11),0) -> 2393 | N22: =SUM(D22:M22) -> 18130 | O22: =+N22-N23 -> 245
C23: Perfil Drywall 0,48 - Venta | D23: =+Ej_Producción!O45 -> 270 | E23: =+Ej_Producción!AD45 -> 1620 | F23: =ROUND(F22*(1-Supuestos!$B$8),0) -> 1675 | G23: =ROUND(G22*(1-Supuestos!$B$8),0) -> 1759 | H23: =ROUND(H22*(1-Supuestos!$B$8),0) -> 1847 | I23: =ROUND(I22*(1-Supuestos!$B$8),0) -> 1939 | J23: =ROUND(J22*(1-Supuestos!$B$8),0) -> 2036 | K23: =ROUND(K22*(1-Supuestos!$B$8),0) -> 2137 | L23: =ROUND(L22*(1-Supuestos!$B$8),0) -> 2245 | M23: =ROUND(M22*(1-Supuestos!$B$8),0) -> 2357 | N23: =SUM(D23:M23) -> 17885
B24: 10 | C24: Steel Frame - Producción | D24: =+Ej_Producción!O31 -> 0 | E24: =+Ej_Producción!AD31 -> 930 | F24: =ROUND(E24*(1+Supuestos!$B$11),0) -> 977 | G24: =ROUND(F24*(1+Supuestos!$B$11),0) -> 1026 | H24: =ROUND(G24*(1+Supuestos!$B$11),0) -> 1077 | I24: =ROUND(H24*(1+Supuestos!$B$11),0) -> 1131 | J24: =ROUND(I24*(1+Supuestos!$B$11),0) -> 1188 | K24: =ROUND(J24*(1+Supuestos!$B$11),0) -> 1247 | L24: =ROUND(K24*(1+Supuestos!$B$11),0) -> 1309 | M24: =ROUND(L24*(1+Supuestos!$B$11),0) -> 1374 | N24: =SUM(D24:M24) -> 10259 | O24: =+N24-N25 -> 141
C25: Steel Frame - Venta | D25: =+Ej_Producción!O46 -> 0 | E25: =+Ej_Producción!AD46 -> 930 | F25: =ROUND(F24*(1-Supuestos!$B$8),0) -> 962 | G25: =ROUND(G24*(1-Supuestos!$B$8),0) -> 1011 | H25: =ROUND(H24*(1-Supuestos!$B$8),0) -> 1061 | I25: =ROUND(I24*(1-Supuestos!$B$8),0) -> 1114 | J25: =ROUND(J24*(1-Supuestos!$B$8),0) -> 1170 | K25: =ROUND(K24*(1-Supuestos!$B$8),0) -> 1228 | L25: =ROUND(L24*(1-Supuestos!$B$8),0) -> 1289 | M25: =ROUND(M24*(1-Supuestos!$B$8),0) -> 1353 | N25: =SUM(D25:M25) -> 10118
B26: 11 | C26: Accesorios Metálicos - Producción | D26: 0 | E26: =+Ej_Producción!AD32 -> 330 | F26: =ROUND(E26*(1+Supuestos!$B$11),0) -> 347 | G26: =ROUND(F26*(1+Supuestos!$B$11),0) -> 364 | H26: =ROUND(G26*(1+Supuestos!$B$11),0) -> 382 | I26: =ROUND(H26*(1+Supuestos!$B$11),0) -> 401 | J26: =ROUND(I26*(1+Supuestos!$B$11),0) -> 421 | K26: =ROUND(J26*(1+Supuestos!$B$11),0) -> 442 | L26: =ROUND(K26*(1+Supuestos!$B$11),0) -> 464 | M26: =ROUND(L26*(1+Supuestos!$B$11),0) -> 487 | N26: =SUM(D26:M26) -> 3638 | O26: =+N26-N27 -> 49
C27: Accesorios Metálicos - Venta | D27: =+Ej_Producción!O47 -> 0 | E27: =+Ej_Producción!AD47 -> 330 | F27: =ROUND(F26*(1-Supuestos!$B$8),0) -> 342 | G27: =ROUND(G26*(1-Supuestos!$B$8),0) -> 359 | H27: =ROUND(H26*(1-Supuestos!$B$8),0) -> 376 | I27: =ROUND(I26*(1-Supuestos!$B$8),0) -> 395 | J27: =ROUND(J26*(1-Supuestos!$B$8),0) -> 415 | K27: =ROUND(K26*(1-Supuestos!$B$8),0) -> 435 | L27: =ROUND(L26*(1-Supuestos!$B$8),0) -> 457 | M27: =ROUND(M26*(1-Supuestos!$B$8),0) -> 480 | N27: =SUM(D27:M27) -> 3589
C28: TOTAL PRODUCCIÓN (Tn) | D28: =D6+D8+D10+D14+D16+D18+D20+D22+D24+D26+D12 -> 4315.166 | E28: =E6+E8+E10+E14+E16+E18+E20+E22+E24+E26+E12 -> 14235 | F28: =F6+F8+F10+F14+F16+F18+F20+F22+F24+F26+F12 -> 14950 | G28: =G6+G8+G10+G14+G16+G18+G20+G22+G24+G26+G12 -> 15698 | H28: =H6+H8+H10+H14+H16+H18+H20+H22+H24+H26+H12 -> 16482 | I28: =I6+I8+I10+I14+I16+I18+I20+I22+I24+I26+I12 -> 17306 | J28: =J6+J8+J10+J14+J16+J18+J20+J22+J24+J26+J12 -> 18170 | K28: =K6+K8+K10+K14+K16+K18+K20+K22+K24+K26+K12 -> 19076 | ... M28: =M6+M8+M10+M14+M16+M18+M20+M22+M24+M26+M12 -> 21030
C29: TOTAL VENTAS (Tn) | D29: =D7+D9+D11+D15+D17+D19+D21+D23+D25+D27+D13 -> 4195.166 | E29: =E7+E9+E11+E15+E17+E19+E21+E23+E25+E27+E13 -> 14235 | F29: =F7+F9+F11+F15+F17+F19+F21+F23+F25+F27+F13 -> 14726 | G29: =G7+G9+G11+G15+G17+G19+G21+G23+G25+G27+G13 -> 15464 | H29: =H7+H9+H11+H15+H17+H19+H21+H23+H25+H27+H13 -> 16235 | I29: =I7+I9+I11+I15+I17+I19+I21+I23+I25+I27+I13 -> 17046 | J29: =J7+J9+J11+J15+J17+J19+J21+J23+J25+J27+J13 -> 17897 | K29: =K7+K9+K11+K15+K17+K19+K21+K23+K25+K27+K13 -> 18789 | ... M29: =M7+M9+M11+M15+M17+M19+M21+M23+M25+M27+M13 -> 20713

Sheet Ingresos
A1: ok
B2: INGRESOS ANUALES PROYECTADOS (Cuadro 8)
B3: Valores en dólares - Sin IVA (Régimen Maquila)
D4: ok | E4: ok
B5: # | C5: Concepto | D5: AÑO 1 | E5: AÑO 2 | F5: AÑO 3 | G5: AÑO 4 | H5: AÑO 5 | I5: AÑO 6 | J5: AÑO 7 | K5: AÑO 8 | L5: AÑO 9 | M5: AÑO 10
B6: 1 | C6: Slitter Portas Automatizadas - Precio USD/Tn | D6: =+Ej_Ingresos!O8 -> 836.11239 | E6: =+Ej_Ingresos!AD8 -> 858 | F6: =E6*(1+Supuestos!$B$14) -> 900.9 | G6: =F6*(1+Supuestos!$B$15) -> 918.918 | H6: =G6*(1+Supuestos!$B$15) -> 937.29636 | I6: =H6*(1+Supuestos!$B$15) -> 956.04229 | J6: =I6*(1+Supuestos!$B$15) -> 975.16313 | K6: =J6*(1+Supuestos!$B$15) -> 994.6664 | L6: =K6*(1+Supuestos!$B$15) -> 1014.5597 | M6: =L6*(1+Supuestos!$B$15) -> 1034.8509
C7: Slitter Portas Automatizadas - Ingreso USD | D7: =D6*Producción!D7 -> 595295.3 | E7: =E6*Producción!E7 -> 849420 | F7: =F6*Producción!F7 -> 922521.6 | G7: =G6*Producción!G7 -> 988755.77 | H7: =H6*Producción!H7 -> 1059144.9 | I7: =I6*Producción!I7 -> 1133866.2 | J7: =J6*Producción!J7 -> 1214078.1 | K7: =K6*Producción!K7 -> 1300029 | ... M7: =M6*Producción!M7 -> 1491220.2
B8: 2 | C8: Slitter Drywall 0,43 y 0,48 - Precio USD/Tn | D8: =+Ej_Ingresos!O9 -> 905.50966 | E8: =+Ej_Ingresos!AD9 -> 964 | F8: =E8*(1+Supuestos!$B$14) -> 1012.2 | G8: =F8*(1+Supuestos!$B$15) -> 1032.444 | H8: =G8*(1+Supuestos!$B$15) -> 1053.0929 | I8: =H8*(1+Supuestos!$B$15) -> 1074.1547 | J8: =I8*(1+Supuestos!$B$15) -> 1095.6378 | K8: =J8*(1+Supuestos!$B$15) -> 1117.5506 | L8: =K8*(1+Supuestos!$B$15) -> 1139.9016 | M8: =L8*(1+Supuestos!$B$15) -> 1162.6996
C9: Slitter Drywall 0,43 y 0,48 - Ingreso USD | D9: =D8*Producción!D9 -> 1581060.6 | E9: =E8*Producción!E9 -> 4598280 | F9: =F8*Producción!F9 -> 4994194.8 | G9: =G8*Producción!G9 -> 5348059.9 | H9: =H8*Producción!H9 -> 5727772.2 | I9: =I8*Producción!I9 -> 6134497.7 | J9: =J8*Producción!J9 -> 6570540.1 | K9: =K8*Producción!K9 -> 7036098.5 | ... M9: =M8*Producción!M9 -> 8071460.9
B10: 3 | C10: Slitter Drywall 0,50 - Precio USD/Tn | D10: =+Ej_Ingresos!O10 -> 1047.5821 | E10: =+Ej_Ingresos!AD10 -> 1080 | F10: =E10*(1+Supuestos!$B$14) -> 1134 | G10: =F10*(1+Supuestos!$B$15) -> 1156.68 | H10: =G10*(1+Supuestos!$B$15) -> 1179.8136 | I10: =H10*(1+Supuestos!$B$15) -> 1203.4099 | J10: =I10*(1+Supuestos!$B$15) -> 1227.4781 | K10: =J10*(1+Supuestos!$B$15) -> 1252.0276 | L10: =K10*(1+Supuestos!$B$15) -> 1277.0682 | M10: =L10*(1+Supuestos!$B$15) -> 1302.6095
C11: Slitter Drywall 0,50 - Ingreso USD | D11: =D10*Producción!D11 -> 397181.31 | E11: =E10*Producción!E11 -> 1782000 | F11: =F10*Producción!F11 -> 1935738 | G11: =G10*Producción!G11 -> 2073927.2 | H11: =H10*Producción!H11 -> 2220409.2 | I11: =I10*Producción!I11 -> 2379141.3 | J11: =J10*Producción!J11 -> 2547017 | K11: =K10*Producción!K11 -> 2728168.2 | ... M11: =M10*Producción!M11 -> 3128868.1
B12: 4 | C12: Slitter Steel Frame 0,80/0,95 - Precio USD/Tn | D12: =+Ej_Ingresos!O11 -> 1080 | E12: =+Ej_Ingresos!AD11 -> 1080 | F12: =E12*(1+Supuestos!$B$14) -> 1134 | G12: =F12*(1+Supuestos!$B$15) -> 1156.68 | H12: =G12*(1+Supuestos!$B$15) -> 1179.8136 | I12: =H12*(1+Supuestos!$B$15) -> 1203.4099 | J12: =I12*(1+Supuestos!$B$15) -> 1227.4781 | K12: =J12*(1+Supuestos!$B$15) -> 1252.0276 | L12: =K12*(1+Supuestos!$B$15) -> 1277.0682 | M12: =L12*(1+Supuestos!$B$15) -> 1302.6095
C13: Slitter Steel Frame 0,80/0,95 - Ingreso USD/Tn | D13: =D12*Producción!D13 -> 486000 | E13: =E12*Producción!E13 -> 1782000 | F13: =F12*Producción!F13 -> 1935738 | G13: =G12*Producción!G13 -> 2073927.2 | H13: =H12*Producción!H13 -> 2220409.2 | I13: =I12*Producción!I13 -> 2379141.3 | J13: =J12*Producción!J13 -> 2547017 | K13: =K12*Producción!K13 -> 2728168.2 | ... M13: =M12*Producción!M13 -> 3128868.1
B14: 5 | C14: Telhas Metálicas Naturales - Precio USD/Tn | D14: =+Ej_Ingresos!O12 -> 1218 | E14: =+Ej_Ingresos!AD12 -> 1218 | F14: =E14*(1+Supuestos!$B$14) -> 1278.9 | G14: =F14*(1+Supuestos!$B$15) -> 1304.478 | H14: =G14*(1+Supuestos!$B$15) -> 1330.5676 | I14: =H14*(1+Supuestos!$B$15) -> 1357.1789 | J14: =I14*(1+Supuestos!$B$15) -> 1384.3225 | K14: =J14*(1+Supuestos!$B$15) -> 1412.0089 | L14: =K14*(1+Supuestos!$B$15) -> 1440.2491 | M14: =L14*(1+Supuestos!$B$15) -> 1469.0541
C15: Telhas Metálicas Naturales - Ingreso USD | D15: =D14*Producción!D15 -> 292320 | E15: =E14*Producción!E15 -> 803880 | F15: =F14*Producción!F15 -> 873488.7 | G15: =G14*Producción!G15 -> 935310.73 | H15: =H14*Producción!H15 -> 1001917.4 | I15: =I14*Producción!I15 -> 1072171.3 | J15: =J14*Producción!J15 -> 1147603.3 | K15: =K14*Producción!K15 -> 1229859.8 | ... M15: =M14*Producción!M15 -> 1408822.9
B16: 6 | C16: Telhas Metálicas Pre Pintadas - Precio USD/Tn | D16: =+Ej_Ingresos!O13 -> 1380.8228 | E16: =+Ej_Ingresos!AD13 -> 1399 | F16: =E16*(1+Supuestos!$B$14) -> 1468.95 | G16: =F16*(1+Supuestos!$B$15) -> 1498.329 | H16: =G16*(1+Supuestos!$B$15) -> 1528.2956 | I16: =H16*(1+Supuestos!$B$15) -> 1558.8615 | J16: =I16*(1+Supuestos!$B$15) -> 1590.0387 | K16: =J16*(1+Supuestos!$B$15) -> 1621.8395 | L16: =K16*(1+Supuestos!$B$15) -> 1654.2763 | M16: =L16*(1+Supuestos!$B$15) -> 1687.3618
C17: Telhas Metálicas Pre Pintadas - Ingreso USD | D17: =D16*Producción!D17 -> 218170 | E17: =E16*Producción!E17 -> 461670 | F17: =F16*Producción!F17 -> 502380.9 | G17: =G16*Producción!G17 -> 537900.11 | H17: =H16*Producción!H17 -> 574639.14 | I17: =I16*Producción!I17 -> 615750.29 | J17: =J16*Producción!J17 -> 659866.07 | K17: =K16*Producción!K17 -> 705500.18 | ... M17: =M16*Producción!M17 -> 809933.67
B18: 7 | C18: Perfil Drywall 0,43 Prepintado - Precio USD/Tn | D18: =+Ej_Ingresos!O14 -> 1399 | E18: =+Ej_Ingresos!AD14 -> 1399 | F18: =E18*(1+Supuestos!$B$14) -> 1468.95 | G18: =F18*(1+Supuestos!$B$15) -> 1498.329 | H18: =G18*(1+Supuestos!$B$15) -> 1528.2956 | I18: =H18*(1+Supuestos!$B$15) -> 1558.8615 | J18: =I18*(1+Supuestos!$B$15) -> 1590.0387 | K18: =J18*(1+Supuestos!$B$15) -> 1621.8395 | L18: =K18*(1+Supuestos!$B$15) -> 1654.2763 | M18: =L18*(1+Supuestos!$B$15) -> 1687.3618
C19: Perfil Drywall 0,43 Prepintado - Ingreso USD | D19: =D18*Producción!D19 -> 167880 | E19: =E18*Producción!E19 -> 902355 | F19: =F18*Producción!F19 -> 979789.65 | G19: =G18*Producción!G19 -> 1048830.3 | H19: =H18*Producción!H19 -> 1124825.5 | I19: =I18*Producción!I19 -> 1203441.1 | J19: =J18*Producción!J19 -> 1289521.4 | K19: =K18*Producción!K19 -> 1380185.4 | ... M19: =M18*Producción!M19 -> 1582745.4
