Workbook

Sheet Guia
A1: Modelo financiero de maquila CIE-PERG — guía de uso
A2: Base documental: plan «Procesamiento de chapas para gabinetes metálicos» (Mujica & Saldivar, Oct-2025) e informe de validación (29/09/2026).
A4: Propósito
C5: Reconstruir el plan publicado, documentar sus inconsistencias y convertirlo en un modelo de actualización continua: reales + forecast, escenarios y evaluación de rentabilidad, liquidez, financiamiento y creación de valor por separado.
C6: Tres capas: (1) PDF publicado Oct-2025 (Base_PDF, inalterado); (2) Base depurada (supuestos históricos + correcciones C1-C6 + motor mensual); (3) Reales + forecast (Datos_Reales hasta el último mes cerrado; escenario activo para el futuro).
A8: Hojas
B9: Resumen | C9: Tablero ejecutivo: PDF vs escenario activo, alertas y gráficos.
B10: Supuestos | C10: Selector único de escenario, prueba de sensibilidad, parámetros generales, préstamo, correcciones metodológicas, drivers por escenario, dividendos y aportes.
B11: Calendario | C11: Meses del modelo (0 = inicio de implantación), años de proyecto y operativos, banderas de operación/horizonte/reales, TC y factores de descuento.
B12: Produccion_Ventas | C12: Capacidad, demanda, rampa, recuperación de volumen, producción buena, rechazos, inventario de PT en unidades, precios y ventas.
B13: Costos_Personal | C13: Nómina por puesto (PYG), maestro de costos fijos con moneda de origen, materiales, costos variables, fijos y resúmenes.
B14: Inversion_Activos | C14: Presupuesto original, ejecutado, comprometido, por contratar, costo final estimado, pagos, altas y depreciación por ítem.
B15: Capital_Trabajo | C15: Clientes por cohortes (DSO interpolado), inventarios, proveedores, anticipos y CT operativo neto (sin caja mínima).
B16: Deuda_Tributos | C16: IVA recuperable, préstamo original (reproduce el PDF), tramo 2 opcional y aportes.
B17: Resultados_Caja | C17: Estado de resultados, caja por método directo con control indirecto, tesorería (caja mínima, brecha, dividendos, línea hipotética), balance de control y flujos de valuación.
B18: Resultados_Anuales | C18: Agregación anual, comparación con el PDF, indicadores (VAN/TIR proyecto y socios, payback, DSCR, equilibrio, rentabilidad por producto).
B19: Escenarios_Sensib | C19: Capturas identificadas de escenarios, pruebas de sensibilidad y puente de correcciones, con verificación en vivo.
B20: Datos_Reales | C20: Tablas vacías para fechas, saldos al corte, CAPEX por ítem, movimientos mensuales, documentación y campos mínimos.
... B22: Validaciones | C22: Controles con tolerancia, registro de inconsistencias del PDF y pruebas realizadas.
A24: Convenciones
B25: Colores | C25: Azul sobre amarillo claro = entrada editable. Amarillo intenso = pendiente de cargar. Verde = vínculo a otra hoja. Negro = fórmula. Gris itálica = valor heredado de la base (sobrescribir para cambiar). Salmón = dato histórico del PDF.
B26: Moneda | C26: Presentación en USD. Nómina y varios costos fijos tienen origen en PYG y se convierten con el TC de cada año; compras en USD no cambian con el TC. Nunca se suman PYG con USD.
B27: Tiempo | C27: Mes 0 = inicio de implantación/desembolso. Sin fecha del mes 0 el modelo trabaja en meses relativos (no se asume año 1 = 2025 o 2026).
B28: Signos | C28: Costos y pagos positivos en sus filas; los flujos (FCFF, socios) llevan signo: negativo = salida.
A30: Cómo usar
B31: Cambiar escenario | C31: Supuestos!D5. Los escenarios Conservador y Recuperación son ILUSTRATIVOS. Actualizado y Personalizado heredan la base hasta que se sobrescriban (columna E/H).
B32: Prueba de sensibilidad | C32: Supuestos!D8 aplica un choque sobre el escenario activo y recalcula todo (tributos, CT, financiamiento e intereses). Volver a «Ninguna».
B33: Correcciones | C33: Supuestos sección C: poner 0 reproduce el criterio del PDF de esa corrección (para el puente de conciliación).
B34: Cierre mensual | C34: 1) Cargar movimientos del mes en Datos_Reales T7 (código, mes, moneda, importe, TC, fuente, estado). 2) Cargar saldos al corte en T2 y CAPEX por ítem en T3. 3) Actualizar T1 «Último mes cerrado». 4) Revisar Validaciones (meses reales sin registros, ajustes de conciliación a patrimonio). 5) Ajustar supuestos futuros en la columna Actualizado. 6) Revisar Resumen y alertas.
B35: Congelamiento | C35: Los meses ≤ último mes cerrado usan solo reales; los escenarios afectan únicamente el futuro. Una diferencia entre saldos reales y calculados se registra como «ajuste de conciliación» en patrimonio y debe investigarse.
A37: Métricas
B38: VAN/TIR del proyecto | C38: FCFF: flujo operativo después de tributos - CAPEX - ΔCT operativo, sin préstamos, intereses, aportes ni dividendos. Tasa del proyecto (G17), mensual equivalente.
B39: VAN/TIR de socios | C39: Aportes (negativos), dividendos efectivamente pagados y valor final atribuible (caja + activos netos - deuda), descontados a Ke. No suma FCFE no distribuido.
B40: Payback | C40: Simple y descontado sobre la misma serie; «No recupera en el horizonte» si no cruza.
B41: Necesidad de financiamiento | C41: Pico antes de aportes adicionales (caja acumulada con préstamo original y aporte inicial vs caja mínima) y brecha no cubierta después del financiamiento planificado.
B42: CFADS y DSCR | C42: CFADS = flujo operativo - CAPEX de mantenimiento. DSCR = CFADS / (capital + intereses + IVA + comisiones). EBITDA/servicio es solo una aproximación.
B43: Equilibrio | C43: En ventas con el mix del año y unidades por producto; no se mezclan gabinetes y cajas como unidades equivalentes.
B44: Valor terminal | C44: Liquidación realizable (por defecto) o negocio en marcha; nunca ambos.
A46: Registro de avance
B47: Versión | C47: v1.0 — 29/09/2026. Libro construido con generar_modelo.py (reproducible).
B48: Terminado | C48: Base_PDF reproducida (diferencias ≤ redondeo), motor mensual integrado con balance y método directo/indirecto cuadrados, 5 escenarios, 16 pruebas, puente de correcciones, registro de inconsistencias y tablas de reales.
B49: Último control | C49: Ver Validaciones: controles V01-V33 y pruebas P01 en adelante (recálculo completo sin errores ni circularidades).
B50: Pendiente | C50: Datos reales desde Oct-2025, fecha del mes 0, CAPEX ejecutado/comprometido, contrato y modalidad de maquila, verificación de Ley 7547/2025 y Decreto 5714/2026, naturaleza del alquiler, gastos de venta, tasas vigentes, TC real/proyectado, vida útil del CAPEX adicional, respaldo técnico de capacidad.

Sheet Resumen
A1: Resumen ejecutivo — Maquila CIE-PERG: procesamiento de chapas para gabinetes y cajas metálicas (USD)
A2: ="Escenario: "&p_Escenario&" | Prueba: "&p_Shock&" | "&INDEX(Supuestos!$D$98:$H$98,1,p_EscIdx) -> Escenario: Base depurada (supuestos Oct-2025) | Prueba: Ninguna | Supuestos históricos Oct-2025 con correcciones metodológicas. NO es ejecución real.
A4: A. Estado del modelo
B5: Escenario activo | C5: =p_Escenario -> Base depurada (supuestos Oct-2025)
B6: Prueba de sensibilidad activa | C6: =p_Shock -> Ninguna
B7: Correcciones metodológicas activas (de 6) | C7: =p_NCorr -> 6
B8: Último mes cerrado con datos reales | C8: =IF(p_MesCorte<0,"Ninguno: proyección con supuestos históricos",p_MesCorte) -> Ninguno: proyección con supuestos históricos
B9: Campos mínimos para forecast actualizado | C9: =r_MinCompletos -> 0 de 10
B10: Calendario | C10: =IF(p_FechaInicio="","PENDIENTE: meses relativos (sin fecha del mes 0)","Mes 0 = "&MONTH(p_FechaInicio)&"/"&YEAR(p_FechaInicio)) -> PENDIENTE: meses relativos (sin fecha del mes 0)
B11: Tasa del proyecto aplicada | C11: =FIXED(p_TasaProy*100,2)&"% — "&p_TasaEstado -> 9.49% — Ponderada inicial PDF (histórica)
B12: Ke aplicado (histórico) | C12: =FIXED(p_Ke*100,2)&"%" -> 16.32%
B13: Controles de Validaciones en estado REVISAR | C13: =v_Revisar -> 0
A15: B. PDF publicado (histórico) vs escenario activo recalculado
B16: Indicador | C16: PDF publicado Oct-2025 (histórico) | D16: Escenario activo (motor) | E16: Diferencia | F16: Nota
B17: Inversión fija inicial / CAPEX estimado total | C17: =Base_PDF!$E$50 -> 655044 | D17: =k_capex_e -> 755044.1 | E17: =IF(AND(ISNUMBER(C17),ISNUMBER(D17)),D17-C17,"") -> 100000.1 | F17: El motor incluye el CAPEX adicional del año 2 (USD 100.000).
B18: Capital operativo inicial (PDF) / CT operativo neto máximo (motor) | C18: =Base_PDF!$E$51 -> 2336543 | D18: =k_ctn_max -> 4942519.1 | E18: =IF(AND(ISNUMBER(C18),ISNUMBER(D18)),D18-C18,"") -> 2605976.1 | F18: Conceptos distintos: el PDF suma CT de un año al inicio; el motor lo construye mes a mes.
B19: Ventas año 1 | C19: =Base_PDF!$F$102 -> 4850000 | D19: =k_v1 -> 4850000 | E19: =IF(AND(ISNUMBER(C19),ISNUMBER(D19)),D19-C19,"") -> 0 | F19: Año de proyecto 1.
B20: Ventas totales 10 años | C20: =Base_PDF!$P$102 -> 81222448 | D20: =k_vt -> 81222448 | E20: =IF(AND(ISNUMBER(C20),ISNUMBER(D20)),D20-C20,"") -> -0.27835459
B21: EBITDA año 1 | C21: =Base_PDF!$F$358 -> 573024 | D21: =k_e1 -> 526818.42 | E21: =IF(AND(ISNUMBER(C21),ISNUMBER(D21)),D21-C21,"") -> -46205.577 | F21: Tributo de maquila incluido una sola vez dentro del EBITDA.
B22: EBITDA total 10 años | C22: =Base_PDF!$P$358 -> 17354010 | D22: =k_et -> 16318100 | E22: =IF(AND(ISNUMBER(C22),ISNUMBER(D22)),D22-C22,"") -> -1035910.1
B23: Resultado neto total | C23: =Base_PDF!$P$359 -> 15945168 | D23: =k_nit -> 14759842 | E23: =IF(AND(ISNUMBER(C23),ISNUMBER(D23)),D23-C23,"") -> -1185326.4
B24: VAN (PDF: cuadro 19 mezcla perspectivas / motor: FCFF del proyecto) | C24: =Base_PDF!$E$58 -> 4588736 | D24: =k_van_p -> 6732540.9 | E24: =IF(AND(ISNUMBER(C24),ISNUMBER(D24)),D24-C24,"") -> 2143804.9 | F24: PUBLICADO, METODOLOGÍA POR DEPURAR vs VAN del proyecto. No son comparables en sentido estricto.
B25: TIR (PDF «con financiamiento» / motor: TIR del proyecto) | C25: =Base_PDF!$E$59 -> 0.2261 | D25: =k_tir_p -> 0.32312817 | E25: =IF(AND(ISNUMBER(C25),ISNUMBER(D25)),D25-C25,"") -> 0.09702817 | F25: Una TIR alta no implica decisión conveniente sin VAN, caja y riesgo.
B26: VAN de los socios a Ke (PDF reexpresado / motor) | C26: =Base_PDF!$E$427 -> 3912957.6 | D26: =k_van_e -> 3748260 | E26: =IF(AND(ISNUMBER(C26),ISNUMBER(D26)),D26-C26,"") -> -164697.58 | F26: Aportes, dividendos pagados y valor final.
B27: TIR de los socios (PDF reexpresado / motor) | C27: =Base_PDF!$E$428 -> 0.49362358 | D27: =k_tir_e -> 0.44982914 | E27: =IF(AND(ISNUMBER(C27),ISNUMBER(D27)),D27-C27,"") -> -0.043794439
B28: Payback descontado (PDF: serie desde -2.791.587 / motor: FCFF) | C28: =Base_PDF!$E$60 -> 7 | D28: =k_pb_d -> 5.1359395 | E28: =IF(AND(ISNUMBER(C28),ISNUMBER(D28)),D28-C28,"") -> -1.8640605 | F28: Años. PDF «durante el 7mo año»; sobre la serie del VAN ≈ 6,89. Motor simple en Resultados_Anuales.
B29: Aportes de socios en efectivo (total) | C29: =Base_PDF!$E$14+Base_PDF!$E$386 -> 1139710 | D29: =k_ap -> 1139710 | E29: =IF(AND(ISNUMBER(C29),ISNUMBER(D29)),D29-C29,"") -> 0
B30: Pico de necesidad de fondos adicionales (antes de aportes adicionales) | C30: =Base_PDF!$E$386 -> 939710 | D30: =k_nec -> 1529018.5 | E30: =IF(AND(ISNUMBER(C30),ISNUMBER(D30)),D30-C30,"") -> 589308.48 | F30: PDF: aportes adicionales planificados. Motor: necesidad mensual acumulada incluida la caja mínima.
B31: Brecha no cubierta máxima (con financiamiento planificado) | C31: 0 | D31: =k_brecha_nc -> 589308.48 | E31: =IF(AND(ISNUMBER(C31),ISNUMBER(D31)),D31-C31,"") -> 589308.48 | F31: El motor no inserta fondos ficticios: la brecha queda visible.
B32: Deuda financiera máxima | C32: =Base_PDF!$E$15 -> 2791587 | D32: =k_deuda_max -> 2791587 | E32: =IF(AND(ISNUMBER(C32),ISNUMBER(D32)),D32-C32,"") -> 0
B33: DSCR mínimo (CFADS / servicio de deuda) | C33: n/d en el PDF | D33: =k_dscr_min -> -2.5448787 | E33: =IF(AND(ISNUMBER(C33),ISNUMBER(D33)),D33-C33,"") | F33: EBITDA/servicio año 1 PDF ≈ 1,08x (aproximación, no DSCR).
B34: Equilibrio año 1 (PDF: unidades mezcladas / motor: ventas USD) | C34: =Base_PDF!$F$392 -> 66042 | D34: =k_pe1 -> 3538366.4 | E34: =IF(AND(ISNUMBER(C34),ISNUMBER(D34)),D34-C34,"") -> 3472324.4 | F34: Motor: ver gabinetes y cajas en equilibrio con el mix del año.
A36: C. Alertas específicas
B37: =IF(p_EscIdx=1,"Base depurada: supuestos de Oct-2025 con correcciones metodológicas; NO es situación real de 2026.",IF(p_EscIdx=2,INDEX(Supuestos!$D$98:$H$98,1,2),"Escenario "&p_Escenario&": "&INDEX(Supuestos!$D$98:$H$98,1,p_EscIdx))) -> Base depurada: supuestos de Oct-2025 con correcciones metodológicas; NO es situación real de 2026.
B38: =IF(p_ShockIdx>1,"PRUEBA DE SENSIBILIDAD ACTIVA («"&p_Shock&"»): los resultados son un choque ilustrativo. Volver a «Ninguna».","")
B39: =IF(k_brecha_nc>0.5,"Brecha de caja no cubierta: máx. USD "&FIXED(k_brecha_nc,0)&" en "&k_brecha_nc_n&" meses. El financiamiento planificado no alcanza; definir aportes, deuda o mejoras de CT.","Sin brecha de caja no cubierta con el financiamiento planificado.") -> Brecha de caja no cubierta: máx. USD 589,308 en 32 meses. El financiamiento planificado no alcanza; definir aportes, deuda o mejoras de CT.
B40: ="Pico de necesidad antes de aportes adicionales: USD "&FIXED(k_nec,0)&" en el mes "&k_nec_m&" (PDF planificó USD 939.710 de aportes adicionales)." -> Pico de necesidad antes de aportes adicionales: USD 1,529,018 en el mes 28 (PDF planificó USD 939.710 de aportes adicionales).
B41: =IF(k_chk_cap>0,k_chk_cap&" meses con producción sobre la capacidad del plan: requiere horas extra, turno o inversión explícitos.","") -> 2 meses con producción sobre la capacidad del plan: requiere horas extra, turno o inversión explícitos.
B42: =IF(ISNUMBER(k_dscr_min),IF(k_dscr_min<1,"DSCR mínimo "&FIXED(k_dscr_min,2)&"x: el flujo operativo (incluida la formación de CT del arranque) no cubre el servicio de deuda en algún año; se financia con aportes o caja.",""),"") -> DSCR mínimo -2.54x: el flujo operativo (incluida la formación de CT del arranque) no cubre el servicio de deuda en algún año; se financia con aportes o caja.
B43: =IF(ISNUMBER(k_tir_p),IF(LEFT(k_tir_p_u,5)<>"Única","TIR del proyecto con posibles valores múltiples: priorizar VAN.",""),"TIR del proyecto no disponible: "&k_tir_p)
B44: =IF(p_MesCorte<0,"Sin datos reales cargados: la situación desde Oct-2025 no está incorporada. Ver Datos_Reales.","") -> Sin datos reales cargados: la situación desde Oct-2025 no está incorporada. Ver Datos_Reales.
B45: =IF(p_FechaInicio="","Calendarización pendiente: el año 1 no se asocia a 2025 ni a 2026 hasta cargar la fecha del mes 0.","") -> Calendarización pendiente: el año 1 no se asocia a 2025 ni a 2026 hasta cargar la fecha del mes 0.
B46: =IF(p_MetodoTasa=1,"Tasa del proyecto = ponderada inicial del PDF (93% deuda a 9%): hipótesis histórica, no WACC vigente.","") -> Tasa del proyecto = ponderada inicial del PDF (93% deuda a 9%): hipótesis histórica, no WACC vigente.
B47: =IF(OR(p_BaseTrib=1,p_Modalidad=1),"Tributo de maquila, IVA y modalidad contractual: criterio histórico del PDF, pendiente de verificación con Ley 7547/2025 y el contrato.","") -> Tributo de maquila, IVA y modalidad contractual: criterio histórico del PDF, pendiente de verificación con Ley 7547/2025 y el contrato.
B48: =IF(p_NCorr<6,"Correcciones metodológicas incompletas ("&p_NCorr&" de 6): el resultado no es la base depurada.","")
B49: =IF(k_chk_bal+k_chk_ind>0.01,"ERROR DE INTEGRIDAD: balance o método directo/indirecto no cuadran. Revisar Validaciones.","")
B50: =IF(v_Revisar>0,v_Revisar&" controles en estado REVISAR (hoja Validaciones).","")
B51: =IF(p_ApAuto=1,"Aportes hipotéticos de cobertura ACTIVOS (no aprobados): USD "&FIXED(k_ap_auto,0)&" incluidos en el flujo de socios.",IF(k_brecha_nc>0.5,"El VAN/TIR de socios supone que la brecha se cubre sin costo; activar Supuestos G63 para medir el aporte adicional requerido.","")) -> El VAN/TIR de socios supone que la brecha se cubre sin costo; activar Supuestos G63 para medir el aporte adicional requerido.
B52: =IF(AND(p_MesCorte>=0,p_ArranqueReal=""),"Hay reales cargados sin «mes real de arranque» (Datos_Reales T1): el atraso del escenario puede contradecir la operación real.","")
A54: D. Lectura para la decisión
B55: • Esta versión reconstruye el plan de octubre de 2025, corrige su metodología y permite simular. No acredita la viabilidad actual del negocio: no se cargó ejecución real, compromisos vigentes ni condiciones contractuales.
B56: • Rentabilidad, liquidez y creación de valor se leen por separado: VAN/TIR del proyecto (FCFF), VAN/TIR de socios (Ke), brecha de caja y DSCR.
B57: • La base depurada mantiene ventas y precios del PDF; las diferencias de EBITDA y caja provienen de correcciones (C1-C6) y del calendario mensual del capital de trabajo.
B58: • La recomendación actualizada debe emitirse cuando se incorporen reales, CAPEX comprometido, contrato de maquila y tasas vigentes.
A60: E. Gráficos (años de proyecto 1 a 10)
B61: CAPEX presupuesto original | C61: =k_capex_o -> 755044.1
B62: CAPEX costo final estimado | C62: =k_capex_e -> 755044.1

Sheet Supuestos
A1: Supuestos — selector de escenario, parámetros y drivers
A2: Celdas amarillas con texto azul = entradas editables. Gris itálica = hereda de la base (sobrescribir para cambiar). Los parámetros tributarios y económicos no están embebidos en fórmulas.
A4: A. Selector de escenario y prueba de sensibilidad
B5: Escenario activo (único selector de supuestos futuros) | D5: Base depurada (supuestos Oct-2025) | H5: Cambia solo el futuro: los meses reales (hasta el último mes cerrado) no se modifican.
B6: Índice del escenario activo | D6: =MATCH(p_Escenario,$D$97:$H$97,0) -> 1
B7: Estado del escenario activo | D7: =INDEX($D$98:$H$98,1,p_EscIdx) -> Supuestos históricos Oct-2025 con correcciones metodológicas. NO es ejecución real.
B8: Prueba de sensibilidad activa (choque ilustrativo sobre el escenario) | D8: Ninguna | H8: Choques de prueba del modelo, no premisas de negocio. Volver a «Ninguna» al terminar.
B9: Índice de la prueba activa | D9: =MATCH(p_Shock,$B$192:$B$207,0) -> 1
A11: B. Parámetros generales (no dependen del escenario)
A12: Cód. | B12: Parámetro | C12: Unidad / moneda | D12: Valor | E12: Vigencia | F12: Fuente / pág. | G12: Estado | H12: Nota
A13: G01 | B13: Tipo de cambio de referencia del plan | C13: Gs/USD | D13: =Base_PDF!$E$7 -> 7300 | E13: Histórico Oct-2025 | F13: PDF p. 4-5 | G13: Publicado (PDF)
A14: G02 | B14: TC implícito en la nómina del PDF (solo para reproducir) | C14: Gs/USD | D14: =Base_PDF!$E$10 -> 8000 | E14: Histórico | F14: PDF p. 30-34 | G14: Inferido | H14: Se usa únicamente si la corrección C1 está desactivada.
A15: G03 | B15: Meses de implantación previstos antes del primer mes operativo | C15: meses | D15: 0 | E15: Plan | F15: PDF: año 0 puntual | G15: Supuesto provisional | H15: El PDF concentra la inversión en el año 0 y opera desde el año 1. Cargar el cronograma real si difiere.
A16: G04 | B16: Fecha calendario del mes 0 (inicio de implantación / desembolso) | C16: fecha | E16: — | F16: No informada en el PDF | G16: Pendiente de confirmar | H16: Sin fecha el modelo usa meses relativos. No se infiere que año 1 = 2025 o 2026.
A17: G05 | B17: Modo de horizonte (1 = fecha final fija; 2 = 10 años desde el arranque efectivo) | C17: 1/2 | D17: 1 | E17: Todo | F17: Prompt 5.6 | G17: Supuesto provisional | H17: Con 1 un atraso acorta la operación (no prolonga la vida). Con 2 se compara 10 años desde la puesta en marcha efectiva.
A18: G06 | B18: Años operativos del plan | C18: años | D18: 10 | E18: Todo | F18: PDF | G18: Publicado (PDF)
A19: G07 | B19: Meses operativos del plan | C19: meses | D19: =p_AniosOp*12 -> 120 | E19: Todo | F19: Cálculo | G19: Cálculo
A20: G08 | B20: Días por año (convención de días de CT) | C20: días | D20: 365 | E20: Todo | F20: PDF cuadro 16 | G20: Publicado (PDF)
A21: G09 | B21: Días promedio por mes | C21: días | D21: =p_DiasAnio/12 -> 30.416667 | E21: Todo | F21: Cálculo | G21: Cálculo
A22: G10 | B22: Costo del capital propio Ke (anual efectiva, USD nominal) | C22: % | D22: =Base_PDF!$E$11 -> 0.1632 | E22: Histórico | F22: PDF p. 9 | G22: Publicado (PDF) - histórico no vigente confirmado | H22: Hipótesis histórica. Actualizar con fecha y fundamento (tasa libre de riesgo, prima, riesgo país, tamaño).
A23: G11 | B23: Tasa bancaria de referencia (nominal anual) | C23: % | D23: =Base_PDF!$E$12 -> 0.09 | E23: Histórico | F23: PDF p. 4 | G23: Publicado (PDF) - histórico
A24: G12 | B24: Tasa de descuento del proyecto: 1 = ponderada inicial PDF; 2 = WACC con estructura objetivo; 3 = manual | C24: 1/2/3 | D24: 1 | E24: Todo | F24: Prompt 8.5 | G24: Supuesto provisional | H24: La ponderada inicial usa pesos del momento 0 (6,7%/93,3%), que no representan la estructura durante 10 años.
A25: G13 | B25: Peso objetivo de la deuda D/(D+E) para el método 2 | C25: % | E25: Todo | F25: — | G25: Pendiente de definir | H25: Definir estructura objetivo justificada o usar APV si el apalancamiento cambia materialmente.
A26: G14 | B26: Costo efectivo de la deuda = tasa x (1 + IVA intereses no recuperable) | C26: % | D26: =p_Kd*(1+p_IVAint) -> 0.099 | E26: Todo | F26: Cálculo | G26: Cálculo | H26: Sin escudo de IRE: el plan asume IRE no aplicable bajo maquila (verificar).
A27: G15 | B27: Tasa manual del proyecto (método 3) | C27: % | E27: Todo | F27: — | G27: Pendiente de definir
A28: G16 | B28: Tasa ponderada inicial exacta (método 1) | C28: % | D28: =Base_PDF!$E$409 -> 0.094893724 | E28: Histórico | F28: PDF p. 28 | G28: Publicado (PDF) - cálculo exacto
A29: G17 | B29: Tasa de descuento del proyecto aplicada (anual efectiva) | C29: % | D29: =IF(p_MetodoTasa=2,IF(p_DV="",p_TasaPDF,p_DV*p_KdEf+(1-p_DV)*p_Ke),IF(p_MetodoTasa=3,IF(p_TasaManual="",p_TasaPDF,p_TasaManual),p_TasaPDF)) -> 0.094893724 | E29: Todo | F29: Cálculo | G29: Cálculo | H29: Si faltan datos del método elegido, vuelve al método 1 y lo informa en el estado siguiente.
A30: G18 | B30: Estado de la tasa del proyecto | C30: texto | D30: =IF(AND(p_MetodoTasa=2,p_DV=""),"Método 2 sin peso objetivo: se usa ponderada inicial",IF(AND(p_MetodoTasa=3,p_TasaManual=""),"Método 3 sin tasa: se usa ponderada inicial",IF(p_MetodoTasa=1,"Ponderada inicial PDF (histórica)","OK"))) -> Ponderada inicial PDF (histórica) | E30: Todo | F30: Cálculo | G30: Cálculo
A31: G19 | B31: IRE sobre resultado (régimen de maquila) | C31: % | D31: 0 | E31: Todo | F31: PDF p. 7-8 | G31: Publicado (PDF) - verificar Ley 7547/2025 | H31: El plan considera IRE no aplicable. No se aplica escudo fiscal de intereses. Impuesto a dividendos: pendiente de verificar.
A32: G20 | B32: Valor terminal: 1 = liquidación realizable; 2 = negocio en marcha (perpetuidad) | C32: 1/2 | D32: 1 | E32: Fin de horizonte | F32: Prompt 8.9 | G32: Supuesto provisional | H32: En negocio en marcha no se recupera el CT ni se vende el activo (se necesitan para operar).
A33: G21 | B33: Crecimiento perpetuo nominal en USD (solo método 2) | C33: % | D33: 0 | E33: Perpetuidad | F33: — | G33: Supuesto provisional
A34: G22 | B34: Realización de cuentas por cobrar al cierre (liquidación) | C34: % | D34: 1 | E34: Fin de horizonte | F34: — | G34: Supuesto provisional
A35: G23 | B35: Realización de inventarios al cierre (liquidación) | C35: % | D35: 1 | E35: Fin de horizonte | F35: — | G35: Supuesto provisional
A36: G24 | B36: Realización del activo fijo (% del valor neto contable) | C36: % | D36: 1 | E36: Fin de horizonte | F36: — | G36: Supuesto provisional | H36: Un valor contable residual no es automáticamente precio de venta. Reemplazar por tasación.
A37: G25 | B37: Costos e impuestos de cierre / liquidación | C37: USD | D37: 0 | E37: Fin de horizonte | F37: — | G37: Pendiente de estimar
A38: G26 | B38: Modalidad de facturación: 1 = venta de producto (PDF); 2 = servicio de maquila | C38: 1/2 | D38: 1 | E38: Todo | F38: PDF p. 6; contrato pendiente | G38: Pendiente de confirmar | H38: Con 2 los ingresos son tarifa de servicio y los materiales del cliente no son costo ni inventario propio.
A39: G27 | B39: Tarifa de servicio de maquila por gabinete (modalidad 2) | C39: USD/u | E39: Año 1 | F39: Contrato | G39: Pendiente de cargar
A40: G28 | B40: Tarifa de servicio de maquila por caja (modalidad 2) | C40: USD/u | E40: Año 1 | F40: Contrato | G40: Pendiente de cargar
A41: G29 | B41: % de materiales (MP, insumos, flete MP) propiedad del cliente en modalidad 2 | C41: % | D41: 1 | E41: Todo | F41: Contrato | G41: Pendiente de confirmar
A42: G30 | B42: Driver de costos comunes: 1 = kg procesado; 2 = costo directo (criterio PDF); 3 = horas estándar | C42: 1/2/3 | D42: 1 | E42: Todo | F42: Prompt 6.6 | G42: Supuesto provisional | H42: Reparto provisional. Reemplazar por horas máquina/hombre cuando se disponga.
A43: G31 | B43: Peso por gabinete | C43: kg/u | D43: =Base_PDF!$E$48 -> 153 | E43: Todo | F43: PDF p. 1 | G43: Publicado (PDF)
A44: G32 | B44: Peso por caja | C44: kg/u | D44: =Base_PDF!$E$49 -> 13 | E44: Todo | F44: PDF p. 1 | G44: Publicado (PDF)
A45: G33 | B45: Horas estándar por gabinete (driver 3) | C45: h/u | E45: Todo | F45: Ingeniería | G45: Pendiente de cargar
A46: G34 | B46: Horas estándar por caja (driver 3) | C46: h/u | E46: Todo | F46: Ingeniería | G46: Pendiente de cargar
A47: G35 | B47: Superficie de nave | C47: m2 | D47: =Base_PDF!$E$21 -> 3865 | E47: Todo | F47: PDF p. 6 | G47: Publicado (PDF)
A48: G36 | B48: Alquiler neto de IVA | C48: USD/m2/mes | D48: =Base_PDF!$E$22 -> 4 | E48: Año 1 | F48: PDF p. 6 | G48: Publicado (PDF)
A49: G37 | B49: IVA incluido en el alquiler | C49: % | D49: =Base_PDF!$E$23 -> 0.1 | E49: Todo | F49: PDF p. 6 | G49: Publicado (PDF)
A50: G38 | B50: Incremento anual de alquiler y expensas | C50: % | D50: 0.03 | E50: Desde año 2 | F50: PDF cuadro 10a (inferido) | G50: Inferido
A51: G39 | B51: Expensas | C51: USD/m2/mes | D51: =Base_PDF!$E$24 -> 0.2 | E51: Año 1 | F51: PDF p. 19 | G51: Publicado (PDF)
A52: G40 | B52: Alquiler: 1 = pago real a tercero; 2 = pago a relacionada (CIE); 3 = costo económico sin desembolso | C52: 1/2/3 | D52: 1 | E52: Todo | F52: PDF p. 6 («costo de oportunidad») | G52: Pendiente de confirmar | H52: Con 3 el alquiler sigue en resultados y en el FCFF (costo económico) pero no sale de tesorería; se registra como aporte en especie.
A53: G41 | B53: IVA sobre intereses (costo, no recuperable) | C53: % | D53: =Base_PDF!$E$19 -> 0.1 | E53: Todo | F53: PDF p. 4 | G53: Publicado (PDF)
A54: G42 | B54: Tributo único de maquila | C54: % | D54: =Base_PDF!$E$28 -> 0.01 | E54: Todo | F54: PDF p. 7; Ley 7547/2025 (fuente secundaria) | G54: Publicado (PDF) - verificar
A55: G43 | B55: Base del tributo: 1 = factura de exportación (PDF); 2 = mayor entre factura y valor agregado nacional | C55: 1/2 | D55: 1 | E55: Todo | F55: Ley 7547/2025 y Dec. 5714/2026 según fuentes secundarias | G55: Pendiente de verificar en texto oficial | H55: No se pudo acceder a mic.gov.py ni bacn.gov.py desde este entorno (29/09/2026). Verificar texto vigente y transición.
A56: G44 | B56: Tope de recuperación de IVA para maquila de servicios (% de facturación) | C56: % | D56: 0.005 | E56: Todo | F56: Ley 7547/2025 según fuentes secundarias | G56: Pendiente de verificar en texto oficial | H56: Se aplica solo en modalidad 2.
A57: G45 | B57: Seguro de caución maquila (% de ventas) | C57: % | D57: =Base_PDF!$E$205 -> 0.001 | E57: Todo | F57: PDF cuadro 10a (inferido exacto) | G57: Inferido
A58: G46 | B58: Despacho de importación (% de MP + insumos) | C58: % | D58: =Base_PDF!$E$25 -> 0.03 | E58: Todo | F58: PDF p. 19; base inferida | G58: Publicado (PDF) / base inferida
A59: G47 | B59: Packaging (% de materiales + flete + MO directa con cargas y alimentación) | C59: % | D59: =Base_PDF!$E$26 -> 0.01 | E59: Todo | F59: PDF p. 19; base inferida | G59: Publicado (PDF) / base inferida | H59: Base reproducida del PDF. Reemplazar por USD/unidad si se dispone del costo real de embalaje.
A60: G48 | B60: Imprevistos de producción (% costos producción excl. imprevistos y tributo) | C60: % | D60: =Base_PDF!$E$27 -> 0.05 | E60: Todo | F60: PDF p. 19; base inferida | G60: Publicado (PDF) / base inferida
A61: G49 | B61: Imprevistos de administración (% adm. excl. alquiler y expensas) | C61: % | D61: =Base_PDF!$E$27 -> 0.05 | E61: Todo | F61: PDF p. 19; base inferida | G61: Publicado (PDF) / base inferida
A62: G50 | B62: Prestaciones sociales (coeficiente del plan) | C62: % s/ remun. | D62: =Base_PDF!$E$20 -> 0.4309 | E62: Todo | F62: PDF p. 19 | G62: Publicado (PDF) - no validado legalmente | H62: Desagregar IPS, aguinaldo, vacaciones y provisiones cuando se aporten, evitando duplicaciones.
A63: G51 | B63: Alimentación por persona | C63: Gs/mes | D63: =Base_PDF!$E$61 -> 576000 | E63: Todo | F63: PDF cuadro 10a (inferido) | G63: Inferido
A64: G52 | B64: Mantenimiento de planta: incremento lineal anual (% del año 1) | C64: % | D64: =Base_PDF!$E$204 -> 0.02 | E64: Desde año 2 | F64: PDF cuadro 10a (inferido) | G64: Inferido
A65: G53 | B65: Meses entre el cierre del año y el pago de dividendos | C65: meses | D65: 4 | E65: Todo | F65: PDF: pago al año siguiente | G65: Supuesto provisional
A66: G54 | B66: Pagar dividendos solo con caja sobre el mínimo (1 = sí; 0 = no) | C66: 1/0 | D66: 1 | E66: Todo | F66: Prompt 8.2 | G66: Supuesto provisional | H66: Los dividendos no se pagan solo porque existe utilidad.
A67: G55 | B67: Caja mínima operativa (días de ventas del mes) | C67: días | D67: =Base_PDF!$E$29 -> 3 | E67: Todo | F67: PDF cuadro 16 (3 días) | G67: Publicado (PDF) | H67: Se modela en tesorería, separada del capital de trabajo operativo.
A68: G56 | B68: Caja mínima fija adicional | C68: USD | D68: 0 | E68: Todo | F68: — | G68: Supuesto provisional
A69: G57 | B69: Costos de espera: % del personal indirecto y administrativo activo antes del arranque | C69: % | D69: 1 | E69: Meses pre-operativos | F69: — | G69: Supuesto provisional (ilustrativo) | H69: Aplica a meses de implantación/atraso. Reemplazar por dotación real.
A70: G58 | B70: Costos de espera: % del personal directo activo antes del arranque | C70: % | D70: 0.5 | E70: Meses pre-operativos | F70: — | G70: Supuesto provisional (ilustrativo)
A71: G59 | B71: Costos de espera: % de energía y mantenimiento de planta | C71: % | D71: 0.25 | E71: Meses pre-operativos | F71: — | G71: Supuesto provisional (ilustrativo)
A72: G60 | B72: Costos de espera: % de alquiler, expensas y costos fijos administrativos | C72: % | D72: 1 | E72: Meses pre-operativos | F72: — | G72: Supuesto provisional (ilustrativo)
A73: G61 | B73: Mes de revisión para la evaluación incremental (continuar vs. salir; -1 = desde el inicio) | C73: mes modelo | D73: =p_MesCorte -> -1 | E73: — | F73: Prompt 8.8 | G73: Cálculo (editable) | H73: Por defecto = último mes cerrado. Los costos anteriores son hundidos y no se cargan.
A74: G62 | B74: Alternativa de salida: valor neto recuperable en el mes de revisión | C74: USD | E74: Mes de revisión | F74: — | G74: Pendiente de estimar | H74: Venta de activos + recuperación de CT - pasivos a cancelar - costos de salida.
A75: G63 | B75: Aportes hipotéticos de socios para cubrir la brecha de caja (1 = activar) — NO APROBADOS | C75: 1/0 | D75: 0 | E75: Horizonte | F75: Prompt 7.8 | G75: Supuesto provisional | H75: Apagado: la brecha queda visible y el VAN/TIR de socios supone cobertura implícita sin costo. Encendido: mide el esfuerzo de los socios.
A77: B2. Préstamo original (condiciones contractuales; modificar solo si el contrato lo establece)
A78: L01 | B78: Préstamo 1: monto | C78: USD | D78: =Base_PDF!$E$15 -> 2791587 | E78: Contrato | F78: PDF p. 4 | G78: Publicado (PDF) - confirmar contrato
A79: L02 | B79: Préstamo 1: mes de desembolso | C79: mes modelo | D79: 0 | E79: Contrato | F79: PDF: año 0 | G79: Supuesto provisional
A80: L03 | B80: Préstamo 1: tasa nominal anual (mensual = tasa/12) | C80: % | D80: =Base_PDF!$E$12 -> 0.09 | E80: Contrato | F80: PDF p. 4 | G80: Publicado (PDF) | H80: Tasa nominal bancaria con capitalización mensual: tasa mensual = nominal/12 (no aplica a tasas efectivas anuales).
A81: L04 | B81: Préstamo 1: meses de gracia (solo intereses) | C81: meses | D81: =Base_PDF!$E$17 -> 6 | E81: Contrato | F81: PDF p. 4 | G81: Publicado (PDF)
A82: L05 | B82: Préstamo 1: cuotas francesas | C82: meses | D82: =Base_PDF!$E$18 -> 54 | E82: Contrato | F82: PDF p. 4 | G82: Publicado (PDF)
A83: L06 | B83: Préstamo 1: comisión inicial (% del monto) | C83: % | D83: 0 | E83: Contrato | F83: No informada | G83: Pendiente de confirmar
A85: C. Correcciones metodológicas (1 = aplicada; 0 = criterio del PDF). Base depurada = todas en 1
A86: Cód. | B86: Corrección | C86: Valor | E86: Efecto esperado | G86: Fuente | H86: Detalle
A87: C1 | B87: Tipo de cambio único para la nómina (Gs/USD del escenario en lugar de 8.000 implícito) | C87: 1 | E87: Mayor costo USD de nómina (≈ USD 59.730/año a 7.300). | G87: Informe validación 1
A88: C2 | B88: Materia prima de cajas con incremento acumulativo de 1% anual (texto del PDF) | C88: 1 | E88: Mayor costo desde año 3 (≈ USD 74.413 en año 10). | G88: Informe validación 4
A89: C3 | B89: Depreciación desde la puesta en servicio (año 1) y no desde el año 2 | C89: 1 | E89: Resultado contable; en FCFF solo vía valor terminal si la realización del activo se aproxima con su valor contable (G24). | G89: Informe validación 9
A90: C4 | B90: CAPEX adicional del año 2 incorporado al activo depreciable (vida provisional) | C90: 1 | E90: Resultado contable; menor valor contable final (afecta el valor terminal vía G24). | G90: Informe validación 9
A91: C5 | B91: Inventario de materiales valuado a costo de adquisición (incluye flete y despacho) | C91: 1 | E91: Más capital de trabajo inmovilizado en stock. | G91: Prompt 2.5 / 7.4
A92: C6 | B92: Supervisión e indirectos de fábrica clasificados como costo de producción | C92: 1 | E92: Cambia costo de ventas/adm. y valuación de PT; EBITDA casi igual. | G92: Prompt 6.5
B93: Cantidad de correcciones activas (6 = base depurada completa) | C93: =SUM(C87:C92) -> 6
B94: Correcciones inherentes al motor (no desactivables): CxC por calendario de ventas; CT mensual; FCFF y flujo de socios separados; payback sobre la misma serie; márgenes rotulados; valor terminal explícito; dividendos pagados con caja disponible.
A96: D. Drivers por escenario (columna J = valor efectivo que usa el motor, incluye la prueba de sensibilidad)
A97: Cód. | B97: Driver | C97: Unidad | D97: Base depurada (supuestos Oct-2025) | E97: Actualizado | F97: Conservador | G97: Recuperación operativa | H97: Personalizado | I97: Activo | J97: Efectivo | K97: Vigencia | L97: Fuente / estado | M97: Nota
B98: Estado del escenario | D98: Supuestos históricos Oct-2025 con correcciones metodológicas. NO es ejecución real. | E98: =IF(p_MesCorte<0,"PENDIENTE: sin datos reales cargados; hereda supuestos históricos. No presentar como actualizado.","Reales hasta mes "&p_MesCorte&"; forecast con supuestos heredados salvo los modificados. Verificar campos mínimos.") -> PENDIENTE: sin datos reales cargados; hereda supuestos históricos. No presentar como actualizado. | F98: ILUSTRATIVO: choques de prueba, no premisas aprobadas. | G98: ILUSTRATIVO: atraso con recuperación parcial y mejoras de CT, no premisas aprobadas. | H98: Combinación definida por el usuario (hereda la base hasta que se modifique).
A99: E01 | B99: Atraso de arranque respecto del plan | C99: meses | D99: 0 | E99: =$D99 -> 0 | F99: 3 | G99: 6 | H99: =$D99 -> 0 | I99: =INDEX($D99:$H99,1,p_EscIdx) -> 0 | J99: =$I99+s_Atraso -> 0 | K99: Arranque | L99: Ilustrativo en escenarios 3-4 | M99: Si se carga el mes real de arranque en Datos_Reales, prevalece el real.
A100: E02 | B100: Meses de rampa de aprendizaje | C100: meses | D100: 0 | E100: =$D100 -> 0 | F100: 3 | G100: 6 | H100: =$D100 -> 0 | I100: =INDEX($D100:$H100,1,p_EscIdx) -> 0 | J100: =$I100 -> 0 | K100: Desde arranque | L100: Ilustrativo
A101: E03 | B101: Eficiencia del primer mes de rampa (% del ritmo del plan) | C101: % | D101: 1 | E101: =$D101 -> 1 | F101: 0.6 | G101: 0.5 | H101: =$D101 -> 1 | I101: =INDEX($D101:$H101,1,p_EscIdx) -> 1 | J101: =$I101 -> 1 | K101: Rampa | L101: Ilustrativo
A102: E04 | B102: % del volumen no producido (atraso/rampa) recuperable luego | C102: % | D102: 0 | E102: =$D102 -> 0 | F102: 0 | G102: 0.5 | H102: =$D102 -> 0 | I102: =INDEX($D102:$H102,1,p_EscIdx) -> 0 | J102: =$I102 -> 0 | K102: Horizonte | L102: Ilustrativo | M102: 0% = pérdida definitiva; >0% = desplazamiento recuperable sujeto a holgura de capacidad.
A103: E05 | B103: Volumen gabinetes año operativo 1 (% del plan PDF) | C103: % | D103: 1 | E103: =$D103 -> 1 | F103: 0.9 | G103: 0.8 | H103: =$D103 -> 1 | I103: =INDEX($D103:$H103,1,p_EscIdx) -> 1 | J103: =$I103*(1+s_Vol) -> 1 | K103: Año op. 1 | L103: Plan PDF = 100%
A104: E06 | B104: Volumen gabinetes año operativo 2 (% del plan PDF) | C104: % | D104: 1 | E104: =$D104 -> 1 | F104: 0.9 | G104: 0.9 | H104: =$D104 -> 1 | I104: =INDEX($D104:$H104,1,p_EscIdx) -> 1 | J104: =$I104*(1+s_Vol) -> 1 | K104: Año op. 2 | L104: Plan PDF = 100%
A105: E07 | B105: Volumen gabinetes año operativo 3 (% del plan PDF) | C105: % | D105: 1 | E105: =$D105 -> 1 | F105: 0.9 | G105: 1 | H105: =$D105 -> 1 | I105: =INDEX($D105:$H105,1,p_EscIdx) -> 1 | J105: =$I105*(1+s_Vol) -> 1 | K105: Año op. 3 | L105: Plan PDF = 100%
...

Sheet Calendario
A1: Calendario — meses del modelo, años, banderas de operación/horizonte/reales, TC y factores de descuento
A2: Motor único: fórmulas homogéneas por mes. Columna E = total del horizonte o saldo al cierre del horizonte. No editar fórmulas; los supuestos se cambian en Supuestos / Datos_Reales.
B4: Calendario del modelo (meses relativos; fechas solo si se cargó la fecha del mes 0)
A5: m | B5: Mes del modelo (0 = inicio de implantación / desembolso) | C5: n° | F5: 0 | G5: 1 | H5: 2 | I5: 3 | J5: 4 | K5: 5 | L5: 6 | M5: 7 | N5: 8 | O5: 9 | P5: 10 | Q5: 11 | R5: 12 | S5: 13 | T5: 14 | U5: 15 | V5: 16 | W5: 17 | X5: 18 | Y5: 19 | Z5: 20 | AA5: 21 | AB5: 22 | AC5: 23 | AD5: 24 | AE5: 25 | AF5: 26 | AG5: 27 | AH5: 28 | AI5: 29 | AJ5: 30 | AK5: 31 | AL5: 32 | AM5: 33 | AN5: 34 | AO5: 35 | AP5: 36 | AQ5: 37 | AR5: 38 | AS5: 39 | AT5: 40 | AU5: 41 | AV5: 42 | AW5: 43 | AX5: 44 | AY5: 45 | AZ5: 46 | BA5: 47 | BB5: 48 | BC5: 49 | BD5: 50 | BE5: 51 | BF5: 52 | BG5: 53 | BH5: 54 | BI5: 55 | BJ5: 56 | BK5: 57 | BL5: 58 | BM5: 59 | BN5: 60 | BO5: 61 | BP5: 62 | BQ5: 63 | BR5: 64 | BS5: 65 | BT5: 66 | BU5: 67 | BV5: 68 | BW5: 69 | BX5: 70 | BY5: 71 | BZ5: 72 | CA5: 73 | CB5: 74 | CC5: 75 | CD5: 76 | CE5: 77 | CF5: 78 | CG5: 79 | CH5: 80 | CI5: 81 | CJ5: 82 | CK5: 83 | CL5: 84 | CM5: 85 | CN5: 86 | CO5: 87 | CP5: 88 | CQ5: 89 | CR5: 90 | CS5: 91 | CT5: 92 | CU5: 93 | CV5: 94 | CW5: 95 | CX5: 96 | CY5: 97 | CZ5: 98 | DA5: 99 | DB5: 100 | DC5: 101 | DD5: 102 | DE5: 103 | DF5: 104 | DG5: 105 | DH5: 106 | DI5: 107 | DJ5: 108 | DK5: 109 | DL5: 110 | DM5: 111 | DN5: 112 | DO5: 113 | DP5: 114 | DQ5: 115 | DR5: 116 | DS5: 117 | DT5: 118 | DU5: 119 | DV5: 120 | DW5: 121 | DX5: 122 | DY5: 123 | DZ5: 124 | EA5: 125 | EB5: 126 | EC5: 127 | ED5: 128 | EE5: 129 | EF5: 130 | EG5: 131 | EH5: 132 | EI5: 133 | EJ5: 134 | EK5: 135 | EL5: 136 | EM5: 137 | EN5: 138 | EO5: 139 | EP5: 140 | EQ5: 141 | ER5: 142 | ES5: 143 | ET5: 144 | EU5: 145 | EV5: 146 | EW5: 147 | EX5: 148 | EY5: 149 | EZ5: 150 | FA5: 151 | FB5: 152 | FC5: 153 | FD5: 154 | FE5: 155 | FF5: 156
A6: fecha | B6: Fecha de fin de mes | C6: fecha | F6: =IF(p_FechaInicio="","s/f",EOMONTH(p_FechaInicio,0)) -> s/f | G6: =IF(p_FechaInicio="","s/f",EOMONTH(p_FechaInicio,1)) -> s/f | H6: =IF(p_FechaInicio="","s/f",EOMONTH(p_FechaInicio,2)) -> s/f | I6: =IF(p_FechaInicio="","s/f",EOMONTH(p_FechaInicio,3)) -> s/f | J6: =IF(p_FechaInicio="","s/f",EOMONTH(p_FechaInicio,4)) -> s/f | K6: =IF(p_FechaInicio="","s/f",EOMONTH(p_FechaInicio,5)) -> s/f | L6: =IF(p_FechaInicio="","s/f",EOMONTH(p_FechaInicio,6)) -> s/f | M6: =IF(p_FechaInicio="","s/f",EOMONTH(p_FechaInicio,7)) -> s/f | N6: =IF(p_FechaInicio="","s/f",EOMONTH(p_FechaInicio,8)) -> s/f | O6: =IF(p_FechaInicio="","s/f",EOMONTH(p_FechaInicio,9)) -> s/f | P6: =IF(p_FechaInicio="","s/f",EOMONTH(p_FechaInicio,10)) -> s/f | Q6: =IF(p_FechaInicio="","s/f",EOMONTH(p_FechaInicio,11)) -> s/f | R6: =IF(p_FechaInicio="","s/f",EOMONTH(p_FechaInicio,12)) -> s/f | S6: =IF(p_FechaInicio="","s/f",EOMONTH(p_FechaInicio,13)) -> s/f | T6: =IF(p_FechaInicio="","s/f",EOMONTH(p_FechaInicio,14)) -> s/f | U6: =IF(p_FechaInicio="","s/f",EOMONTH(p_FechaInicio,15)) -> s/f | V6: =IF(p_FechaInicio="","s/f",EOMONTH(p_FechaInicio,16)) -> s/f | W6: =IF(p_FechaInicio="","s/f",EOMONTH(p_FechaInicio,17)) -> s/f | X6: =IF(p_FechaInicio="","s/f",EOMONTH(p_FechaInicio,18)) -> s/f | Y6: =IF(p_FechaInicio="","s/f",EOMONTH(p_FechaInicio,19)) -> s/f | Z6: =IF(p_FechaInicio="","s/f",EOMONTH(p_FechaInicio,20)) -> s/f | AA6: =IF(p_FechaInicio="","s/f",EOMONTH(p_FechaInicio,21)) -> s/f | AB6: =IF(p_FechaInicio="","s/f",EOMONTH(p_FechaInicio,22)) -> s/f | AC6: =IF(p_FechaInicio="","s/f",EOMONTH(p_FechaInicio,23)) -> s/f | AD6: =IF(p_FechaInicio="","s/f",EOMONTH(p_FechaInicio,24)) -> s/f | AE6: =IF(p_FechaInicio="","s/f",EOMONTH(p_FechaInicio,25)) -> s/f | AF6: =IF(p_FechaInicio="","s/f",EOMONTH(p_FechaInicio,26)) -> s/f | AG6: =IF(p_FechaInicio="","s/f",EOMONTH(p_FechaInicio,27)) -> s/f | AH6: =IF(p_FechaInicio="","s/f",EOMONTH(p_FechaInicio,28)) -> s/f | AI6: =IF(p_FechaInicio="","s/f",EOMONTH(p_FechaInicio,29)) -> s/f | AJ6: =IF(p_FechaInicio="","s/f",EOMONTH(p_FechaInicio,30)) -> s/f | AK6: =IF(p_FechaInicio="","s/f",EOMONTH(p_FechaInicio,31)) -> s/f | AL6: =IF(p_FechaInicio="","s/f",EOMONTH(p_FechaInicio,32)) -> s/f | AM6: =IF(p_FechaInicio="","s/f",EOMONTH(p_FechaInicio,33)) -> s/f | AN6: =IF(p_FechaInicio="","s/f",EOMONTH(p_FechaInicio,34)) -> s/f | AO6: =IF(p_FechaInicio="","s/f",EOMONTH(p_FechaInicio,35)) -> s/f | AP6: =IF(p_FechaInicio="","s/f",EOMONTH(p_FechaInicio,36)) -> s/f | AQ6: =IF(p_FechaInicio="","s/f",EOMONTH(p_FechaInicio,37)) -> s/f | AR6: =IF(p_FechaInicio="","s/f",EOMONTH(p_FechaInicio,38)) -> s/f | AS6: =IF(p_FechaInicio="","s/f",EOMONTH(p_FechaInicio,39)) -> s/f | AT6: =IF(p_FechaInicio="","s/f",EOMONTH(p_FechaInicio,40)) -> s/f | AU6: =IF(p_FechaInicio="","s/f",EOMONTH(p_FechaInicio,41)) -> s/f | AV6: =IF(p_FechaInicio="","s/f",EOMONTH(p_FechaInicio,42)) -> s/f | AW6: =IF(p_FechaInicio="","s/f",EOMONTH(p_FechaInicio,43)) -> s/f | AX6: =IF(p_FechaInicio="","s/f",EOMONTH(p_FechaInicio,44)) -> s/f | AY6: =IF(p_FechaInicio="","s/f",EOMONTH(p_FechaInicio,45)) -> s/f | AZ6: =IF(p_FechaInicio="","s/f",EOMONTH(p_FechaInicio,46)) -> s/f | BA6: =IF(p_FechaInicio="","s/f",EOMONTH(p_FechaInicio,47)) -> s/f | BB6: =IF(p_FechaInicio="","s/f",EOMONTH(p_FechaInicio,48)) -> s/f | BC6: =IF(p_FechaInicio="","s/f",EOMONTH(p_FechaInicio,49)) -> s/f | BD6: =IF(p_FechaInicio="","s/f",EOMONTH(p_FechaInicio,50)) -> s/f | BE6: =IF(p_FechaInicio="","s/f",EOMONTH(p_FechaInicio,51)) -> s/f | BF6: =IF(p_FechaInicio="","s/f",EOMONTH(p_FechaInicio,52)) -> s/f | BG6: =IF(p_FechaInicio="","s/f",EOMONTH(p_FechaInicio,53)) -> s/f | BH6: =IF(p_FechaInicio="","s/f",EOMONTH(p_FechaInicio,54)) -> s/f | BI6: =IF(p_FechaInicio="","s/f",EOMONTH(p_FechaInicio,55)) -> s/f | BJ6: =IF(p_FechaInicio="","s/f",EOMONTH(p_FechaInicio,56)) -> s/f | BK6: =IF(p_FechaInicio="","s/f",EOMONTH(p_FechaInicio,57)) -> s/f | BL6: =IF(p_FechaInicio="","s/f",EOMONTH(p_FechaInicio,58)) -> s/f | BM6: =IF(p_FechaInicio="","s/f",EOMONTH(p_FechaInicio,59)) -> s/f | BN6: =IF(p_FechaInicio="","s/f",EOMONTH(p_FechaInicio,60)) -> s/f | BO6: =IF(p_FechaInicio="","s/f",EOMONTH(p_FechaInicio,61)) -> s/f | BP6: =IF(p_FechaInicio="","s/f",EOMONTH(p_FechaInicio,62)) -> s/f | BQ6: =IF(p_FechaInicio="","s/f",EOMONTH(p_FechaInicio,63)) -> s/f | BR6: =IF(p_FechaInicio="","s/f",EOMONTH(p_FechaInicio,64)) -> s/f | BS6: =IF(p_FechaInicio="","s/f",EOMONTH(p_FechaInicio,65)) -> s/f | BT6: =IF(p_FechaInicio="","s/f",EOMONTH(p_FechaInicio,66)) -> s/f | BU6: =IF(p_FechaInicio="","s/f",EOMONTH(p_FechaInicio,67)) -> s/f | BV6: =IF(p_FechaInicio="","s/f",EOMONTH(p_FechaInicio,68)) -> s/f | BW6: =IF(p_FechaInicio="","s/f",EOMONTH(p_FechaInicio,69)) -> s/f | BX6: =IF(p_FechaInicio="","s/f",EOMONTH(p_FechaInicio,70)) -> s/f | BY6: =IF(p_FechaInicio="","s/f",EOMONTH(p_FechaInicio,71)) -> s/f | BZ6: =IF(p_FechaInicio="","s/f",EOMONTH(p_FechaInicio,72)) -> s/f | CA6: =IF(p_FechaInicio="","s/f",EOMONTH(p_FechaInicio,73)) -> s/f | CB6: =IF(p_FechaInicio="","s/f",EOMONTH(p_FechaInicio,74)) -> s/f | CC6: =IF(p_FechaInicio="","s/f",EOMONTH(p_FechaInicio,75)) -> s/f | CD6: =IF(p_FechaInicio="","s/f",EOMONTH(p_FechaInicio,76)) -> s/f | CE6: =IF(p_FechaInicio="","s/f",EOMONTH(p_FechaInicio,77)) -> s/f | CF6: =IF(p_FechaInicio="","s/f",EOMONTH(p_FechaInicio,78)) -> s/f | CG6: =IF(p_FechaInicio="","s/f",EOMONTH(p_FechaInicio,79)) -> s/f | CH6: =IF(p_FechaInicio="","s/f",EOMONTH(p_FechaInicio,80)) -> s/f | CI6: =IF(p_FechaInicio="","s/f",EOMONTH(p_FechaInicio,81)) -> s/f | CJ6: =IF(p_FechaInicio="","s/f",EOMONTH(p_FechaInicio,82)) -> s/f | CK6: =IF(p_FechaInicio="","s/f",EOMONTH(p_FechaInicio,83)) -> s/f | CL6: =IF(p_FechaInicio="","s/f",EOMONTH(p_FechaInicio,84)) -> s/f | CM6: =IF(p_FechaInicio="","s/f",EOMONTH(p_FechaInicio,85)) -> s/f | CN6: =IF(p_FechaInicio="","s/f",EOMONTH(p_FechaInicio,86)) -> s/f | CO6: =IF(p_FechaInicio="","s/f",EOMONTH(p_FechaInicio,87)) -> s/f | CP6: =IF(p_FechaInicio="","s/f",EOMONTH(p_FechaInicio,88)) -> s/f | CQ6: =IF(p_FechaInicio="","s/f",EOMONTH(p_FechaInicio,89)) -> s/f | CR6: =IF(p_FechaInicio="","s/f",EOMONTH(p_FechaInicio,90)) -> s/f | CS6: =IF(p_FechaInicio="","s/f",EOMONTH(p_FechaInicio,91)) -> s/f | CT6: =IF(p_FechaInicio="","s/f",EOMONTH(p_FechaInicio,92)) -> s/f | CU6: =IF(p_FechaInicio="","s/f",EOMONTH(p_FechaInicio,93)) -> s/f | CV6: =IF(p_FechaInicio="","s/f",EOMONTH(p_FechaInicio,94)) -> s/f | CW6: =IF(p_FechaInicio="","s/f",EOMONTH(p_FechaInicio,95)) -> s/f | CX6: =IF(p_FechaInicio="","s/f",EOMONTH(p_FechaInicio,96)) -> s/f | CY6: =IF(p_FechaInicio="","s/f",EOMONTH(p_FechaInicio,97)) -> s/f | CZ6: =IF(p_FechaInicio="","s/f",EOMONTH(p_FechaInicio,98)) -> s/f | DA6: =IF(p_FechaInicio="","s/f",EOMONTH(p_FechaInicio,99)) -> s/f | DB6: =IF(p_FechaInicio="","s/f",EOMONTH(p_FechaInicio,100)) -> s/f | DC6: =IF(p_FechaInicio="","s/f",EOMONTH(p_FechaInicio,101)) -> s/f | DD6: =IF(p_FechaInicio="","s/f",EOMONTH(p_FechaInicio,102)) -> s/f | DE6: =IF(p_FechaInicio="","s/f",EOMONTH(p_FechaInicio,103)) -> s/f | DF6: =IF(p_FechaInicio="","s/f",EOMONTH(p_FechaInicio,104)) -> s/f | DG6: =IF(p_FechaInicio="","s/f",EOMONTH(p_FechaInicio,105)) -> s/f | DH6: =IF(p_FechaInicio="","s/f",EOMONTH(p_FechaInicio,106)) -> s/f | DI6: =IF(p_FechaInicio="","s/f",EOMONTH(p_FechaInicio,107)) -> s/f | DJ6: =IF(p_FechaInicio="","s/f",EOMONTH(p_FechaInicio,108)) -> s/f | DK6: =IF(p_FechaInicio="","s/f",EOMONTH(p_FechaInicio,109)) -> s/f | DL6: =IF(p_FechaInicio="","s/f",EOMONTH(p_FechaInicio,110)) -> s/f | DM6: =IF(p_FechaInicio="","s/f",EOMONTH(p_FechaInicio,111)) -> s/f | DN6: =IF(p_FechaInicio="","s/f",EOMONTH(p_FechaInicio,112)) -> s/f | DO6: =IF(p_FechaInicio="","s/f",EOMONTH(p_FechaInicio,113)) -> s/f | DP6: =IF(p_FechaInicio="","s/f",EOMONTH(p_FechaInicio,114)) -> s/f | DQ6: =IF(p_FechaInicio="","s/f",EOMONTH(p_FechaInicio,115)) -> s/f | DR6: =IF(p_FechaInicio="","s/f",EOMONTH(p_FechaInicio,116)) -> s/f | DS6: =IF(p_FechaInicio="","s/f",EOMONTH(p_FechaInicio,117)) -> s/f | DT6: =IF(p_FechaInicio="","s/f",EOMONTH(p_FechaInicio,118)) -> s/f | DU6: =IF(p_FechaInicio="","s/f",EOMONTH(p_FechaInicio,119)) -> s/f | DV6: =IF(p_FechaInicio="","s/f",EOMONTH(p_FechaInicio,120)) -> s/f | DW6: =IF(p_FechaInicio="","s/f",EOMONTH(p_FechaInicio,121)) -> s/f | DX6: =IF(p_FechaInicio="","s/f",EOMONTH(p_FechaInicio,122)) -> s/f | DY6: =IF(p_FechaInicio="","s/f",EOMONTH(p_FechaInicio,123)) -> s/f | DZ6: =IF(p_FechaInicio="","s/f",EOMONTH(p_FechaInicio,124)) -> s/f | EA6: =IF(p_FechaInicio="","s/f",EOMONTH(p_FechaInicio,125)) -> s/f | EB6: =IF(p_FechaInicio="","s/f",EOMONTH(p_FechaInicio,126)) -> s/f | EC6: =IF(p_FechaInicio="","s/f",EOMONTH(p_FechaInicio,127)) -> s/f | ED6: =IF(p_FechaInicio="","s/f",EOMONTH(p_FechaInicio,128)) -> s/f | EE6: =IF(p_FechaInicio="","s/f",EOMONTH(p_FechaInicio,129)) -> s/f | EF6: =IF(p_FechaInicio="","s/f",EOMONTH(p_FechaInicio,130)) -> s/f | EG6: =IF(p_FechaInicio="","s/f",EOMONTH(p_FechaInicio,131)) -> s/f | EH6: =IF(p_FechaInicio="","s/f",EOMONTH(p_FechaInicio,132)) -> s/f | EI6: =IF(p_FechaInicio="","s/f",EOMONTH(p_FechaInicio,133)) -> s/f | EJ6: =IF(p_FechaInicio="","s/f",EOMONTH(p_FechaInicio,134)) -> s/f | EK6: =IF(p_FechaInicio="","s/f",EOMONTH(p_FechaInicio,135)) -> s/f | EL6: =IF(p_FechaInicio="","s/f",EOMONTH(p_FechaInicio,136)) -> s/f | EM6: =IF(p_FechaInicio="","s/f",EOMONTH(p_FechaInicio,137)) -> s/f | EN6: =IF(p_FechaInicio="","s/f",EOMONTH(p_FechaInicio,138)) -> s/f | EO6: =IF(p_FechaInicio="","s/f",EOMONTH(p_FechaInicio,139)) -> s/f | EP6: =IF(p_FechaInicio="","s/f",EOMONTH(p_FechaInicio,140)) -> s/f | EQ6: =IF(p_FechaInicio="","s/f",EOMONTH(p_FechaInicio,141)) -> s/f | ER6: =IF(p_FechaInicio="","s/f",EOMONTH(p_FechaInicio,142)) -> s/f | ES6: =IF(p_FechaInicio="","s/f",EOMONTH(p_FechaInicio,143)) -> s/f | ET6: =IF(p_FechaInicio="","s/f",EOMONTH(p_FechaInicio,144)) -> s/f | EU6: =IF(p_FechaInicio="","s/f",EOMONTH(p_FechaInicio,145)) -> s/f | EV6: =IF(p_FechaInicio="","s/f",EOMONTH(p_FechaInicio,146)) -> s/f | EW6: =IF(p_FechaInicio="","s/f",EOMONTH(p_FechaInicio,147)) -> s/f | EX6: =IF(p_FechaInicio="","s/f",EOMONTH(p_FechaInicio,148)) -> s/f | EY6: =IF(p_FechaInicio="","s/f",EOMONTH(p_FechaInicio,149)) -> s/f | EZ6: =IF(p_FechaInicio="","s/f",EOMONTH(p_FechaInicio,150)) -> s/f | FA6: =IF(p_FechaInicio="","s/f",EOMONTH(p_FechaInicio,151)) -> s/f | FB6: =IF(p_FechaInicio="","s/f",EOMONTH(p_FechaInicio,152)) -> s/f | FC6: =IF(p_FechaInicio="","s/f",EOMONTH(p_FechaInicio,153)) -> s/f | FD6: =IF(p_FechaInicio="","s/f",EOMONTH(p_FechaInicio,154)) -> s/f | FE6: =IF(p_FechaInicio="","s/f",EOMONTH(p_FechaInicio,155)) -> s/f | FF6: =IF(p_FechaInicio="","s/f",EOMONTH(p_FechaInicio,156)) -> s/f
A7: anio | B7: Año de proyecto (0 = implantación) | C7: n° | F7: =IF(0<=p_ImplMeses,0,ROUNDUP((0-p_ImplMeses)/12,0)) -> 0 | G7: =IF(1<=p_ImplMeses,0,ROUNDUP((1-p_ImplMeses)/12,0)) -> 1 | H7: =IF(2<=p_ImplMeses,0,ROUNDUP((2-p_ImplMeses)/12,0)) -> 1 | I7: =IF(3<=p_ImplMeses,0,ROUNDUP((3-p_ImplMeses)/12,0)) -> 1 | J7: =IF(4<=p_ImplMeses,0,ROUNDUP((4-p_ImplMeses)/12,0)) -> 1 | K7: =IF(5<=p_ImplMeses,0,ROUNDUP((5-p_ImplMeses)/12,0)) -> 1 | L7: =IF(6<=p_ImplMeses,0,ROUNDUP((6-p_ImplMeses)/12,0)) -> 1 | M7: =IF(7<=p_ImplMeses,0,ROUNDUP((7-p_ImplMeses)/12,0)) -> 1 | N7: =IF(8<=p_ImplMeses,0,ROUNDUP((8-p_ImplMeses)/12,0)) -> 1 | O7: =IF(9<=p_ImplMeses,0,ROUNDUP((9-p_ImplMeses)/12,0)) -> 1 | P7: =IF(10<=p_ImplMeses,0,ROUNDUP((10-p_ImplMeses)/12,0)) -> 1 | Q7: =IF(11<=p_ImplMeses,0,ROUNDUP((11-p_ImplMeses)/12,0)) -> 1 | R7: =IF(12<=p_ImplMeses,0,ROUNDUP((12-p_ImplMeses)/12,0)) -> 1 | S7: =IF(13<=p_ImplMeses,0,ROUNDUP((13-p_ImplMeses)/12,0)) -> 2 | T7: =IF(14<=p_ImplMeses,0,ROUNDUP((14-p_ImplMeses)/12,0)) -> 2 | U7: =IF(15<=p_ImplMeses,0,ROUNDUP((15-p_ImplMeses)/12,0)) -> 2 | V7: =IF(16<=p_ImplMeses,0,ROUNDUP((16-p_ImplMeses)/12,0)) -> 2 | W7: =IF(17<=p_ImplMeses,0,ROUNDUP((17-p_ImplMeses)/12,0)) -> 2 | X7: =IF(18<=p_ImplMeses,0,ROUNDUP((18-p_ImplMeses)/12,0)) -> 2 | Y7: =IF(19<=p_ImplMeses,0,ROUNDUP((19-p_ImplMeses)/12,0)) -> 2 | Z7: =IF(20<=p_ImplMeses,0,ROUNDUP((20-p_ImplMeses)/12,0)) -> 2 | AA7: =IF(21<=p_ImplMeses,0,ROUNDUP((21-p_ImplMeses)/12,0)) -> 2 | AB7: =IF(22<=p_ImplMeses,0,ROUNDUP((22-p_ImplMeses)/12,0)) -> 2 | AC7: =IF(23<=p_ImplMeses,0,ROUNDUP((23-p_ImplMeses)/12,0)) -> 2 | AD7: =IF(24<=p_ImplMeses,0,ROUNDUP((24-p_ImplMeses)/12,0)) -> 2 | AE7: =IF(25<=p_ImplMeses,0,ROUNDUP((25-p_ImplMeses)/12,0)) -> 3 | AF7: =IF(26<=p_ImplMeses,0,ROUNDUP((26-p_ImplMeses)/12,0)) -> 3 | AG7: =IF(27<=p_ImplMeses,0,ROUNDUP((27-p_ImplMeses)/12,0)) -> 3 | AH7: =IF(28<=p_ImplMeses,0,ROUNDUP((28-p_ImplMeses)/12,0)) -> 3 | AI7: =IF(29<=p_ImplMeses,0,ROUNDUP((29-p_ImplMeses)/12,0)) -> 3 | AJ7: =IF(30<=p_ImplMeses,0,ROUNDUP((30-p_ImplMeses)/12,0)) -> 3 | AK7: =IF(31<=p_ImplMeses,0,ROUNDUP((31-p_ImplMeses)/12,0)) -> 3 | AL7: =IF(32<=p_ImplMeses,0,ROUNDUP((32-p_ImplMeses)/12,0)) -> 3 | AM7: =IF(33<=p_ImplMeses,0,ROUNDUP((33-p_ImplMeses)/12,0)) -> 3 | AN7: =IF(34<=p_ImplMeses,0,ROUNDUP((34-p_ImplMeses)/12,0)) -> 3 | AO7: =IF(35<=p_ImplMeses,0,ROUNDUP((35-p_ImplMeses)/12,0)) -> 3 | AP7: =IF(36<=p_ImplMeses,0,ROUNDUP((36-p_ImplMeses)/12,0)) -> 3 | AQ7: =IF(37<=p_ImplMeses,0,ROUNDUP((37-p_ImplMeses)/12,0)) -> 4 | AR7: =IF(38<=p_ImplMeses,0,ROUNDUP((38-p_ImplMeses)/12,0)) -> 4 | AS7: =IF(39<=p_ImplMeses,0,ROUNDUP((39-p_ImplMeses)/12,0)) -> 4 | AT7: =IF(40<=p_ImplMeses,0,ROUNDUP((40-p_ImplMeses)/12,0)) -> 4 | AU7: =IF(41<=p_ImplMeses,0,ROUNDUP((41-p_ImplMeses)/12,0)) -> 4 | AV7: =IF(42<=p_ImplMeses,0,ROUNDUP((42-p_ImplMeses)/12,0)) -> 4 | AW7: =IF(43<=p_ImplMeses,0,ROUNDUP((43-p_ImplMeses)/12,0)) -> 4 | AX7: =IF(44<=p_ImplMeses,0,ROUNDUP((44-p_ImplMeses)/12,0)) -> 4 | AY7: =IF(45<=p_ImplMeses,0,ROUNDUP((45-p_ImplMeses)/12,0)) -> 4 | AZ7: =IF(46<=p_ImplMeses,0,ROUNDUP((46-p_ImplMeses)/12,0)) -> 4 | BA7: =IF(47<=p_ImplMeses,0,ROUNDUP((47-p_ImplMeses)/12,0)) -> 4 | BB7: =IF(48<=p_ImplMeses,0,ROUNDUP((48-p_ImplMeses)/12,0)) -> 4 | BC7: =IF(49<=p_ImplMeses,0,ROUNDUP((49-p_ImplMeses)/12,0)) -> 5 | BD7: =IF(50<=p_ImplMeses,0,ROUNDUP((50-p_ImplMeses)/12,0)) -> 5 | BE7: =IF(51<=p_ImplMeses,0,ROUNDUP((51-p_ImplMeses)/12,0)) -> 5 | BF7: =IF(52<=p_ImplMeses,0,ROUNDUP((52-p_ImplMeses)/12,0)) -> 5 | BG7: =IF(53<=p_ImplMeses,0,ROUNDUP((53-p_ImplMeses)/12,0)) -> 5 | BH7: =IF(54<=p_ImplMeses,0,ROUNDUP((54-p_ImplMeses)/12,0)) -> 5 | BI7: =IF(55<=p_ImplMeses,0,ROUNDUP((55-p_ImplMeses)/12,0)) -> 5 | BJ7: =IF(56<=p_ImplMeses,0,ROUNDUP((56-p_ImplMeses)/12,0)) -> 5 | BK7: =IF(57<=p_ImplMeses,0,ROUNDUP((57-p_ImplMeses)/12,0)) -> 5 | BL7: =IF(58<=p_ImplMeses,0,ROUNDUP((58-p_ImplMeses)/12,0)) -> 5 | BM7: =IF(59<=p_ImplMeses,0,ROUNDUP((59-p_ImplMeses)/12,0)) -> 5 | BN7: =IF(60<=p_ImplMeses,0,ROUNDUP((60-p_ImplMeses)/12,0)) -> 5 | BO7: =IF(61<=p_ImplMeses,0,ROUNDUP((61-p_ImplMeses)/12,0)) -> 6 | BP7: =IF(62<=p_ImplMeses,0,ROUNDUP((62-p_ImplMeses)/12,0)) -> 6 | BQ7: =IF(63<=p_ImplMeses,0,ROUNDUP((63-p_ImplMeses)/12,0)) -> 6 | BR7: =IF(64<=p_ImplMeses,0,ROUNDUP((64-p_ImplMeses)/12,0)) -> 6 | BS7: =IF(65<=p_ImplMeses,0,ROUNDUP((65-p_ImplMeses)/12,0)) -> 6 | BT7: =IF(66<=p_ImplMeses,0,ROUNDUP((66-p_ImplMeses)/12,0)) -> 6 | BU7: =IF(67<=p_ImplMeses,0,ROUNDUP((67-p_ImplMeses)/12,0)) -> 6 | BV7: =IF(68<=p_ImplMeses,0,ROUNDUP((68-p_ImplMeses)/12,0)) -> 6 | BW7: =IF(69<=p_ImplMeses,0,ROUNDUP((69-p_ImplMeses)/12,0)) -> 6 | BX7: =IF(70<=p_ImplMeses,0,ROUNDUP((70-p_ImplMeses)/12,0)) -> 6 | BY7: =IF(71<=p_ImplMeses,0,ROUNDUP((71-p_ImplMeses)/12,0)) -> 6 | BZ7: =IF(72<=p_ImplMeses,0,ROUNDUP((72-p_ImplMeses)/12,0)) -> 6 | CA7: =IF(73<=p_ImplMeses,0,ROUNDUP((73-p_ImplMeses)/12,0)) -> 7 | CB7: =IF(74<=p_ImplMeses,0,ROUNDUP((74-p_ImplMeses)/12,0)) -> 7 | CC7: =IF(75<=p_ImplMeses,0,ROUNDUP((75-p_ImplMeses)/12,0)) -> 7 | CD7: =IF(76<=p_ImplMeses,0,ROUNDUP((76-p_ImplMeses)/12,0)) -> 7 | CE7: =IF(77<=p_ImplMeses,0,ROUNDUP((77-p_ImplMeses)/12,0)) -> 7 | CF7: =IF(78<=p_ImplMeses,0,ROUNDUP((78-p_ImplMeses)/12,0)) -> 7 | CG7: =IF(79<=p_ImplMeses,0,ROUNDUP((79-p_ImplMeses)/12,0)) -> 7 | CH7: =IF(80<=p_ImplMeses,0,ROUNDUP((80-p_ImplMeses)/12,0)) -> 7 | CI7: =IF(81<=p_ImplMeses,0,ROUNDUP((81-p_ImplMeses)/12,0)) -> 7 | CJ7: =IF(82<=p_ImplMeses,0,ROUNDUP((82-p_ImplMeses)/12,0)) -> 7 | CK7: =IF(83<=p_ImplMeses,0,ROUNDUP((83-p_ImplMeses)/12,0)) -> 7 | CL7: =IF(84<=p_ImplMeses,0,ROUNDUP((84-p_ImplMeses)/12,0)) -> 7 | CM7: =IF(85<=p_ImplMeses,0,ROUNDUP((85-p_ImplMeses)/12,0)) -> 8 | CN7: =IF(86<=p_ImplMeses,0,ROUNDUP((86-p_ImplMeses)/12,0)) -> 8 | CO7: =IF(87<=p_ImplMeses,0,ROUNDUP((87-p_ImplMeses)/12,0)) -> 8 | CP7: =IF(88<=p_ImplMeses,0,ROUNDUP((88-p_ImplMeses)/12,0)) -> 8 | CQ7: =IF(89<=p_ImplMeses,0,ROUNDUP((89-p_ImplMeses)/12,0)) -> 8 | CR7: =IF(90<=p_ImplMeses,0,ROUNDUP((90-p_ImplMeses)/12,0)) -> 8 | CS7: =IF(91<=p_ImplMeses,0,ROUNDUP((91-p_ImplMeses)/12,0)) -> 8 | CT7: =IF(92<=p_ImplMeses,0,ROUNDUP((92-p_ImplMeses)/12,0)) -> 8 | CU7: =IF(93<=p_ImplMeses,0,ROUNDUP((93-p_ImplMeses)/12,0)) -> 8 | CV7: =IF(94<=p_ImplMeses,0,ROUNDUP((94-p_ImplMeses)/12,0)) -> 8 | CW7: =IF(95<=p_ImplMeses,0,ROUNDUP((95-p_ImplMeses)/12,0)) -> 8 | CX7: =IF(96<=p_ImplMeses,0,ROUNDUP((96-p_ImplMeses)/12,0)) -> 8 | CY7: =IF(97<=p_ImplMeses,0,ROUNDUP((97-p_ImplMeses)/12,0)) -> 9 | CZ7: =IF(98<=p_ImplMeses,0,ROUNDUP((98-p_ImplMeses)/12,0)) -> 9 | DA7: =IF(99<=p_ImplMeses,0,ROUNDUP((99-p_ImplMeses)/12,0)) -> 9 | DB7: =IF(100<=p_ImplMeses,0,ROUNDUP((100-p_ImplMeses)/12,0)) -> 9 | DC7: =IF(101<=p_ImplMeses,0,ROUNDUP((101-p_ImplMeses)/12,0)) -> 9 | DD7: =IF(102<=p_ImplMeses,0,ROUNDUP((102-p_ImplMeses)/12,0)) -> 9 | DE7: =IF(103<=p_ImplMeses,0,ROUNDUP((103-p_ImplMeses)/12,0)) -> 9 | DF7: =IF(104<=p_ImplMeses,0,ROUNDUP((104-p_ImplMeses)/12,0)) -> 9 | DG7: =IF(105<=p_ImplMeses,0,ROUNDUP((105-p_ImplMeses)/12,0)) -> 9 | DH7: =IF(106<=p_ImplMeses,0,ROUNDUP((106-p_ImplMeses)/12,0)) -> 9 | DI7: =IF(107<=p_ImplMeses,0,ROUNDUP((107-p_ImplMeses)/12,0)) -> 9 | DJ7: =IF(108<=p_ImplMeses,0,ROUNDUP((108-p_ImplMeses)/12,0)) -> 9 | DK7: =IF(109<=p_ImplMeses,0,ROUNDUP((109-p_ImplMeses)/12,0)) -> 10 | DL7: =IF(110<=p_ImplMeses,0,ROUNDUP((110-p_ImplMeses)/12,0)) -> 10 | DM7: =IF(111<=p_ImplMeses,0,ROUNDUP((111-p_ImplMeses)/12,0)) -> 10 | DN7: =IF(112<=p_ImplMeses,0,ROUNDUP((112-p_ImplMeses)/12,0)) -> 10 | DO7: =IF(113<=p_ImplMeses,0,ROUNDUP((113-p_ImplMeses)/12,0)) -> 10 | DP7: =IF(114<=p_ImplMeses,0,ROUNDUP((114-p_ImplMeses)/12,0)) -> 10 | DQ7: =IF(115<=p_ImplMeses,0,ROUNDUP((115-p_ImplMeses)/12,0)) -> 10 | DR7: =IF(116<=p_ImplMeses,0,ROUNDUP((116-p_ImplMeses)/12,0)) -> 10 | DS7: =IF(117<=p_ImplMeses,0,ROUNDUP((117-p_ImplMeses)/12,0)) -> 10 | DT7: =IF(118<=p_ImplMeses,0,ROUNDUP((118-p_ImplMeses)/12,0)) -> 10 | DU7: =IF(119<=p_ImplMeses,0,ROUNDUP((119-p_ImplMeses)/12,0)) -> 10 | DV7: =IF(120<=p_ImplMeses,0,ROUNDUP((120-p_ImplMeses)/12,0)) -> 10 | DW7: =IF(121<=p_ImplMeses,0,ROUNDUP((121-p_ImplMeses)/12,0)) -> 11 | DX7: =IF(122<=p_ImplMeses,0,ROUNDUP((122-p_ImplMeses)/12,0)) -> 11 | DY7: =IF(123<=p_ImplMeses,0,ROUNDUP((123-p_ImplMeses)/12,0)) -> 11 | DZ7: =IF(124<=p_ImplMeses,0,ROUNDUP((124-p_ImplMeses)/12,0)) -> 11 | EA7: =IF(125<=p_ImplMeses,0,ROUNDUP((125-p_ImplMeses)/12,0)) -> 11 | EB7: =IF(126<=p_ImplMeses,0,ROUNDUP((126-p_ImplMeses)/12,0)) -> 11 | EC7: =IF(127<=p_ImplMeses,0,ROUNDUP((127-p_ImplMeses)/12,0)) -> 11 | ED7: =IF(128<=p_ImplMeses,0,ROUNDUP((128-p_ImplMeses)/12,0)) -> 11 | EE7: =IF(129<=p_ImplMeses,0,ROUNDUP((129-p_ImplMeses)/12,0)) -> 11 | EF7: =IF(130<=p_ImplMeses,0,ROUNDUP((130-p_ImplMeses)/12,0)) -> 11 | EG7: =IF(131<=p_ImplMeses,0,ROUNDUP((131-p_ImplMeses)/12,0)) -> 11 | EH7: =IF(132<=p_ImplMeses,0,ROUNDUP((132-p_ImplMeses)/12,0)) -> 11 | EI7: =IF(133<=p_ImplMeses,0,ROUNDUP((133-p_ImplMeses)/12,0)) -> 12 | EJ7: =IF(134<=p_ImplMeses,0,ROUNDUP((134-p_ImplMeses)/12,0)) -> 12 | EK7: =IF(135<=p_ImplMeses,0,ROUNDUP((135-p_ImplMeses)/12,0)) -> 12 | EL7: =IF(136<=p_ImplMeses,0,ROUNDUP((136-p_ImplMeses)/12,0)) -> 12 | EM7: =IF(137<=p_ImplMeses,0,ROUNDUP((137-p_ImplMeses)/12,0)) -> 12 | EN7: =IF(138<=p_ImplMeses,0,ROUNDUP((138-p_ImplMeses)/12,0)) -> 12 | EO7: =IF(139<=p_ImplMeses,0,ROUNDUP((139-p_ImplMeses)/12,0)) -> 12 | EP7: =IF(140<=p_ImplMeses,0,ROUNDUP((140-p_ImplMeses)/12,0)) -> 12 | EQ7: =IF(141<=p_ImplMeses,0,ROUNDUP((141-p_ImplMeses)/12,0)) -> 12 | ER7: =IF(142<=p_ImplMeses,0,ROUNDUP((142-p_ImplMeses)/12,0)) -> 12 | ES7: =IF(143<=p_ImplMeses,0,ROUNDUP((143-p_ImplMeses)/12,0)) -> 12 | ET7: =IF(144<=p_ImplMeses,0,ROUNDUP((144-p_ImplMeses)/12,0)) -> 12 | EU7: =IF(145<=p_ImplMeses,0,ROUNDUP((145-p_ImplMeses)/12,0)) -> 13 | EV7: =IF(146<=p_ImplMeses,0,ROUNDUP((146-p_ImplMeses)/12,0)) -> 13 | EW7: =IF(147<=p_ImplMeses,0,ROUNDUP((147-p_ImplMeses)/12,0)) -> 13 | EX7: =IF(148<=p_ImplMeses,0,ROUNDUP((148-p_ImplMeses)/12,0)) -> 13 | EY7: =IF(149<=p_ImplMeses,0,ROUNDUP((149-p_ImplMeses)/12,0)) -> 13 | EZ7: =IF(150<=p_ImplMeses,0,ROUNDUP((150-p_ImplMeses)/12,0)) -> 13 | FA7: =IF(151<=p_ImplMeses,0,ROUNDUP((151-p_ImplMeses)/12,0)) -> 13 | FB7: =IF(152<=p_ImplMeses,0,ROUNDUP((152-p_ImplMeses)/12,0)) -> 13 | FC7: =IF(153<=p_ImplMeses,0,ROUNDUP((153-p_ImplMeses)/12,0)) -> 13 | FD7: =IF(154<=p_ImplMeses,0,ROUNDUP((154-p_ImplMeses)/12,0)) -> 13 | FE7: =IF(155<=p_ImplMeses,0,ROUNDUP((155-p_ImplMeses)/12,0)) -> 13 | FF7: =IF(156<=p_ImplMeses,0,ROUNDUP((156-p_ImplMeses)/12,0)) -> 13
A8: ini | B8: Inicio de año de proyecto (1/0) | C8: 1/0 | F8: =IF(AND(0>p_ImplMeses,MOD(0-p_ImplMeses-1,12)=0),1,0) -> 0 | G8: =IF(AND(1>p_ImplMeses,MOD(1-p_ImplMeses-1,12)=0),1,0) -> 1 | H8: =IF(AND(2>p_ImplMeses,MOD(2-p_ImplMeses-1,12)=0),1,0) -> 0 | I8: =IF(AND(3>p_ImplMeses,MOD(3-p_ImplMeses-1,12)=0),1,0) -> 0 | J8: =IF(AND(4>p_ImplMeses,MOD(4-p_ImplMeses-1,12)=0),1,0) -> 0 | K8: =IF(AND(5>p_ImplMeses,MOD(5-p_ImplMeses-1,12)=0),1,0) -> 0 | L8: =IF(AND(6>p_ImplMeses,MOD(6-p_ImplMeses-1,12)=0),1,0) -> 0 | M8: =IF(AND(7>p_ImplMeses,MOD(7-p_ImplMeses-1,12)=0),1,0) -> 0 | N8: =IF(AND(8>p_ImplMeses,MOD(8-p_ImplMeses-1,12)=0),1,0) -> 0 | O8: =IF(AND(9>p_ImplMeses,MOD(9-p_ImplMeses-1,12)=0),1,0) -> 0 | P8: =IF(AND(10>p_ImplMeses,MOD(10-p_ImplMeses-1,12)=0),1,0) -> 0 | Q8: =IF(AND(11>p_ImplMeses,MOD(11-p_ImplMeses-1,12)=0),1,0) -> 0 | R8: =IF(AND(12>p_ImplMeses,MOD(12-p_ImplMeses-1,12)=0),1,0) -> 0 | S8: =IF(AND(13>p_ImplMeses,MOD(13-p_ImplMeses-1,12)=0),1,0) -> 1 | T8: =IF(AND(14>p_ImplMeses,MOD(14-p_ImplMeses-1,12)=0),1,0) -> 0 | U8: =IF(AND(15>p_ImplMeses,MOD(15-p_ImplMeses-1,12)=0),1,0) -> 0 | V8: =IF(AND(16>p_ImplMeses,MOD(16-p_ImplMeses-1,12)=0),1,0) -> 0 | W8: =IF(AND(17>p_ImplMeses,MOD(17-p_ImplMeses-1,12)=0),1,0) -> 0 | X8: =IF(AND(18>p_ImplMeses,MOD(18-p_ImplMeses-1,12)=0),1,0) -> 0 | Y8: =IF(AND(19>p_ImplMeses,MOD(19-p_ImplMeses-1,12)=0),1,0) -> 0 | Z8: =IF(AND(20>p_ImplMeses,MOD(20-p_ImplMeses-1,12)=0),1,0) -> 0 | AA8: =IF(AND(21>p_ImplMeses,MOD(21-p_ImplMeses-1,12)=0),1,0) -> 0 | AB8: =IF(AND(22>p_ImplMeses,MOD(22-p_ImplMeses-1,12)=0),1,0) -> 0 | AC8: =IF(AND(23>p_ImplMeses,MOD(23-p_ImplMeses-1,12)=0),1,0) -> 0 | AD8: =IF(AND(24>p_ImplMeses,MOD(24-p_ImplMeses-1,12)=0),1,0) -> 0 | AE8: =IF(AND(25>p_ImplMeses,MOD(25-p_ImplMeses-1,12)=0),1,0) -> 1 | AF8: =IF(AND(26>p_ImplMeses,MOD(26-p_ImplMeses-1,12)=0),1,0) -> 0 | AG8: =IF(AND(27>p_ImplMeses,MOD(27-p_ImplMeses-1,12)=0),1,0) -> 0 | AH8: =IF(AND(28>p_ImplMeses,MOD(28-p_ImplMeses-1,12)=0),1,0) -> 0 | AI8: =IF(AND(29>p_ImplMeses,MOD(29-p_ImplMeses-1,12)=0),1,0) -> 0 | AJ8: =IF(AND(30>p_ImplMeses,MOD(30-p_ImplMeses-1,12)=0),1,0) -> 0 | AK8: =IF(AND(31>p_ImplMeses,MOD(31-p_ImplMeses-1,12)=0),1,0) -> 0 | AL8: =IF(AND(32>p_ImplMeses,MOD(32-p_ImplMeses-1,12)=0),1,0) -> 0 | AM8: =IF(AND(33>p_ImplMeses,MOD(33-p_ImplMeses-1,12)=0),1,0) -> 0 | AN8: =IF(AND(34>p_ImplMeses,MOD(34-p_ImplMeses-1,12)=0),1,0) -> 0 | AO8: =IF(AND(35>p_ImplMeses,MOD(35-p_ImplMeses-1,12)=0),1,0) -> 0 | AP8: =IF(AND(36>p_ImplMeses,MOD(36-p_ImplMeses-1,12)=0),1,0) -> 0 | AQ8: =IF(AND(37>p_ImplMeses,MOD(37-p_ImplMeses-1,12)=0),1,0) -> 1 | AR8: =IF(AND(38>p_ImplMeses,MOD(38-p_ImplMeses-1,12)=0),1,0) -> 0 | AS8: =IF(AND(39>p_ImplMeses,MOD(39-p_ImplMeses-1,12)=0),1,0) -> 0 | AT8: =IF(AND(40>p_ImplMeses,MOD(40-p_ImplMeses-1,12)=0),1,0) -> 0 | AU8: =IF(AND(41>p_ImplMeses,MOD(41-p_ImplMeses-1,12)=0),1,0) -> 0 | AV8: =IF(AND(42>p_ImplMeses,MOD(42-p_ImplMeses-1,12)=0),1,0) -> 0 | AW8: =IF(AND(43>p_ImplMeses,MOD(43-p_ImplMeses-1,12)=0),1,0) -> 0 | AX8: =IF(AND(44>p_ImplMeses,MOD(44-p_ImplMeses-1,12)=0),1,0) -> 0 | AY8: =IF(AND(45>p_ImplMeses,MOD(45-p_ImplMeses-1,12)=0),1,0) -> 0 | AZ8: =IF(AND(46>p_ImplMeses,MOD(46-p_ImplMeses-1,12)=0),1,0) -> 0 | BA8: =IF(AND(47>p_ImplMeses,MOD(47-p_ImplMeses-1,12)=0),1,0) -> 0 | BB8: =IF(AND(48>p_ImplMeses,MOD(48-p_ImplMeses-1,12)=0),1,0) -> 0 | BC8: =IF(AND(49>p_ImplMeses,MOD(49-p_ImplMeses-1,12)=0),1,0) -> 1 | BD8: =IF(AND(50>p_ImplMeses,MOD(50-p_ImplMeses-1,12)=0),1,0) -> 0 | BE8: =IF(AND(51>p_ImplMeses,MOD(51-p_ImplMeses-1,12)=0),1,0) -> 0 | BF8: =IF(AND(52>p_ImplMeses,MOD(52-p_ImplMeses-1,12)=0),1,0) -> 0 | BG8: =IF(AND(53>p_ImplMeses,MOD(53-p_ImplMeses-1,12)=0),1,0) -> 0 | BH8: =IF(AND(54>p_ImplMeses,MOD(54-p_ImplMeses-1,12)=0),1,0) -> 0 | BI8: =IF(AND(55>p_ImplMeses,MOD(55-p_ImplMeses-1,12)=0),1,0) -> 0 | BJ8: =IF(AND(56>p_ImplMeses,MOD(56-p_ImplMeses-1,12)=0),1,0) -> 0 | BK8: =IF(AND(57>p_ImplMeses,MOD(57-p_ImplMeses-1,12)=0),1,0) -> 0 | BL8: =IF(AND(58>p_ImplMeses,MOD(58-p_ImplMeses-1,12)=0),1,0) -> 0 | BM8: =IF(AND(59>p_ImplMeses,MOD(59-p_ImplMeses-1,12)=0),1,0) -> 0 | BN8: =IF(AND(60>p_ImplMeses,MOD(60-p_ImplMeses-1,12)=0),1,0) -> 0 | BO8: =IF(AND(61>p_ImplMeses,MOD(61-p_ImplMeses-1,12)=0),1,0) -> 1 | BP8: =IF(AND(62>p_ImplMeses,MOD(62-p_ImplMeses-1,12)=0),1,0) -> 0 | BQ8: =IF(AND(63>p_ImplMeses,MOD(63-p_ImplMeses-1,12)=0),1,0) -> 0 | BR8: =IF(AND(64>p_ImplMeses,MOD(64-p_ImplMeses-1,12)=0),1,0) -> 0 | BS8: =IF(AND(65>p_ImplMeses,MOD(65-p_ImplMeses-1,12)=0),1,0) -> 0 | BT8: =IF(AND(66>p_ImplMeses,MOD(66-p_ImplMeses-1,12)=0),1,0) -> 0 | BU8: =IF(AND(67>p_ImplMeses,MOD(67-p_ImplMeses-1,12)=0),1,0) -> 0 | BV8: =IF(AND(68>p_ImplMeses,MOD(68-p_ImplMeses-1,12)=0),1,0) -> 0 | BW8: =IF(AND(69>p_ImplMeses,MOD(69-p_ImplMeses-1,12)=0),1,0) -> 0 | BX8: =IF(AND(70>p_ImplMeses,MOD(70-p_ImplMeses-1,12)=0),1,0) -> 0 | BY8: =IF(AND(71>p_ImplMeses,MOD(71-p_ImplMeses-1,12)=0),1,0) -> 0 | BZ8: =IF(AND(72>p_ImplMeses,MOD(72-p_ImplMeses-1,12)=0),1,0) -> 0 | CA8: =IF(AND(73>p_ImplMeses,MOD(73-p_ImplMeses-1,12)=0),1,0) -> 1 | CB8: =IF(AND(74>p_ImplMeses,MOD(74-p_ImplMeses-1,12)=0),1,0) -> 0 | CC8: =IF(AND(75>p_ImplMeses,MOD(75-p_ImplMeses-1,12)=0),1,0) -> 0 | CD8: =IF(AND(76>p_ImplMeses,MOD(76-p_ImplMeses-1,12)=0),1,0) -> 0 | CE8: =IF(AND(77>p_ImplMeses,MOD(77-p_ImplMeses-1,12)=0),1,0) -> 0 | CF8: =IF(AND(78>p_ImplMeses,MOD(78-p_ImplMeses-1,12)=0),1,0) -> 0 | CG8: =IF(AND(79>p_ImplMeses,MOD(79-p_ImplMeses-1,12)=0),1,0) -> 0 | CH8: =IF(AND(80>p_ImplMeses,MOD(80-p_ImplMeses-1,12)=0),1,0) -> 0 | CI8: =IF(AND(81>p_ImplMeses,MOD(81-p_ImplMeses-1,12)=0),1,0) -> 0 | CJ8: =IF(AND(82>p_ImplMeses,MOD(82-p_ImplMeses-1,12)=0),1,0) -> 0 | CK8: =IF(AND(83>p_ImplMeses,MOD(83-p_ImplMeses-1,12)=0),1,0) -> 0 | CL8: =IF(AND(84>p_ImplMeses,MOD(84-p_ImplMeses-1,12)=0),1,0) -> 0 | CM8: =IF(AND(85>p_ImplMeses,MOD(85-p_ImplMeses-1,12)=0),1,0) -> 1 | CN8: =IF(AND(86>p_ImplMeses,MOD(86-p_ImplMeses-1,12)=0),1,0) -> 0 | CO8: =IF(AND(87>p_ImplMeses,MOD(87-p_ImplMeses-1,12)=0),1,0) -> 0 | CP8: =IF(AND(88>p_ImplMeses,MOD(88-p_ImplMeses-1,12)=0),1,0) -> 0 | CQ8: =IF(AND(89>p_ImplMeses,MOD(89-p_ImplMeses-1,12)=0),1,0) -> 0 | CR8: =IF(AND(90>p_ImplMeses,MOD(90-p_ImplMeses-1,12)=0),1,0) -> 0 | CS8: =IF(AND(91>p_ImplMeses,MOD(91-p_ImplMeses-1,12)=0),1,0) -> 0 | CT8: =IF(AND(92>p_ImplMeses,MOD(92-p_ImplMeses-1,12)=0),1,0) -> 0 | CU8: =IF(AND(93>p_ImplMeses,MOD(93-p_ImplMeses-1,12)=0),1,0) -> 0 | CV8: =IF(AND(94>p_ImplMeses,MOD(94-p_ImplMeses-1,12)=0),1,0) -> 0 | CW8: =IF(AND(95>p_ImplMeses,MOD(95-p_ImplMeses-1,12)=0),1,0) -> 0 | CX8: =IF(AND(96>p_ImplMeses,MOD(96-p_ImplMeses-1,12)=0),1,0) -> 0 | CY8: =IF(AND(97>p_ImplMeses,MOD(97-p_ImplMeses-1,12)=0),1,0) -> 1 | CZ8: =IF(AND(98>p_ImplMeses,MOD(98-p_ImplMeses-1,12)=0),1,0) -> 0 | DA8: =IF(AND(99>p_ImplMeses,MOD(99-p_ImplMeses-1,12)=0),1,0) -> 0 | DB8: =IF(AND(100>p_ImplMeses,MOD(100-p_ImplMeses-1,12)=0),1,0) -> 0 | DC8: =IF(AND(101>p_ImplMeses,MOD(101-p_ImplMeses-1,12)=0),1,0) -> 0 | DD8: =IF(AND(102>p_ImplMeses,MOD(102-p_ImplMeses-1,12)=0),1,0) -> 0 | DE8: =IF(AND(103>p_ImplMeses,MOD(103-p_ImplMeses-1,12)=0),1,0) -> 0 | DF8: =IF(AND(104>p_ImplMeses,MOD(104-p_ImplMeses-1,12)=0),1,0) -> 0 | DG8: =IF(AND(105>p_ImplMeses,MOD(105-p_ImplMeses-1,12)=0),1,0) -> 0 | DH8: =IF(AND(106>p_ImplMeses,MOD(106-p_ImplMeses-1,12)=0),1,0) -> 0 | DI8: =IF(AND(107>p_ImplMeses,MOD(107-p_ImplMeses-1,12)=0),1,0) -> 0 | DJ8: =IF(AND(108>p_ImplMeses,MOD(108-p_ImplMeses-1,12)=0),1,0) -> 0 | DK8: =IF(AND(109>p_ImplMeses,MOD(109-p_ImplMeses-1,12)=0),1,0) -> 1 | DL8: =IF(AND(110>p_ImplMeses,MOD(110-p_ImplMeses-1,12)=0),1,0) -> 0 | DM8: =IF(AND(111>p_ImplMeses,MOD(111-p_ImplMeses-1,12)=0),1,0) -> 0 | DN8: =IF(AND(112>p_ImplMeses,MOD(112-p_ImplMeses-1,12)=0),1,0) -> 0 | DO8: =IF(AND(113>p_ImplMeses,MOD(113-p_ImplMeses-1,12)=0),1,0) -> 0 | DP8: =IF(AND(114>p_ImplMeses,MOD(114-p_ImplMeses-1,12)=0),1,0) -> 0 | DQ8: =IF(AND(115>p_ImplMeses,MOD(115-p_ImplMeses-1,12)=0),1,0) -> 0 | DR8: =IF(AND(116>p_ImplMeses,MOD(116-p_ImplMeses-1,12)=0),1,0) -> 0 | DS8: =IF(AND(117>p_ImplMeses,MOD(117-p_ImplMeses-1,12)=0),1,0) -> 0 | DT8: =IF(AND(118>p_ImplMeses,MOD(118-p_ImplMeses-1,12)=0),1,0) -> 0 | DU8: =IF(AND(119>p_ImplMeses,MOD(119-p_ImplMeses-1,12)=0),1,0) -> 0 | DV8: =IF(AND(120>p_ImplMeses,MOD(120-p_ImplMeses-1,12)=0),1,0) -> 0 | DW8: =IF(AND(121>p_ImplMeses,MOD(121-p_ImplMeses-1,12)=0),1,0) -> 1 | DX8: =IF(AND(122>p_ImplMeses,MOD(122-p_ImplMeses-1,12)=0),1,0) -> 0 | DY8: =IF(AND(123>p_ImplMeses,MOD(123-p_ImplMeses-1,12)=0),1,0) -> 0 | DZ8: =IF(AND(124>p_ImplMeses,MOD(124-p_ImplMeses-1,12)=0),1,0) -> 0 | EA8: =IF(AND(125>p_ImplMeses,MOD(125-p_ImplMeses-1,12)=0),1,0) -> 0 | EB8: =IF(AND(126>p_ImplMeses,MOD(126-p_ImplMeses-1,12)=0),1,0) -> 0 | EC8: =IF(AND(127>p_ImplMeses,MOD(127-p_ImplMeses-1,12)=0),1,0) -> 0 | ED8: =IF(AND(128>p_ImplMeses,MOD(128-p_ImplMeses-1,12)=0),1,0) -> 0 | EE8: =IF(AND(129>p_ImplMeses,MOD(129-p_ImplMeses-1,12)=0),1,0) -> 0 | EF8: =IF(AND(130>p_ImplMeses,MOD(130-p_ImplMeses-1,12)=0),1,0) -> 0 | EG8: =IF(AND(131>p_ImplMeses,MOD(131-p_ImplMeses-1,12)=0),1,0) -> 0 | EH8: =IF(AND(132>p_ImplMeses,MOD(132-p_ImplMeses-1,12)=0),1,0) -> 0 | EI8: =IF(AND(133>p_ImplMeses,MOD(133-p_ImplMeses-1,12)=0),1,0) -> 1 | EJ8: =IF(AND(134>p_ImplMeses,MOD(134-p_ImplMeses-1,12)=0),1,0) -> 0 | EK8: =IF(AND(135>p_ImplMeses,MOD(135-p_ImplMeses-1,12)=0),1,0) -> 0 | EL8: =IF(AND(136>p_ImplMeses,MOD(136-p_ImplMeses-1,12)=0),1,0) -> 0 | EM8: =IF(AND(137>p_ImplMeses,MOD(137-p_ImplMeses-1,12)=0),1,0) -> 0 | EN8: =IF(AND(138>p_ImplMeses,MOD(138-p_ImplMeses-1,12)=0),1,0) -> 0 | EO8: =IF(AND(139>p_ImplMeses,MOD(139-p_ImplMeses-1,12)=0),1,0) -> 0 | EP8: =IF(AND(140>p_ImplMeses,MOD(140-p_ImplMeses-1,12)=0),1,0) -> 0 | EQ8: =IF(AND(141>p_ImplMeses,MOD(141-p_ImplMeses-1,12)=0),1,0) -> 0 | ER8: =IF(AND(142>p_ImplMeses,MOD(142-p_ImplMeses-1,12)=0),1,0) -> 0 | ES8: =IF(AND(143>p_ImplMeses,MOD(143-p_ImplMeses-1,12)=0),1,0) -> 0 | ET8: =IF(AND(144>p_ImplMeses,MOD(144-p_ImplMeses-1,12)=0),1,0) -> 0 | EU8: =IF(AND(145>p_ImplMeses,MOD(145-p_ImplMeses-1,12)=0),1,0) -> 1 | EV8: =IF(AND(146>p_ImplMeses,MOD(146-p_ImplMeses-1,12)=0),1,0) -> 0 | EW8: =IF(AND(147>p_ImplMeses,MOD(147-p_ImplMeses-1,12)=0),1,0) -> 0 | EX8: =IF(AND(148>p_ImplMeses,MOD(148-p_ImplMeses-1,12)=0),1,0) -> 0 | EY8: =IF(AND(149>p_ImplMeses,MOD(149-p_ImplMeses-1,12)=0),1,0) -> 0 | EZ8: =IF(AND(150>p_ImplMeses,MOD(150-p_ImplMeses-1,12)=0),1,0) -> 0 | FA8: =IF(AND(151>p_ImplMeses,MOD(151-p_ImplMeses-1,12)=0),1,0) -> 0 | FB8: =IF(AND(152>p_ImplMeses,MOD(152-p_ImplMeses-1,12)=0),1,0) -> 0 | FC8: =IF(AND(153>p_ImplMeses,MOD(153-p_ImplMeses-1,12)=0),1,0) -> 0 | FD8: =IF(AND(154>p_ImplMeses,MOD(154-p_ImplMeses-1,12)=0),1,0) -> 0 | FE8: =IF(AND(155>p_ImplMeses,MOD(155-p_ImplMeses-1,12)=0),1,0) -> 0 | FF8: =IF(AND(156>p_ImplMeses,MOD(156-p_ImplMeses-1,12)=0),1,0) -> 0
A9: cierre | B9: Cierre de año de proyecto (1/0) | C9: 1/0 | F9: =IF(AND(0>p_ImplMeses,MOD(0-p_ImplMeses,12)=0),1,0) -> 0 | G9: =IF(AND(1>p_ImplMeses,MOD(1-p_ImplMeses,12)=0),1,0) -> 0 | H9: =IF(AND(2>p_ImplMeses,MOD(2-p_ImplMeses,12)=0),1,0) -> 0 | I9: =IF(AND(3>p_ImplMeses,MOD(3-p_ImplMeses,12)=0),1,0) -> 0 | J9: =IF(AND(4>p_ImplMeses,MOD(4-p_ImplMeses,12)=0),1,0) -> 0 | K9: =IF(AND(5>p_ImplMeses,MOD(5-p_ImplMeses,12)=0),1,0) -> 0 | L9: =IF(AND(6>p_ImplMeses,MOD(6-p_ImplMeses,12)=0),1,0) -> 0 | M9: =IF(AND(7>p_ImplMeses,MOD(7-p_ImplMeses,12)=0),1,0) -> 0 | N9: =IF(AND(8>p_ImplMeses,MOD(8-p_ImplMeses,12)=0),1,0) -> 0 | O9: =IF(AND(9>p_ImplMeses,MOD(9-p_ImplMeses,12)=0),1,0) -> 0 | P9: =IF(AND(10>p_ImplMeses,MOD(10-p_ImplMeses,12)=0),1,0) -> 0 | Q9: =IF(AND(11>p_ImplMeses,MOD(11-p_ImplMeses,12)=0),1,0) -> 0 | R9: =IF(AND(12>p_ImplMeses,MOD(12-p_ImplMeses,12)=0),1,0) -> 1 | S9: =IF(AND(13>p_ImplMeses,MOD(13-p_ImplMeses,12)=0),1,0) -> 0 | T9: =IF(AND(14>p_ImplMeses,MOD(14-p_ImplMeses,12)=0),1,0) -> 0 | U9: =IF(AND(15>p_ImplMeses,MOD(15-p_ImplMeses,12)=0),1,0) -> 0 | V9: =IF(AND(16>p_ImplMeses,MOD(16-p_ImplMeses,12)=0),1,0) -> 0 | W9: =IF(AND(17>p_ImplMeses,MOD(17-p_ImplMeses,12)=0),1,0) -> 0 | X9: =IF(AND(18>p_ImplMeses,MOD(18-p_ImplMeses,12)=0),1,0) -> 0 | Y9: =IF(AND(19>p_ImplMeses,MOD(19-p_ImplMeses,12)=0),1,0) -> 0 | Z9: =IF(AND(20>p_ImplMeses,MOD(20-p_ImplMeses,12)=0),1,0) -> 0 | AA9: =IF(AND(21>p_ImplMeses,MOD(21-p_ImplMeses,12)=0),1,0) -> 0 | AB9: =IF(AND(22>p_ImplMeses,MOD(22-p_ImplMeses,12)=0),1,0) -> 0 | AC9: =IF(AND(23>p_ImplMeses,MOD(23-p_ImplMeses,12)=0),1,0) -> 0 | AD9: =IF(AND(24>p_ImplMeses,MOD(24-p_ImplMeses,12)=0),1,0) -> 1 | AE9: =IF(AND(25>p_ImplMeses,MOD(25-p_ImplMeses,12)=0),1,0) -> 0 | AF9: =IF(AND(26>p_ImplMeses,MOD(26-p_ImplMeses,12)=0),1,0) -> 0 | AG9: =IF(AND(27>p_ImplMeses,MOD(27-p_ImplMeses,12)=0),1,0) -> 0 | AH9: =IF(AND(28>p_ImplMeses,MOD(28-p_ImplMeses,12)=0),1,0) -> 0 | AI9: =IF(AND(29>p_ImplMeses,MOD(29-p_ImplMeses,12)=0),1,0) -> 0 | AJ9: =IF(AND(30>p_ImplMeses,MOD(30-p_ImplMeses,12)=0),1,0) -> 0 | AK9: =IF(AND(31>p_ImplMeses,MOD(31-p_ImplMeses,12)=0),1,0) -> 0 | AL9: =IF(AND(32>p_ImplMeses,MOD(32-p_ImplMeses,12)=0),1,0) -> 0 | AM9: =IF(AND(33>p_ImplMeses,MOD(33-p_ImplMeses,12)=0),1,0) -> 0 | AN9: =IF(AND(34>p_ImplMeses,MOD(34-p_ImplMeses,12)=0),1,0) -> 0 | AO9: =IF(AND(35>p_ImplMeses,MOD(35-p_ImplMeses,12)=0),1,0) -> 0 | AP9: =IF(AND(36>p_ImplMeses,MOD(36-p_ImplMeses,12)=0),1,0) -> 1 | AQ9: =IF(AND(37>p_ImplMeses,MOD(37-p_ImplMeses,12)=0),1,0) -> 0 | AR9: =IF(AND(38>p_ImplMeses,MOD(38-p_ImplMeses,12)=0),1,0) -> 0 | AS9: =IF(AND(39>p_ImplMeses,MOD(39-p_ImplMeses,12)=0),1,0) -> 0 | AT9: =IF(AND(40>p_ImplMeses,MOD(40-p_ImplMeses,12)=0),1,0) -> 0 | AU9: =IF(AND(41>p_ImplMeses,MOD(41-p_ImplMeses,12)=0),1,0) -> 0 | AV9: =IF(AND(42>p_ImplMeses,MOD(42-p_ImplMeses,12)=0),1,0) -> 0 | AW9: =IF(AND(43>p_ImplMeses,MOD(43-p_ImplMeses,12)=0),1,0) -> 0 | AX9: =IF(AND(44>p_ImplMeses,MOD(44-p_ImplMeses,12)=0),1,0) -> 0 | AY9: =IF(AND(45>p_ImplMeses,MOD(45-p_ImplMeses,12)=0),1,0) -> 0 | AZ9: =IF(AND(46>p_ImplMeses,MOD(46-p_ImplMeses,12)=0),1,0) -> 0 | BA9: =IF(AND(47>p_ImplMeses,MOD(47-p_ImplMeses,12)=0),1,0) -> 0 | BB9: =IF(AND(48>p_ImplMeses,MOD(48-p_ImplMeses,12)=0),1,0) -> 1 | BC9: =IF(AND(49>p_ImplMeses,MOD(49-p_ImplMeses,12)=0),1,0) -> 0 | BD9: =IF(AND(50>p_ImplMeses,MOD(50-p_ImplMeses,12)=0),1,0) -> 0 | BE9: =IF(AND(51>p_ImplMeses,MOD(51-p_ImplMeses,12)=0),1,0) -> 0 | BF9: =IF(AND(52>p_ImplMeses,MOD(52-p_ImplMeses,12)=0),1,0) -> 0 | BG9: =IF(AND(53>p_ImplMeses,MOD(53-p_ImplMeses,12)=0),1,0) -> 0 | BH9: =IF(AND(54>p_ImplMeses,MOD(54-p_ImplMeses,12)=0),1,0) -> 0 | BI9: =IF(AND(55>p_ImplMeses,MOD(55-p_ImplMeses,12)=0),1,0) -> 0 | BJ9: =IF(AND(56>p_ImplMeses,MOD(56-p_ImplMeses,12)=0),1,0) -> 0 | BK9: =IF(AND(57>p_ImplMeses,MOD(57-p_ImplMeses,12)=0),1,0) -> 0 | BL9: =IF(AND(58>p_ImplMeses,MOD(58-p_ImplMeses,12)=0),1,0) -> 0 | BM9: =IF(AND(59>p_ImplMeses,MOD(59-p_ImplMeses,12)=0),1,0) -> 0 | BN9: =IF(AND(60>p_ImplMeses,MOD(60-p_ImplMeses,12)=0),1,0) -> 1 | BO9: =IF(AND(61>p_ImplMeses,MOD(61-p_ImplMeses,12)=0),1,0) -> 0 | BP9: =IF(AND(62>p_ImplMeses,MOD(62-p_ImplMeses,12)=0),1,0) -> 0 | BQ9: =IF(AND(63>p_ImplMeses,MOD(63-p_ImplMeses,12)=0),1,0) -> 0 | BR9: =IF(AND(64>p_ImplMeses,MOD(64-p_ImplMeses,12)=0),1,0) -> 0 | BS9: =IF(AND(65>p_ImplMeses,MOD(65-p_ImplMeses,12)=0),1,0) -> 0 | BT9: =IF(AND(66>p_ImplMeses,MOD(66-p_ImplMeses,12)=0),1,0) -> 0 | BU9: =IF(AND(67>p_ImplMeses,MOD(67-p_ImplMeses,12)=0),1,0) -> 0 | BV9: =IF(AND(68>p_ImplMeses,MOD(68-p_ImplMeses,12)=0),1,0) -> 0 | BW9: =IF(AND(69>p_ImplMeses,MOD(69-p_ImplMeses,12)=0),1,0) -> 0 | BX9: =IF(AND(70>p_ImplMeses,MOD(70-p_ImplMeses,12)=0),1,0) -> 0 | BY9: =IF(AND(71>p_ImplMeses,MOD(71-p_ImplMeses,12)=0),1,0) -> 0 | BZ9: =IF(AND(72>p_ImplMeses,MOD(72-p_ImplMeses,12)=0),1,0) -> 1 | CA9: =IF(AND(73>p_ImplMeses,MOD(73-p_ImplMeses,12)=0),1,0) -> 0 | CB9: =IF(AND(74>p_ImplMeses,MOD(74-p_ImplMeses,12)=0),1,0) -> 0 | CC9: =IF(AND(75>p_ImplMeses,MOD(75-p_ImplMeses,12)=0),1,0) -> 0 | CD9: =IF(AND(76>p_ImplMeses,MOD(76-p_ImplMeses,12)=0),1,0) -> 0 | CE9: =IF(AND(77>p_ImplMeses,MOD(77-p_ImplMeses,12)=0),1,0) -> 0 | CF9: =IF(AND(78>p_ImplMeses,MOD(78-p_ImplMeses,12)=0),1,0) -> 0 | CG9: =IF(AND(79>p_ImplMeses,MOD(79-p_ImplMeses,12)=0),1,0) -> 0 | CH9: =IF(AND(80>p_ImplMeses,MOD(80-p_ImplMeses,12)=0),1,0) -> 0 | CI9: =IF(AND(81>p_ImplMeses,MOD(81-p_ImplMeses,12)=0),1,0) -> 0 | CJ9: =IF(AND(82>p_ImplMeses,MOD(82-p_ImplMeses,12)=0),1,0) -> 0 | CK9: =IF(AND(83>p_ImplMeses,MOD(83-p_ImplMeses,12)=0),1,0) -> 0 | CL9: =IF(AND(84>p_ImplMeses,MOD(84-p_ImplMeses,12)=0),1,0) -> 1 | CM9: =IF(AND(85>p_ImplMeses,MOD(85-p_ImplMeses,12)=0),1,0) -> 0 | CN9: =IF(AND(86>p_ImplMeses,MOD(86-p_ImplMeses,12)=0),1,0) -> 0 | CO9: =IF(AND(87>p_ImplMeses,MOD(87-p_ImplMeses,12)=0),1,0) -> 0 | CP9: =IF(AND(88>p_ImplMeses,MOD(88-p_ImplMeses,12)=0),1,0) -> 0 | CQ9: =IF(AND(89>p_ImplMeses,MOD(89-p_ImplMeses,12)=0),1,0) -> 0 | CR9: =IF(AND(90>p_ImplMeses,MOD(90-p_ImplMeses,12)=0),1,0) -> 0 | CS9: =IF(AND(91>p_ImplMeses,MOD(91-p_ImplMeses,12)=0),1,0) -> 0 | CT9: =IF(AND(92>p_ImplMeses,MOD(92-p_ImplMeses,12)=0),1,0) -> 0 | CU9: =IF(AND(93>p_ImplMeses,MOD(93-p_ImplMeses,12)=0),1,0) -> 0 | CV9: =IF(AND(94>p_ImplMeses,MOD(94-p_ImplMeses,12)=0),1,0) -> 0 | CW9: =IF(AND(95>p_ImplMeses,MOD(95-p_ImplMeses,12)=0),1,0) -> 0 | CX9: =IF(AND(96>p_ImplMeses,MOD(96-p_ImplMeses,12)=0),1,0) -> 1 | CY9: =IF(AND(97>p_ImplMeses,MOD(97-p_ImplMeses,12)=0),1,0) -> 0 | CZ9: =IF(AND(98>p_ImplMeses,MOD(98-p_ImplMeses,12)=0),1,0) -> 0 | DA9: =IF(AND(99>p_ImplMeses,MOD(99-p_ImplMeses,12)=0),1,0) -> 0 | DB9: =IF(AND(100>p_ImplMeses,MOD(100-p_ImplMeses,12)=0),1,0) -> 0 | DC9: =IF(AND(101>p_ImplMeses,MOD(101-p_ImplMeses,12)=0),1,0) -> 0 | DD9: =IF(AND(102>p_ImplMeses,MOD(102-p_ImplMeses,12)=0),1,0) -> 0 | DE9: =IF(AND(103>p_ImplMeses,MOD(103-p_ImplMeses,12)=0),1,0) -> 0 | DF9: =IF(AND(104>p_ImplMeses,MOD(104-p_ImplMeses,12)=0),1,0) -> 0 | DG9: =IF(AND(105>p_ImplMeses,MOD(105-p_ImplMeses,12)=0),1,0) -> 0 | DH9: =IF(AND(106>p_ImplMeses,MOD(106-p_ImplMeses,12)=0),1,0) -> 0 | DI9: =IF(AND(107>p_ImplMeses,MOD(107-p_ImplMeses,12)=0),1,0) -> 0 | DJ9: =IF(AND(108>p_ImplMeses,MOD(108-p_ImplMeses,12)=0),1,0) -> 1 | DK9: =IF(AND(109>p_ImplMeses,MOD(109-p_ImplMeses,12)=0),1,0) -> 0 | DL9: =IF(AND(110>p_ImplMeses,MOD(110-p_ImplMeses,12)=0),1,0) -> 0 | DM9: =IF(AND(111>p_ImplMeses,MOD(111-p_ImplMeses,12)=0),1,0) -> 0 | DN9: =IF(AND(112>p_ImplMeses,MOD(112-p_ImplMeses,12)=0),1,0) -> 0 | DO9: =IF(AND(113>p_ImplMeses,MOD(113-p_ImplMeses,12)=0),1,0) -> 0 | DP9: =IF(AND(114>p_ImplMeses,MOD(114-p_ImplMeses,12)=0),1,0) -> 0 | DQ9: =IF(AND(115>p_ImplMeses,MOD(115-p_ImplMeses,12)=0),1,0) -> 0 | DR9: =IF(AND(116>p_ImplMeses,MOD(116-p_ImplMeses,12)=0),1,0) -> 0 | DS9: =IF(AND(117>p_ImplMeses,MOD(117-p_ImplMeses,12)=0),1,0) -> 0 | DT9: =IF(AND(118>p_ImplMeses,MOD(118-p_ImplMeses,12)=0),1,0) -> 0 | DU9: =IF(AND(119>p_ImplMeses,MOD(119-p_ImplMeses,12)=0),1,0) -> 0 | DV9: =IF(AND(120>p_ImplMeses,MOD(120-p_ImplMeses,12)=0),1,0) -> 1 | DW9: =IF(AND(121>p_ImplMeses,MOD(121-p_ImplMeses,12)=0),1,0) -> 0 | DX9: =IF(AND(122>p_ImplMeses,MOD(122-p_ImplMeses,12)=0),1,0) -> 0 | DY9: =IF(AND(123>p_ImplMeses,MOD(123-p_ImplMeses,12)=0),1,0) -> 0 | DZ9: =IF(AND(124>p_ImplMeses,MOD(124-p_ImplMeses,12)=0),1,0) -> 0 | EA9: =IF(AND(125>p_ImplMeses,MOD(125-p_ImplMeses,12)=0),1,0) -> 0 | EB9: =IF(AND(126>p_ImplMeses,MOD(126-p_ImplMeses,12)=0),1,0) -> 0 | EC9: =IF(AND(127>p_ImplMeses,MOD(127-p_ImplMeses,12)=0),1,0) -> 0 | ED9: =IF(AND(128>p_ImplMeses,MOD(128-p_ImplMeses,12)=0),1,0) -> 0 | EE9: =IF(AND(129>p_ImplMeses,MOD(129-p_ImplMeses,12)=0),1,0) -> 0 | EF9: =IF(AND(130>p_ImplMeses,MOD(130-p_ImplMeses,12)=0),1,0) -> 0 | EG9: =IF(AND(131>p_ImplMeses,MOD(131-p_ImplMeses,12)=0),1,0) -> 0 | EH9: =IF(AND(132>p_ImplMeses,MOD(132-p_ImplMeses,12)=0),1,0) -> 1 | EI9: =IF(AND(133>p_ImplMeses,MOD(133-p_ImplMeses,12)=0),1,0) -> 0 | EJ9: =IF(AND(134>p_ImplMeses,MOD(134-p_ImplMeses,12)=0),1,0) -> 0 | EK9: =IF(AND(135>p_ImplMeses,MOD(135-p_ImplMeses,12)=0),1,0) -> 0 | EL9: =IF(AND(136>p_ImplMeses,MOD(136-p_ImplMeses,12)=0),1,0) -> 0 | EM9: =IF(AND(137>p_ImplMeses,MOD(137-p_ImplMeses,12)=0),1,0) -> 0 | EN9: =IF(AND(138>p_ImplMeses,MOD(138-p_ImplMeses,12)=0),1,0) -> 0 | EO9: =IF(AND(139>p_ImplMeses,MOD(139-p_ImplMeses,12)=0),1,0) -> 0 | EP9: =IF(AND(140>p_ImplMeses,MOD(140-p_ImplMeses,12)=0),1,0) -> 0 | EQ9: =IF(AND(141>p_ImplMeses,MOD(141-p_ImplMeses,12)=0),1,0) -> 0 | ER9: =IF(AND(142>p_ImplMeses,MOD(142-p_ImplMeses,12)=0),1,0) -> 0 | ES9: =IF(AND(143>p_ImplMeses,MOD(143-p_ImplMeses,12)=0),1,0) -> 0 | ET9: =IF(AND(144>p_ImplMeses,MOD(144-p_ImplMeses,12)=0),1,0) -> 1 | EU9: =IF(AND(145>p_ImplMeses,MOD(145-p_ImplMeses,12)=0),1,0) -> 0 | EV9: =IF(AND(146>p_ImplMeses,MOD(146-p_ImplMeses,12)=0),1,0) -> 0 | EW9: =IF(AND(147>p_ImplMeses,MOD(147-p_ImplMeses,12)=0),1,0) -> 0 | EX9: =IF(AND(148>p_ImplMeses,MOD(148-p_ImplMeses,12)=0),1,0) -> 0 | EY9: =IF(AND(149>p_ImplMeses,MOD(149-p_ImplMeses,12)=0),1,0) -> 0 | EZ9: =IF(AND(150>p_ImplMeses,MOD(150-p_ImplMeses,12)=0),1,0) -> 0 | FA9: =IF(AND(151>p_ImplMeses,MOD(151-p_ImplMeses,12)=0),1,0) -> 0 | FB9: =IF(AND(152>p_ImplMeses,MOD(152-p_ImplMeses,12)=0),1,0) -> 0 | FC9: =IF(AND(153>p_ImplMeses,MOD(153-p_ImplMeses,12)=0),1,0) -> 0 | FD9: =IF(AND(154>p_ImplMeses,MOD(154-p_ImplMeses,12)=0),1,0) -> 0 | FE9: =IF(AND(155>p_ImplMeses,MOD(155-p_ImplMeses,12)=0),1,0) -> 0 | FF9: =IF(AND(156>p_ImplMeses,MOD(156-p_ImplMeses,12)=0),1,0) -> 1
A10: mes_op | B10: Mes operativo desde el arranque efectivo | C10: n° | F10: =IF(AND(0>=p_MesArranque,0<=p_MesFin),0-p_MesArranque+1,0) -> 0 | G10: =IF(AND(1>=p_MesArranque,1<=p_MesFin),1-p_MesArranque+1,0) -> 1 | H10: =IF(AND(2>=p_MesArranque,2<=p_MesFin),2-p_MesArranque+1,0) -> 2 | I10: =IF(AND(3>=p_MesArranque,3<=p_MesFin),3-p_MesArranque+1,0) -> 3 | J10: =IF(AND(4>=p_MesArranque,4<=p_MesFin),4-p_MesArranque+1,0) -> 4 | K10: =IF(AND(5>=p_MesArranque,5<=p_MesFin),5-p_MesArranque+1,0) -> 5 | L10: =IF(AND(6>=p_MesArranque,6<=p_MesFin),6-p_MesArranque+1,0) -> 6 | M10: =IF(AND(7>=p_MesArranque,7<=p_MesFin),7-p_MesArranque+1,0) -> 7 | N10: =IF(AND(8>=p_MesArranque,8<=p_MesFin),8-p_MesArranque+1,0) -> 8 | O10: =IF(AND(9>=p_MesArranque,9<=p_MesFin),9-p_MesArranque+1,0) -> 9 | P10: =IF(AND(10>=p_MesArranque,10<=p_MesFin),10-p_MesArranque+1,0) -> 10 | Q10: =IF(AND(11>=p_MesArranque,11<=p_MesFin),11-p_MesArranque+1,0) -> 11 | R10: =IF(AND(12>=p_MesArranque,12<=p_MesFin),12-p_MesArranque+1,0) -> 12 | S10: =IF(AND(13>=p_MesArranque,13<=p_MesFin),13-p_MesArranque+1,0) -> 13 | T10: =IF(AND(14>=p_MesArranque,14<=p_MesFin),14-p_MesArranque+1,0) -> 14 | U10: =IF(AND(15>=p_MesArranque,15<=p_MesFin),15-p_MesArranque+1,0) -> 15 | V10: =IF(AND(16>=p_MesArranque,16<=p_MesFin),16-p_MesArranque+1,0) -> 16 | W10: =IF(AND(17>=p_MesArranque,17<=p_MesFin),17-p_MesArranque+1,0) -> 17 | X10: =IF(AND(18>=p_MesArranque,18<=p_MesFin),18-p_MesArranque+1,0) -> 18 | Y10: =IF(AND(19>=p_MesArranque,19<=p_MesFin),19-p_MesArranque+1,0) -> 19 | Z10: =IF(AND(20>=p_MesArranque,20<=p_MesFin),20-p_MesArranque+1,0) -> 20 | AA10: =IF(AND(21>=p_MesArranque,21<=p_MesFin),21-p_MesArranque+1,0) -> 21 | AB10: =IF(AND(22>=p_MesArranque,22<=p_MesFin),22-p_MesArranque+1,0) -> 22 | AC10: =IF(AND(23>=p_MesArranque,23<=p_MesFin),23-p_MesArranque+1,0) -> 23 | AD10: =IF(AND(24>=p_MesArranque,24<=p_MesFin),24-p_MesArranque+1,0) -> 24 | AE10: =IF(AND(25>=p_MesArranque,25<=p_MesFin),25-p_MesArranque+1,0) -> 25 | AF10: =IF(AND(26>=p_MesArranque,26<=p_MesFin),26-p_MesArranque+1,0) -> 26 | AG10: =IF(AND(27>=p_MesArranque,27<=p_MesFin),27-p_MesArranque+1,0) -> 27 | AH10: =IF(AND(28>=p_MesArranque,28<=p_MesFin),28-p_MesArranque+1,0) -> 28 | AI10: =IF(AND(29>=p_MesArranque,29<=p_MesFin),29-p_MesArranque+1,0) -> 29 | AJ10: =IF(AND(30>=p_MesArranque,30<=p_MesFin),30-p_MesArranque+1,0) -> 30 | AK10: =IF(AND(31>=p_MesArranque,31<=p_MesFin),31-p_MesArranque+1,0) -> 31 | AL10: =IF(AND(32>=p_MesArranque,32<=p_MesFin),32-p_MesArranque+1,0) -> 32 | AM10: =IF(AND(33>=p_MesArranque,33<=p_MesFin),33-p_MesArranque+1,0) -> 33 | AN10: =IF(AND(34>=p_MesArranque,34<=p_MesFin),34-p_MesArranque+1,0) -> 34 | AO10: =IF(AND(35>=p_MesArranque,35<=p_MesFin),35-p_MesArranque+1,0) -> 35 | AP10: =IF(AND(36>=p_MesArranque,36<=p_MesFin),36-p_MesArranque+1,0) -> 36 | AQ10: =IF(AND(37>=p_MesArranque,37<=p_MesFin),37-p_MesArranque+1,0) -> 37 | AR10: =IF(AND(38>=p_MesArranque,38<=p_MesFin),38-p_MesArranque+1,0) -> 38 | AS10: =IF(AND(39>=p_MesArranque,39<=p_MesFin),39-p_MesArranque+1,0) -> 39 | AT10: =IF(AND(40>=p_MesArranque,40<=p_MesFin),40-p_MesArranque+1,0) -> 40 | AU10: =IF(AND(41>=p_MesArranque,41<=p_MesFin),41-p_MesArranque+1,0) -> 41 | AV10: =IF(AND(42>=p_MesArranque,42<=p_MesFin),42-p_MesArranque+1,0) -> 42 | AW10: =IF(AND(43>=p_MesArranque,43<=p_MesFin),43-p_MesArranque+1,0) -> 43 | AX10: =IF(AND(44>=p_MesArranque,44<=p_MesFin),44-p_MesArranque+1,0) -> 44 | AY10: =IF(AND(45>=p_MesArranque,45<=p_MesFin),45-p_MesArranque+1,0) -> 45 | AZ10: =IF(AND(46>=p_MesArranque,46<=p_MesFin),46-p_MesArranque+1,0) -> 46 | BA10: =IF(AND(47>=p_MesArranque,47<=p_MesFin),47-p_MesArranque+1,0) -> 47 | BB10: =IF(AND(48>=p_MesArranque,48<=p_MesFin),48-p_MesArranque+1,0) -> 48 | BC10: =IF(AND(49>=p_MesArranque,49<=p_MesFin),49-p_MesArranque+1,0) -> 49 | BD10: =IF(AND(50>=p_MesArranque,50<=p_MesFin),50-p_MesArranque+1,0) -> 50 | BE10: =IF(AND(51>=p_MesArranque,51<=p_MesFin),51-p_MesArranque+1,0) -> 51 | BF10: =IF(AND(52>=p_MesArranque,52<=p_MesFin),52-p_MesArranque+1,0) -> 52 | BG10: =IF(AND(53>=p_MesArranque,53<=p_MesFin),53-p_MesArranque+1,0) -> 53 | BH10: =IF(AND(54>=p_MesArranque,54<=p_MesFin),54-p_MesArranque+1,0) -> 54 | BI10: =IF(AND(55>=p_MesArranque,55<=p_MesFin),55-p_MesArranque+1,0) -> 55 | BJ10: =IF(AND(56>=p_MesArranque,56<=p_MesFin),56-p_MesArranque+1,0) -> 56 | BK10: =IF(AND(57>=p_MesArranque,57<=p_MesFin),57-p_MesArranque+1,0) -> 57 | BL10: =IF(AND(58>=p_MesArranque,58<=p_MesFin),58-p_MesArranque+1,0) -> 58 | BM10: =IF(AND(59>=p_MesArranque,59<=p_MesFin),59-p_MesArranque+1,0) -> 59 | BN10: =IF(AND(60>=p_MesArranque,60<=p_MesFin),60-p_MesArranque+1,0) -> 60 | BO10: =IF(AND(61>=p_MesArranque,61<=p_MesFin),61-p_MesArranque+1,0) -> 61 | BP10: =IF(AND(62>=p_MesArranque,62<=p_MesFin),62-p_MesArranque+1,0) -> 62 | BQ10: =IF(AND(63>=p_MesArranque,63<=p_MesFin),63-p_MesArranque+1,0) -> 63 | BR10: =IF(AND(64>=p_MesArranque,64<=p_MesFin),64-p_MesArranque+1,0) -> 64 | BS10: =IF(AND(65>=p_MesArranque,65<=p_MesFin),65-p_MesArranque+1,0) -> 65 | BT10: =IF(AND(66>=p_MesArranque,66<=p_MesFin),66-p_MesArranque+1,0) -> 66 | BU10: =IF(AND(67>=p_MesArranque,67<=p_MesFin),67-p_MesArranque+1,0) -> 67 | BV10: =IF(AND(68>=p_MesArranque,68<=p_MesFin),68-p_MesArranque+1,0) -> 68 | BW10: =IF(AND(69>=p_MesArranque,69<=p_MesFin),69-p_MesArranque+1,0) -> 69 | BX10: =IF(AND(70>=p_MesArranque,70<=p_MesFin),70-p_MesArranque+1,0) -> 70 | BY10: =IF(AND(71>=p_MesArranque,71<=p_MesFin),71-p_MesArranque+1,0) -> 71 | BZ10: =IF(AND(72>=p_MesArranque,72<=p_MesFin),72-p_MesArranque+1,0) -> 72 | CA10: =IF(AND(73>=p_MesArranque,73<=p_MesFin),73-p_MesArranque+1,0) -> 73 | CB10: =IF(AND(74>=p_MesArranque,74<=p_MesFin),74-p_MesArranque+1,0) -> 74 | CC10: =IF(AND(75>=p_MesArranque,75<=p_MesFin),75-p_MesArranque+1,0) -> 75 | CD10: =IF(AND(76>=p_MesArranque,76<=p_MesFin),76-p_MesArranque+1,0) -> 76 | CE10: =IF(AND(77>=p_MesArranque,77<=p_MesFin),77-p_MesArranque+1,0) -> 77 | CF10: =IF(AND(78>=p_MesArranque,78<=p_MesFin),78-p_MesArranque+1,0) -> 78 | CG10: =IF(AND(79>=p_MesArranque,79<=p_MesFin),79-p_MesArranque+1,0) -> 79 | CH10: =IF(AND(80>=p_MesArranque,80<=p_MesFin),80-p_MesArranque+1,0) -> 80 | CI10: =IF(AND(81>=p_MesArranque,81<=p_MesFin),81-p_MesArranque+1,0) -> 81 | CJ10: =IF(AND(82>=p_MesArranque,82<=p_MesFin),82-p_MesArranque+1,0) -> 82 | CK10: =IF(AND(83>=p_MesArranque,83<=p_MesFin),83-p_MesArranque+1,0) -> 83 | CL10: =IF(AND(84>=p_MesArranque,84<=p_MesFin),84-p_MesArranque+1,0) -> 84 | CM10: =IF(AND(85>=p_MesArranque,85<=p_MesFin),85-p_MesArranque+1,0) -> 85 | CN10: =IF(AND(86>=p_MesArranque,86<=p_MesFin),86-p_MesArranque+1,0) -> 86 | CO10: =IF(AND(87>=p_MesArranque,87<=p_MesFin),87-p_MesArranque+1,0) -> 87 | CP10: =IF(AND(88>=p_MesArranque,88<=p_MesFin),88-p_MesArranque+1,0) -> 88 | CQ10: =IF(AND(89>=p_MesArranque,89<=p_MesFin),89-p_MesArranque+1,0) -> 89 | CR10: =IF(AND(90>=p_MesArranque,90<=p_MesFin),90-p_MesArranque+1,0) -> 90 | CS10: =IF(AND(91>=p_MesArranque,91<=p_MesFin),91-p_MesArranque+1,0) -> 91 | CT10: =IF(AND(92>=p_MesArranque,92<=p_MesFin),92-p_MesArranque+1,0) -> 92 | CU10: =IF(AND(93>=p_MesArranque,93<=p_MesFin),93-p_MesArranque+1,0) -> 93 | CV10: =IF(AND(94>=p_MesArranque,94<=p_MesFin),94-p_MesArranque+1,0) -> 94 | CW10: =IF(AND(95>=p_MesArranque,95<=p_MesFin),95-p_MesArranque+1,0) -> 95 | CX10: =IF(AND(96>=p_MesArranque,96<=p_MesFin),96-p_MesArranque+1,0) -> 96 | CY10: =IF(AND(97>=p_MesArranque,97<=p_MesFin),97-p_MesArranque+1,0) -> 97 | CZ10: =IF(AND(98>=p_MesArranque,98<=p_MesFin),98-p_MesArranque+1,0) -> 98 | DA10: =IF(AND(99>=p_MesArranque,99<=p_MesFin),99-p_MesArranque+1,0) -> 99 | DB10: =IF(AND(100>=p_MesArranque,100<=p_MesFin),100-p_MesArranque+1,0) -> 100 | DC10: =IF(AND(101>=p_MesArranque,101<=p_MesFin),101-p_MesArranque+1,0) -> 101 | DD10: =IF(AND(102>=p_MesArranque,102<=p_MesFin),102-p_MesArranque+1,0) -> 102 | DE10: =IF(AND(103>=p_MesArranque,103<=p_MesFin),103-p_MesArranque+1,0) -> 103 | DF10: =IF(AND(104>=p_MesArranque,104<=p_MesFin),104-p_MesArranque+1,0) -> 104 | DG10: =IF(AND(105>=p_MesArranque,105<=p_MesFin),105-p_MesArranque+1,0) -> 105 | DH10: =IF(AND(106>=p_MesArranque,106<=p_MesFin),106-p_MesArranque+1,0) -> 106 | DI10: =IF(AND(107>=p_MesArranque,107<=p_MesFin),107-p_MesArranque+1,0) -> 107 | DJ10: =IF(AND(108>=p_MesArranque,108<=p_MesFin),108-p_MesArranque+1,0) -> 108 | DK10: =IF(AND(109>=p_MesArranque,109<=p_MesFin),109-p_MesArranque+1,0) -> 109 | DL10: =IF(AND(110>=p_MesArranque,110<=p_MesFin),110-p_MesArranque+1,0) -> 110 | DM10: =IF(AND(111>=p_MesArranque,111<=p_MesFin),111-p_MesArranque+1,0) -> 111 | DN10: =IF(AND(112>=p_MesArranque,112<=p_MesFin),112-p_MesArranque+1,0) -> 112 | DO10: =IF(AND(113>=p_MesArranque,113<=p_MesFin),113-p_MesArranque+1,0) -> 113 | DP10: =IF(AND(114>=p_MesArranque,114<=p_MesFin),114-p_MesArranque+1,0) -> 114 | DQ10: =IF(AND(115>=p_MesArranque,115<=p_MesFin),115-p_MesArranque+1,0) -> 115 | DR10: =IF(AND(116>=p_MesArranque,116<=p_MesFin),116-p_MesArranque+1,0) -> 116 | DS10: =IF(AND(117>=p_MesArranque,117<=p_MesFin),117-p_MesArranque+1,0) -> 117 | DT10: =IF(AND(118>=p_MesArranque,118<=p_MesFin),118-p_MesArranque+1,0) -> 118 | DU10: =IF(AND(119>=p_MesArranque,119<=p_MesFin),119-p_MesArranque+1,0) -> 119 | DV10: =IF(AND(120>=p_MesArranque,120<=p_MesFin),120-p_MesArranque+1,0) -> 120 | DW10: =IF(AND(121>=p_MesArranque,121<=p_MesFin),121-p_MesArranque+1,0) -> 0 | DX10: =IF(AND(122>=p_MesArranque,122<=p_MesFin),122-p_MesArranque+1,0) -> 0 | DY10: =IF(AND(123>=p_MesArranque,123<=p_MesFin),123-p_MesArranque+1,0) -> 0 | DZ10: =IF(AND(124>=p_MesArranque,124<=p_MesFin),124-p_MesArranque+1,0) -> 0 | EA10: =IF(AND(125>=p_MesArranque,125<=p_MesFin),125-p_MesArranque+1,0) -> 0 | EB10: =IF(AND(126>=p_MesArranque,126<=p_MesFin),126-p_MesArranque+1,0) -> 0 | EC10: =IF(AND(127>=p_MesArranque,127<=p_MesFin),127-p_MesArranque+1,0) -> 0 | ED10: =IF(AND(128>=p_MesArranque,128<=p_MesFin),128-p_MesArranque+1,0) -> 0 | EE10: =IF(AND(129>=p_MesArranque,129<=p_MesFin),129-p_MesArranque+1,0) -> 0 | EF10: =IF(AND(130>=p_MesArranque,130<=p_MesFin),130-p_MesArranque+1,0) -> 0 | EG10: =IF(AND(131>=p_MesArranque,131<=p_MesFin),131-p_MesArranque+1,0) -> 0 | EH10: =IF(AND(132>=p_MesArranque,132<=p_MesFin),132-p_MesArranque+1,0) -> 0 | EI10: =IF(AND(133>=p_MesArranque,133<=p_MesFin),133-p_MesArranque+1,0) -> 0 | EJ10: =IF(AND(134>=p_MesArranque,134<=p_MesFin),134-p_MesArranque+1,0) -> 0 | EK10: =IF(AND(135>=p_MesArranque,135<=p_MesFin),135-p_MesArranque+1,0) -> 0 | EL10: =IF(AND(136>=p_MesArranque,136<=p_MesFin),136-p_MesArranque+1,0) -> 0 | EM10: =IF(AND(137>=p_MesArranque,137<=p_MesFin),137-p_MesArranque+1,0) -> 0 | EN10: =IF(AND(138>=p_MesArranque,138<=p_MesFin),138-p_MesArranque+1,0) -> 0 | EO10: =IF(AND(139>=p_MesArranque,139<=p_MesFin),139-p_MesArranque+1,0) -> 0 | EP10: =IF(AND(140>=p_MesArranque,140<=p_MesFin),140-p_MesArranque+1,0) -> 0 | EQ10: =IF(AND(141>=p_MesArranque,141<=p_MesFin),141-p_MesArranque+1,0) -> 0 | ER10: =IF(AND(142>=p_MesArranque,142<=p_MesFin),142-p_MesArranque+1,0) -> 0 | ES10: =IF(AND(143>=p_MesArranque,143<=p_MesFin),143-p_MesArranque+1,0) -> 0 | ET10: =IF(AND(144>=p_MesArranque,144<=p_MesFin),144-p_MesArranque+1,0) -> 0 | EU10: =IF(AND(145>=p_MesArranque,145<=p_MesFin),145-p_MesArranque+1,0) -> 0 | EV10: =IF(AND(146>=p_MesArranque,146<=p_MesFin),146-p_MesArranque+1,0) -> 0 | EW10: =IF(AND(147>=p_MesArranque,147<=p_MesFin),147-p_MesArranque+1,0) -> 0 | EX10: =IF(AND(148>=p_MesArranque,148<=p_MesFin),148-p_MesArranque+1,0) -> 0 | EY10: =IF(AND(149>=p_MesArranque,149<=p_MesFin),149-p_MesArranque+1,0) -> 0 | EZ10: =IF(AND(150>=p_MesArranque,150<=p_MesFin),150-p_MesArranque+1,0) -> 0 | FA10: =IF(AND(151>=p_MesArranque,151<=p_MesFin),151-p_MesArranque+1,0) -> 0 | FB10: =IF(AND(152>=p_MesArranque,152<=p_MesFin),152-p_MesArranque+1,0) -> 0 | FC10: =IF(AND(153>=p_MesArranque,153<=p_MesFin),153-p_MesArranque+1,0) -> 0 | FD10: =IF(AND(154>=p_MesArranque,154<=p_MesFin),154-p_MesArranque+1,0) -> 0 | FE10: =IF(AND(155>=p_MesArranque,155<=p_MesFin),155-p_MesArranque+1,0) -> 0 | FF10: =IF(AND(156>=p_MesArranque,156<=p_MesFin),156-p_MesArranque+1,0) -> 0
A11: anio_op | B11: Año operativo (curva de volumen, capacidad y dotación) | C11: n° | F11: =IF(F$10>0,MIN(p_AniosOp,ROUNDUP(F$10/12,0)),0) -> 0 | G11: =IF(G$10>0,MIN(p_AniosOp,ROUNDUP(G$10/12,0)),0) -> 1 | H11: =IF(H$10>0,MIN(p_AniosOp,ROUNDUP(H$10/12,0)),0) -> 1 | I11: =IF(I$10>0,MIN(p_AniosOp,ROUNDUP(I$10/12,0)),0) -> 1 | J11: =IF(J$10>0,MIN(p_AniosOp,ROUNDUP(J$10/12,0)),0) -> 1 | K11: =IF(K$10>0,MIN(p_AniosOp,ROUNDUP(K$10/12,0)),0) -> 1 | L11: =IF(L$10>0,MIN(p_AniosOp,ROUNDUP(L$10/12,0)),0) -> 1 | M11: =IF(M$10>0,MIN(p_AniosOp,ROUNDUP(M$10/12,0)),0) -> 1 | ... FF11: =IF(FF$10>0,MIN(p_AniosOp,ROUNDUP(FF$10/12,0)),0) -> 0
A12: f_op | B12: Operación (1/0) | C12: 1/0 | E12: =SUM($F12:$FF12) -> 120 | F12: =IF(F$10>0,1,0) -> 0 | G12: =IF(G$10>0,1,0) -> 1 | H12: =IF(H$10>0,1,0) -> 1 | I12: =IF(I$10>0,1,0) -> 1 | J12: =IF(J$10>0,1,0) -> 1 | K12: =IF(K$10>0,1,0) -> 1 | L12: =IF(L$10>0,1,0) -> 1 | M12: =IF(M$10>0,1,0) -> 1 | ... FF12: =IF(FF$10>0,1,0) -> 0
A13: f_hor | B13: Dentro del horizonte evaluado (1/0) | C13: 1/0 | E13: =SUM($F13:$FF13) -> 121 | F13: =IF(0<=p_MesFin,1,0) -> 1 | G13: =IF(1<=p_MesFin,1,0) -> 1 | H13: =IF(2<=p_MesFin,1,0) -> 1 | I13: =IF(3<=p_MesFin,1,0) -> 1 | J13: =IF(4<=p_MesFin,1,0) -> 1 | K13: =IF(5<=p_MesFin,1,0) -> 1 | L13: =IF(6<=p_MesFin,1,0) -> 1 | M13: =IF(7<=p_MesFin,1,0) -> 1 | N13: =IF(8<=p_MesFin,1,0) -> 1 | O13: =IF(9<=p_MesFin,1,0) -> 1 | P13: =IF(10<=p_MesFin,1,0) -> 1 | Q13: =IF(11<=p_MesFin,1,0) -> 1 | R13: =IF(12<=p_MesFin,1,0) -> 1 | S13: =IF(13<=p_MesFin,1,0) -> 1 | T13: =IF(14<=p_MesFin,1,0) -> 1 | U13: =IF(15<=p_MesFin,1,0) -> 1 | V13: =IF(16<=p_MesFin,1,0) -> 1 | W13: =IF(17<=p_MesFin,1,0) -> 1 | X13: =IF(18<=p_MesFin,1,0) -> 1 | Y13: =IF(19<=p_MesFin,1,0) -> 1 | Z13: =IF(20<=p_MesFin,1,0) -> 1 | AA13: =IF(21<=p_MesFin,1,0) -> 1 | AB13: =IF(22<=p_MesFin,1,0) -> 1 | AC13: =IF(23<=p_MesFin,1,0) -> 1 | AD13: =IF(24<=p_MesFin,1,0) -> 1 | AE13: =IF(25<=p_MesFin,1,0) -> 1 | AF13: =IF(26<=p_MesFin,1,0) -> 1 | AG13: =IF(27<=p_MesFin,1,0) -> 1 | AH13: =IF(28<=p_MesFin,1,0) -> 1 | AI13: =IF(29<=p_MesFin,1,0) -> 1 | AJ13: =IF(30<=p_MesFin,1,0) -> 1 | AK13: =IF(31<=p_MesFin,1,0) -> 1 | AL13: =IF(32<=p_MesFin,1,0) -> 1 | AM13: =IF(33<=p_MesFin,1,0) -> 1 | AN13: =IF(34<=p_MesFin,1,0) -> 1 | AO13: =IF(35<=p_MesFin,1,0) -> 1 | AP13: =IF(36<=p_MesFin,1,0) -> 1 | AQ13: =IF(37<=p_MesFin,1,0) -> 1 | AR13: =IF(38<=p_MesFin,1,0) -> 1 | AS13: =IF(39<=p_MesFin,1,0) -> 1 | AT13: =IF(40<=p_MesFin,1,0) -> 1 | AU13: =IF(41<=p_MesFin,1,0) -> 1 | AV13: =IF(42<=p_MesFin,1,0) -> 1 | AW13: =IF(43<=p_MesFin,1,0) -> 1 | AX13: =IF(44<=p_MesFin,1,0) -> 1 | AY13: =IF(45<=p_MesFin,1,0) -> 1 | AZ13: =IF(46<=p_MesFin,1,0) -> 1 | BA13: =IF(47<=p_MesFin,1,0) -> 1 | BB13: =IF(48<=p_MesFin,1,0) -> 1 | BC13: =IF(49<=p_MesFin,1,0) -> 1 | BD13: =IF(50<=p_MesFin,1,0) -> 1 | BE13: =IF(51<=p_MesFin,1,0) -> 1 | BF13: =IF(52<=p_MesFin,1,0) -> 1 | BG13: =IF(53<=p_MesFin,1,0) -> 1 | BH13: =IF(54<=p_MesFin,1,0) -> 1 | BI13: =IF(55<=p_MesFin,1,0) -> 1 | BJ13: =IF(56<=p_MesFin,1,0) -> 1 | BK13: =IF(57<=p_MesFin,1,0) -> 1 | BL13: =IF(58<=p_MesFin,1,0) -> 1 | BM13: =IF(59<=p_MesFin,1,0) -> 1 | BN13: =IF(60<=p_MesFin,1,0) -> 1 | BO13: =IF(61<=p_MesFin,1,0) -> 1 | BP13: =IF(62<=p_MesFin,1,0) -> 1 | BQ13: =IF(63<=p_MesFin,1,0) -> 1 | BR13: =IF(64<=p_MesFin,1,0) -> 1 | BS13: =IF(65<=p_MesFin,1,0) -> 1 | BT13: =IF(66<=p_MesFin,1,0) -> 1 | BU13: =IF(67<=p_MesFin,1,0) -> 1 | BV13: =IF(68<=p_MesFin,1,0) -> 1 | BW13: =IF(69<=p_MesFin,1,0) -> 1 | BX13: =IF(70<=p_MesFin,1,0) -> 1 | BY13: =IF(71<=p_MesFin,1,0) -> 1 | BZ13: =IF(72<=p_MesFin,1,0) -> 1 | CA13: =IF(73<=p_MesFin,1,0) -> 1 | CB13: =IF(74<=p_MesFin,1,0) -> 1 | CC13: =IF(75<=p_MesFin,1,0) -> 1 | CD13: =IF(76<=p_MesFin,1,0) -> 1 | CE13: =IF(77<=p_MesFin,1,0) -> 1 | CF13: =IF(78<=p_MesFin,1,0) -> 1 | CG13: =IF(79<=p_MesFin,1,0) -> 1 | CH13: =IF(80<=p_MesFin,1,0) -> 1 | CI13: =IF(81<=p_MesFin,1,0) -> 1 | CJ13: =IF(82<=p_MesFin,1,0) -> 1 | CK13: =IF(83<=p_MesFin,1,0) -> 1 | CL13: =IF(84<=p_MesFin,1,0) -> 1 | CM13: =IF(85<=p_MesFin,1,0) -> 1 | CN13: =IF(86<=p_MesFin,1,0) -> 1 | CO13: =IF(87<=p_MesFin,1,0) -> 1 | CP13: =IF(88<=p_MesFin,1,0) -> 1 | CQ13: =IF(89<=p_MesFin,1,0) -> 1 | CR13: =IF(90<=p_MesFin,1,0) -> 1 | CS13: =IF(91<=p_MesFin,1,0) -> 1 | CT13: =IF(92<=p_MesFin,1,0) -> 1 | CU13: =IF(93<=p_MesFin,1,0) -> 1 | CV13: =IF(94<=p_MesFin,1,0) -> 1 | CW13: =IF(95<=p_MesFin,1,0) -> 1 | CX13: =IF(96<=p_MesFin,1,0) -> 1 | CY13: =IF(97<=p_MesFin,1,0) -> 1 | CZ13: =IF(98<=p_MesFin,1,0) -> 1 | DA13: =IF(99<=p_MesFin,1,0) -> 1 | DB13: =IF(100<=p_MesFin,1,0) -> 1 | DC13: =IF(101<=p_MesFin,1,0) -> 1 | DD13: =IF(102<=p_MesFin,1,0) -> 1 | DE13: =IF(103<=p_MesFin,1,0) -> 1 | DF13: =IF(104<=p_MesFin,1,0) -> 1 | DG13: =IF(105<=p_MesFin,1,0) -> 1 | DH13: =IF(106<=p_MesFin,1,0) -> 1 | DI13: =IF(107<=p_MesFin,1,0) -> 1 | DJ13: =IF(108<=p_MesFin,1,0) -> 1 | DK13: =IF(109<=p_MesFin,1,0) -> 1 | DL13: =IF(110<=p_MesFin,1,0) -> 1 | DM13: =IF(111<=p_MesFin,1,0) -> 1 | DN13: =IF(112<=p_MesFin,1,0) -> 1 | DO13: =IF(113<=p_MesFin,1,0) -> 1 | DP13: =IF(114<=p_MesFin,1,0) -> 1 | DQ13: =IF(115<=p_MesFin,1,0) -> 1 | DR13: =IF(116<=p_MesFin,1,0) -> 1 | DS13: =IF(117<=p_MesFin,1,0) -> 1 | DT13: =IF(118<=p_MesFin,1,0) -> 1 | DU13: =IF(119<=p_MesFin,1,0) -> 1 | DV13: =IF(120<=p_MesFin,1,0) -> 1 | DW13: =IF(121<=p_MesFin,1,0) -> 0 | DX13: =IF(122<=p_MesFin,1,0) -> 0 | DY13: =IF(123<=p_MesFin,1,0) -> 0 | DZ13: =IF(124<=p_MesFin,1,0) -> 0 | EA13: =IF(125<=p_MesFin,1,0) -> 0 | EB13: =IF(126<=p_MesFin,1,0) -> 0 | EC13: =IF(127<=p_MesFin,1,0) -> 0 | ED13: =IF(128<=p_MesFin,1,0) -> 0 | EE13: =IF(129<=p_MesFin,1,0) -> 0 | EF13: =IF(130<=p_MesFin,1,0) -> 0 | EG13: =IF(131<=p_MesFin,1,0) -> 0 | EH13: =IF(132<=p_MesFin,1,0) -> 0 | EI13: =IF(133<=p_MesFin,1,0) -> 0 | EJ13: =IF(134<=p_MesFin,1,0) -> 0 | EK13: =IF(135<=p_MesFin,1,0) -> 0 | EL13: =IF(136<=p_MesFin,1,0) -> 0 | EM13: =IF(137<=p_MesFin,1,0) -> 0 | EN13: =IF(138<=p_MesFin,1,0) -> 0 | EO13: =IF(139<=p_MesFin,1,0) -> 0 | EP13: =IF(140<=p_MesFin,1,0) -> 0 | EQ13: =IF(141<=p_MesFin,1,0) -> 0 | ER13: =IF(142<=p_MesFin,1,0) -> 0 | ES13: =IF(143<=p_MesFin,1,0) -> 0 | ET13: =IF(144<=p_MesFin,1,0) -> 0 | EU13: =IF(145<=p_MesFin,1,0) -> 0 | EV13: =IF(146<=p_MesFin,1,0) -> 0 | EW13: =IF(147<=p_MesFin,1,0) -> 0 | EX13: =IF(148<=p_MesFin,1,0) -> 0 | EY13: =IF(149<=p_MesFin,1,0) -> 0 | EZ13: =IF(150<=p_MesFin,1,0) -> 0 | FA13: =IF(151<=p_MesFin,1,0) -> 0 | FB13: =IF(152<=p_MesFin,1,0) -> 0 | FC13: =IF(153<=p_MesFin,1,0) -> 0 | FD13: =IF(154<=p_MesFin,1,0) -> 0 | FE13: =IF(155<=p_MesFin,1,0) -> 0 | FF13: =IF(156<=p_MesFin,1,0) -> 0
A14: f_pre | B14: Pre-operación: implantación o atraso con costos de espera (1/0) | C14: 1/0 | E14: =SUM($F14:$FF14) -> 0 | F14: =IF(AND(0>=1,0<p_MesArranque,0<=p_MesFin),1,0) -> 0 | G14: =IF(AND(1>=1,1<p_MesArranque,1<=p_MesFin),1,0) -> 0 | H14: =IF(AND(2>=1,2<p_MesArranque,2<=p_MesFin),1,0) -> 0 | I14: =IF(AND(3>=1,3<p_MesArranque,3<=p_MesFin),1,0) -> 0 | J14: =IF(AND(4>=1,4<p_MesArranque,4<=p_MesFin),1,0) -> 0 | K14: =IF(AND(5>=1,5<p_MesArranque,5<=p_MesFin),1,0) -> 0 | L14: =IF(AND(6>=1,6<p_MesArranque,6<=p_MesFin),1,0) -> 0 | M14: =IF(AND(7>=1,7<p_MesArranque,7<=p_MesFin),1,0) -> 0 | N14: =IF(AND(8>=1,8<p_MesArranque,8<=p_MesFin),1,0) -> 0 | O14: =IF(AND(9>=1,9<p_MesArranque,9<=p_MesFin),1,0) -> 0 | P14: =IF(AND(10>=1,10<p_MesArranque,10<=p_MesFin),1,0) -> 0 | Q14: =IF(AND(11>=1,11<p_MesArranque,11<=p_MesFin),1,0) -> 0 | R14: =IF(AND(12>=1,12<p_MesArranque,12<=p_MesFin),1,0) -> 0 | S14: =IF(AND(13>=1,13<p_MesArranque,13<=p_MesFin),1,0) -> 0 | T14: =IF(AND(14>=1,14<p_MesArranque,14<=p_MesFin),1,0) -> 0 | U14: =IF(AND(15>=1,15<p_MesArranque,15<=p_MesFin),1,0) -> 0 | V14: =IF(AND(16>=1,16<p_MesArranque,16<=p_MesFin),1,0) -> 0 | W14: =IF(AND(17>=1,17<p_MesArranque,17<=p_MesFin),1,0) -> 0 | X14: =IF(AND(18>=1,18<p_MesArranque,18<=p_MesFin),1,0) -> 0 | Y14: =IF(AND(19>=1,19<p_MesArranque,19<=p_MesFin),1,0) -> 0 | Z14: =IF(AND(20>=1,20<p_MesArranque,20<=p_MesFin),1,0) -> 0 | AA14: =IF(AND(21>=1,21<p_MesArranque,21<=p_MesFin),1,0) -> 0 | AB14: =IF(AND(22>=1,22<p_MesArranque,22<=p_MesFin),1,0) -> 0 | AC14: =IF(AND(23>=1,23<p_MesArranque,23<=p_MesFin),1,0) -> 0 | AD14: =IF(AND(24>=1,24<p_MesArranque,24<=p_MesFin),1,0) -> 0 | AE14: =IF(AND(25>=1,25<p_MesArranque,25<=p_MesFin),1,0) -> 0 | AF14: =IF(AND(26>=1,26<p_MesArranque,26<=p_MesFin),1,0) -> 0 | AG14: =IF(AND(27>=1,27<p_MesArranque,27<=p_MesFin),1,0) -> 0 | AH14: =IF(AND(28>=1,28<p_MesArranque,28<=p_MesFin),1,0) -> 0 | AI14: =IF(AND(29>=1,29<p_MesArranque,29<=p_MesFin),1,0) -> 0 | AJ14: =IF(AND(30>=1,30<p_MesArranque,30<=p_MesFin),1,0) -> 0 | AK14: =IF(AND(31>=1,31<p_MesArranque,31<=p_MesFin),1,0) -> 0 | AL14: =IF(AND(32>=1,32<p_MesArranque,32<=p_MesFin),1,0) -> 0 | AM14: =IF(AND(33>=1,33<p_MesArranque,33<=p_MesFin),1,0) -> 0 | AN14: =IF(AND(34>=1,34<p_MesArranque,34<=p_MesFin),1,0) -> 0 | AO14: =IF(AND(35>=1,35<p_MesArranque,35<=p_MesFin),1,0) -> 0 | AP14: =IF(AND(36>=1,36<p_MesArranque,36<=p_MesFin),1,0) -> 0 | AQ14: =IF(AND(37>=1,37<p_MesArranque,37<=p_MesFin),1,0) -> 0 | AR14: =IF(AND(38>=1,38<p_MesArranque,38<=p_MesFin),1,0) -> 0 | AS14: =IF(AND(39>=1,39<p_MesArranque,39<=p_MesFin),1,0) -> 0 | AT14: =IF(AND(40>=1,40<p_MesArranque,40<=p_MesFin),1,0) -> 0 | AU14: =IF(AND(41>=1,41<p_MesArranque,41<=p_MesFin),1,0) -> 0 | AV14: =IF(AND(42>=1,42<p_MesArranque,42<=p_MesFin),1,0) -> 0 | AW14: =IF(AND(43>=1,43<p_MesArranque,43<=p_MesFin),1,0) -> 0 | AX14: =IF(AND(44>=1,44<p_MesArranque,44<=p_MesFin),1,0) -> 0 | AY14: =IF(AND(45>=1,45<p_MesArranque,45<=p_MesFin),1,0) -> 0 | AZ14: =IF(AND(46>=1,46<p_MesArranque,46<=p_MesFin),1,0) -> 0 | BA14: =IF(AND(47>=1,47<p_MesArranque,47<=p_MesFin),1,0) -> 0 | BB14: =IF(AND(48>=1,48<p_MesArranque,48<=p_MesFin),1,0) -> 0 | BC14: =IF(AND(49>=1,49<p_MesArranque,49<=p_MesFin),1,0) -> 0 | BD14: =IF(AND(50>=1,50<p_MesArranque,50<=p_MesFin),1,0) -> 0 | BE14: =IF(AND(51>=1,51<p_MesArranque,51<=p_MesFin),1,0) -> 0 | BF14: =IF(AND(52>=1,52<p_MesArranque,52<=p_MesFin),1,0) -> 0 | BG14: =IF(AND(53>=1,53<p_MesArranque,53<=p_MesFin),1,0) -> 0 | BH14: =IF(AND(54>=1,54<p_MesArranque,54<=p_MesFin),1,0) -> 0 | BI14: =IF(AND(55>=1,55<p_MesArranque,55<=p_MesFin),1,0) -> 0 | BJ14: =IF(AND(56>=1,56<p_MesArranque,56<=p_MesFin),1,0) -> 0 | BK14: =IF(AND(57>=1,57<p_MesArranque,57<=p_MesFin),1,0) -> 0 | BL14: =IF(AND(58>=1,58<p_MesArranque,58<=p_MesFin),1,0) -> 0 | BM14: =IF(AND(59>=1,59<p_MesArranque,59<=p_MesFin),1,0) -> 0 | BN14: =IF(AND(60>=1,60<p_MesArranque,60<=p_MesFin),1,0) -> 0 | BO14: =IF(AND(61>=1,61<p_MesArranque,61<=p_MesFin),1,0) -> 0 | BP14: =IF(AND(62>=1,62<p_MesArranque,62<=p_MesFin),1,0) -> 0 | BQ14: =IF(AND(63>=1,63<p_MesArranque,63<=p_MesFin),1,0) -> 0 | BR14: =IF(AND(64>=1,64<p_MesArranque,64<=p_MesFin),1,0) -> 0 | BS14: =IF(AND(65>=1,65<p_MesArranque,65<=p_MesFin),1,0) -> 0 | BT14: =IF(AND(66>=1,66<p_MesArranque,66<=p_MesFin),1,0) -> 0 | BU14: =IF(AND(67>=1,67<p_MesArranque,67<=p_MesFin),1,0) -> 0 | BV14: =IF(AND(68>=1,68<p_MesArranque,68<=p_MesFin),1,0) -> 0 | BW14: =IF(AND(69>=1,69<p_MesArranque,69<=p_MesFin),1,0) -> 0 | BX14: =IF(AND(70>=1,70<p_MesArranque,70<=p_MesFin),1,0) -> 0 | BY14: =IF(AND(71>=1,71<p_MesArranque,71<=p_MesFin),1,0) -> 0 | BZ14: =IF(AND(72>=1,72<p_MesArranque,72<=p_MesFin),1,0) -> 0 | CA14: =IF(AND(73>=1,73<p_MesArranque,73<=p_MesFin),1,0) -> 0 | CB14: =IF(AND(74>=1,74<p_MesArranque,74<=p_MesFin),1,0) -> 0 | CC14: =IF(AND(75>=1,75<p_MesArranque,75<=p_MesFin),1,0) -> 0 | CD14: =IF(AND(76>=1,76<p_MesArranque,76<=p_MesFin),1,0) -> 0 | CE14: =IF(AND(77>=1,77<p_MesArranque,77<=p_MesFin),1,0) -> 0 | CF14: =IF(AND(78>=1,78<p_MesArranque,78<=p_MesFin),1,0) -> 0 | CG14: =IF(AND(79>=1,79<p_MesArranque,79<=p_MesFin),1,0) -> 0 | CH14: =IF(AND(80>=1,80<p_MesArranque,80<=p_MesFin),1,0) -> 0 | CI14: =IF(AND(81>=1,81<p_MesArranque,81<=p_MesFin),1,0) -> 0 | CJ14: =IF(AND(82>=1,82<p_MesArranque,82<=p_MesFin),1,0) -> 0 | CK14: =IF(AND(83>=1,83<p_MesArranque,83<=p_MesFin),1,0) -> 0 | CL14: =IF(AND(84>=1,84<p_MesArranque,84<=p_MesFin),1,0) -> 0 | CM14: =IF(AND(85>=1,85<p_MesArranque,85<=p_MesFin),1,0) -> 0 | CN14: =IF(AND(86>=1,86<p_MesArranque,86<=p_MesFin),1,0) -> 0 | CO14: =IF(AND(87>=1,87<p_MesArranque,87<=p_MesFin),1,0) -> 0 | CP14: =IF(AND(88>=1,88<p_MesArranque,88<=p_MesFin),1,0) -> 0 | CQ14: =IF(AND(89>=1,89<p_MesArranque,89<=p_MesFin),1,0) -> 0 | CR14: =IF(AND(90>=1,90<p_MesArranque,90<=p_MesFin),1,0) -> 0 | CS14: =IF(AND(91>=1,91<p_MesArranque,91<=p_MesFin),1,0) -> 0 | CT14: =IF(AND(92>=1,92<p_MesArranque,92<=p_MesFin),1,0) -> 0 | CU14: =IF(AND(93>=1,93<p_MesArranque,93<=p_MesFin),1,0) -> 0 | CV14: =IF(AND(94>=1,94<p_MesArranque,94<=p_MesFin),1,0) -> 0 | CW14: =IF(AND(95>=1,95<p_MesArranque,95<=p_MesFin),1,0) -> 0 | CX14: =IF(AND(96>=1,96<p_MesArranque,96<=p_MesFin),1,0) -> 0 | CY14: =IF(AND(97>=1,97<p_MesArranque,97<=p_MesFin),1,0) -> 0 | CZ14: =IF(AND(98>=1,98<p_MesArranque,98<=p_MesFin),1,0) -> 0 | DA14: =IF(AND(99>=1,99<p_MesArranque,99<=p_MesFin),1,0) -> 0 | DB14: =IF(AND(100>=1,100<p_MesArranque,100<=p_MesFin),1,0) -> 0 | DC14: =IF(AND(101>=1,101<p_MesArranque,101<=p_MesFin),1,0) -> 0 | DD14: =IF(AND(102>=1,102<p_MesArranque,102<=p_MesFin),1,0) -> 0 | DE14: =IF(AND(103>=1,103<p_MesArranque,103<=p_MesFin),1,0) -> 0 | DF14: =IF(AND(104>=1,104<p_MesArranque,104<=p_MesFin),1,0) -> 0 | DG14: =IF(AND(105>=1,105<p_MesArranque,105<=p_MesFin),1,0) -> 0 | DH14: =IF(AND(106>=1,106<p_MesArranque,106<=p_MesFin),1,0) -> 0 | DI14: =IF(AND(107>=1,107<p_MesArranque,107<=p_MesFin),1,0) -> 0 | DJ14: =IF(AND(108>=1,108<p_MesArranque,108<=p_MesFin),1,0) -> 0 | DK14: =IF(AND(109>=1,109<p_MesArranque,109<=p_MesFin),1,0) -> 0 | DL14: =IF(AND(110>=1,110<p_MesArranque,110<=p_MesFin),1,0) -> 0 | DM14: =IF(AND(111>=1,111<p_MesArranque,111<=p_MesFin),1,0) -> 0 | DN14: =IF(AND(112>=1,112<p_MesArranque,112<=p_MesFin),1,0) -> 0 | DO14: =IF(AND(113>=1,113<p_MesArranque,113<=p_MesFin),1,0) -> 0 | DP14: =IF(AND(114>=1,114<p_MesArranque,114<=p_MesFin),1,0) -> 0 | DQ14: =IF(AND(115>=1,115<p_MesArranque,115<=p_MesFin),1,0) -> 0 | DR14: =IF(AND(116>=1,116<p_MesArranque,116<=p_MesFin),1,0) -> 0 | DS14: =IF(AND(117>=1,117<p_MesArranque,117<=p_MesFin),1,0) -> 0 | DT14: =IF(AND(118>=1,118<p_MesArranque,118<=p_MesFin),1,0) -> 0 | DU14: =IF(AND(119>=1,119<p_MesArranque,119<=p_MesFin),1,0) -> 0 | DV14: =IF(AND(120>=1,120<p_MesArranque,120<=p_MesFin),1,0) -> 0 | DW14: =IF(AND(121>=1,121<p_MesArranque,121<=p_MesFin),1,0) -> 0 | DX14: =IF(AND(122>=1,122<p_MesArranque,122<=p_MesFin),1,0) -> 0 | DY14: =IF(AND(123>=1,123<p_MesArranque,123<=p_MesFin),1,0) -> 0 | DZ14: =IF(AND(124>=1,124<p_MesArranque,124<=p_MesFin),1,0) -> 0 | EA14: =IF(AND(125>=1,125<p_MesArranque,125<=p_MesFin),1,0) -> 0 | EB14: =IF(AND(126>=1,126<p_MesArranque,126<=p_MesFin),1,0) -> 0 | EC14: =IF(AND(127>=1,127<p_MesArranque,127<=p_MesFin),1,0) -> 0 | ED14: =IF(AND(128>=1,128<p_MesArranque,128<=p_MesFin),1,0) -> 0 | EE14: =IF(AND(129>=1,129<p_MesArranque,129<=p_MesFin),1,0) -> 0 | EF14: =IF(AND(130>=1,130<p_MesArranque,130<=p_MesFin),1,0) -> 0 | EG14: =IF(AND(131>=1,131<p_MesArranque,131<=p_MesFin),1,0) -> 0 | EH14: =IF(AND(132>=1,132<p_MesArranque,132<=p_MesFin),1,0) -> 0 | EI14: =IF(AND(133>=1,133<p_MesArranque,133<=p_MesFin),1,0) -> 0 | EJ14: =IF(AND(134>=1,134<p_MesArranque,134<=p_MesFin),1,0) -> 0 | EK14: =IF(AND(135>=1,135<p_MesArranque,135<=p_MesFin),1,0) -> 0 | EL14: =IF(AND(136>=1,136<p_MesArranque,136<=p_MesFin),1,0) -> 0 | EM14: =IF(AND(137>=1,137<p_MesArranque,137<=p_MesFin),1,0) -> 0 | EN14: =IF(AND(138>=1,138<p_MesArranque,138<=p_MesFin),1,0) -> 0 | EO14: =IF(AND(139>=1,139<p_MesArranque,139<=p_MesFin),1,0) -> 0 | EP14: =IF(AND(140>=1,140<p_MesArranque,140<=p_MesFin),1,0) -> 0 | EQ14: =IF(AND(141>=1,141<p_MesArranque,141<=p_MesFin),1,0) -> 0 | ER14: =IF(AND(142>=1,142<p_MesArranque,142<=p_MesFin),1,0) -> 0 | ES14: =IF(AND(143>=1,143<p_MesArranque,143<=p_MesFin),1,0) -> 0 | ET14: =IF(AND(144>=1,144<p_MesArranque,144<=p_MesFin),1,0) -> 0 | EU14: =IF(AND(145>=1,145<p_MesArranque,145<=p_MesFin),1,0) -> 0 | EV14: =IF(AND(146>=1,146<p_MesArranque,146<=p_MesFin),1,0) -> 0 | EW14: =IF(AND(147>=1,147<p_MesArranque,147<=p_MesFin),1,0) -> 0 | EX14: =IF(AND(148>=1,148<p_MesArranque,148<=p_MesFin),1,0) -> 0 | EY14: =IF(AND(149>=1,149<p_MesArranque,149<=p_MesFin),1,0) -> 0 | EZ14: =IF(AND(150>=1,150<p_MesArranque,150<=p_MesFin),1,0) -> 0 | FA14: =IF(AND(151>=1,151<p_MesArranque,151<=p_MesFin),1,0) -> 0 | FB14: =IF(AND(152>=1,152<p_MesArranque,152<=p_MesFin),1,0) -> 0 | FC14: =IF(AND(153>=1,153<p_MesArranque,153<=p_MesFin),1,0) -> 0 | FD14: =IF(AND(154>=1,154<p_MesArranque,154<=p_MesFin),1,0) -> 0 | FE14: =IF(AND(155>=1,155<p_MesArranque,155<=p_MesFin),1,0) -> 0 | FF14: =IF(AND(156>=1,156<p_MesArranque,156<=p_MesFin),1,0) -> 0
A15: f_fin | B15: Mes final del horizonte (1/0) | C15: 1/0 | E15: =SUM($F15:$FF15) -> 1 | F15: =IF(0=p_MesFin,1,0) -> 0 | G15: =IF(1=p_MesFin,1,0) -> 0 | H15: =IF(2=p_MesFin,1,0) -> 0 | I15: =IF(3=p_MesFin,1,0) -> 0 | J15: =IF(4=p_MesFin,1,0) -> 0 | K15: =IF(5=p_MesFin,1,0) -> 0 | L15: =IF(6=p_MesFin,1,0) -> 0 | M15: =IF(7=p_MesFin,1,0) -> 0 | N15: =IF(8=p_MesFin,1,0) -> 0 | O15: =IF(9=p_MesFin,1,0) -> 0 | P15: =IF(10=p_MesFin,1,0) -> 0 | Q15: =IF(11=p_MesFin,1,0) -> 0 | R15: =IF(12=p_MesFin,1,0) -> 0 | S15: =IF(13=p_MesFin,1,0) -> 0 | T15: =IF(14=p_MesFin,1,0) -> 0 | U15: =IF(15=p_MesFin,1,0) -> 0 | V15: =IF(16=p_MesFin,1,0) -> 0 | W15: =IF(17=p_MesFin,1,0) -> 0 | X15: =IF(18=p_MesFin,1,0) -> 0 | Y15: =IF(19=p_MesFin,1,0) -> 0 | Z15: =IF(20=p_MesFin,1,0) -> 0 | AA15: =IF(21=p_MesFin,1,0) -> 0 | AB15: =IF(22=p_MesFin,1,0) -> 0 | AC15: =IF(23=p_MesFin,1,0) -> 0 | AD15: =IF(24=p_MesFin,1,0) -> 0 | AE15: =IF(25=p_MesFin,1,0) -> 0 | AF15: =IF(26=p_MesFin,1,0) -> 0 | AG15: =IF(27=p_MesFin,1,0) -> 0 | AH15: =IF(28=p_MesFin,1,0) -> 0 | AI15: =IF(29=p_MesFin,1,0) -> 0 | AJ15: =IF(30=p_MesFin,1,0) -> 0 | AK15: =IF(31=p_MesFin,1,0) -> 0 | AL15: =IF(32=p_MesFin,1,0) -> 0 | AM15: =IF(33=p_MesFin,1,0) -> 0 | AN15: =IF(34=p_MesFin,1,0) -> 0 | AO15: =IF(35=p_MesFin,1,0) -> 0 | AP15: =IF(36=p_MesFin,1,0) -> 0 | AQ15: =IF(37=p_MesFin,1,0) -> 0 | AR15: =IF(38=p_MesFin,1,0) -> 0 | AS15: =IF(39=p_MesFin,1,0) -> 0 | AT15: =IF(40=p_MesFin,1,0) -> 0 | AU15: =IF(41=p_MesFin,1,0) -> 0 | AV15: =IF(42=p_MesFin,1,0) -> 0 | AW15: =IF(43=p_MesFin,1,0) -> 0 | AX15: =IF(44=p_MesFin,1,0) -> 0 | AY15: =IF(45=p_MesFin,1,0) -> 0 | AZ15: =IF(46=p_MesFin,1,0) -> 0 | BA15: =IF(47=p_MesFin,1,0) -> 0 | BB15: =IF(48=p_MesFin,1,0) -> 0 | BC15: =IF(49=p_MesFin,1,0) -> 0 | BD15: =IF(50=p_MesFin,1,0) -> 0 | BE15: =IF(51=p_MesFin,1,0) -> 0 | BF15: =IF(52=p_MesFin,1,0) -> 0 | BG15: =IF(53=p_MesFin,1,0) -> 0 | BH15: =IF(54=p_MesFin,1,0) -> 0 | BI15: =IF(55=p_MesFin,1,0) -> 0 | BJ15: =IF(56=p_MesFin,1,0) -> 0 | BK15: =IF(57=p_MesFin,1,0) -> 0 | BL15: =IF(58=p_MesFin,1,0) -> 0 | BM15: =IF(59=p_MesFin,1,0) -> 0 | BN15: =IF(60=p_MesFin,1,0) -> 0 | BO15: =IF(61=p_MesFin,1,0) -> 0 | BP15: =IF(62=p_MesFin,1,0) -> 0 | BQ15: =IF(63=p_MesFin,1,0) -> 0 | BR15: =IF(64=p_MesFin,1,0) -> 0 | BS15: =IF(65=p_MesFin,1,0) -> 0 | BT15: =IF(66=p_MesFin,1,0) -> 0 | BU15: =IF(67=p_MesFin,1,0) -> 0 | BV15: =IF(68=p_MesFin,1,0) -> 0 | BW15: =IF(69=p_MesFin,1,0) -> 0 | BX15: =IF(70=p_MesFin,1,0) -> 0 | BY15: =IF(71=p_MesFin,1,0) -> 0 | BZ15: =IF(72=p_MesFin,1,0) -> 0 | CA15: =IF(73=p_MesFin,1,0) -> 0 | CB15: =IF(74=p_MesFin,1,0) -> 0 | CC15: =IF(75=p_MesFin,1,0) -> 0 | CD15: =IF(76=p_MesFin,1,0) -> 0 | CE15: =IF(77=p_MesFin,1,0) -> 0 | CF15: =IF(78=p_MesFin,1,0) -> 0 | CG15: =IF(79=p_MesFin,1,0) -> 0 | CH15: =IF(80=p_MesFin,1,0) -> 0 | CI15: =IF(81=p_MesFin,1,0) -> 0 | CJ15: =IF(82=p_MesFin,1,0) -> 0 | CK15: =IF(83=p_MesFin,1,0) -> 0 | CL15: =IF(84=p_MesFin,1,0) -> 0 | CM15: =IF(85=p_MesFin,1,0) -> 0 | CN15: =IF(86=p_MesFin,1,0) -> 0 | CO15: =IF(87=p_MesFin,1,0) -> 0 | CP15: =IF(88=p_MesFin,1,0) -> 0 | CQ15: =IF(89=p_MesFin,1,0) -> 0 | CR15: =IF(90=p_MesFin,1,0) -> 0 | CS15: =IF(91=p_MesFin,1,0) -> 0 | CT15: =IF(92=p_MesFin,1,0) -> 0 | CU15: =IF(93=p_MesFin,1,0) -> 0 | CV15: =IF(94=p_MesFin,1,0) -> 0 | CW15: =IF(95=p_MesFin,1,0) -> 0 | CX15: =IF(96=p_MesFin,1,0) -> 0 | CY15: =IF(97=p_MesFin,1,0) -> 0 | CZ15: =IF(98=p_MesFin,1,0) -> 0 | DA15: =IF(99=p_MesFin,1,0) -> 0 | DB15: =IF(100=p_MesFin,1,0) -> 0 | DC15: =IF(101=p_MesFin,1,0) -> 0 | DD15: =IF(102=p_MesFin,1,0) -> 0 | DE15: =IF(103=p_MesFin,1,0) -> 0 | DF15: =IF(104=p_MesFin,1,0) -> 0 | DG15: =IF(105=p_MesFin,1,0) -> 0 | DH15: =IF(106=p_MesFin,1,0) -> 0 | DI15: =IF(107=p_MesFin,1,0) -> 0 | DJ15: =IF(108=p_MesFin,1,0) -> 0 | DK15: =IF(109=p_MesFin,1,0) -> 0 | DL15: =IF(110=p_MesFin,1,0) -> 0 | DM15: =IF(111=p_MesFin,1,0) -> 0 | DN15: =IF(112=p_MesFin,1,0) -> 0 | DO15: =IF(113=p_MesFin,1,0) -> 0 | DP15: =IF(114=p_MesFin,1,0) -> 0 | DQ15: =IF(115=p_MesFin,1,0) -> 0 | DR15: =IF(116=p_MesFin,1,0) -> 0 | DS15: =IF(117=p_MesFin,1,0) -> 0 | DT15: =IF(118=p_MesFin,1,0) -> 0 | DU15: =IF(119=p_MesFin,1,0) -> 0 | DV15: =IF(120=p_MesFin,1,0) -> 1 | DW15: =IF(121=p_MesFin,1,0) -> 0 | DX15: =IF(122=p_MesFin,1,0) -> 0 | DY15: =IF(123=p_MesFin,1,0) -> 0 | DZ15: =IF(124=p_MesFin,1,0) -> 0 | EA15: =IF(125=p_MesFin,1,0) -> 0 | EB15: =IF(126=p_MesFin,1,0) -> 0 | EC15: =IF(127=p_MesFin,1,0) -> 0 | ED15: =IF(128=p_MesFin,1,0) -> 0 | EE15: =IF(129=p_MesFin,1,0) -> 0 | EF15: =IF(130=p_MesFin,1,0) -> 0 | EG15: =IF(131=p_MesFin,1,0) -> 0 | EH15: =IF(132=p_MesFin,1,0) -> 0 | EI15: =IF(133=p_MesFin,1,0) -> 0 | EJ15: =IF(134=p_MesFin,1,0) -> 0 | EK15: =IF(135=p_MesFin,1,0) -> 0 | EL15: =IF(136=p_MesFin,1,0) -> 0 | EM15: =IF(137=p_MesFin,1,0) -> 0 | EN15: =IF(138=p_MesFin,1,0) -> 0 | EO15: =IF(139=p_MesFin,1,0) -> 0 | EP15: =IF(140=p_MesFin,1,0) -> 0 | EQ15: =IF(141=p_MesFin,1,0) -> 0 | ER15: =IF(142=p_MesFin,1,0) -> 0 | ES15: =IF(143=p_MesFin,1,0) -> 0 | ET15: =IF(144=p_MesFin,1,0) -> 0 | EU15: =IF(145=p_MesFin,1,0) -> 0 | EV15: =IF(146=p_MesFin,1,0) -> 0 | EW15: =IF(147=p_MesFin,1,0) -> 0 | EX15: =IF(148=p_MesFin,1,0) -> 0 | EY15: =IF(149=p_MesFin,1,0) -> 0 | EZ15: =IF(150=p_MesFin,1,0) -> 0 | FA15: =IF(151=p_MesFin,1,0) -> 0 | FB15: =IF(152=p_MesFin,1,0) -> 0 | FC15: =IF(153=p_MesFin,1,0) -> 0 | FD15: =IF(154=p_MesFin,1,0) -> 0 | FE15: =IF(155=p_MesFin,1,0) -> 0 | FF15: =IF(156=p_MesFin,1,0) -> 0
A16: mes_plan | B16: Mes operativo del plan original (sin atraso) | C16: n° | F16: =IF(AND(0>p_ImplMeses,0<=p_ImplMeses+p_MesesOp),0-p_ImplMeses,0) -> 0 | G16: =IF(AND(1>p_ImplMeses,1<=p_ImplMeses+p_MesesOp),1-p_ImplMeses,0) -> 1 | H16: =IF(AND(2>p_ImplMeses,2<=p_ImplMeses+p_MesesOp),2-p_ImplMeses,0) -> 2 | I16: =IF(AND(3>p_ImplMeses,3<=p_ImplMeses+p_MesesOp),3-p_ImplMeses,0) -> 3 | J16: =IF(AND(4>p_ImplMeses,4<=p_ImplMeses+p_MesesOp),4-p_ImplMeses,0) -> 4 | K16: =IF(AND(5>p_ImplMeses,5<=p_ImplMeses+p_MesesOp),5-p_ImplMeses,0) -> 5 | L16: =IF(AND(6>p_ImplMeses,6<=p_ImplMeses+p_MesesOp),6-p_ImplMeses,0) -> 6 | M16: =IF(AND(7>p_ImplMeses,7<=p_ImplMeses+p_MesesOp),7-p_ImplMeses,0) -> 7 | N16: =IF(AND(8>p_ImplMeses,8<=p_ImplMeses+p_MesesOp),8-p_ImplMeses,0) -> 8 | O16: =IF(AND(9>p_ImplMeses,9<=p_ImplMeses+p_MesesOp),9-p_ImplMeses,0) -> 9 | P16: =IF(AND(10>p_ImplMeses,10<=p_ImplMeses+p_MesesOp),10-p_ImplMeses,0) -> 10 | Q16: =IF(AND(11>p_ImplMeses,11<=p_ImplMeses+p_MesesOp),11-p_ImplMeses,0) -> 11 | R16: =IF(AND(12>p_ImplMeses,12<=p_ImplMeses+p_MesesOp),12-p_ImplMeses,0) -> 12 | S16: =IF(AND(13>p_ImplMeses,13<=p_ImplMeses+p_MesesOp),13-p_ImplMeses,0) -> 13 | T16: =IF(AND(14>p_ImplMeses,14<=p_ImplMeses+p_MesesOp),14-p_ImplMeses,0) -> 14 | U16: =IF(AND(15>p_ImplMeses,15<=p_ImplMeses+p_MesesOp),15-p_ImplMeses,0) -> 15 | V16: =IF(AND(16>p_ImplMeses,16<=p_ImplMeses+p_MesesOp),16-p_ImplMeses,0) -> 16 | W16: =IF(AND(17>p_ImplMeses,17<=p_ImplMeses+p_MesesOp),17-p_ImplMeses,0) -> 17 | X16: =IF(AND(18>p_ImplMeses,18<=p_ImplMeses+p_MesesOp),18-p_ImplMeses,0) -> 18 | Y16: =IF(AND(19>p_ImplMeses,19<=p_ImplMeses+p_MesesOp),19-p_ImplMeses,0) -> 19 | Z16: =IF(AND(20>p_ImplMeses,20<=p_ImplMeses+p_MesesOp),20-p_ImplMeses,0) -> 20 | AA16: =IF(AND(21>p_ImplMeses,21<=p_ImplMeses+p_MesesOp),21-p_ImplMeses,0) -> 21 | AB16: =IF(AND(22>p_ImplMeses,22<=p_ImplMeses+p_MesesOp),22-p_ImplMeses,0) -> 22 | AC16: =IF(AND(23>p_ImplMeses,23<=p_ImplMeses+p_MesesOp),23-p_ImplMeses,0) -> 23 | AD16: =IF(AND(24>p_ImplMeses,24<=p_ImplMeses+p_MesesOp),24-p_ImplMeses,0) -> 24 | AE16: =IF(AND(25>p_ImplMeses,25<=p_ImplMeses+p_MesesOp),25-p_ImplMeses,0) -> 25 | AF16: =IF(AND(26>p_ImplMeses,26<=p_ImplMeses+p_MesesOp),26-p_ImplMeses,0) -> 26 | AG16: =IF(AND(27>p_ImplMeses,27<=p_ImplMeses+p_MesesOp),27-p_ImplMeses,0) -> 27 | AH16: =IF(AND(28>p_ImplMeses,28<=p_ImplMeses+p_MesesOp),28-p_ImplMeses,0) -> 28 | AI16: =IF(AND(29>p_ImplMeses,29<=p_ImplMeses+p_MesesOp),29-p_ImplMeses,0) -> 29 | AJ16: =IF(AND(30>p_ImplMeses,30<=p_ImplMeses+p_MesesOp),30-p_ImplMeses,0) -> 30 | AK16: =IF(AND(31>p_ImplMeses,31<=p_ImplMeses+p_MesesOp),31-p_ImplMeses,0) -> 31 | AL16: =IF(AND(32>p_ImplMeses,32<=p_ImplMeses+p_MesesOp),32-p_ImplMeses,0) -> 32 | AM16: =IF(AND(33>p_ImplMeses,33<=p_ImplMeses+p_MesesOp),33-p_ImplMeses,0) -> 33 | AN16: =IF(AND(34>p_ImplMeses,34<=p_ImplMeses+p_MesesOp),34-p_ImplMeses,0) -> 34 | AO16: =IF(AND(35>p_ImplMeses,35<=p_ImplMeses+p_MesesOp),35-p_ImplMeses,0) -> 35 | AP16: =IF(AND(36>p_ImplMeses,36<=p_ImplMeses+p_MesesOp),36-p_ImplMeses,0) -> 36 | AQ16: =IF(AND(37>p_ImplMeses,37<=p_ImplMeses+p_MesesOp),37-p_ImplMeses,0) -> 37 | AR16: =IF(AND(38>p_ImplMeses,38<=p_ImplMeses+p_MesesOp),38-p_ImplMeses,0) -> 38 | AS16: =IF(AND(39>p_ImplMeses,39<=p_ImplMeses+p_MesesOp),39-p_ImplMeses,0) -> 39 | AT16: =IF(AND(40>p_ImplMeses,40<=p_ImplMeses+p_MesesOp),40-p_ImplMeses,0) -> 40 | AU16: =IF(AND(41>p_ImplMeses,41<=p_ImplMeses+p_MesesOp),41-p_ImplMeses,0) -> 41 | AV16: =IF(AND(42>p_ImplMeses,42<=p_ImplMeses+p_MesesOp),42-p_ImplMeses,0) -> 42 | AW16: =IF(AND(43>p_ImplMeses,43<=p_ImplMeses+p_MesesOp),43-p_ImplMeses,0) -> 43 | AX16: =IF(AND(44>p_ImplMeses,44<=p_ImplMeses+p_MesesOp),44-p_ImplMeses,0) -> 44 | AY16: =IF(AND(45>p_ImplMeses,45<=p_ImplMeses+p_MesesOp),45-p_ImplMeses,0) -> 45 | AZ16: =IF(AND(46>p_ImplMeses,46<=p_ImplMeses+p_MesesOp),46-p_ImplMeses,0) -> 46 | BA16: =IF(AND(47>p_ImplMeses,47<=p_ImplMeses+p_MesesOp),47-p_ImplMeses,0) -> 47 | BB16: =IF(AND(48>p_ImplMeses,48<=p_ImplMeses+p_MesesOp),48-p_ImplMeses,0) -> 48 | BC16: =IF(AND(49>p_ImplMeses,49<=p_ImplMeses+p_MesesOp),49-p_ImplMeses,0) -> 49 | BD16: =IF(AND(50>p_ImplMeses,50<=p_ImplMeses+p_MesesOp),50-p_ImplMeses,0) -> 50 | BE16: =IF(AND(51>p_ImplMeses,51<=p_ImplMeses+p_MesesOp),51-p_ImplMeses,0) -> 51 | BF16: =IF(AND(52>p_ImplMeses,52<=p_ImplMeses+p_MesesOp),52-p_ImplMeses,0) -> 52 | BG16: =IF(AND(53>p_ImplMeses,53<=p_ImplMeses+p_MesesOp),53-p_ImplMeses,0) -> 53 | BH16: =IF(AND(54>p_ImplMeses,54<=p_ImplMeses+p_MesesOp),54-p_ImplMeses,0) -> 54 | BI16: =IF(AND(55>p_ImplMeses,55<=p_ImplMeses+p_MesesOp),55-p_ImplMeses,0) -> 55 | BJ16: =IF(AND(56>p_ImplMeses,56<=p_ImplMeses+p_MesesOp),56-p_ImplMeses,0) -> 56 | BK16: =IF(AND(57>p_ImplMeses,57<=p_ImplMeses+p_MesesOp),57-p_ImplMeses,0) -> 57 | BL16: =IF(AND(58>p_ImplMeses,58<=p_ImplMeses+p_MesesOp),58-p_ImplMeses,0) -> 58 | BM16: =IF(AND(59>p_ImplMeses,59<=p_ImplMeses+p_MesesOp),59-p_ImplMeses,0) -> 59 | BN16: =IF(AND(60>p_ImplMeses,60<=p_ImplMeses+p_MesesOp),60-p_ImplMeses,0) -> 60 | BO16: =IF(AND(61>p_ImplMeses,61<=p_ImplMeses+p_MesesOp),61-p_ImplMeses,0) -> 61 | BP16: =IF(AND(62>p_ImplMeses,62<=p_ImplMeses+p_MesesOp),62-p_ImplMeses,0) -> 62 | BQ16: =IF(AND(63>p_ImplMeses,63<=p_ImplMeses+p_MesesOp),63-p_ImplMeses,0) -> 63 | BR16: =IF(AND(64>p_ImplMeses,64<=p_ImplMeses+p_MesesOp),64-p_ImplMeses,0) -> 64 | BS16: =IF(AND(65>p_ImplMeses,65<=p_ImplMeses+p_MesesOp),65-p_ImplMeses,0) -> 65 | BT16: =IF(AND(66>p_ImplMeses,66<=p_ImplMeses+p_MesesOp),66-p_ImplMeses,0) -> 66 | BU16: =IF(AND(67>p_ImplMeses,67<=p_ImplMeses+p_MesesOp),67-p_ImplMeses,0) -> 67 | BV16: =IF(AND(68>p_ImplMeses,68<=p_ImplMeses+p_MesesOp),68-p_ImplMeses,0) -> 68 | BW16: =IF(AND(69>p_ImplMeses,69<=p_ImplMeses+p_MesesOp),69-p_ImplMeses,0) -> 69 | BX16: =IF(AND(70>p_ImplMeses,70<=p_ImplMeses+p_MesesOp),70-p_ImplMeses,0) -> 70 | BY16: =IF(AND(71>p_ImplMeses,71<=p_ImplMeses+p_MesesOp),71-p_ImplMeses,0) -> 71 | BZ16: =IF(AND(72>p_ImplMeses,72<=p_ImplMeses+p_MesesOp),72-p_ImplMeses,0) -> 72 | CA16: =IF(AND(73>p_ImplMeses,73<=p_ImplMeses+p_MesesOp),73-p_ImplMeses,0) -> 73 | CB16: =IF(AND(74>p_ImplMeses,74<=p_ImplMeses+p_MesesOp),74-p_ImplMeses,0) -> 74 | CC16: =IF(AND(75>p_ImplMeses,75<=p_ImplMeses+p_MesesOp),75-p_ImplMeses,0) -> 75 | CD16: =IF(AND(76>p_ImplMeses,76<=p_ImplMeses+p_MesesOp),76-p_ImplMeses,0) -> 76 | CE16: =IF(AND(77>p_ImplMeses,77<=p_ImplMeses+p_MesesOp),77-p_ImplMeses,0) -> 77 | CF16: =IF(AND(78>p_ImplMeses,78<=p_ImplMeses+p_MesesOp),78-p_ImplMeses,0) -> 78 | CG16: =IF(AND(79>p_ImplMeses,79<=p_ImplMeses+p_MesesOp),79-p_ImplMeses,0) -> 79 | CH16: =IF(AND(80>p_ImplMeses,80<=p_ImplMeses+p_MesesOp),80-p_ImplMeses,0) -> 80 | CI16: =IF(AND(81>p_ImplMeses,81<=p_ImplMeses+p_MesesOp),81-p_ImplMeses,0) -> 81 | CJ16: =IF(AND(82>p_ImplMeses,82<=p_ImplMeses+p_MesesOp),82-p_ImplMeses,0) -> 82 | CK16: =IF(AND(83>p_ImplMeses,83<=p_ImplMeses+p_MesesOp),83-p_ImplMeses,0) -> 83 | CL16: =IF(AND(84>p_ImplMeses,84<=p_ImplMeses+p_MesesOp),84-p_ImplMeses,0) -> 84 | CM16: =IF(AND(85>p_ImplMeses,85<=p_ImplMeses+p_MesesOp),85-p_ImplMeses,0) -> 85 | CN16: =IF(AND(86>p_ImplMeses,86<=p_ImplMeses+p_MesesOp),86-p_ImplMeses,0) -> 86 | CO16: =IF(AND(87>p_ImplMeses,87<=p_ImplMeses+p_MesesOp),87-p_ImplMeses,0) -> 87 | CP16: =IF(AND(88>p_ImplMeses,88<=p_ImplMeses+p_MesesOp),88-p_ImplMeses,0) -> 88 | CQ16: =IF(AND(89>p_ImplMeses,89<=p_ImplMeses+p_MesesOp),89-p_ImplMeses,0) -> 89 | CR16: =IF(AND(90>p_ImplMeses,90<=p_ImplMeses+p_MesesOp),90-p_ImplMeses,0) -> 90 | CS16: =IF(AND(91>p_ImplMeses,91<=p_ImplMeses+p_MesesOp),91-p_ImplMeses,0) -> 91 | CT16: =IF(AND(92>p_ImplMeses,92<=p_ImplMeses+p_MesesOp),92-p_ImplMeses,0) -> 92 | CU16: =IF(AND(93>p_ImplMeses,93<=p_ImplMeses+p_MesesOp),93-p_ImplMeses,0) -> 93 | CV16: =IF(AND(94>p_ImplMeses,94<=p_ImplMeses+p_MesesOp),94-p_ImplMeses,0) -> 94 | CW16: =IF(AND(95>p_ImplMeses,95<=p_ImplMeses+p_MesesOp),95-p_ImplMeses,0) -> 95 | CX16: =IF(AND(96>p_ImplMeses,96<=p_ImplMeses+p_MesesOp),96-p_ImplMeses,0) -> 96 | CY16: =IF(AND(97>p_ImplMeses,97<=p_ImplMeses+p_MesesOp),97-p_ImplMeses,0) -> 97 | CZ16: =IF(AND(98>p_ImplMeses,98<=p_ImplMeses+p_MesesOp),98-p_ImplMeses,0) -> 98 | DA16: =IF(AND(99>p_ImplMeses,99<=p_ImplMeses+p_MesesOp),99-p_ImplMeses,0) -> 99 | DB16: =IF(AND(100>p_ImplMeses,100<=p_ImplMeses+p_MesesOp),100-p_ImplMeses,0) -> 100 | DC16: =IF(AND(101>p_ImplMeses,101<=p_ImplMeses+p_MesesOp),101-p_ImplMeses,0) -> 101 | DD16: =IF(AND(102>p_ImplMeses,102<=p_ImplMeses+p_MesesOp),102-p_ImplMeses,0) -> 102 | DE16: =IF(AND(103>p_ImplMeses,103<=p_ImplMeses+p_MesesOp),103-p_ImplMeses,0) -> 103 | DF16: =IF(AND(104>p_ImplMeses,104<=p_ImplMeses+p_MesesOp),104-p_ImplMeses,0) -> 104 | DG16: =IF(AND(105>p_ImplMeses,105<=p_ImplMeses+p_MesesOp),105-p_ImplMeses,0) -> 105 | DH16: =IF(AND(106>p_ImplMeses,106<=p_ImplMeses+p_MesesOp),106-p_ImplMeses,0) -> 106 | DI16: =IF(AND(107>p_ImplMeses,107<=p_ImplMeses+p_MesesOp),107-p_ImplMeses,0) -> 107 | DJ16: =IF(AND(108>p_ImplMeses,108<=p_ImplMeses+p_MesesOp),108-p_ImplMeses,0) -> 108 | DK16: =IF(AND(109>p_ImplMeses,109<=p_ImplMeses+p_MesesOp),109-p_ImplMeses,0) -> 109 | DL16: =IF(AND(110>p_ImplMeses,110<=p_ImplMeses+p_MesesOp),110-p_ImplMeses,0) -> 110 | DM16: =IF(AND(111>p_ImplMeses,111<=p_ImplMeses+p_MesesOp),111-p_ImplMeses,0) -> 111 | DN16: =IF(AND(112>p_ImplMeses,112<=p_ImplMeses+p_MesesOp),112-p_ImplMeses,0) -> 112 | DO16: =IF(AND(113>p_ImplMeses,113<=p_ImplMeses+p_MesesOp),113-p_ImplMeses,0) -> 113 | DP16: =IF(AND(114>p_ImplMeses,114<=p_ImplMeses+p_MesesOp),114-p_ImplMeses,0) -> 114 | DQ16: =IF(AND(115>p_ImplMeses,115<=p_ImplMeses+p_MesesOp),115-p_ImplMeses,0) -> 115 | DR16: =IF(AND(116>p_ImplMeses,116<=p_ImplMeses+p_MesesOp),116-p_ImplMeses,0) -> 116 | DS16: =IF(AND(117>p_ImplMeses,117<=p_ImplMeses+p_MesesOp),117-p_ImplMeses,0) -> 117 | DT16: =IF(AND(118>p_ImplMeses,118<=p_ImplMeses+p_MesesOp),118-p_ImplMeses,0) -> 118 | DU16: =IF(AND(119>p_ImplMeses,119<=p_ImplMeses+p_MesesOp),119-p_ImplMeses,0) -> 119 | DV16: =IF(AND(120>p_ImplMeses,120<=p_ImplMeses+p_MesesOp),120-p_ImplMeses,0) -> 120 | DW16: =IF(AND(121>p_ImplMeses,121<=p_ImplMeses+p_MesesOp),121-p_ImplMeses,0) -> 0 | DX16: =IF(AND(122>p_ImplMeses,122<=p_ImplMeses+p_MesesOp),122-p_ImplMeses,0) -> 0 | DY16: =IF(AND(123>p_ImplMeses,123<=p_ImplMeses+p_MesesOp),123-p_ImplMeses,0) -> 0 | DZ16: =IF(AND(124>p_ImplMeses,124<=p_ImplMeses+p_MesesOp),124-p_ImplMeses,0) -> 0 | EA16: =IF(AND(125>p_ImplMeses,125<=p_ImplMeses+p_MesesOp),125-p_ImplMeses,0) -> 0 | EB16: =IF(AND(126>p_ImplMeses,126<=p_ImplMeses+p_MesesOp),126-p_ImplMeses,0) -> 0 | EC16: =IF(AND(127>p_ImplMeses,127<=p_ImplMeses+p_MesesOp),127-p_ImplMeses,0) -> 0 | ED16: =IF(AND(128>p_ImplMeses,128<=p_ImplMeses+p_MesesOp),128-p_ImplMeses,0) -> 0 | EE16: =IF(AND(129>p_ImplMeses,129<=p_ImplMeses+p_MesesOp),129-p_ImplMeses,0) -> 0 | EF16: =IF(AND(130>p_ImplMeses,130<=p_ImplMeses+p_MesesOp),130-p_ImplMeses,0) -> 0 | EG16: =IF(AND(131>p_ImplMeses,131<=p_ImplMeses+p_MesesOp),131-p_ImplMeses,0) -> 0 | EH16: =IF(AND(132>p_ImplMeses,132<=p_ImplMeses+p_MesesOp),132-p_ImplMeses,0) -> 0 | EI16: =IF(AND(133>p_ImplMeses,133<=p_ImplMeses+p_MesesOp),133-p_ImplMeses,0) -> 0 | EJ16: =IF(AND(134>p_ImplMeses,134<=p_ImplMeses+p_MesesOp),134-p_ImplMeses,0) -> 0 | EK16: =IF(AND(135>p_ImplMeses,135<=p_ImplMeses+p_MesesOp),135-p_ImplMeses,0) -> 0 | EL16: =IF(AND(136>p_ImplMeses,136<=p_ImplMeses+p_MesesOp),136-p_ImplMeses,0) -> 0 | EM16: =IF(AND(137>p_ImplMeses,137<=p_ImplMeses+p_MesesOp),137-p_ImplMeses,0) -> 0 | EN16: =IF(AND(138>p_ImplMeses,138<=p_ImplMeses+p_MesesOp),138-p_ImplMeses,0) -> 0 | EO16: =IF(AND(139>p_ImplMeses,139<=p_ImplMeses+p_MesesOp),139-p_ImplMeses,0) -> 0 | EP16: =IF(AND(140>p_ImplMeses,140<=p_ImplMeses+p_MesesOp),140-p_ImplMeses,0) -> 0 | EQ16: =IF(AND(141>p_ImplMeses,141<=p_ImplMeses+p_MesesOp),141-p_ImplMeses,0) -> 0 | ER16: =IF(AND(142>p_ImplMeses,142<=p_ImplMeses+p_MesesOp),142-p_ImplMeses,0) -> 0 | ES16: =IF(AND(143>p_ImplMeses,143<=p_ImplMeses+p_MesesOp),143-p_ImplMeses,0) -> 0 | ET16: =IF(AND(144>p_ImplMeses,144<=p_ImplMeses+p_MesesOp),144-p_ImplMeses,0) -> 0 | EU16: =IF(AND(145>p_ImplMeses,145<=p_ImplMeses+p_MesesOp),145-p_ImplMeses,0) -> 0 | EV16: =IF(AND(146>p_ImplMeses,146<=p_ImplMeses+p_MesesOp),146-p_ImplMeses,0) -> 0 | EW16: =IF(AND(147>p_ImplMeses,147<=p_ImplMeses+p_MesesOp),147-p_ImplMeses,0) -> 0 | EX16: =IF(AND(148>p_ImplMeses,148<=p_ImplMeses+p_MesesOp),148-p_ImplMeses,0) -> 0 | EY16: =IF(AND(149>p_ImplMeses,149<=p_ImplMeses+p_MesesOp),149-p_ImplMeses,0) -> 0 | EZ16: =IF(AND(150>p_ImplMeses,150<=p_ImplMeses+p_MesesOp),150-p_ImplMeses,0) -> 0 | FA16: =IF(AND(151>p_ImplMeses,151<=p_ImplMeses+p_MesesOp),151-p_ImplMeses,0) -> 0 | FB16: =IF(AND(152>p_ImplMeses,152<=p_ImplMeses+p_MesesOp),152-p_ImplMeses,0) -> 0 | FC16: =IF(AND(153>p_ImplMeses,153<=p_ImplMeses+p_MesesOp),153-p_ImplMeses,0) -> 0 | FD16: =IF(AND(154>p_ImplMeses,154<=p_ImplMeses+p_MesesOp),154-p_ImplMeses,0) -> 0 | FE16: =IF(AND(155>p_ImplMeses,155<=p_ImplMeses+p_MesesOp),155-p_ImplMeses,0) -> 0 | FF16: =IF(AND(156>p_ImplMeses,156<=p_ImplMeses+p_MesesOp),156-p_ImplMeses,0) -> 0
A17: anio_plan | B17: Año operativo del plan original | C17: n° | F17: =IF(F$16>0,ROUNDUP(F$16/12,0),0) -> 0 | G17: =IF(G$16>0,ROUNDUP(G$16/12,0),0) -> 1 | H17: =IF(H$16>0,ROUNDUP(H$16/12,0),0) -> 1 | I17: =IF(I$16>0,ROUNDUP(I$16/12,0),0) -> 1 | J17: =IF(J$16>0,ROUNDUP(J$16/12,0),0) -> 1 | K17: =IF(K$16>0,ROUNDUP(K$16/12,0),0) -> 1 | L17: =IF(L$16>0,ROUNDUP(L$16/12,0),0) -> 1 | M17: =IF(M$16>0,ROUNDUP(M$16/12,0),0) -> 1 | ... FF17: =IF(FF$16>0,ROUNDUP(FF$16/12,0),0) -> 0
A18: f_real | B18: Mes real cerrado (1/0) — congelado | C18: 1/0 | E18: =SUM($F18:$FF18) -> 0 | F18: =IF(0<=p_MesCorte,1,0) -> 0 | G18: =IF(1<=p_MesCorte,1,0) -> 0 | H18: =IF(2<=p_MesCorte,1,0) -> 0 | I18: =IF(3<=p_MesCorte,1,0) -> 0 | J18: =IF(4<=p_MesCorte,1,0) -> 0 | K18: =IF(5<=p_MesCorte,1,0) -> 0 | L18: =IF(6<=p_MesCorte,1,0) -> 0 | M18: =IF(7<=p_MesCorte,1,0) -> 0 | N18: =IF(8<=p_MesCorte,1,0) -> 0 | O18: =IF(9<=p_MesCorte,1,0) -> 0 | P18: =IF(10<=p_MesCorte,1,0) -> 0 | Q18: =IF(11<=p_MesCorte,1,0) -> 0 | R18: =IF(12<=p_MesCorte,1,0) -> 0 | S18: =IF(13<=p_MesCorte,1,0) -> 0 | T18: =IF(14<=p_MesCorte,1,0) -> 0 | U18: =IF(15<=p_MesCorte,1,0) -> 0 | V18: =IF(16<=p_MesCorte,1,0) -> 0 | W18: =IF(17<=p_MesCorte,1,0) -> 0 | X18: =IF(18<=p_MesCorte,1,0) -> 0 | Y18: =IF(19<=p_MesCorte,1,0) -> 0 | Z18: =IF(20<=p_MesCorte,1,0) -> 0 | AA18: =IF(21<=p_MesCorte,1,0) -> 0 | AB18: =IF(22<=p_MesCorte,1,0) -> 0 | AC18: =IF(23<=p_MesCorte,1,0) -> 0 | AD18: =IF(24<=p_MesCorte,1,0) -> 0 | AE18: =IF(25<=p_MesCorte,1,0) -> 0 | AF18: =IF(26<=p_MesCorte,1,0) -> 0 | AG18: =IF(27<=p_MesCorte,1,0) -> 0 | AH18: =IF(28<=p_MesCorte,1,0) -> 0 | AI18: =IF(29<=p_MesCorte,1,0) -> 0 | AJ18: =IF(30<=p_MesCorte,1,0) -> 0 | AK18: =IF(31<=p_MesCorte,1,0) -> 0 | AL18: =IF(32<=p_MesCorte,1,0) -> 0 | AM18: =IF(33<=p_MesCorte,1,0) -> 0 | AN18: =IF(34<=p_MesCorte,1,0) -> 0 | AO18: =IF(35<=p_MesCorte,1,0) -> 0 | AP18: =IF(36<=p_MesCorte,1,0) -> 0 | AQ18: =IF(37<=p_MesCorte,1,0) -> 0 | AR18: =IF(38<=p_MesCorte,1,0) -> 0 | AS18: =IF(39<=p_MesCorte,1,0) -> 0 | AT18: =IF(40<=p_MesCorte,1,0) -> 0 | AU18: =IF(41<=p_MesCorte,1,0) -> 0 | AV18: =IF(42<=p_MesCorte,1,0) -> 0 | AW18: =IF(43<=p_MesCorte,1,0) -> 0 | AX18: =IF(44<=p_MesCorte,1,0) -> 0 | AY18: =IF(45<=p_MesCorte,1,0) -> 0 | AZ18: =IF(46<=p_MesCorte,1,0) -> 0 | BA18: =IF(47<=p_MesCorte,1,0) -> 0 | BB18: =IF(48<=p_MesCorte,1,0) -> 0 | BC18: =IF(49<=p_MesCorte,1,0) -> 0 | BD18: =IF(50<=p_MesCorte,1,0) -> 0 | BE18: =IF(51<=p_MesCorte,1,0) -> 0 | BF18: =IF(52<=p_MesCorte,1,0) -> 0 | BG18: =IF(53<=p_MesCorte,1,0) -> 0 | BH18: =IF(54<=p_MesCorte,1,0) -> 0 | BI18: =IF(55<=p_MesCorte,1,0) -> 0 | BJ18: =IF(56<=p_MesCorte,1,0) -> 0 | BK18: =IF(57<=p_MesCorte,1,0) -> 0 | BL18: =IF(58<=p_MesCorte,1,0) -> 0 | BM18: =IF(59<=p_MesCorte,1,0) -> 0 | BN18: =IF(60<=p_MesCorte,1,0) -> 0 | BO18: =IF(61<=p_MesCorte,1,0) -> 0 | BP18: =IF(62<=p_MesCorte,1,0) -> 0 | BQ18: =IF(63<=p_MesCorte,1,0) -> 0 | BR18: =IF(64<=p_MesCorte,1,0) -> 0 | BS18: =IF(65<=p_MesCorte,1,0) -> 0 | BT18: =IF(66<=p_MesCorte,1,0) -> 0 | BU18: =IF(67<=p_MesCorte,1,0) -> 0 | BV18: =IF(68<=p_MesCorte,1,0) -> 0 | BW18: =IF(69<=p_MesCorte,1,0) -> 0 | BX18: =IF(70<=p_MesCorte,1,0) -> 0 | BY18: =IF(71<=p_MesCorte,1,0) -> 0 | BZ18: =IF(72<=p_MesCorte,1,0) -> 0 | CA18: =IF(73<=p_MesCorte,1,0) -> 0 | CB18: =IF(74<=p_MesCorte,1,0) -> 0 | CC18: =IF(75<=p_MesCorte,1,0) -> 0 | CD18: =IF(76<=p_MesCorte,1,0) -> 0 | CE18: =IF(77<=p_MesCorte,1,0) -> 0 | CF18: =IF(78<=p_MesCorte,1,0) -> 0 | CG18: =IF(79<=p_MesCorte,1,0) -> 0 | CH18: =IF(80<=p_MesCorte,1,0) -> 0 | CI18: =IF(81<=p_MesCorte,1,0) -> 0 | CJ18: =IF(82<=p_MesCorte,1,0) -> 0 | CK18: =IF(83<=p_MesCorte,1,0) -> 0 | CL18: =IF(84<=p_MesCorte,1,0) -> 0 | CM18: =IF(85<=p_MesCorte,1,0) -> 0 | CN18: =IF(86<=p_MesCorte,1,0) -> 0 | CO18: =IF(87<=p_MesCorte,1,0) -> 0 | CP18: =IF(88<=p_MesCorte,1,0) -> 0 | CQ18: =IF(89<=p_MesCorte,1,0) -> 0 | CR18: =IF(90<=p_MesCorte,1,0) -> 0 | CS18: =IF(91<=p_MesCorte,1,0) -> 0 | CT18: =IF(92<=p_MesCorte,1,0) -> 0 | CU18: =IF(93<=p_MesCorte,1,0) -> 0 | CV18: =IF(94<=p_MesCorte,1,0) -> 0 | CW18: =IF(95<=p_MesCorte,1,0) -> 0 | CX18: =IF(96<=p_MesCorte,1,0) -> 0 | CY18: =IF(97<=p_MesCorte,1,0) -> 0 | CZ18: =IF(98<=p_MesCorte,1,0) -> 0 | DA18: =IF(99<=p_MesCorte,1,0) -> 0 | DB18: =IF(100<=p_MesCorte,1,0) -> 0 | DC18: =IF(101<=p_MesCorte,1,0) -> 0 | DD18: =IF(102<=p_MesCorte,1,0) -> 0 | DE18: =IF(103<=p_MesCorte,1,0) -> 0 | DF18: =IF(104<=p_MesCorte,1,0) -> 0 | DG18: =IF(105<=p_MesCorte,1,0) -> 0 | DH18: =IF(106<=p_MesCorte,1,0) -> 0 | DI18: =IF(107<=p_MesCorte,1,0) -> 0 | DJ18: =IF(108<=p_MesCorte,1,0) -> 0 | DK18: =IF(109<=p_MesCorte,1,0) -> 0 | DL18: =IF(110<=p_MesCorte,1,0) -> 0 | DM18: =IF(111<=p_MesCorte,1,0) -> 0 | DN18: =IF(112<=p_MesCorte,1,0) -> 0 | DO18: =IF(113<=p_MesCorte,1,0) -> 0 | DP18: =IF(114<=p_MesCorte,1,0) -> 0 | DQ18: =IF(115<=p_MesCorte,1,0) -> 0 | DR18: =IF(116<=p_MesCorte,1,0) -> 0 | DS18: =IF(117<=p_MesCorte,1,0) -> 0 | DT18: =IF(118<=p_MesCorte,1,0) -> 0 | DU18: =IF(119<=p_MesCorte,1,0) -> 0 | DV18: =IF(120<=p_MesCorte,1,0) -> 0 | DW18: =IF(121<=p_MesCorte,1,0) -> 0 | DX18: =IF(122<=p_MesCorte,1,0) -> 0 | DY18: =IF(123<=p_MesCorte,1,0) -> 0 | DZ18: =IF(124<=p_MesCorte,1,0) -> 0 | EA18: =IF(125<=p_MesCorte,1,0) -> 0 | EB18: =IF(126<=p_MesCorte,1,0) -> 0 | EC18: =IF(127<=p_MesCorte,1,0) -> 0 | ED18: =IF(128<=p_MesCorte,1,0) -> 0 | EE18: =IF(129<=p_MesCorte,1,0) -> 0 | EF18: =IF(130<=p_MesCorte,1,0) -> 0 | EG18: =IF(131<=p_MesCorte,1,0) -> 0 | EH18: =IF(132<=p_MesCorte,1,0) -> 0 | EI18: =IF(133<=p_MesCorte,1,0) -> 0 | EJ18: =IF(134<=p_MesCorte,1,0) -> 0 | EK18: =IF(135<=p_MesCorte,1,0) -> 0 | EL18: =IF(136<=p_MesCorte,1,0) -> 0 | EM18: =IF(137<=p_MesCorte,1,0) -> 0 | EN18: =IF(138<=p_MesCorte,1,0) -> 0 | EO18: =IF(139<=p_MesCorte,1,0) -> 0 | EP18: =IF(140<=p_MesCorte,1,0) -> 0 | EQ18: =IF(141<=p_MesCorte,1,0) -> 0 | ER18: =IF(142<=p_MesCorte,1,0) -> 0 | ES18: =IF(143<=p_MesCorte,1,0) -> 0 | ET18: =IF(144<=p_MesCorte,1,0) -> 0 | EU18: =IF(145<=p_MesCorte,1,0) -> 0 | EV18: =IF(146<=p_MesCorte,1,0) -> 0 | EW18: =IF(147<=p_MesCorte,1,0) -> 0 | EX18: =IF(148<=p_MesCorte,1,0) -> 0 | EY18: =IF(149<=p_MesCorte,1,0) -> 0 | EZ18: =IF(150<=p_MesCorte,1,0) -> 0 | FA18: =IF(151<=p_MesCorte,1,0) -> 0 | FB18: =IF(152<=p_MesCorte,1,0) -> 0 | FC18: =IF(153<=p_MesCorte,1,0) -> 0 | FD18: =IF(154<=p_MesCorte,1,0) -> 0 | FE18: =IF(155<=p_MesCorte,1,0) -> 0 | FF18: =IF(156<=p_MesCorte,1,0) -> 0
A19: anio_px | B19: Índice de año para precios, costos y TC (año de proyecto, mín. 1) | C19: n° | F19: =MAX(1,F$7) -> 1 | G19: =MAX(1,G$7) -> 1 | H19: =MAX(1,H$7) -> 1 | I19: =MAX(1,I$7) -> 1 | J19: =MAX(1,J$7) -> 1 | K19: =MAX(1,K$7) -> 1 | L19: =MAX(1,L$7) -> 1 | M19: =MAX(1,M$7) -> 1 | ... FF19: =MAX(1,FF$7) -> 13
A20: tc | B20: Tipo de cambio del mes (escenario efectivo) | C20: Gs/USD | F20: =INDEX(e_TC,MIN(14,F$7+1)) -> 7300 | G20: =INDEX(e_TC,MIN(14,G$7+1)) -> 7300 | H20: =INDEX(e_TC,MIN(14,H$7+1)) -> 7300 | I20: =INDEX(e_TC,MIN(14,I$7+1)) -> 7300 | J20: =INDEX(e_TC,MIN(14,J$7+1)) -> 7300 | K20: =INDEX(e_TC,MIN(14,K$7+1)) -> 7300 | L20: =INDEX(e_TC,MIN(14,L$7+1)) -> 7300 | M20: =INDEX(e_TC,MIN(14,M$7+1)) -> 7300 | ... FF20: =INDEX(e_TC,MIN(14,FF$7+1)) -> 7300
A21: df_p | B21: Factor de descuento del proyecto (tasa anual efectiva, capitalización mensual) | C21: factor | F21: =1/(1+p_TasaProy)^(0/12) -> 1 | G21: =1/(1+p_TasaProy)^(1/12) -> 0.99247369 | H21: =1/(1+p_TasaProy)^(2/12) -> 0.98500403 | I21: =1/(1+p_TasaProy)^(3/12) -> 0.97759058 | J21: =1/(1+p_TasaProy)^(4/12) -> 0.97023293 | K21: =1/(1+p_TasaProy)^(5/12) -> 0.96293066 | L21: =1/(1+p_TasaProy)^(6/12) -> 0.95568334 | M21: =1/(1+p_TasaProy)^(7/12) -> 0.94849057 | N21: =1/(1+p_TasaProy)^(8/12) -> 0.94135194 | O21: =1/(1+p_TasaProy)^(9/12) -> 0.93426704 | P21: =1/(1+p_TasaProy)^(10/12) -> 0.92723545 | Q21: =1/(1+p_TasaProy)^(11/12) -> 0.92025679 | R21: =1/(1+p_TasaProy)^(12/12) -> 0.91333065 | S21: =1/(1+p_TasaProy)^(13/12) -> 0.90645664 | T21: =1/(1+p_TasaProy)^(14/12) -> 0.89963437 | U21: =1/(1+p_TasaProy)^(15/12) -> 0.89286344 | V21: =1/(1+p_TasaProy)^(16/12) -> 0.88614348 | W21: =1/(1+p_TasaProy)^(17/12) -> 0.87947409 | X21: =1/(1+p_TasaProy)^(18/12) -> 0.87285489 | Y21: =1/(1+p_TasaProy)^(19/12) -> 0.86628552 | Z21: =1/(1+p_TasaProy)^(20/12) -> 0.85976558 | AA21: =1/(1+p_TasaProy)^(21/12) -> 0.85329472 | AB21: =1/(1+p_TasaProy)^(22/12) -> 0.84687256 | AC21: =1/(1+p_TasaProy)^(23/12) -> 0.84049874 | AD21: =1/(1+p_TasaProy)^(24/12) -> 0.83417288 | AE21: =1/(1+p_TasaProy)^(25/12) -> 0.82789464 | AF21: =1/(1+p_TasaProy)^(26/12) -> 0.82166365 | AG21: =1/(1+p_TasaProy)^(27/12) -> 0.81547955 | AH21: =1/(1+p_TasaProy)^(28/12) -> 0.809342 | AI21: =1/(1+p_TasaProy)^(29/12) -> 0.80325064 | AJ21: =1/(1+p_TasaProy)^(30/12) -> 0.79720513 | AK21: =1/(1+p_TasaProy)^(31/12) -> 0.79120512 | AL21: =1/(1+p_TasaProy)^(32/12) -> 0.78525026 | AM21: =1/(1+p_TasaProy)^(33/12) -> 0.77934023 | AN21: =1/(1+p_TasaProy)^(34/12) -> 0.77347467 | AO21: =1/(1+p_TasaProy)^(35/12) -> 0.76765326 | AP21: =1/(1+p_TasaProy)^(36/12) -> 0.76187566 | AQ21: =1/(1+p_TasaProy)^(37/12) -> 0.75614155 | AR21: =1/(1+p_TasaProy)^(38/12) -> 0.7504506 | AS21: =1/(1+p_TasaProy)^(39/12) -> 0.74480247 | AT21: =1/(1+p_TasaProy)^(40/12) -> 0.73919686 | AU21: =1/(1+p_TasaProy)^(41/12) -> 0.73363343 | AV21: =1/(1+p_TasaProy)^(42/12) -> 0.72811188 | AW21: =1/(1+p_TasaProy)^(43/12) -> 0.72263189 | AX21: =1/(1+p_TasaProy)^(44/12) -> 0.71719314 | AY21: =1/(1+p_TasaProy)^(45/12) -> 0.71179532 | AZ21: =1/(1+p_TasaProy)^(46/12) -> 0.70643813 | BA21: =1/(1+p_TasaProy)^(47/12) -> 0.70112125 | BB21: =1/(1+p_TasaProy)^(48/12) -> 0.6958444 | BC21: =1/(1+p_TasaProy)^(49/12) -> 0.69060726 | BD21: =1/(1+p_TasaProy)^(50/12) -> 0.68540953 | BE21: =1/(1+p_TasaProy)^(51/12) -> 0.68025093 | BF21: =1/(1+p_TasaProy)^(52/12) -> 0.67513115 | BG21: =1/(1+p_TasaProy)^(53/12) -> 0.6700499 | BH21: =1/(1+p_TasaProy)^(54/12) -> 0.6650069 | BI21: =1/(1+p_TasaProy)^(55/12) -> 0.66000185 | BJ21: =1/(1+p_TasaProy)^(56/12) -> 0.65503447 | BK21: =1/(1+p_TasaProy)^(57/12) -> 0.65010448 | BL21: =1/(1+p_TasaProy)^(58/12) -> 0.64521159 | BM21: =1/(1+p_TasaProy)^(59/12) -> 0.64035553 | BN21: =1/(1+p_TasaProy)^(60/12) -> 0.63553602 | BO21: =1/(1+p_TasaProy)^(61/12) -> 0.63075278 | BP21: =1/(1+p_TasaProy)^(62/12) -> 0.62600554 | BQ21: =1/(1+p_TasaProy)^(63/12) -> 0.62129403 | BR21: =1/(1+p_TasaProy)^(64/12) -> 0.61661797 | BS21: =1/(1+p_TasaProy)^(65/12) -> 0.61197712 | BT21: =1/(1+p_TasaProy)^(66/12) -> 0.60737119 | BU21: =1/(1+p_TasaProy)^(67/12) -> 0.60279992 | BV21: =1/(1+p_TasaProy)^(68/12) -> 0.59826306 | BW21: =1/(1+p_TasaProy)^(69/12) -> 0.59376035 | BX21: =1/(1+p_TasaProy)^(70/12) -> 0.58929153 | BY21: =1/(1+p_TasaProy)^(71/12) -> 0.58485634 | BZ21: =1/(1+p_TasaProy)^(72/12) -> 0.58045453 | CA21: =1/(1+p_TasaProy)^(73/12) -> 0.57608585 | CB21: =1/(1+p_TasaProy)^(74/12) -> 0.57175005 | CC21: =1/(1+p_TasaProy)^(75/12) -> 0.56744688 | CD21: =1/(1+p_TasaProy)^(76/12) -> 0.5631761 | CE21: =1/(1+p_TasaProy)^(77/12) -> 0.55893746 | CF21: =1/(1+p_TasaProy)^(78/12) -> 0.55473072 | CG21: =1/(1+p_TasaProy)^(79/12) -> 0.55055565 | CH21: =1/(1+p_TasaProy)^(80/12) -> 0.546412 | CI21: =1/(1+p_TasaProy)^(81/12) -> 0.54229953 | CJ21: =1/(1+p_TasaProy)^(82/12) -> 0.53821802 | CK21: =1/(1+p_TasaProy)^(83/12) -> 0.53416722 | CL21: =1/(1+p_TasaProy)^(84/12) -> 0.53014691 | CM21: =1/(1+p_TasaProy)^(85/12) -> 0.52615686 | CN21: =1/(1+p_TasaProy)^(86/12) -> 0.52219684 | CO21: =1/(1+p_TasaProy)^(87/12) -> 0.51826663 | CP21: =1/(1+p_TasaProy)^(88/12) -> 0.51436599 | CQ21: =1/(1+p_TasaProy)^(89/12) -> 0.51049472 | CR21: =1/(1+p_TasaProy)^(90/12) -> 0.50665257 | CS21: =1/(1+p_TasaProy)^(91/12) -> 0.50283935 | CT21: =1/(1+p_TasaProy)^(92/12) -> 0.49905483 | CU21: =1/(1+p_TasaProy)^(93/12) -> 0.49529878 | CV21: =1/(1+p_TasaProy)^(94/12) -> 0.49157101 | CW21: =1/(1+p_TasaProy)^(95/12) -> 0.4878713 | CX21: =1/(1+p_TasaProy)^(96/12) -> 0.48419943 | CY21: =1/(1+p_TasaProy)^(97/12) -> 0.48055519 | CZ21: =1/(1+p_TasaProy)^(98/12) -> 0.47693838 | DA21: =1/(1+p_TasaProy)^(99/12) -> 0.4733488 | DB21: =1/(1+p_TasaProy)^(100/12) -> 0.46978623 | DC21: =1/(1+p_TasaProy)^(101/12) -> 0.46625047 | DD21: =1/(1+p_TasaProy)^(102/12) -> 0.46274133 | DE21: =1/(1+p_TasaProy)^(103/12) -> 0.45925859 | DF21: =1/(1+p_TasaProy)^(104/12) -> 0.45580207 | DG21: =1/(1+p_TasaProy)^(105/12) -> 0.45237156 | DH21: =1/(1+p_TasaProy)^(106/12) -> 0.44896687 | DI21: =1/(1+p_TasaProy)^(107/12) -> 0.44558781 | DJ21: =1/(1+p_TasaProy)^(108/12) -> 0.44223418 | DK21: =1/(1+p_TasaProy)^(109/12) -> 0.43890579 | DL21: =1/(1+p_TasaProy)^(110/12) -> 0.43560245 | DM21: =1/(1+p_TasaProy)^(111/12) -> 0.43232397 | DN21: =1/(1+p_TasaProy)^(112/12) -> 0.42907016 | DO21: =1/(1+p_TasaProy)^(113/12) -> 0.42584085 | DP21: =1/(1+p_TasaProy)^(114/12) -> 0.42263584 | DQ21: =1/(1+p_TasaProy)^(115/12) -> 0.41945495 | DR21: =1/(1+p_TasaProy)^(116/12) -> 0.416298 | DS21: =1/(1+p_TasaProy)^(117/12) -> 0.41316481 | DT21: =1/(1+p_TasaProy)^(118/12) -> 0.41005521 | DU21: =1/(1+p_TasaProy)^(119/12) -> 0.40696901 | DV21: =1/(1+p_TasaProy)^(120/12) -> 0.40390603 | DW21: =1/(1+p_TasaProy)^(121/12) -> 0.40086611 | DX21: =1/(1+p_TasaProy)^(122/12) -> 0.39784907 | DY21: =1/(1+p_TasaProy)^(123/12) -> 0.39485473 | DZ21: =1/(1+p_TasaProy)^(124/12) -> 0.39188293 | EA21: =1/(1+p_TasaProy)^(125/12) -> 0.3889335 | EB21: =1/(1+p_TasaProy)^(126/12) -> 0.38600627 | EC21: =1/(1+p_TasaProy)^(127/12) -> 0.38310106 | ED21: =1/(1+p_TasaProy)^(128/12) -> 0.38021773 | EE21: =1/(1+p_TasaProy)^(129/12) -> 0.37735609 | EF21: =1/(1+p_TasaProy)^(130/12) -> 0.37451599 | EG21: =1/(1+p_TasaProy)^(131/12) -> 0.37169727 | EH21: =1/(1+p_TasaProy)^(132/12) -> 0.36889976 | EI21: =1/(1+p_TasaProy)^(133/12) -> 0.36612331 | EJ21: =1/(1+p_TasaProy)^(134/12) -> 0.36336775 | EK21: =1/(1+p_TasaProy)^(135/12) -> 0.36063293 | EL21: =1/(1+p_TasaProy)^(136/12) -> 0.35791869 | EM21: =1/(1+p_TasaProy)^(137/12) -> 0.35522489 | EN21: =1/(1+p_TasaProy)^(138/12) -> 0.35255136 | EO21: =1/(1+p_TasaProy)^(139/12) -> 0.34989794 | EP21: =1/(1+p_TasaProy)^(140/12) -> 0.3472645 | EQ21: =1/(1+p_TasaProy)^(141/12) -> 0.34465088 | ER21: =1/(1+p_TasaProy)^(142/12) -> 0.34205693 | ES21: =1/(1+p_TasaProy)^(143/12) -> 0.33948251 | ET21: =1/(1+p_TasaProy)^(144/12) -> 0.33692746 | EU21: =1/(1+p_TasaProy)^(145/12) -> 0.33439164 | EV21: =1/(1+p_TasaProy)^(146/12) -> 0.3318749 | EW21: =1/(1+p_TasaProy)^(147/12) -> 0.32937711 | EX21: =1/(1+p_TasaProy)^(148/12) -> 0.32689812 | EY21: =1/(1+p_TasaProy)^(149/12) -> 0.32443778 | EZ21: =1/(1+p_TasaProy)^(150/12) -> 0.32199596 | FA21: =1/(1+p_TasaProy)^(151/12) -> 0.31957252 | FB21: =1/(1+p_TasaProy)^(152/12) -> 0.31716732 | FC21: =1/(1+p_TasaProy)^(153/12) -> 0.31478022 | FD21: =1/(1+p_TasaProy)^(154/12) -> 0.31241108 | FE21: =1/(1+p_TasaProy)^(155/12) -> 0.31005978 | FF21: =1/(1+p_TasaProy)^(156/12) -> 0.30772618
A22: df_e | B22: Factor de descuento del capital propio (Ke) | C22: factor | F22: =1/(1+p_Ke)^(0/12) -> 1 | G22: =1/(1+p_Ke)^(1/12) -> 0.98748112 | H22: =1/(1+p_Ke)^(2/12) -> 0.97511896 | I22: =1/(1+p_Ke)^(3/12) -> 0.96291156 | J22: =1/(1+p_Ke)^(4/12) -> 0.95085699 | K22: =1/(1+p_Ke)^(5/12) -> 0.93895332 | L22: =1/(1+p_Ke)^(6/12) -> 0.92719868 | M22: =1/(1+p_Ke)^(7/12) -> 0.91559119 | N22: =1/(1+p_Ke)^(8/12) -> 0.90412901 | O22: =1/(1+p_Ke)^(9/12) -> 0.89281033 | P22: =1/(1+p_Ke)^(10/12) -> 0.88163334 | Q22: =1/(1+p_Ke)^(11/12) -> 0.87059628 | R22: =1/(1+p_Ke)^(12/12) -> 0.85969739 | S22: =1/(1+p_Ke)^(13/12) -> 0.84893494 | T22: =1/(1+p_Ke)^(14/12) -> 0.83830722 | U22: =1/(1+p_Ke)^(15/12) -> 0.82781255 | V22: =1/(1+p_Ke)^(16/12) -> 0.81744927 | W22: =1/(1+p_Ke)^(17/12) -> 0.80721572 | X22: =1/(1+p_Ke)^(18/12) -> 0.79711028 | Y22: =1/(1+p_Ke)^(19/12) -> 0.78713135 | Z22: =1/(1+p_Ke)^(20/12) -> 0.77727735 | AA22: =1/(1+p_Ke)^(21/12) -> 0.7675467 | AB22: =1/(1+p_Ke)^(22/12) -> 0.75793788 | AC22: =1/(1+p_Ke)^(23/12) -> 0.74844934 | AD22: =1/(1+p_Ke)^(24/12) -> 0.7390796 | AE22: =1/(1+p_Ke)^(25/12) -> 0.72982715 | AF22: =1/(1+p_Ke)^(26/12) -> 0.72069053 | AG22: =1/(1+p_Ke)^(27/12) -> 0.71166829 | AH22: =1/(1+p_Ke)^(28/12) -> 0.702759 | AI22: =1/(1+p_Ke)^(29/12) -> 0.69396124 | AJ22: =1/(1+p_Ke)^(30/12) -> 0.68527362 | AK22: =1/(1+p_Ke)^(31/12) -> 0.67669477 | AL22: =1/(1+p_Ke)^(32/12) -> 0.6682233 | AM22: =1/(1+p_Ke)^(33/12) -> 0.6598579 | AN22: =1/(1+p_Ke)^(34/12) -> 0.65159721 | AO22: =1/(1+p_Ke)^(35/12) -> 0.64343995 | AP22: =1/(1+p_Ke)^(36/12) -> 0.6353848 | AQ22: =1/(1+p_Ke)^(37/12) -> 0.62743049 | AR22: =1/(1+p_Ke)^(38/12) -> 0.61957576 | AS22: =1/(1+p_Ke)^(39/12) -> 0.61181937 | AT22: =1/(1+p_Ke)^(40/12) -> 0.60416007 | AU22: =1/(1+p_Ke)^(41/12) -> 0.59659667 | AV22: =1/(1+p_Ke)^(42/12) -> 0.58912794 | AW22: =1/(1+p_Ke)^(43/12) -> 0.58175272 | AX22: =1/(1+p_Ke)^(44/12) -> 0.57446983 | AY22: =1/(1+p_Ke)^(45/12) -> 0.56727811 | AZ22: =1/(1+p_Ke)^(46/12) -> 0.56017642 | BA22: =1/(1+p_Ke)^(47/12) -> 0.55316364 | BB22: =1/(1+p_Ke)^(48/12) -> 0.54623865 | BC22: =1/(1+p_Ke)^(49/12) -> 0.53940035 | BD22: =1/(1+p_Ke)^(50/12) -> 0.53264766 | BE22: =1/(1+p_Ke)^(51/12) -> 0.52597951 | BF22: =1/(1+p_Ke)^(52/12) -> 0.51939484 | BG22: =1/(1+p_Ke)^(53/12) -> 0.51289259 | BH22: =1/(1+p_Ke)^(54/12) -> 0.50647175 | BI22: =1/(1+p_Ke)^(55/12) -> 0.50013129 | BJ22: =1/(1+p_Ke)^(56/12) -> 0.49387021 | BK22: =1/(1+p_Ke)^(57/12) -> 0.48768751 | BL22: =1/(1+p_Ke)^(58/12) -> 0.48158221 | BM22: =1/(1+p_Ke)^(59/12) -> 0.47555334 | BN22: =1/(1+p_Ke)^(60/12) -> 0.46959994 | BO22: =1/(1+p_Ke)^(61/12) -> 0.46372107 | BP22: =1/(1+p_Ke)^(62/12) -> 0.45791581 | BQ22: =1/(1+p_Ke)^(63/12) -> 0.45218321 | BR22: =1/(1+p_Ke)^(64/12) -> 0.44652238 | BS22: =1/(1+p_Ke)^(65/12) -> 0.44093242 | BT22: =1/(1+p_Ke)^(66/12) -> 0.43541244 | BU22: =1/(1+p_Ke)^(67/12) -> 0.42996157 | BV22: =1/(1+p_Ke)^(68/12) -> 0.42457893 | BW22: =1/(1+p_Ke)^(69/12) -> 0.41926368 | BX22: =1/(1+p_Ke)^(70/12) -> 0.41401496 | BY22: =1/(1+p_Ke)^(71/12) -> 0.40883196 | BZ22: =1/(1+p_Ke)^(72/12) -> 0.40371384 | CA22: =1/(1+p_Ke)^(73/12) -> 0.3986598 | CB22: =1/(1+p_Ke)^(74/12) -> 0.39366902 | CC22: =1/(1+p_Ke)^(75/12) -> 0.38874073 | CD22: =1/(1+p_Ke)^(76/12) -> 0.38387413 | CE22: =1/(1+p_Ke)^(77/12) -> 0.37906845 | CF22: =1/(1+p_Ke)^(78/12) -> 0.37432294 | CG22: =1/(1+p_Ke)^(79/12) -> 0.36963683 | CH22: =1/(1+p_Ke)^(80/12) -> 0.3650094 | CI22: =1/(1+p_Ke)^(81/12) -> 0.36043989 | CJ22: =1/(1+p_Ke)^(82/12) -> 0.35592758 | CK22: =1/(1+p_Ke)^(83/12) -> 0.35147177 | CL22: =1/(1+p_Ke)^(84/12) -> 0.34707173 | CM22: =1/(1+p_Ke)^(85/12) -> 0.34272678 | CN22: =1/(1+p_Ke)^(86/12) -> 0.33843623 | CO22: =1/(1+p_Ke)^(87/12) -> 0.33419939 | CP22: =1/(1+p_Ke)^(88/12) -> 0.33001558 | CQ22: =1/(1+p_Ke)^(89/12) -> 0.32588416 | CR22: =1/(1+p_Ke)^(90/12) -> 0.32180445 | CS22: =1/(1+p_Ke)^(91/12) -> 0.31777582 | CT22: =1/(1+p_Ke)^(92/12) -> 0.31379762 | CU22: =1/(1+p_Ke)^(93/12) -> 0.30986923 | CV22: =1/(1+p_Ke)^(94/12) -> 0.30599001 | CW22: =1/(1+p_Ke)^(95/12) -> 0.30215936 | CX22: =1/(1+p_Ke)^(96/12) -> 0.29837666 | CY22: =1/(1+p_Ke)^(97/12) -> 0.29464132 | CZ22: =1/(1+p_Ke)^(98/12) -> 0.29095274 | DA22: =1/(1+p_Ke)^(99/12) -> 0.28731034 | DB22: =1/(1+p_Ke)^(100/12) -> 0.28371353 | DC22: =1/(1+p_Ke)^(101/12) -> 0.28016176 | DD22: =1/(1+p_Ke)^(102/12) -> 0.27665445 | DE22: =1/(1+p_Ke)^(103/12) -> 0.27319104 | DF22: =1/(1+p_Ke)^(104/12) -> 0.269771 | DG22: =1/(1+p_Ke)^(105/12) -> 0.26639377 | DH22: =1/(1+p_Ke)^(106/12) -> 0.26305881 | DI22: =1/(1+p_Ke)^(107/12) -> 0.25976561 | DJ22: =1/(1+p_Ke)^(108/12) -> 0.25651364 | DK22: =1/(1+p_Ke)^(109/12) -> 0.25330237 | DL22: =1/(1+p_Ke)^(110/12) -> 0.25013131 | DM22: =1/(1+p_Ke)^(111/12) -> 0.24699995 | DN22: =1/(1+p_Ke)^(112/12) -> 0.24390778 | DO22: =1/(1+p_Ke)^(113/12) -> 0.24085433 | DP22: =1/(1+p_Ke)^(114/12) -> 0.2378391 | DQ22: =1/(1+p_Ke)^(115/12) -> 0.23486163 | DR22: =1/(1+p_Ke)^(116/12) -> 0.23192142 | DS22: =1/(1+p_Ke)^(117/12) -> 0.22901802 | DT22: =1/(1+p_Ke)^(118/12) -> 0.22615097 | DU22: =1/(1+p_Ke)^(119/12) -> 0.22331982 | DV22: =1/(1+p_Ke)^(120/12) -> 0.2205241 | DW22: =1/(1+p_Ke)^(121/12) -> 0.21776339 | DX22: =1/(1+p_Ke)^(122/12) -> 0.21503723 | DY22: =1/(1+p_Ke)^(123/12) -> 0.21234521 | DZ22: =1/(1+p_Ke)^(124/12) -> 0.20968688 | EA22: =1/(1+p_Ke)^(125/12) -> 0.20706184 | EB22: =1/(1+p_Ke)^(126/12) -> 0.20446966 | EC22: =1/(1+p_Ke)^(127/12) -> 0.20190993 | ED22: =1/(1+p_Ke)^(128/12) -> 0.19938224 | EE22: =1/(1+p_Ke)^(129/12) -> 0.1968862 | EF22: =1/(1+p_Ke)^(130/12) -> 0.1944214 | EG22: =1/(1+p_Ke)^(131/12) -> 0.19198746 | EH22: =1/(1+p_Ke)^(132/12) -> 0.189584 | EI22: =1/(1+p_Ke)^(133/12) -> 0.18721062 | EJ22: =1/(1+p_Ke)^(134/12) -> 0.18486695 | EK22: =1/(1+p_Ke)^(135/12) -> 0.18255262 | EL22: =1/(1+p_Ke)^(136/12) -> 0.18026727 | EM22: =1/(1+p_Ke)^(137/12) -> 0.17801052 | EN22: =1/(1+p_Ke)^(138/12) -> 0.17578203 | EO22: =1/(1+p_Ke)^(139/12) -> 0.17358144 | EP22: =1/(1+p_Ke)^(140/12) -> 0.17140839 | EQ22: =1/(1+p_Ke)^(141/12) -> 0.16926255 | ER22: =1/(1+p_Ke)^(142/12) -> 0.16714357 | ES22: =1/(1+p_Ke)^(143/12) -> 0.16505112 | ET22: =1/(1+p_Ke)^(144/12) -> 0.16298487 | EU22: =1/(1+p_Ke)^(145/12) -> 0.16094448 | EV22: =1/(1+p_Ke)^(146/12) -> 0.15892963 | EW22: =1/(1+p_Ke)^(147/12) -> 0.15694001 | EX22: =1/(1+p_Ke)^(148/12) -> 0.1549753 | EY22: =1/(1+p_Ke)^(149/12) -> 0.15303518 | EZ22: =1/(1+p_Ke)^(150/12) -> 0.15111935 | FA22: =1/(1+p_Ke)^(151/12) -> 0.14922751 | FB22: =1/(1+p_Ke)^(152/12) -> 0.14735934 | FC22: =1/(1+p_Ke)^(153/12) -> 0.14551457 | FD22: =1/(1+p_Ke)^(154/12) -> 0.14369289 | FE22: =1/(1+p_Ke)^(155/12) -> 0.14189402 | FF22: =1/(1+p_Ke)^(156/12) -> 0.14011766

Sheet Produccion_Ventas
A1: Produccion_Ventas — capacidad, demanda, rampa, recuperación, producción buena, inventario PT, precios y ventas (mensual)
A2: Motor único: fórmulas homogéneas por mes. Columna E = total del horizonte o saldo al cierre del horizonte. No editar fórmulas; los supuestos se cambian en Supuestos / Datos_Reales.
A4: h_m | B4: Mes del modelo | E4: Total / cierre | F4: =Calendario!F$5 -> 0 | G4: =Calendario!G$5 -> 1 | H4: =Calendario!H$5 -> 2 | I4: =Calendario!I$5 -> 3 | J4: =Calendario!J$5 -> 4 | K4: =Calendario!K$5 -> 5 | L4: =Calendario!L$5 -> 6 | M4: =Calendario!M$5 -> 7 | ... FF4: =Calendario!FF$5 -> 156
A5: h_fecha | B5: Fecha | F5: =Calendario!F$6 -> s/f | G5: =Calendario!G$6 -> s/f | H5: =Calendario!H$6 -> s/f | I5: =Calendario!I$6 -> s/f | J5: =Calendario!J$6 -> s/f | K5: =Calendario!K$6 -> s/f | L5: =Calendario!L$6 -> s/f | M5: =Calendario!M$6 -> s/f | ... FF5: =Calendario!FF$6 -> s/f
A6: h_anio | B6: Año de proyecto | F6: =Calendario!F$7 -> 0 | G6: =Calendario!G$7 -> 1 | H6: =Calendario!H$7 -> 1 | I6: =Calendario!I$7 -> 1 | J6: =Calendario!J$7 -> 1 | K6: =Calendario!K$7 -> 1 | L6: =Calendario!L$7 -> 1 | M6: =Calendario!M$7 -> 1 | ... FF6: =Calendario!FF$7 -> 13
A7: h_aop | B7: Año operativo | F7: =Calendario!F$11 -> 0 | G7: =Calendario!G$11 -> 1 | H7: =Calendario!H$11 -> 1 | I7: =Calendario!I$11 -> 1 | J7: =Calendario!J$11 -> 1 | K7: =Calendario!K$11 -> 1 | L7: =Calendario!L$11 -> 1 | M7: =Calendario!M$11 -> 1 | ... FF7: =Calendario!FF$11 -> 0
A8: h_fop | B8: Operación (1/0) | F8: =Calendario!F$12 -> 0 | G8: =Calendario!G$12 -> 1 | H8: =Calendario!H$12 -> 1 | I8: =Calendario!I$12 -> 1 | J8: =Calendario!J$12 -> 1 | K8: =Calendario!K$12 -> 1 | L8: =Calendario!L$12 -> 1 | M8: =Calendario!M$12 -> 1 | ... FF8: =Calendario!FF$12 -> 0
A9: h_freal | B9: Real cerrado (1/0) | F9: =Calendario!F$18 -> 0 | G9: =Calendario!G$18 -> 0 | H9: =Calendario!H$18 -> 0 | I9: =Calendario!I$18 -> 0 | J9: =Calendario!J$18 -> 0 | K9: =Calendario!K$18 -> 0 | L9: =Calendario!L$18 -> 0 | M9: =Calendario!M$18 -> 0 | ... FF9: =Calendario!FF$18 -> 0
B10: Curva de aprendizaje (común a ambos productos)
A11: rampa | B11: Factor de rampa (% del ritmo del plan alcanzado) | C11: % | F11: =IF(F$8=0,0,IF(e_Rampa<=0,1,MIN(1,e_Eff0+(1-e_Eff0)*(Calendario!F$10-1)/e_Rampa))) -> 0 | G11: =IF(G$8=0,0,IF(e_Rampa<=0,1,MIN(1,e_Eff0+(1-e_Eff0)*(Calendario!G$10-1)/e_Rampa))) -> 1 | H11: =IF(H$8=0,0,IF(e_Rampa<=0,1,MIN(1,e_Eff0+(1-e_Eff0)*(Calendario!H$10-1)/e_Rampa))) -> 1 | I11: =IF(I$8=0,0,IF(e_Rampa<=0,1,MIN(1,e_Eff0+(1-e_Eff0)*(Calendario!I$10-1)/e_Rampa))) -> 1 | J11: =IF(J$8=0,0,IF(e_Rampa<=0,1,MIN(1,e_Eff0+(1-e_Eff0)*(Calendario!J$10-1)/e_Rampa))) -> 1 | K11: =IF(K$8=0,0,IF(e_Rampa<=0,1,MIN(1,e_Eff0+(1-e_Eff0)*(Calendario!K$10-1)/e_Rampa))) -> 1 | L11: =IF(L$8=0,0,IF(e_Rampa<=0,1,MIN(1,e_Eff0+(1-e_Eff0)*(Calendario!L$10-1)/e_Rampa))) -> 1 | M11: =IF(M$8=0,0,IF(e_Rampa<=0,1,MIN(1,e_Eff0+(1-e_Eff0)*(Calendario!M$10-1)/e_Rampa))) -> 1 | ... FF11: =IF(FF$8=0,0,IF(e_Rampa<=0,1,MIN(1,e_Eff0+(1-e_Eff0)*(Calendario!FF$10-1)/e_Rampa))) -> 0
B12: Gabinetes (153 kg) — unidades
A13: cap_g | B13: Capacidad instalada del plan (u/mes) | C13: u | E13: =SUM($F13:$FF13) -> 206000 | F13: =IF(F$8=1,INDEX(Base_PDF!$F$86:$O$86,1,F$7)/12*(1+e_CapAdic),0) -> 0 | G13: =IF(G$8=1,INDEX(Base_PDF!$F$86:$O$86,1,G$7)/12*(1+e_CapAdic),0) -> 1250 | H13: =IF(H$8=1,INDEX(Base_PDF!$F$86:$O$86,1,H$7)/12*(1+e_CapAdic),0) -> 1250 | I13: =IF(I$8=1,INDEX(Base_PDF!$F$86:$O$86,1,I$7)/12*(1+e_CapAdic),0) -> 1250 | J13: =IF(J$8=1,INDEX(Base_PDF!$F$86:$O$86,1,J$7)/12*(1+e_CapAdic),0) -> 1250 | K13: =IF(K$8=1,INDEX(Base_PDF!$F$86:$O$86,1,K$7)/12*(1+e_CapAdic),0) -> 1250 | L13: =IF(L$8=1,INDEX(Base_PDF!$F$86:$O$86,1,L$7)/12*(1+e_CapAdic),0) -> 1250 | M13: =IF(M$8=1,INDEX(Base_PDF!$F$86:$O$86,1,M$7)/12*(1+e_CapAdic),0) -> 1250 | ... FF13: =IF(FF$8=1,INDEX(Base_PDF!$F$86:$O$86,1,FF$7)/12*(1+e_CapAdic),0) -> 0
A14: plan_g | B14: Plan PDF de ventas según año operativo (u/mes) | C14: u | E14: =SUM($F14:$FF14) -> 192000 | F14: =IF(F$8=1,INDEX(Base_PDF!$F$88:$O$88,1,F$7)/12,0) -> 0 | G14: =IF(G$8=1,INDEX(Base_PDF!$F$88:$O$88,1,G$7)/12,0) -> 1000 | H14: =IF(H$8=1,INDEX(Base_PDF!$F$88:$O$88,1,H$7)/12,0) -> 1000 | I14: =IF(I$8=1,INDEX(Base_PDF!$F$88:$O$88,1,I$7)/12,0) -> 1000 | J14: =IF(J$8=1,INDEX(Base_PDF!$F$88:$O$88,1,J$7)/12,0) -> 1000 | K14: =IF(K$8=1,INDEX(Base_PDF!$F$88:$O$88,1,K$7)/12,0) -> 1000 | L14: =IF(L$8=1,INDEX(Base_PDF!$F$88:$O$88,1,L$7)/12,0) -> 1000 | M14: =IF(M$8=1,INDEX(Base_PDF!$F$88:$O$88,1,M$7)/12,0) -> 1000 | ... FF14: =IF(FF$8=1,INDEX(Base_PDF!$F$88:$O$88,1,FF$7)/12,0) -> 0
A15: fvol_g | B15: Factor de volumen del escenario | C15: % | F15: =IF(F$8=1,INDEX(e_VolG,F$7),0) -> 0 | G15: =IF(G$8=1,INDEX(e_VolG,G$7),0) -> 1 | H15: =IF(H$8=1,INDEX(e_VolG,H$7),0) -> 1 | I15: =IF(I$8=1,INDEX(e_VolG,I$7),0) -> 1 | J15: =IF(J$8=1,INDEX(e_VolG,J$7),0) -> 1 | K15: =IF(K$8=1,INDEX(e_VolG,K$7),0) -> 1 | L15: =IF(L$8=1,INDEX(e_VolG,L$7),0) -> 1 | M15: =IF(M$8=1,INDEX(e_VolG,M$7),0) -> 1 | ... FF15: =IF(FF$8=1,INDEX(e_VolG,FF$7),0) -> 0
A16: dem_g | B16: Demanda del escenario (u) | C16: u | E16: =SUM($F16:$FF16) -> 192000 | F16: =F$14*F$15 -> 0 | G16: =G$14*G$15 -> 1000 | H16: =H$14*H$15 -> 1000 | I16: =I$14*I$15 -> 1000 | J16: =J$14*J$15 -> 1000 | K16: =K$14*K$15 -> 1000 | L16: =L$14*L$15 -> 1000 | M16: =M$14*M$15 -> 1000 | ... FF16: =FF$14*FF$15 -> 0
A17: vbase_g | B17: Ventas posibles con rampa (u) | C17: u | E17: =SUM($F17:$FF17) -> 192000 | F17: =F$16*F$11 -> 0 | G17: =G$16*G$11 -> 1000 | H17: =H$16*H$11 -> 1000 | I17: =I$16*I$11 -> 1000 | J17: =J$16*J$11 -> 1000 | K17: =K$16*K$11 -> 1000 | L17: =L$16*L$11 -> 1000 | M17: =M$16*M$11 -> 1000 | ... FF17: =FF$16*FF$11 -> 0
A18: prampa_g | B18: Volumen no producido por rampa (u) | C18: u | E18: =SUM($F18:$FF18) -> 0 | F18: =F$16-F$17 -> 0 | G18: =G$16-G$17 -> 0 | H18: =H$16-H$17 -> 0 | I18: =I$16-I$17 -> 0 | J18: =J$16-J$17 -> 0 | K18: =K$16-K$17 -> 0 | L18: =L$16-L$17 -> 0 | M18: =M$16-M$17 -> 0 | ... FF18: =FF$16-FF$17 -> 0
A19: patraso_g | B19: Demanda del plan no atendida por atraso (u) | C19: u | E19: =SUM($F19:$FF19) -> 0 | F19: =IF(AND(Calendario!F$16>0,0<p_MesArranque),INDEX(Base_PDF!$F$88:$O$88,1,Calendario!F$17)/12*INDEX(e_VolG,Calendario!F$17),0) -> 0 | G19: =IF(AND(Calendario!G$16>0,1<p_MesArranque),INDEX(Base_PDF!$F$88:$O$88,1,Calendario!G$17)/12*INDEX(e_VolG,Calendario!G$17),0) -> 0 | H19: =IF(AND(Calendario!H$16>0,2<p_MesArranque),INDEX(Base_PDF!$F$88:$O$88,1,Calendario!H$17)/12*INDEX(e_VolG,Calendario!H$17),0) -> 0 | I19: =IF(AND(Calendario!I$16>0,3<p_MesArranque),INDEX(Base_PDF!$F$88:$O$88,1,Calendario!I$17)/12*INDEX(e_VolG,Calendario!I$17),0) -> 0 | J19: =IF(AND(Calendario!J$16>0,4<p_MesArranque),INDEX(Base_PDF!$F$88:$O$88,1,Calendario!J$17)/12*INDEX(e_VolG,Calendario!J$17),0) -> 0 | K19: =IF(AND(Calendario!K$16>0,5<p_MesArranque),INDEX(Base_PDF!$F$88:$O$88,1,Calendario!K$17)/12*INDEX(e_VolG,Calendario!K$17),0) -> 0 | L19: =IF(AND(Calendario!L$16>0,6<p_MesArranque),INDEX(Base_PDF!$F$88:$O$88,1,Calendario!L$17)/12*INDEX(e_VolG,Calendario!L$17),0) -> 0 | M19: =IF(AND(Calendario!M$16>0,7<p_MesArranque),INDEX(Base_PDF!$F$88:$O$88,1,Calendario!M$17)/12*INDEX(e_VolG,Calendario!M$17),0) -> 0 | N19: =IF(AND(Calendario!N$16>0,8<p_MesArranque),INDEX(Base_PDF!$F$88:$O$88,1,Calendario!N$17)/12*INDEX(e_VolG,Calendario!N$17),0) -> 0 | O19: =IF(AND(Calendario!O$16>0,9<p_MesArranque),INDEX(Base_PDF!$F$88:$O$88,1,Calendario!O$17)/12*INDEX(e_VolG,Calendario!O$17),0) -> 0 | P19: =IF(AND(Calendario!P$16>0,10<p_MesArranque),INDEX(Base_PDF!$F$88:$O$88,1,Calendario!P$17)/12*INDEX(e_VolG,Calendario!P$17),0) -> 0 | Q19: =IF(AND(Calendario!Q$16>0,11<p_MesArranque),INDEX(Base_PDF!$F$88:$O$88,1,Calendario!Q$17)/12*INDEX(e_VolG,Calendario!Q$17),0) -> 0 | R19: =IF(AND(Calendario!R$16>0,12<p_MesArranque),INDEX(Base_PDF!$F$88:$O$88,1,Calendario!R$17)/12*INDEX(e_VolG,Calendario!R$17),0) -> 0 | S19: =IF(AND(Calendario!S$16>0,13<p_MesArranque),INDEX(Base_PDF!$F$88:$O$88,1,Calendario!S$17)/12*INDEX(e_VolG,Calendario!S$17),0) -> 0 | T19: =IF(AND(Calendario!T$16>0,14<p_MesArranque),INDEX(Base_PDF!$F$88:$O$88,1,Calendario!T$17)/12*INDEX(e_VolG,Calendario!T$17),0) -> 0 | U19: =IF(AND(Calendario!U$16>0,15<p_MesArranque),INDEX(Base_PDF!$F$88:$O$88,1,Calendario!U$17)/12*INDEX(e_VolG,Calendario!U$17),0) -> 0 | V19: =IF(AND(Calendario!V$16>0,16<p_MesArranque),INDEX(Base_PDF!$F$88:$O$88,1,Calendario!V$17)/12*INDEX(e_VolG,Calendario!V$17),0) -> 0 | W19: =IF(AND(Calendario!W$16>0,17<p_MesArranque),INDEX(Base_PDF!$F$88:$O$88,1,Calendario!W$17)/12*INDEX(e_VolG,Calendario!W$17),0) -> 0 | X19: =IF(AND(Calendario!X$16>0,18<p_MesArranque),INDEX(Base_PDF!$F$88:$O$88,1,Calendario!X$17)/12*INDEX(e_VolG,Calendario!X$17),0) -> 0 | Y19: =IF(AND(Calendario!Y$16>0,19<p_MesArranque),INDEX(Base_PDF!$F$88:$O$88,1,Calendario!Y$17)/12*INDEX(e_VolG,Calendario!Y$17),0) -> 0 | Z19: =IF(AND(Calendario!Z$16>0,20<p_MesArranque),INDEX(Base_PDF!$F$88:$O$88,1,Calendario!Z$17)/12*INDEX(e_VolG,Calendario!Z$17),0) -> 0 | AA19: =IF(AND(Calendario!AA$16>0,21<p_MesArranque),INDEX(Base_PDF!$F$88:$O$88,1,Calendario!AA$17)/12*INDEX(e_VolG,Calendario!AA$17),0) -> 0 | AB19: =IF(AND(Calendario!AB$16>0,22<p_MesArranque),INDEX(Base_PDF!$F$88:$O$88,1,Calendario!AB$17)/12*INDEX(e_VolG,Calendario!AB$17),0) -> 0 | AC19: =IF(AND(Calendario!AC$16>0,23<p_MesArranque),INDEX(Base_PDF!$F$88:$O$88,1,Calendario!AC$17)/12*INDEX(e_VolG,Calendario!AC$17),0) -> 0 | AD19: =IF(AND(Calendario!AD$16>0,24<p_MesArranque),INDEX(Base_PDF!$F$88:$O$88,1,Calendario!AD$17)/12*INDEX(e_VolG,Calendario!AD$17),0) -> 0 | AE19: =IF(AND(Calendario!AE$16>0,25<p_MesArranque),INDEX(Base_PDF!$F$88:$O$88,1,Calendario!AE$17)/12*INDEX(e_VolG,Calendario!AE$17),0) -> 0 | AF19: =IF(AND(Calendario!AF$16>0,26<p_MesArranque),INDEX(Base_PDF!$F$88:$O$88,1,Calendario!AF$17)/12*INDEX(e_VolG,Calendario!AF$17),0) -> 0 | AG19: =IF(AND(Calendario!AG$16>0,27<p_MesArranque),INDEX(Base_PDF!$F$88:$O$88,1,Calendario!AG$17)/12*INDEX(e_VolG,Calendario!AG$17),0) -> 0 | AH19: =IF(AND(Calendario!AH$16>0,28<p_MesArranque),INDEX(Base_PDF!$F$88:$O$88,1,Calendario!AH$17)/12*INDEX(e_VolG,Calendario!AH$17),0) -> 0 | AI19: =IF(AND(Calendario!AI$16>0,29<p_MesArranque),INDEX(Base_PDF!$F$88:$O$88,1,Calendario!AI$17)/12*INDEX(e_VolG,Calendario!AI$17),0) -> 0 | AJ19: =IF(AND(Calendario!AJ$16>0,30<p_MesArranque),INDEX(Base_PDF!$F$88:$O$88,1,Calendario!AJ$17)/12*INDEX(e_VolG,Calendario!AJ$17),0) -> 0 | AK19: =IF(AND(Calendario!AK$16>0,31<p_MesArranque),INDEX(Base_PDF!$F$88:$O$88,1,Calendario!AK$17)/12*INDEX(e_VolG,Calendario!AK$17),0) -> 0 | AL19: =IF(AND(Calendario!AL$16>0,32<p_MesArranque),INDEX(Base_PDF!$F$88:$O$88,1,Calendario!AL$17)/12*INDEX(e_VolG,Calendario!AL$17),0) -> 0 | AM19: =IF(AND(Calendario!AM$16>0,33<p_MesArranque),INDEX(Base_PDF!$F$88:$O$88,1,Calendario!AM$17)/12*INDEX(e_VolG,Calendario!AM$17),0) -> 0 | AN19: =IF(AND(Calendario!AN$16>0,34<p_MesArranque),INDEX(Base_PDF!$F$88:$O$88,1,Calendario!AN$17)/12*INDEX(e_VolG,Calendario!AN$17),0) -> 0 | AO19: =IF(AND(Calendario!AO$16>0,35<p_MesArranque),INDEX(Base_PDF!$F$88:$O$88,1,Calendario!AO$17)/12*INDEX(e_VolG,Calendario!AO$17),0) -> 0 | AP19: =IF(AND(Calendario!AP$16>0,36<p_MesArranque),INDEX(Base_PDF!$F$88:$O$88,1,Calendario!AP$17)/12*INDEX(e_VolG,Calendario!AP$17),0) -> 0 | AQ19: =IF(AND(Calendario!AQ$16>0,37<p_MesArranque),INDEX(Base_PDF!$F$88:$O$88,1,Calendario!AQ$17)/12*INDEX(e_VolG,Calendario!AQ$17),0) -> 0 | AR19: =IF(AND(Calendario!AR$16>0,38<p_MesArranque),INDEX(Base_PDF!$F$88:$O$88,1,Calendario!AR$17)/12*INDEX(e_VolG,Calendario!AR$17),0) -> 0 | AS19: =IF(AND(Calendario!AS$16>0,39<p_MesArranque),INDEX(Base_PDF!$F$88:$O$88,1,Calendario!AS$17)/12*INDEX(e_VolG,Calendario!AS$17),0) -> 0 | AT19: =IF(AND(Calendario!AT$16>0,40<p_MesArranque),INDEX(Base_PDF!$F$88:$O$88,1,Calendario!AT$17)/12*INDEX(e_VolG,Calendario!AT$17),0) -> 0 | AU19: =IF(AND(Calendario!AU$16>0,41<p_MesArranque),INDEX(Base_PDF!$F$88:$O$88,1,Calendario!AU$17)/12*INDEX(e_VolG,Calendario!AU$17),0) -> 0 | AV19: =IF(AND(Calendario!AV$16>0,42<p_MesArranque),INDEX(Base_PDF!$F$88:$O$88,1,Calendario!AV$17)/12*INDEX(e_VolG,Calendario!AV$17),0) -> 0 | AW19: =IF(AND(Calendario!AW$16>0,43<p_MesArranque),INDEX(Base_PDF!$F$88:$O$88,1,Calendario!AW$17)/12*INDEX(e_VolG,Calendario!AW$17),0) -> 0 | AX19: =IF(AND(Calendario!AX$16>0,44<p_MesArranque),INDEX(Base_PDF!$F$88:$O$88,1,Calendario!AX$17)/12*INDEX(e_VolG,Calendario!AX$17),0) -> 0 | AY19: =IF(AND(Calendario!AY$16>0,45<p_MesArranque),INDEX(Base_PDF!$F$88:$O$88,1,Calendario!AY$17)/12*INDEX(e_VolG,Calendario!AY$17),0) -> 0 | AZ19: =IF(AND(Calendario!AZ$16>0,46<p_MesArranque),INDEX(Base_PDF!$F$88:$O$88,1,Calendario!AZ$17)/12*INDEX(e_VolG,Calendario!AZ$17),0) -> 0 | BA19: =IF(AND(Calendario!BA$16>0,47<p_MesArranque),INDEX(Base_PDF!$F$88:$O$88,1,Calendario!BA$17)/12*INDEX(e_VolG,Calendario!BA$17),0) -> 0 | BB19: =IF(AND(Calendario!BB$16>0,48<p_MesArranque),INDEX(Base_PDF!$F$88:$O$88,1,Calendario!BB$17)/12*INDEX(e_VolG,Calendario!BB$17),0) -> 0 | BC19: =IF(AND(Calendario!BC$16>0,49<p_MesArranque),INDEX(Base_PDF!$F$88:$O$88,1,Calendario!BC$17)/12*INDEX(e_VolG,Calendario!BC$17),0) -> 0 | BD19: =IF(AND(Calendario!BD$16>0,50<p_MesArranque),INDEX(Base_PDF!$F$88:$O$88,1,Calendario!BD$17)/12*INDEX(e_VolG,Calendario!BD$17),0) -> 0 | BE19: =IF(AND(Calendario!BE$16>0,51<p_MesArranque),INDEX(Base_PDF!$F$88:$O$88,1,Calendario!BE$17)/12*INDEX(e_VolG,Calendario!BE$17),0) -> 0 | BF19: =IF(AND(Calendario!BF$16>0,52<p_MesArranque),INDEX(Base_PDF!$F$88:$O$88,1,Calendario!BF$17)/12*INDEX(e_VolG,Calendario!BF$17),0) -> 0 | BG19: =IF(AND(Calendario!BG$16>0,53<p_MesArranque),INDEX(Base_PDF!$F$88:$O$88,1,Calendario!BG$17)/12*INDEX(e_VolG,Calendario!BG$17),0) -> 0 | BH19: =IF(AND(Calendario!BH$16>0,54<p_MesArranque),INDEX(Base_PDF!$F$88:$O$88,1,Calendario!BH$17)/12*INDEX(e_VolG,Calendario!BH$17),0) -> 0 | BI19: =IF(AND(Calendario!BI$16>0,55<p_MesArranque),INDEX(Base_PDF!$F$88:$O$88,1,Calendario!BI$17)/12*INDEX(e_VolG,Calendario!BI$17),0) -> 0 | BJ19: =IF(AND(Calendario!BJ$16>0,56<p_MesArranque),INDEX(Base_PDF!$F$88:$O$88,1,Calendario!BJ$17)/12*INDEX(e_VolG,Calendario!BJ$17),0) -> 0 | BK19: =IF(AND(Calendario!BK$16>0,57<p_MesArranque),INDEX(Base_PDF!$F$88:$O$88,1,Calendario!BK$17)/12*INDEX(e_VolG,Calendario!BK$17),0) -> 0 | BL19: =IF(AND(Calendario!BL$16>0,58<p_MesArranque),INDEX(Base_PDF!$F$88:$O$88,1,Calendario!BL$17)/12*INDEX(e_VolG,Calendario!BL$17),0) -> 0 | BM19: =IF(AND(Calendario!BM$16>0,59<p_MesArranque),INDEX(Base_PDF!$F$88:$O$88,1,Calendario!BM$17)/12*INDEX(e_VolG,Calendario!BM$17),0) -> 0 | BN19: =IF(AND(Calendario!BN$16>0,60<p_MesArranque),INDEX(Base_PDF!$F$88:$O$88,1,Calendario!BN$17)/12*INDEX(e_VolG,Calendario!BN$17),0) -> 0 | BO19: =IF(AND(Calendario!BO$16>0,61<p_MesArranque),INDEX(Base_PDF!$F$88:$O$88,1,Calendario!BO$17)/12*INDEX(e_VolG,Calendario!BO$17),0) -> 0 | BP19: =IF(AND(Calendario!BP$16>0,62<p_MesArranque),INDEX(Base_PDF!$F$88:$O$88,1,Calendario!BP$17)/12*INDEX(e_VolG,Calendario!BP$17),0) -> 0 | BQ19: =IF(AND(Calendario!BQ$16>0,63<p_MesArranque),INDEX(Base_PDF!$F$88:$O$88,1,Calendario!BQ$17)/12*INDEX(e_VolG,Calendario!BQ$17),0) -> 0 | BR19: =IF(AND(Calendario!BR$16>0,64<p_MesArranque),INDEX(Base_PDF!$F$88:$O$88,1,Calendario!BR$17)/12*INDEX(e_VolG,Calendario!BR$17),0) -> 0 | BS19: =IF(AND(Calendario!BS$16>0,65<p_MesArranque),INDEX(Base_PDF!$F$88:$O$88,1,Calendario!BS$17)/12*INDEX(e_VolG,Calendario!BS$17),0) -> 0 | BT19: =IF(AND(Calendario!BT$16>0,66<p_MesArranque),INDEX(Base_PDF!$F$88:$O$88,1,Calendario!BT$17)/12*INDEX(e_VolG,Calendario!BT$17),0) -> 0 | BU19: =IF(AND(Calendario!BU$16>0,67<p_MesArranque),INDEX(Base_PDF!$F$88:$O$88,1,Calendario!BU$17)/12*INDEX(e_VolG,Calendario!BU$17),0) -> 0 | BV19: =IF(AND(Calendario!BV$16>0,68<p_MesArranque),INDEX(Base_PDF!$F$88:$O$88,1,Calendario!BV$17)/12*INDEX(e_VolG,Calendario!BV$17),0) -> 0 | BW19: =IF(AND(Calendario!BW$16>0,69<p_MesArranque),INDEX(Base_PDF!$F$88:$O$88,1,Calendario!BW$17)/12*INDEX(e_VolG,Calendario!BW$17),0) -> 0 | BX19: =IF(AND(Calendario!BX$16>0,70<p_MesArranque),INDEX(Base_PDF!$F$88:$O$88,1,Calendario!BX$17)/12*INDEX(e_VolG,Calendario!BX$17),0) -> 0 | BY19: =IF(AND(Calendario!BY$16>0,71<p_MesArranque),INDEX(Base_PDF!$F$88:$O$88,1,Calendario!BY$17)/12*INDEX(e_VolG,Calendario!BY$17),0) -> 0 | BZ19: =IF(AND(Calendario!BZ$16>0,72<p_MesArranque),INDEX(Base_PDF!$F$88:$O$88,1,Calendario!BZ$17)/12*INDEX(e_VolG,Calendario!BZ$17),0) -> 0 | CA19: =IF(AND(Calendario!CA$16>0,73<p_MesArranque),INDEX(Base_PDF!$F$88:$O$88,1,Calendario!CA$17)/12*INDEX(e_VolG,Calendario!CA$17),0) -> 0 | CB19: =IF(AND(Calendario!CB$16>0,74<p_MesArranque),INDEX(Base_PDF!$F$88:$O$88,1,Calendario!CB$17)/12*INDEX(e_VolG,Calendario!CB$17),0) -> 0 | CC19: =IF(AND(Calendario!CC$16>0,75<p_MesArranque),INDEX(Base_PDF!$F$88:$O$88,1,Calendario!CC$17)/12*INDEX(e_VolG,Calendario!CC$17),0) -> 0 | CD19: =IF(AND(Calendario!CD$16>0,76<p_MesArranque),INDEX(Base_PDF!$F$88:$O$88,1,Calendario!CD$17)/12*INDEX(e_VolG,Calendario!CD$17),0) -> 0 | CE19: =IF(AND(Calendario!CE$16>0,77<p_MesArranque),INDEX(Base_PDF!$F$88:$O$88,1,Calendario!CE$17)/12*INDEX(e_VolG,Calendario!CE$17),0) -> 0 | CF19: =IF(AND(Calendario!CF$16>0,78<p_MesArranque),INDEX(Base_PDF!$F$88:$O$88,1,Calendario!CF$17)/12*INDEX(e_VolG,Calendario!CF$17),0) -> 0 | CG19: =IF(AND(Calendario!CG$16>0,79<p_MesArranque),INDEX(Base_PDF!$F$88:$O$88,1,Calendario!CG$17)/12*INDEX(e_VolG,Calendario!CG$17),0) -> 0 | CH19: =IF(AND(Calendario!CH$16>0,80<p_MesArranque),INDEX(Base_PDF!$F$88:$O$88,1,Calendario!CH$17)/12*INDEX(e_VolG,Calendario!CH$17),0) -> 0 | CI19: =IF(AND(Calendario!CI$16>0,81<p_MesArranque),INDEX(Base_PDF!$F$88:$O$88,1,Calendario!CI$17)/12*INDEX(e_VolG,Calendario!CI$17),0) -> 0 | CJ19: =IF(AND(Calendario!CJ$16>0,82<p_MesArranque),INDEX(Base_PDF!$F$88:$O$88,1,Calendario!CJ$17)/12*INDEX(e_VolG,Calendario!CJ$17),0) -> 0 | CK19: =IF(AND(Calendario!CK$16>0,83<p_MesArranque),INDEX(Base_PDF!$F$88:$O$88,1,Calendario!CK$17)/12*INDEX(e_VolG,Calendario!CK$17),0) -> 0 | CL19: =IF(AND(Calendario!CL$16>0,84<p_MesArranque),INDEX(Base_PDF!$F$88:$O$88,1,Calendario!CL$17)/12*INDEX(e_VolG,Calendario!CL$17),0) -> 0 | CM19: =IF(AND(Calendario!CM$16>0,85<p_MesArranque),INDEX(Base_PDF!$F$88:$O$88,1,Calendario!CM$17)/12*INDEX(e_VolG,Calendario!CM$17),0) -> 0 | CN19: =IF(AND(Calendario!CN$16>0,86<p_MesArranque),INDEX(Base_PDF!$F$88:$O$88,1,Calendario!CN$17)/12*INDEX(e_VolG,Calendario!CN$17),0) -> 0 | CO19: =IF(AND(Calendario!CO$16>0,87<p_MesArranque),INDEX(Base_PDF!$F$88:$O$88,1,Calendario!CO$17)/12*INDEX(e_VolG,Calendario!CO$17),0) -> 0 | CP19: =IF(AND(Calendario!CP$16>0,88<p_MesArranque),INDEX(Base_PDF!$F$88:$O$88,1,Calendario!CP$17)/12*INDEX(e_VolG,Calendario!CP$17),0) -> 0 | CQ19: =IF(AND(Calendario!CQ$16>0,89<p_MesArranque),INDEX(Base_PDF!$F$88:$O$88,1,Calendario!CQ$17)/12*INDEX(e_VolG,Calendario!CQ$17),0) -> 0 | CR19: =IF(AND(Calendario!CR$16>0,90<p_MesArranque),INDEX(Base_PDF!$F$88:$O$88,1,Calendario!CR$17)/12*INDEX(e_VolG,Calendario!CR$17),0) -> 0 | CS19: =IF(AND(Calendario!CS$16>0,91<p_MesArranque),INDEX(Base_PDF!$F$88:$O$88,1,Calendario!CS$17)/12*INDEX(e_VolG,Calendario!CS$17),0) -> 0 | CT19: =IF(AND(Calendario!CT$16>0,92<p_MesArranque),INDEX(Base_PDF!$F$88:$O$88,1,Calendario!CT$17)/12*INDEX(e_VolG,Calendario!CT$17),0) -> 0 | CU19: =IF(AND(Calendario!CU$16>0,93<p_MesArranque),INDEX(Base_PDF!$F$88:$O$88,1,Calendario!CU$17)/12*INDEX(e_VolG,Calendario!CU$17),0) -> 0 | CV19: =IF(AND(Calendario!CV$16>0,94<p_MesArranque),INDEX(Base_PDF!$F$88:$O$88,1,Calendario!CV$17)/12*INDEX(e_VolG,Calendario!CV$17),0) -> 0 | CW19: =IF(AND(Calendario!CW$16>0,95<p_MesArranque),INDEX(Base_PDF!$F$88:$O$88,1,Calendario!CW$17)/12*INDEX(e_VolG,Calendario!CW$17),0) -> 0 | CX19: =IF(AND(Calendario!CX$16>0,96<p_MesArranque),INDEX(Base_PDF!$F$88:$O$88,1,Calendario!CX$17)/12*INDEX(e_VolG,Calendario!CX$17),0) -> 0 | CY19: =IF(AND(Calendario!CY$16>0,97<p_MesArranque),INDEX(Base_PDF!$F$88:$O$88,1,Calendario!CY$17)/12*INDEX(e_VolG,Calendario!CY$17),0) -> 0 | CZ19: =IF(AND(Calendario!CZ$16>0,98<p_MesArranque),INDEX(Base_PDF!$F$88:$O$88,1,Calendario!CZ$17)/12*INDEX(e_VolG,Calendario!CZ$17),0) -> 0 | DA19: =IF(AND(Calendario!DA$16>0,99<p_MesArranque),INDEX(Base_PDF!$F$88:$O$88,1,Calendario!DA$17)/12*INDEX(e_VolG,Calendario!DA$17),0) -> 0 | DB19: =IF(AND(Calendario!DB$16>0,100<p_MesArranque),INDEX(Base_PDF!$F$88:$O$88,1,Calendario!DB$17)/12*INDEX(e_VolG,Calendario!DB$17),0) -> 0 | DC19: =IF(AND(Calendario!DC$16>0,101<p_MesArranque),INDEX(Base_PDF!$F$88:$O$88,1,Calendario!DC$17)/12*INDEX(e_VolG,Calendario!DC$17),0) -> 0 | DD19: =IF(AND(Calendario!DD$16>0,102<p_MesArranque),INDEX(Base_PDF!$F$88:$O$88,1,Calendario!DD$17)/12*INDEX(e_VolG,Calendario!DD$17),0) -> 0 | DE19: =IF(AND(Calendario!DE$16>0,103<p_MesArranque),INDEX(Base_PDF!$F$88:$O$88,1,Calendario!DE$17)/12*INDEX(e_VolG,Calendario!DE$17),0) -> 0 | DF19: =IF(AND(Calendario!DF$16>0,104<p_MesArranque),INDEX(Base_PDF!$F$88:$O$88,1,Calendario!DF$17)/12*INDEX(e_VolG,Calendario!DF$17),0) -> 0 | DG19: =IF(AND(Calendario!DG$16>0,105<p_MesArranque),INDEX(Base_PDF!$F$88:$O$88,1,Calendario!DG$17)/12*INDEX(e_VolG,Calendario!DG$17),0) -> 0 | DH19: =IF(AND(Calendario!DH$16>0,106<p_MesArranque),INDEX(Base_PDF!$F$88:$O$88,1,Calendario!DH$17)/12*INDEX(e_VolG,Calendario!DH$17),0) -> 0 | DI19: =IF(AND(Calendario!DI$16>0,107<p_MesArranque),INDEX(Base_PDF!$F$88:$O$88,1,Calendario!DI$17)/12*INDEX(e_VolG,Calendario!DI$17),0) -> 0 | DJ19: =IF(AND(Calendario!DJ$16>0,108<p_MesArranque),INDEX(Base_PDF!$F$88:$O$88,1,Calendario!DJ$17)/12*INDEX(e_VolG,Calendario!DJ$17),0) -> 0 | DK19: =IF(AND(Calendario!DK$16>0,109<p_MesArranque),INDEX(Base_PDF!$F$88:$O$88,1,Calendario!DK$17)/12*INDEX(e_VolG,Calendario!DK$17),0) -> 0 | DL19: =IF(AND(Calendario!DL$16>0,110<p_MesArranque),INDEX(Base_PDF!$F$88:$O$88,1,Calendario!DL$17)/12*INDEX(e_VolG,Calendario!DL$17),0) -> 0 | DM19: =IF(AND(Calendario!DM$16>0,111<p_MesArranque),INDEX(Base_PDF!$F$88:$O$88,1,Calendario!DM$17)/12*INDEX(e_VolG,Calendario!DM$17),0) -> 0 | DN19: =IF(AND(Calendario!DN$16>0,112<p_MesArranque),INDEX(Base_PDF!$F$88:$O$88,1,Calendario!DN$17)/12*INDEX(e_VolG,Calendario!DN$17),0) -> 0 | DO19: =IF(AND(Calendario!DO$16>0,113<p_MesArranque),INDEX(Base_PDF!$F$88:$O$88,1,Calendario!DO$17)/12*INDEX(e_VolG,Calendario!DO$17),0) -> 0 | DP19: =IF(AND(Calendario!DP$16>0,114<p_MesArranque),INDEX(Base_PDF!$F$88:$O$88,1,Calendario!DP$17)/12*INDEX(e_VolG,Calendario!DP$17),0) -> 0 | DQ19: =IF(AND(Calendario!DQ$16>0,115<p_MesArranque),INDEX(Base_PDF!$F$88:$O$88,1,Calendario!DQ$17)/12*INDEX(e_VolG,Calendario!DQ$17),0) -> 0 | DR19: =IF(AND(Calendario!DR$16>0,116<p_MesArranque),INDEX(Base_PDF!$F$88:$O$88,1,Calendario!DR$17)/12*INDEX(e_VolG,Calendario!DR$17),0) -> 0 | DS19: =IF(AND(Calendario!DS$16>0,117<p_MesArranque),INDEX(Base_PDF!$F$88:$O$88,1,Calendario!DS$17)/12*INDEX(e_VolG,Calendario!DS$17),0) -> 0 | DT19: =IF(AND(Calendario!DT$16>0,118<p_MesArranque),INDEX(Base_PDF!$F$88:$O$88,1,Calendario!DT$17)/12*INDEX(e_VolG,Calendario!DT$17),0) -> 0 | DU19: =IF(AND(Calendario!DU$16>0,119<p_MesArranque),INDEX(Base_PDF!$F$88:$O$88,1,Calendario!DU$17)/12*INDEX(e_VolG,Calendario!DU$17),0) -> 0 | DV19: =IF(AND(Calendario!DV$16>0,120<p_MesArranque),INDEX(Base_PDF!$F$88:$O$88,1,Calendario!DV$17)/12*INDEX(e_VolG,Calendario!DV$17),0) -> 0 | DW19: =IF(AND(Calendario!DW$16>0,121<p_MesArranque),INDEX(Base_PDF!$F$88:$O$88,1,Calendario!DW$17)/12*INDEX(e_VolG,Calendario!DW$17),0) -> 0 | DX19: =IF(AND(Calendario!DX$16>0,122<p_MesArranque),INDEX(Base_PDF!$F$88:$O$88,1,Calendario!DX$17)/12*INDEX(e_VolG,Calendario!DX$17),0) -> 0 | DY19: =IF(AND(Calendario!DY$16>0,123<p_MesArranque),INDEX(Base_PDF!$F$88:$O$88,1,Calendario!DY$17)/12*INDEX(e_VolG,Calendario!DY$17),0) -> 0 | DZ19: =IF(AND(Calendario!DZ$16>0,124<p_MesArranque),INDEX(Base_PDF!$F$88:$O$88,1,Calendario!DZ$17)/12*INDEX(e_VolG,Calendario!DZ$17),0) -> 0 | EA19: =IF(AND(Calendario!EA$16>0,125<p_MesArranque),INDEX(Base_PDF!$F$88:$O$88,1,Calendario!EA$17)/12*INDEX(e_VolG,Calendario!EA$17),0) -> 0 | EB19: =IF(AND(Calendario!EB$16>0,126<p_MesArranque),INDEX(Base_PDF!$F$88:$O$88,1,Calendario!EB$17)/12*INDEX(e_VolG,Calendario!EB$17),0) -> 0 | EC19: =IF(AND(Calendario!EC$16>0,127<p_MesArranque),INDEX(Base_PDF!$F$88:$O$88,1,Calendario!EC$17)/12*INDEX(e_VolG,Calendario!EC$17),0) -> 0 | ED19: =IF(AND(Calendario!ED$16>0,128<p_MesArranque),INDEX(Base_PDF!$F$88:$O$88,1,Calendario!ED$17)/12*INDEX(e_VolG,Calendario!ED$17),0) -> 0 | EE19: =IF(AND(Calendario!EE$16>0,129<p_MesArranque),INDEX(Base_PDF!$F$88:$O$88,1,Calendario!EE$17)/12*INDEX(e_VolG,Calendario!EE$17),0) -> 0 | EF19: =IF(AND(Calendario!EF$16>0,130<p_MesArranque),INDEX(Base_PDF!$F$88:$O$88,1,Calendario!EF$17)/12*INDEX(e_VolG,Calendario!EF$17),0) -> 0 | EG19: =IF(AND(Calendario!EG$16>0,131<p_MesArranque),INDEX(Base_PDF!$F$88:$O$88,1,Calendario!EG$17)/12*INDEX(e_VolG,Calendario!EG$17),0) -> 0 | EH19: =IF(AND(Calendario!EH$16>0,132<p_MesArranque),INDEX(Base_PDF!$F$88:$O$88,1,Calendario!EH$17)/12*INDEX(e_VolG,Calendario!EH$17),0) -> 0 | EI19: =IF(AND(Calendario!EI$16>0,133<p_MesArranque),INDEX(Base_PDF!$F$88:$O$88,1,Calendario!EI$17)/12*INDEX(e_VolG,Calendario!EI$17),0) -> 0 | EJ19: =IF(AND(Calendario!EJ$16>0,134<p_MesArranque),INDEX(Base_PDF!$F$88:$O$88,1,Calendario!EJ$17)/12*INDEX(e_VolG,Calendario!EJ$17),0) -> 0 | EK19: =IF(AND(Calendario!EK$16>0,135<p_MesArranque),INDEX(Base_PDF!$F$88:$O$88,1,Calendario!EK$17)/12*INDEX(e_VolG,Calendario!EK$17),0) -> 0 | EL19: =IF(AND(Calendario!EL$16>0,136<p_MesArranque),INDEX(Base_PDF!$F$88:$O$88,1,Calendario!EL$17)/12*INDEX(e_VolG,Calendario!EL$17),0) -> 0 | EM19: =IF(AND(Calendario!EM$16>0,137<p_MesArranque),INDEX(Base_PDF!$F$88:$O$88,1,Calendario!EM$17)/12*INDEX(e_VolG,Calendario!EM$17),0) -> 0 | EN19: =IF(AND(Calendario!EN$16>0,138<p_MesArranque),INDEX(Base_PDF!$F$88:$O$88,1,Calendario!EN$17)/12*INDEX(e_VolG,Calendario!EN$17),0) -> 0 | EO19: =IF(AND(Calendario!EO$16>0,139<p_MesArranque),INDEX(Base_PDF!$F$88:$O$88,1,Calendario!EO$17)/12*INDEX(e_VolG,Calendario!EO$17),0) -> 0 | EP19: =IF(AND(Calendario!EP$16>0,140<p_MesArranque),INDEX(Base_PDF!$F$88:$O$88,1,Calendario!EP$17)/12*INDEX(e_VolG,Calendario!EP$17),0) -> 0 | EQ19: =IF(AND(Calendario!EQ$16>0,141<p_MesArranque),INDEX(Base_PDF!$F$88:$O$88,1,Calendario!EQ$17)/12*INDEX(e_VolG,Calendario!EQ$17),0) -> 0 | ER19: =IF(AND(Calendario!ER$16>0,142<p_MesArranque),INDEX(Base_PDF!$F$88:$O$88,1,Calendario!ER$17)/12*INDEX(e_VolG,Calendario!ER$17),0) -> 0 | ES19: =IF(AND(Calendario!ES$16>0,143<p_MesArranque),INDEX(Base_PDF!$F$88:$O$88,1,Calendario!ES$17)/12*INDEX(e_VolG,Calendario!ES$17),0) -> 0 | ET19: =IF(AND(Calendario!ET$16>0,144<p_MesArranque),INDEX(Base_PDF!$F$88:$O$88,1,Calendario!ET$17)/12*INDEX(e_VolG,Calendario!ET$17),0) -> 0 | EU19: =IF(AND(Calendario!EU$16>0,145<p_MesArranque),INDEX(Base_PDF!$F$88:$O$88,1,Calendario!EU$17)/12*INDEX(e_VolG,Calendario!EU$17),0) -> 0 | EV19: =IF(AND(Calendario!EV$16>0,146<p_MesArranque),INDEX(Base_PDF!$F$88:$O$88,1,Calendario!EV$17)/12*INDEX(e_VolG,Calendario!EV$17),0) -> 0 | EW19: =IF(AND(Calendario!EW$16>0,147<p_MesArranque),INDEX(Base_PDF!$F$88:$O$88,1,Calendario!EW$17)/12*INDEX(e_VolG,Calendario!EW$17),0) -> 0 | EX19: =IF(AND(Calendario!EX$16>0,148<p_MesArranque),INDEX(Base_PDF!$F$88:$O$88,1,Calendario!EX$17)/12*INDEX(e_VolG,Calendario!EX$17),0) -> 0 | EY19: =IF(AND(Calendario!EY$16>0,149<p_MesArranque),INDEX(Base_PDF!$F$88:$O$88,1,Calendario!EY$17)/12*INDEX(e_VolG,Calendario!EY$17),0) -> 0 | EZ19: =IF(AND(Calendario!EZ$16>0,150<p_MesArranque),INDEX(Base_PDF!$F$88:$O$88,1,Calendario!EZ$17)/12*INDEX(e_VolG,Calendario!EZ$17),0) -> 0 | FA19: =IF(AND(Calendario!FA$16>0,151<p_MesArranque),INDEX(Base_PDF!$F$88:$O$88,1,Calendario!FA$17)/12*INDEX(e_VolG,Calendario!FA$17),0) -> 0 | FB19: =IF(AND(Calendario!FB$16>0,152<p_MesArranque),INDEX(Base_PDF!$F$88:$O$88,1,Calendario!FB$17)/12*INDEX(e_VolG,Calendario!FB$17),0) -> 0 | FC19: =IF(AND(Calendario!FC$16>0,153<p_MesArranque),INDEX(Base_PDF!$F$88:$O$88,1,Calendario!FC$17)/12*INDEX(e_VolG,Calendario!FC$17),0) -> 0 | FD19: =IF(AND(Calendario!FD$16>0,154<p_MesArranque),INDEX(Base_PDF!$F$88:$O$88,1,Calendario!FD$17)/12*INDEX(e_VolG,Calendario!FD$17),0) -> 0 | FE19: =IF(AND(Calendario!FE$16>0,155<p_MesArranque),INDEX(Base_PDF!$F$88:$O$88,1,Calendario!FE$17)/12*INDEX(e_VolG,Calendario!FE$17),0) -> 0 | FF19: =IF(AND(Calendario!FF$16>0,156<p_MesArranque),INDEX(Base_PDF!$F$88:$O$88,1,Calendario!FF$17)/12*INDEX(e_VolG,Calendario!FF$17),0) -> 0
A20: holg_g | B20: Holgura de capacidad para recuperar (u buenas) | C20: u | E20: =SUM($F20:$FF20) -> 14000 | F20: =IF(F$8=1,MAX(0,F$13*F$11*(1-e_Rech)-F$17),0) -> 0 | G20: =IF(G$8=1,MAX(0,G$13*G$11*(1-e_Rech)-G$17),0) -> 250 | H20: =IF(H$8=1,MAX(0,H$13*H$11*(1-e_Rech)-H$17),0) -> 250 | I20: =IF(I$8=1,MAX(0,I$13*I$11*(1-e_Rech)-I$17),0) -> 250 | J20: =IF(J$8=1,MAX(0,J$13*J$11*(1-e_Rech)-J$17),0) -> 250 | K20: =IF(K$8=1,MAX(0,K$13*K$11*(1-e_Rech)-K$17),0) -> 250 | L20: =IF(L$8=1,MAX(0,L$13*L$11*(1-e_Rech)-L$17),0) -> 250 | M20: =IF(M$8=1,MAX(0,M$13*M$11*(1-e_Rech)-M$17),0) -> 250 | ... FF20: =IF(FF$8=1,MAX(0,FF$13*FF$11*(1-e_Rech)-FF$17),0) -> 0
A21: rec_g | B21: Volumen recuperado (desplazamiento) | C21: u | E21: =SUM($F21:$FF21) -> 0 | F21: =0 -> 0 | G21: =MIN(F$22,G$20) -> 0 | H21: =MIN(G$22,H$20) -> 0 | I21: =MIN(H$22,I$20) -> 0 | J21: =MIN(I$22,J$20) -> 0 | K21: =MIN(J$22,K$20) -> 0 | L21: =MIN(K$22,L$20) -> 0 | M21: =MIN(L$22,M$20) -> 0 | N21: =MIN(M$22,N$20) -> 0 | ... FF21: =MIN(FE$22,FF$20) -> 0
A22: pend_g | B22: Pendiente recuperable acumulado (u) | C22: u | E22: =INDEX($F22:$FF22,1,p_MesFin+1) -> 0 | F22: =0+(F$18+F$19)*e_Recup-F$21 -> 0 | G22: =F$22+(G$18+G$19)*e_Recup-G$21 -> 0 | H22: =G$22+(H$18+H$19)*e_Recup-H$21 -> 0 | I22: =H$22+(I$18+I$19)*e_Recup-I$21 -> 0 | J22: =I$22+(J$18+J$19)*e_Recup-J$21 -> 0 | K22: =J$22+(K$18+K$19)*e_Recup-K$21 -> 0 | L22: =K$22+(L$18+L$19)*e_Recup-L$21 -> 0 | M22: =L$22+(M$18+M$19)*e_Recup-M$21 -> 0 | N22: =M$22+(N$18+N$19)*e_Recup-N$21 -> 0 | ... FF22: =FE$22+(FF$18+FF$19)*e_Recup-FF$21 -> 0
A23: pdef_g | B23: Pérdida definitiva de ventas (u) | C23: u | E23: =SUM($F23:$FF23) -> 0 | F23: =(F$18+F$19)*(1-e_Recup) -> 0 | G23: =(G$18+G$19)*(1-e_Recup) -> 0 | H23: =(H$18+H$19)*(1-e_Recup) -> 0 | I23: =(I$18+I$19)*(1-e_Recup) -> 0 | J23: =(J$18+J$19)*(1-e_Recup) -> 0 | K23: =(K$18+K$19)*(1-e_Recup) -> 0 | L23: =(L$18+L$19)*(1-e_Recup) -> 0 | M23: =(M$18+M$19)*(1-e_Recup) -> 0 | ... FF23: =(FF$18+FF$19)*(1-e_Recup) -> 0
A24: vtas_u_g | B24: UNIDADES VENDIDAS | C24: u | E24: =SUM($F24:$FF24) -> 192000 | F24: =IF(F$9=1,SUMIFS(dr_Cant,dr_Mes,0,dr_Cod,"U_VTA_G",dr_Est,"<>Excluido"),F$17+F$21) -> 0 | G24: =IF(G$9=1,SUMIFS(dr_Cant,dr_Mes,1,dr_Cod,"U_VTA_G",dr_Est,"<>Excluido"),G$17+G$21) -> 1000 | H24: =IF(H$9=1,SUMIFS(dr_Cant,dr_Mes,2,dr_Cod,"U_VTA_G",dr_Est,"<>Excluido"),H$17+H$21) -> 1000 | I24: =IF(I$9=1,SUMIFS(dr_Cant,dr_Mes,3,dr_Cod,"U_VTA_G",dr_Est,"<>Excluido"),I$17+I$21) -> 1000 | J24: =IF(J$9=1,SUMIFS(dr_Cant,dr_Mes,4,dr_Cod,"U_VTA_G",dr_Est,"<>Excluido"),J$17+J$21) -> 1000 | K24: =IF(K$9=1,SUMIFS(dr_Cant,dr_Mes,5,dr_Cod,"U_VTA_G",dr_Est,"<>Excluido"),K$17+K$21) -> 1000 | L24: =IF(L$9=1,SUMIFS(dr_Cant,dr_Mes,6,dr_Cod,"U_VTA_G",dr_Est,"<>Excluido"),L$17+L$21) -> 1000 | M24: =IF(M$9=1,SUMIFS(dr_Cant,dr_Mes,7,dr_Cod,"U_VTA_G",dr_Est,"<>Excluido"),M$17+M$21) -> 1000 | N24: =IF(N$9=1,SUMIFS(dr_Cant,dr_Mes,8,dr_Cod,"U_VTA_G",dr_Est,"<>Excluido"),N$17+N$21) -> 1000 | O24: =IF(O$9=1,SUMIFS(dr_Cant,dr_Mes,9,dr_Cod,"U_VTA_G",dr_Est,"<>Excluido"),O$17+O$21) -> 1000 | P24: =IF(P$9=1,SUMIFS(dr_Cant,dr_Mes,10,dr_Cod,"U_VTA_G",dr_Est,"<>Excluido"),P$17+P$21) -> 1000 | Q24: =IF(Q$9=1,SUMIFS(dr_Cant,dr_Mes,11,dr_Cod,"U_VTA_G",dr_Est,"<>Excluido"),Q$17+Q$21) -> 1000 | R24: =IF(R$9=1,SUMIFS(dr_Cant,dr_Mes,12,dr_Cod,"U_VTA_G",dr_Est,"<>Excluido"),R$17+R$21) -> 1000 | S24: =IF(S$9=1,SUMIFS(dr_Cant,dr_Mes,13,dr_Cod,"U_VTA_G",dr_Est,"<>Excluido"),S$17+S$21) -> 1250 | T24: =IF(T$9=1,SUMIFS(dr_Cant,dr_Mes,14,dr_Cod,"U_VTA_G",dr_Est,"<>Excluido"),T$17+T$21) -> 1250 | U24: =IF(U$9=1,SUMIFS(dr_Cant,dr_Mes,15,dr_Cod,"U_VTA_G",dr_Est,"<>Excluido"),U$17+U$21) -> 1250 | V24: =IF(V$9=1,SUMIFS(dr_Cant,dr_Mes,16,dr_Cod,"U_VTA_G",dr_Est,"<>Excluido"),V$17+V$21) -> 1250 | W24: =IF(W$9=1,SUMIFS(dr_Cant,dr_Mes,17,dr_Cod,"U_VTA_G",dr_Est,"<>Excluido"),W$17+W$21) -> 1250 | X24: =IF(X$9=1,SUMIFS(dr_Cant,dr_Mes,18,dr_Cod,"U_VTA_G",dr_Est,"<>Excluido"),X$17+X$21) -> 1250 | Y24: =IF(Y$9=1,SUMIFS(dr_Cant,dr_Mes,19,dr_Cod,"U_VTA_G",dr_Est,"<>Excluido"),Y$17+Y$21) -> 1250 | Z24: =IF(Z$9=1,SUMIFS(dr_Cant,dr_Mes,20,dr_Cod,"U_VTA_G",dr_Est,"<>Excluido"),Z$17+Z$21) -> 1250 | AA24: =IF(AA$9=1,SUMIFS(dr_Cant,dr_Mes,21,dr_Cod,"U_VTA_G",dr_Est,"<>Excluido"),AA$17+AA$21) -> 1250 | AB24: =IF(AB$9=1,SUMIFS(dr_Cant,dr_Mes,22,dr_Cod,"U_VTA_G",dr_Est,"<>Excluido"),AB$17+AB$21) -> 1250 | AC24: =IF(AC$9=1,SUMIFS(dr_Cant,dr_Mes,23,dr_Cod,"U_VTA_G",dr_Est,"<>Excluido"),AC$17+AC$21) -> 1250 | AD24: =IF(AD$9=1,SUMIFS(dr_Cant,dr_Mes,24,dr_Cod,"U_VTA_G",dr_Est,"<>Excluido"),AD$17+AD$21) -> 1250 | AE24: =IF(AE$9=1,SUMIFS(dr_Cant,dr_Mes,25,dr_Cod,"U_VTA_G",dr_Est,"<>Excluido"),AE$17+AE$21) -> 1500 | AF24: =IF(AF$9=1,SUMIFS(dr_Cant,dr_Mes,26,dr_Cod,"U_VTA_G",dr_Est,"<>Excluido"),AF$17+AF$21) -> 1500 | AG24: =IF(AG$9=1,SUMIFS(dr_Cant,dr_Mes,27,dr_Cod,"U_VTA_G",dr_Est,"<>Excluido"),AG$17+AG$21) -> 1500 | AH24: =IF(AH$9=1,SUMIFS(dr_Cant,dr_Mes,28,dr_Cod,"U_VTA_G",dr_Est,"<>Excluido"),AH$17+AH$21) -> 1500 | AI24: =IF(AI$9=1,SUMIFS(dr_Cant,dr_Mes,29,dr_Cod,"U_VTA_G",dr_Est,"<>Excluido"),AI$17+AI$21) -> 1500 | AJ24: =IF(AJ$9=1,SUMIFS(dr_Cant,dr_Mes,30,dr_Cod,"U_VTA_G",dr_Est,"<>Excluido"),AJ$17+AJ$21) -> 1500 | AK24: =IF(AK$9=1,SUMIFS(dr_Cant,dr_Mes,31,dr_Cod,"U_VTA_G",dr_Est,"<>Excluido"),AK$17+AK$21) -> 1500 | AL24: =IF(AL$9=1,SUMIFS(dr_Cant,dr_Mes,32,dr_Cod,"U_VTA_G",dr_Est,"<>Excluido"),AL$17+AL$21) -> 1500 | AM24: =IF(AM$9=1,SUMIFS(dr_Cant,dr_Mes,33,dr_Cod,"U_VTA_G",dr_Est,"<>Excluido"),AM$17+AM$21) -> 1500 | AN24: =IF(AN$9=1,SUMIFS(dr_Cant,dr_Mes,34,dr_Cod,"U_VTA_G",dr_Est,"<>Excluido"),AN$17+AN$21) -> 1500 | AO24: =IF(AO$9=1,SUMIFS(dr_Cant,dr_Mes,35,dr_Cod,"U_VTA_G",dr_Est,"<>Excluido"),AO$17+AO$21) -> 1500 | AP24: =IF(AP$9=1,SUMIFS(dr_Cant,dr_Mes,36,dr_Cod,"U_VTA_G",dr_Est,"<>Excluido"),AP$17+AP$21) -> 1500 | AQ24: =IF(AQ$9=1,SUMIFS(dr_Cant,dr_Mes,37,dr_Cod,"U_VTA_G",dr_Est,"<>Excluido"),AQ$17+AQ$21) -> 1750 | AR24: =IF(AR$9=1,SUMIFS(dr_Cant,dr_Mes,38,dr_Cod,"U_VTA_G",dr_Est,"<>Excluido"),AR$17+AR$21) -> 1750 | AS24: =IF(AS$9=1,SUMIFS(dr_Cant,dr_Mes,39,dr_Cod,"U_VTA_G",dr_Est,"<>Excluido"),AS$17+AS$21) -> 1750 | AT24: =IF(AT$9=1,SUMIFS(dr_Cant,dr_Mes,40,dr_Cod,"U_VTA_G",dr_Est,"<>Excluido"),AT$17+AT$21) -> 1750 | AU24: =IF(AU$9=1,SUMIFS(dr_Cant,dr_Mes,41,dr_Cod,"U_VTA_G",dr_Est,"<>Excluido"),AU$17+AU$21) -> 1750 | AV24: =IF(AV$9=1,SUMIFS(dr_Cant,dr_Mes,42,dr_Cod,"U_VTA_G",dr_Est,"<>Excluido"),AV$17+AV$21) -> 1750 | AW24: =IF(AW$9=1,SUMIFS(dr_Cant,dr_Mes,43,dr_Cod,"U_VTA_G",dr_Est,"<>Excluido"),AW$17+AW$21) -> 1750 | AX24: =IF(AX$9=1,SUMIFS(dr_Cant,dr_Mes,44,dr_Cod,"U_VTA_G",dr_Est,"<>Excluido"),AX$17+AX$21) -> 1750 | AY24: =IF(AY$9=1,SUMIFS(dr_Cant,dr_Mes,45,dr_Cod,"U_VTA_G",dr_Est,"<>Excluido"),AY$17+AY$21) -> 1750 | AZ24: =IF(AZ$9=1,SUMIFS(dr_Cant,dr_Mes,46,dr_Cod,"U_VTA_G",dr_Est,"<>Excluido"),AZ$17+AZ$21) -> 1750 | BA24: =IF(BA$9=1,SUMIFS(dr_Cant,dr_Mes,47,dr_Cod,"U_VTA_G",dr_Est,"<>Excluido"),BA$17+BA$21) -> 1750 | BB24: =IF(BB$9=1,SUMIFS(dr_Cant,dr_Mes,48,dr_Cod,"U_VTA_G",dr_Est,"<>Excluido"),BB$17+BB$21) -> 1750 | BC24: =IF(BC$9=1,SUMIFS(dr_Cant,dr_Mes,49,dr_Cod,"U_VTA_G",dr_Est,"<>Excluido"),BC$17+BC$21) -> 1750 | BD24: =IF(BD$9=1,SUMIFS(dr_Cant,dr_Mes,50,dr_Cod,"U_VTA_G",dr_Est,"<>Excluido"),BD$17+BD$21) -> 1750 | BE24: =IF(BE$9=1,SUMIFS(dr_Cant,dr_Mes,51,dr_Cod,"U_VTA_G",dr_Est,"<>Excluido"),BE$17+BE$21) -> 1750 | BF24: =IF(BF$9=1,SUMIFS(dr_Cant,dr_Mes,52,dr_Cod,"U_VTA_G",dr_Est,"<>Excluido"),BF$17+BF$21) -> 1750 | BG24: =IF(BG$9=1,SUMIFS(dr_Cant,dr_Mes,53,dr_Cod,"U_VTA_G",dr_Est,"<>Excluido"),BG$17+BG$21) -> 1750 | BH24: =IF(BH$9=1,SUMIFS(dr_Cant,dr_Mes,54,dr_Cod,"U_VTA_G",dr_Est,"<>Excluido"),BH$17+BH$21) -> 1750 | BI24: =IF(BI$9=1,SUMIFS(dr_Cant,dr_Mes,55,dr_Cod,"U_VTA_G",dr_Est,"<>Excluido"),BI$17+BI$21) -> 1750 | BJ24: =IF(BJ$9=1,SUMIFS(dr_Cant,dr_Mes,56,dr_Cod,"U_VTA_G",dr_Est,"<>Excluido"),BJ$17+BJ$21) -> 1750 | BK24: =IF(BK$9=1,SUMIFS(dr_Cant,dr_Mes,57,dr_Cod,"U_VTA_G",dr_Est,"<>Excluido"),BK$17+BK$21) -> 1750 | BL24: =IF(BL$9=1,SUMIFS(dr_Cant,dr_Mes,58,dr_Cod,"U_VTA_G",dr_Est,"<>Excluido"),BL$17+BL$21) -> 1750 | BM24: =IF(BM$9=1,SUMIFS(dr_Cant,dr_Mes,59,dr_Cod,"U_VTA_G",dr_Est,"<>Excluido"),BM$17+BM$21) -> 1750 | BN24: =IF(BN$9=1,SUMIFS(dr_Cant,dr_Mes,60,dr_Cod,"U_VTA_G",dr_Est,"<>Excluido"),BN$17+BN$21) -> 1750 | BO24: =IF(BO$9=1,SUMIFS(dr_Cant,dr_Mes,61,dr_Cod,"U_VTA_G",dr_Est,"<>Excluido"),BO$17+BO$21) -> 1750 | BP24: =IF(BP$9=1,SUMIFS(dr_Cant,dr_Mes,62,dr_Cod,"U_VTA_G",dr_Est,"<>Excluido"),BP$17+BP$21) -> 1750 | BQ24: =IF(BQ$9=1,SUMIFS(dr_Cant,dr_Mes,63,dr_Cod,"U_VTA_G",dr_Est,"<>Excluido"),BQ$17+BQ$21) -> 1750 | BR24: =IF(BR$9=1,SUMIFS(dr_Cant,dr_Mes,64,dr_Cod,"U_VTA_G",dr_Est,"<>Excluido"),BR$17+BR$21) -> 1750 | BS24: =IF(BS$9=1,SUMIFS(dr_Cant,dr_Mes,65,dr_Cod,"U_VTA_G",dr_Est,"<>Excluido"),BS$17+BS$21) -> 1750 | BT24: =IF(BT$9=1,SUMIFS(dr_Cant,dr_Mes,66,dr_Cod,"U_VTA_G",dr_Est,"<>Excluido"),BT$17+BT$21) -> 1750 | BU24: =IF(BU$9=1,SUMIFS(dr_Cant,dr_Mes,67,dr_Cod,"U_VTA_G",dr_Est,"<>Excluido"),BU$17+BU$21) -> 1750 | BV24: =IF(BV$9=1,SUMIFS(dr_Cant,dr_Mes,68,dr_Cod,"U_VTA_G",dr_Est,"<>Excluido"),BV$17+BV$21) -> 1750 | BW24: =IF(BW$9=1,SUMIFS(dr_Cant,dr_Mes,69,dr_Cod,"U_VTA_G",dr_Est,"<>Excluido"),BW$17+BW$21) -> 1750 | BX24: =IF(BX$9=1,SUMIFS(dr_Cant,dr_Mes,70,dr_Cod,"U_VTA_G",dr_Est,"<>Excluido"),BX$17+BX$21) -> 1750 | BY24: =IF(BY$9=1,SUMIFS(dr_Cant,dr_Mes,71,dr_Cod,"U_VTA_G",dr_Est,"<>Excluido"),BY$17+BY$21) -> 1750 | BZ24: =IF(BZ$9=1,SUMIFS(dr_Cant,dr_Mes,72,dr_Cod,"U_VTA_G",dr_Est,"<>Excluido"),BZ$17+BZ$21) -> 1750 | CA24: =IF(CA$9=1,SUMIFS(dr_Cant,dr_Mes,73,dr_Cod,"U_VTA_G",dr_Est,"<>Excluido"),CA$17+CA$21) -> 1750 | CB24: =IF(CB$9=1,SUMIFS(dr_Cant,dr_Mes,74,dr_Cod,"U_VTA_G",dr_Est,"<>Excluido"),CB$17+CB$21) -> 1750 | CC24: =IF(CC$9=1,SUMIFS(dr_Cant,dr_Mes,75,dr_Cod,"U_VTA_G",dr_Est,"<>Excluido"),CC$17+CC$21) -> 1750 | CD24: =IF(CD$9=1,SUMIFS(dr_Cant,dr_Mes,76,dr_Cod,"U_VTA_G",dr_Est,"<>Excluido"),CD$17+CD$21) -> 1750 | CE24: =IF(CE$9=1,SUMIFS(dr_Cant,dr_Mes,77,dr_Cod,"U_VTA_G",dr_Est,"<>Excluido"),CE$17+CE$21) -> 1750 | CF24: =IF(CF$9=1,SUMIFS(dr_Cant,dr_Mes,78,dr_Cod,"U_VTA_G",dr_Est,"<>Excluido"),CF$17+CF$21) -> 1750 | CG24: =IF(CG$9=1,SUMIFS(dr_Cant,dr_Mes,79,dr_Cod,"U_VTA_G",dr_Est,"<>Excluido"),CG$17+CG$21) -> 1750 | CH24: =IF(CH$9=1,SUMIFS(dr_Cant,dr_Mes,80,dr_Cod,"U_VTA_G",dr_Est,"<>Excluido"),CH$17+CH$21) -> 1750 | CI24: =IF(CI$9=1,SUMIFS(dr_Cant,dr_Mes,81,dr_Cod,"U_VTA_G",dr_Est,"<>Excluido"),CI$17+CI$21) -> 1750 | CJ24: =IF(CJ$9=1,SUMIFS(dr_Cant,dr_Mes,82,dr_Cod,"U_VTA_G",dr_Est,"<>Excluido"),CJ$17+CJ$21) -> 1750 | CK24: =IF(CK$9=1,SUMIFS(dr_Cant,dr_Mes,83,dr_Cod,"U_VTA_G",dr_Est,"<>Excluido"),CK$17+CK$21) -> 1750 | CL24: =IF(CL$9=1,SUMIFS(dr_Cant,dr_Mes,84,dr_Cod,"U_VTA_G",dr_Est,"<>Excluido"),CL$17+CL$21) -> 1750 | CM24: =IF(CM$9=1,SUMIFS(dr_Cant,dr_Mes,85,dr_Cod,"U_VTA_G",dr_Est,"<>Excluido"),CM$17+CM$21) -> 1750 | CN24: =IF(CN$9=1,SUMIFS(dr_Cant,dr_Mes,86,dr_Cod,"U_VTA_G",dr_Est,"<>Excluido"),CN$17+CN$21) -> 1750 | CO24: =IF(CO$9=1,SUMIFS(dr_Cant,dr_Mes,87,dr_Cod,"U_VTA_G",dr_Est,"<>Excluido"),CO$17+CO$21) -> 1750 | CP24: =IF(CP$9=1,SUMIFS(dr_Cant,dr_Mes,88,dr_Cod,"U_VTA_G",dr_Est,"<>Excluido"),CP$17+CP$21) -> 1750 | CQ24: =IF(CQ$9=1,SUMIFS(dr_Cant,dr_Mes,89,dr_Cod,"U_VTA_G",dr_Est,"<>Excluido"),CQ$17+CQ$21) -> 1750 | CR24: =IF(CR$9=1,SUMIFS(dr_Cant,dr_Mes,90,dr_Cod,"U_VTA_G",dr_Est,"<>Excluido"),CR$17+CR$21) -> 1750 | CS24: =IF(CS$9=1,SUMIFS(dr_Cant,dr_Mes,91,dr_Cod,"U_VTA_G",dr_Est,"<>Excluido"),CS$17+CS$21) -> 1750 | CT24: =IF(CT$9=1,SUMIFS(dr_Cant,dr_Mes,92,dr_Cod,"U_VTA_G",dr_Est,"<>Excluido"),CT$17+CT$21) -> 1750 | CU24: =IF(CU$9=1,SUMIFS(dr_Cant,dr_Mes,93,dr_Cod,"U_VTA_G",dr_Est,"<>Excluido"),CU$17+CU$21) -> 1750 | CV24: =IF(CV$9=1,SUMIFS(dr_Cant,dr_Mes,94,dr_Cod,"U_VTA_G",dr_Est,"<>Excluido"),CV$17+CV$21) -> 1750 | CW24: =IF(CW$9=1,SUMIFS(dr_Cant,dr_Mes,95,dr_Cod,"U_VTA_G",dr_Est,"<>Excluido"),CW$17+CW$21) -> 1750 | CX24: =IF(CX$9=1,SUMIFS(dr_Cant,dr_Mes,96,dr_Cod,"U_VTA_G",dr_Est,"<>Excluido"),CX$17+CX$21) -> 1750 | CY24: =IF(CY$9=1,SUMIFS(dr_Cant,dr_Mes,97,dr_Cod,"U_VTA_G",dr_Est,"<>Excluido"),CY$17+CY$21) -> 1750 | CZ24: =IF(CZ$9=1,SUMIFS(dr_Cant,dr_Mes,98,dr_Cod,"U_VTA_G",dr_Est,"<>Excluido"),CZ$17+CZ$21) -> 1750 | DA24: =IF(DA$9=1,SUMIFS(dr_Cant,dr_Mes,99,dr_Cod,"U_VTA_G",dr_Est,"<>Excluido"),DA$17+DA$21) -> 1750 | DB24: =IF(DB$9=1,SUMIFS(dr_Cant,dr_Mes,100,dr_Cod,"U_VTA_G",dr_Est,"<>Excluido"),DB$17+DB$21) -> 1750 | DC24: =IF(DC$9=1,SUMIFS(dr_Cant,dr_Mes,101,dr_Cod,"U_VTA_G",dr_Est,"<>Excluido"),DC$17+DC$21) -> 1750 | DD24: =IF(DD$9=1,SUMIFS(dr_Cant,dr_Mes,102,dr_Cod,"U_VTA_G",dr_Est,"<>Excluido"),DD$17+DD$21) -> 1750 | DE24: =IF(DE$9=1,SUMIFS(dr_Cant,dr_Mes,103,dr_Cod,"U_VTA_G",dr_Est,"<>Excluido"),DE$17+DE$21) -> 1750 | DF24: =IF(DF$9=1,SUMIFS(dr_Cant,dr_Mes,104,dr_Cod,"U_VTA_G",dr_Est,"<>Excluido"),DF$17+DF$21) -> 1750 | DG24: =IF(DG$9=1,SUMIFS(dr_Cant,dr_Mes,105,dr_Cod,"U_VTA_G",dr_Est,"<>Excluido"),DG$17+DG$21) -> 1750 | DH24: =IF(DH$9=1,SUMIFS(dr_Cant,dr_Mes,106,dr_Cod,"U_VTA_G",dr_Est,"<>Excluido"),DH$17+DH$21) -> 1750 | DI24: =IF(DI$9=1,SUMIFS(dr_Cant,dr_Mes,107,dr_Cod,"U_VTA_G",dr_Est,"<>Excluido"),DI$17+DI$21) -> 1750 | DJ24: =IF(DJ$9=1,SUMIFS(dr_Cant,dr_Mes,108,dr_Cod,"U_VTA_G",dr_Est,"<>Excluido"),DJ$17+DJ$21) -> 1750 | DK24: =IF(DK$9=1,SUMIFS(dr_Cant,dr_Mes,109,dr_Cod,"U_VTA_G",dr_Est,"<>Excluido"),DK$17+DK$21) -> 1750 | DL24: =IF(DL$9=1,SUMIFS(dr_Cant,dr_Mes,110,dr_Cod,"U_VTA_G",dr_Est,"<>Excluido"),DL$17+DL$21) -> 1750 | DM24: =IF(DM$9=1,SUMIFS(dr_Cant,dr_Mes,111,dr_Cod,"U_VTA_G",dr_Est,"<>Excluido"),DM$17+DM$21) -> 1750 | DN24: =IF(DN$9=1,SUMIFS(dr_Cant,dr_Mes,112,dr_Cod,"U_VTA_G",dr_Est,"<>Excluido"),DN$17+DN$21) -> 1750 | DO24: =IF(DO$9=1,SUMIFS(dr_Cant,dr_Mes,113,dr_Cod,"U_VTA_G",dr_Est,"<>Excluido"),DO$17+DO$21) -> 1750 | DP24: =IF(DP$9=1,SUMIFS(dr_Cant,dr_Mes,114,dr_Cod,"U_VTA_G",dr_Est,"<>Excluido"),DP$17+DP$21) -> 1750 | DQ24: =IF(DQ$9=1,SUMIFS(dr_Cant,dr_Mes,115,dr_Cod,"U_VTA_G",dr_Est,"<>Excluido"),DQ$17+DQ$21) -> 1750 | DR24: =IF(DR$9=1,SUMIFS(dr_Cant,dr_Mes,116,dr_Cod,"U_VTA_G",dr_Est,"<>Excluido"),DR$17+DR$21) -> 1750 | DS24: =IF(DS$9=1,SUMIFS(dr_Cant,dr_Mes,117,dr_Cod,"U_VTA_G",dr_Est,"<>Excluido"),DS$17+DS$21) -> 1750 | DT24: =IF(DT$9=1,SUMIFS(dr_Cant,dr_Mes,118,dr_Cod,"U_VTA_G",dr_Est,"<>Excluido"),DT$17+DT$21) -> 1750 | DU24: =IF(DU$9=1,SUMIFS(dr_Cant,dr_Mes,119,dr_Cod,"U_VTA_G",dr_Est,"<>Excluido"),DU$17+DU$21) -> 1750 | DV24: =IF(DV$9=1,SUMIFS(dr_Cant,dr_Mes,120,dr_Cod,"U_VTA_G",dr_Est,"<>Excluido"),DV$17+DV$21) -> 1750 | DW24: =IF(DW$9=1,SUMIFS(dr_Cant,dr_Mes,121,dr_Cod,"U_VTA_G",dr_Est,"<>Excluido"),DW$17+DW$21) -> 0 | DX24: =IF(DX$9=1,SUMIFS(dr_Cant,dr_Mes,122,dr_Cod,"U_VTA_G",dr_Est,"<>Excluido"),DX$17+DX$21) -> 0 | DY24: =IF(DY$9=1,SUMIFS(dr_Cant,dr_Mes,123,dr_Cod,"U_VTA_G",dr_Est,"<>Excluido"),DY$17+DY$21) -> 0 | DZ24: =IF(DZ$9=1,SUMIFS(dr_Cant,dr_Mes,124,dr_Cod,"U_VTA_G",dr_Est,"<>Excluido"),DZ$17+DZ$21) -> 0 | EA24: =IF(EA$9=1,SUMIFS(dr_Cant,dr_Mes,125,dr_Cod,"U_VTA_G",dr_Est,"<>Excluido"),EA$17+EA$21) -> 0 | EB24: =IF(EB$9=1,SUMIFS(dr_Cant,dr_Mes,126,dr_Cod,"U_VTA_G",dr_Est,"<>Excluido"),EB$17+EB$21) -> 0 | EC24: =IF(EC$9=1,SUMIFS(dr_Cant,dr_Mes,127,dr_Cod,"U_VTA_G",dr_Est,"<>Excluido"),EC$17+EC$21) -> 0 | ED24: =IF(ED$9=1,SUMIFS(dr_Cant,dr_Mes,128,dr_Cod,"U_VTA_G",dr_Est,"<>Excluido"),ED$17+ED$21) -> 0 | EE24: =IF(EE$9=1,SUMIFS(dr_Cant,dr_Mes,129,dr_Cod,"U_VTA_G",dr_Est,"<>Excluido"),EE$17+EE$21) -> 0 | EF24: =IF(EF$9=1,SUMIFS(dr_Cant,dr_Mes,130,dr_Cod,"U_VTA_G",dr_Est,"<>Excluido"),EF$17+EF$21) -> 0 | EG24: =IF(EG$9=1,SUMIFS(dr_Cant,dr_Mes,131,dr_Cod,"U_VTA_G",dr_Est,"<>Excluido"),EG$17+EG$21) -> 0 | EH24: =IF(EH$9=1,SUMIFS(dr_Cant,dr_Mes,132,dr_Cod,"U_VTA_G",dr_Est,"<>Excluido"),EH$17+EH$21) -> 0 | EI24: =IF(EI$9=1,SUMIFS(dr_Cant,dr_Mes,133,dr_Cod,"U_VTA_G",dr_Est,"<>Excluido"),EI$17+EI$21) -> 0 | EJ24: =IF(EJ$9=1,SUMIFS(dr_Cant,dr_Mes,134,dr_Cod,"U_VTA_G",dr_Est,"<>Excluido"),EJ$17+EJ$21) -> 0 | EK24: =IF(EK$9=1,SUMIFS(dr_Cant,dr_Mes,135,dr_Cod,"U_VTA_G",dr_Est,"<>Excluido"),EK$17+EK$21) -> 0 | EL24: =IF(EL$9=1,SUMIFS(dr_Cant,dr_Mes,136,dr_Cod,"U_VTA_G",dr_Est,"<>Excluido"),EL$17+EL$21) -> 0 | EM24: =IF(EM$9=1,SUMIFS(dr_Cant,dr_Mes,137,dr_Cod,"U_VTA_G",dr_Est,"<>Excluido"),EM$17+EM$21) -> 0 | EN24: =IF(EN$9=1,SUMIFS(dr_Cant,dr_Mes,138,dr_Cod,"U_VTA_G",dr_Est,"<>Excluido"),EN$17+EN$21) -> 0 | EO24: =IF(EO$9=1,SUMIFS(dr_Cant,dr_Mes,139,dr_Cod,"U_VTA_G",dr_Est,"<>Excluido"),EO$17+EO$21) -> 0 | EP24: =IF(EP$9=1,SUMIFS(dr_Cant,dr_Mes,140,dr_Cod,"U_VTA_G",dr_Est,"<>Excluido"),EP$17+EP$21) -> 0 | EQ24: =IF(EQ$9=1,SUMIFS(dr_Cant,dr_Mes,141,dr_Cod,"U_VTA_G",dr_Est,"<>Excluido"),EQ$17+EQ$21) -> 0 | ER24: =IF(ER$9=1,SUMIFS(dr_Cant,dr_Mes,142,dr_Cod,"U_VTA_G",dr_Est,"<>Excluido"),ER$17+ER$21) -> 0 | ES24: =IF(ES$9=1,SUMIFS(dr_Cant,dr_Mes,143,dr_Cod,"U_VTA_G",dr_Est,"<>Excluido"),ES$17+ES$21) -> 0 | ET24: =IF(ET$9=1,SUMIFS(dr_Cant,dr_Mes,144,dr_Cod,"U_VTA_G",dr_Est,"<>Excluido"),ET$17+ET$21) -> 0 | EU24: =IF(EU$9=1,SUMIFS(dr_Cant,dr_Mes,145,dr_Cod,"U_VTA_G",dr_Est,"<>Excluido"),EU$17+EU$21) -> 0 | EV24: =IF(EV$9=1,SUMIFS(dr_Cant,dr_Mes,146,dr_Cod,"U_VTA_G",dr_Est,"<>Excluido"),EV$17+EV$21) -> 0 | EW24: =IF(EW$9=1,SUMIFS(dr_Cant,dr_Mes,147,dr_Cod,"U_VTA_G",dr_Est,"<>Excluido"),EW$17+EW$21) -> 0 | EX24: =IF(EX$9=1,SUMIFS(dr_Cant,dr_Mes,148,dr_Cod,"U_VTA_G",dr_Est,"<>Excluido"),EX$17+EX$21) -> 0 | EY24: =IF(EY$9=1,SUMIFS(dr_Cant,dr_Mes,149,dr_Cod,"U_VTA_G",dr_Est,"<>Excluido"),EY$17+EY$21) -> 0 | EZ24: =IF(EZ$9=1,SUMIFS(dr_Cant,dr_Mes,150,dr_Cod,"U_VTA_G",dr_Est,"<>Excluido"),EZ$17+EZ$21) -> 0 | FA24: =IF(FA$9=1,SUMIFS(dr_Cant,dr_Mes,151,dr_Cod,"U_VTA_G",dr_Est,"<>Excluido"),FA$17+FA$21) -> 0 | FB24: =IF(FB$9=1,SUMIFS(dr_Cant,dr_Mes,152,dr_Cod,"U_VTA_G",dr_Est,"<>Excluido"),FB$17+FB$21) -> 0 | FC24: =IF(FC$9=1,SUMIFS(dr_Cant,dr_Mes,153,dr_Cod,"U_VTA_G",dr_Est,"<>Excluido"),FC$17+FC$21) -> 0 | FD24: =IF(FD$9=1,SUMIFS(dr_Cant,dr_Mes,154,dr_Cod,"U_VTA_G",dr_Est,"<>Excluido"),FD$17+FD$21) -> 0 | FE24: =IF(FE$9=1,SUMIFS(dr_Cant,dr_Mes,155,dr_Cod,"U_VTA_G",dr_Est,"<>Excluido"),FE$17+FE$21) -> 0 | FF24: =IF(FF$9=1,SUMIFS(dr_Cant,dr_Mes,156,dr_Cod,"U_VTA_G",dr_Est,"<>Excluido"),FF$17+FF$21) -> 0
A25: ptobj_g | B25: Stock objetivo de PT (u) = ventas del mes siguiente x días PT | C25: u | F25: =IF(F$8=1,G$24*p_PTf,0) -> 0 | G25: =IF(G$8=1,H$24*p_PTf,0) -> 328.76712 | H25: =IF(H$8=1,I$24*p_PTf,0) -> 328.76712 | I25: =IF(I$8=1,J$24*p_PTf,0) -> 328.76712 | J25: =IF(J$8=1,K$24*p_PTf,0) -> 328.76712 | K25: =IF(K$8=1,L$24*p_PTf,0) -> 328.76712 | L25: =IF(L$8=1,M$24*p_PTf,0) -> 328.76712 | M25: =IF(M$8=1,N$24*p_PTf,0) -> 328.76712 | ... FE25: =IF(FE$8=1,FF$24*p_PTf,0) -> 0 | FF25: =IF(FF$8=1,0*p_PTf,0) -> 0
